Workbook

Sheet RESUMEN
A2: INGRESOS SEMANALES
B3: Semana 1 | C3: Semana 2 | D3: Semana 3 | E3: Semana 4 | F3: Semana 5 | G3: TOTAL | H3: PROMEDIO
A4: ENERO | G4: =SUM(B5:F5) -> 0 | H4: =G4/5 -> 0
A6: FEBRERO | G6: =SUM(B7:F7) -> 0 | H6: =G6/4 -> 0
A8: MARZO | G8: =SUM(B9:F9) -> 0 | H8: =G8/4 -> 0
A10: ABRIL | G10: =SUM(B11:F11) -> 0 | H10: =G10/5 -> 0
A12: MAYO | G12: =SUM(B13:F13) -> 0 | H12: =G12/4 -> 0
A14: JUNIO | G14: =SUM(B15:F15) -> 0 | H14: =G14/4 -> 0
A16: JULIO | G16: =SUM(B17:F17) -> 0 | H16: =G16/5 -> 0
A18: AGOSTO | G18: =SUM(B19:F19) -> 0 | H18: =G18/4 -> 0
A20: SEPTIEMBRE | G20: =SUM(B21:F21) -> 0 | H20: =G20/4 -> 0
A22: OCTUBRE | G22: =SUM(B23:F23) -> 0 | H22: =G22/5 -> 0
A24: NOVIEMBRE | G24: =SUM(B25:F25) -> 0 | H24: =G24/5 -> 0
A26: DICIEMBRE | G26: =SUM(B27:F27) -> 0 | H26: =G26/5 -> 0
A33: RECAUDACIONES MENSUALES
A34: MES | B34: ENERO | C34: FEBRERO | D34: MARZO | E34: ABRIL | F34: MAYO | G34: JUNIO | H34: JULIO | I34: AGOSTO | J34: SEPTIEMBRE | K34: OCTUBRE | L34: NOVIEMBRE | M34: DICIEMBRE
A35: MONTO | B35: ='DEUDAS, RECAUDADO Y PROYECTADO'!U206 -> 15510435 | C35: ='DEUDAS, RECAUDADO Y PROYECTADO'!V206 -> 9265750 | D35: ='DEUDAS, RECAUDADO Y PROYECTADO'!W206 -> 0 | E35: ='DEUDAS, RECAUDADO Y PROYECTADO'!X206 -> 0 | F35: ='DEUDAS, RECAUDADO Y PROYECTADO'!Y206 -> 0 | G35: ='DEUDAS, RECAUDADO Y PROYECTADO'!Z206 -> 0 | H35: ='DEUDAS, RECAUDADO Y PROYECTADO'!AA206 -> 0 | I35: ='DEUDAS, RECAUDADO Y PROYECTADO'!AB206 -> 0 | ... M35: ='DEUDAS, RECAUDADO Y PROYECTADO'!AF206 -> 0
A36: PROYECCIONES MENSUALES
A37: MES | B37: ENERO | C37: FEBRERO | D37: MARZO | E37: ABRIL | F37: MAYO | G37: JUNIO | H37: JULIO | I37: AGOSTO | J37: SEPTIEMBRE | K37: OCTUBRE | L37: NOVIEMBRE | M37: DICIEMBRE
A38: MONTO | B38: ='DEUDAS, RECAUDADO Y PROYECTADO'!AL207 -> 29674815 | C38: ='DEUDAS, RECAUDADO Y PROYECTADO'!AM207 -> 30038615 | D38: ='DEUDAS, RECAUDADO Y PROYECTADO'!AN207 -> 0 | E38: ='DEUDAS, RECAUDADO Y PROYECTADO'!AO207 -> 0 | F38: ='DEUDAS, RECAUDADO Y PROYECTADO'!AP207 -> 0 | G38: ='DEUDAS, RECAUDADO Y PROYECTADO'!AQ207 -> 0 | H38: ='DEUDAS, RECAUDADO Y PROYECTADO'!AR207 -> 0 | I38: ='DEUDAS, RECAUDADO Y PROYECTADO'!AS207 -> 0 | ... M38: ='DEUDAS, RECAUDADO Y PROYECTADO'!AW207 -> 0
G39: SALDO
A40: MES | B40: ENERO | C40: FEBRERO | D40: MARZO | E40: ABRIL | F40: MAYO | G40: JUNIO | H40: JULIO | I40: AGOSTO | J40: SEPTIEMBRE | K40: OCTUBRE | L40: NOVIEMBRE | M40: DICIEMBRE
A41: TOTAL | B41: ='DEUDAS, RECAUDADO Y PROYECTADO'!D206 -> 10719235 | C41: =C38-C35 -> 20772865 | D41: =D38-D35 -> 0 | E41: =E38-E35 -> 0 | F41: =F38-F35 -> 0 | G41: =G38-G35 -> 0 | H41: =H38-H35 -> 0 | I41: =I38-I35 -> 0 | J41: =J38-J35 -> 0 | ... M41: =M38-M35 -> 0 | N41: =SUM(B41:M41) -> 31492100
A42: % DE MOROSIDAD | B42: =B41/B38 -> 0.36122331 | C42: =C41/C38 -> 0.69153871 | D42: =D41/D38 -> #DIV/0! | E42: =E41/E38 -> #DIV/0! | F42: =F41/F38 -> #DIV/0! | G42: =G41/G38 -> #DIV/0! | H42: =H41/H38 -> #DIV/0! | I42: =I41/I38 -> #DIV/0! | ... M42: =M41/M38 -> #DIV/0! | N42: =AVERAGE(B42:M42) -> #DIV/0!
A45: GASTOS MENSUALES | N45: TOTAL | O45: PROMEDIO
A46: MES | B46: ENERO | C46: FEBRERO | D46: MARZO | E46: ABRIL | F46: MAYO | G46: JUNIO | H46: JULIO | I46: AGOSTO | J46: SEPTIEMBRE | K46: OCTUBRE | L46: NOVIEMBRE | M46: DICIEMBRE
A47: MONTO | B47: =GASTOS!B36 -> 23512839 | C47: =GASTOS!U36 -> 0 | D47: =GASTOS!AN36 -> 0 | E47: =GASTOS!BG36 -> 0 | F47: =GASTOS!BZ36 -> 0 | G47: =GASTOS!CS36 -> 0 | H47: =GASTOS!B80 -> 0 | I47: =GASTOS!U80 -> 0 | J47: =GASTOS!AN80 -> 0 | K47: 0 | L47: =GASTOS!BZ80 -> 0 | M47: =GASTOS!CS80 -> 0 | N47: =SUM(B47:M47) -> 23512839 | O47: =N47/12 -> 1959403.2
A48: GANANCIAS MENSUALES
A49: MES | B49: ENERO | C49: FEBRERO | D49: MARZO | E49: ABRIL | F49: MAYO | G49: JUNIO | H49: JULIO | I49: AGOSTO | J49: SEPTIEMBRE | K49: OCTUBRE | L49: NOVIEMBRE | M49: DICIEMBRE
A50: MONTO | B50: =B35-B47 -> -8002403.6 | C50: =C35-C47 -> 9265750 | D50: =D35-D47 -> 0 | E50: =E35-E47 -> 0 | F50: =F35-F47 -> 0 | G50: =G35-G47 -> 0 | H50: =H35-H47 -> 0 | I50: =I35-I47 -> 0 | ... M50: =M35-M47 -> 0 | N50: =SUM(B50:M50) -> 1263346.4 | O50: =N50/12 -> 105278.87
L51: =L38-L47 -> 0 | M51: =M38-M47 -> 0
A54: Recaudacion | C54: Saldo | J54: Gastos | K54: Gastos/Fact
A55: Enero | B55: =B35 -> 15510435 | C55: =B41 -> 10719235 | I55: Enero | J55: =B47 -> 23512839 | K55: =(J55*100)/B55 -> 151.59368
A56: Febrero | B56: =C35 -> 9265750 | C56: =C41 -> 20772865 | I56: Febrero | J56: =C47 -> 0 | K56: =(J56*100)/B56 -> 0
A57: Marzo | B57: =D35 -> 0 | C57: =D41 -> 0 | I57: Marzo | J57: =D47 -> 0 | K57: =(J57*100)/B57 -> #DIV/0!
A58: Abril | B58: =E35 -> 0 | C58: =E41 -> 0 | I58: Abril | J58: =E47 -> 0 | K58: =(J58*100)/B58 -> #DIV/0!
A59: Mayo | B59: =F35 -> 0 | C59: =F41 -> 0 | I59: Mayo | J59: =F47 -> 0 | K59: =(J59*100)/B59 -> #DIV/0!
A60: Junio | B60: =G35 -> 0 | C60: =G41 -> 0 | I60: Junio | J60: =G47 -> 0 | K60: =(J60*100)/B60 -> #DIV/0!
A61: Julio | B61: =H35 -> 0 | C61: =H41 -> 0 | I61: Julio | J61: =H47 -> 0 | K61: =(J61*100)/B61 -> #DIV/0!
A62: Agosto | B62: =I35 -> 0 | C62: =I41 -> 0 | I62: Agosto | J62: =I47 -> 0 | K62: =(J62*100)/B62 -> #DIV/0!
A63: Septiembre | B63: =J35 -> 0 | C63: =J41 -> 0 | I63: Septiembre | J63: =J47 -> 0 | K63: =(J63*100)/B63 -> #DIV/0!
A64: Octubre | B64: =K35 -> 0 | C64: =K41 -> 0 | I64: Octubre | J64: =K47 -> 0 | K64: =(J64*100)/B64 -> #DIV/0!
A65: Noviembre | B65: =L35 -> 0 | C65: =L41 -> 0 | I65: Noviembre | J65: =L47 -> 0 | K65: =(J65*100)/B65 -> #DIV/0!
A66: Diciembre | B66: =M35 -> 0 | C66: =M41 -> 0 | I66: Diciembre | J66: =M47 -> 0 | K66: =(J66*100)/B66 -> #DIV/0!
A67: Anual | B67: =SUM(B55:B66) -> 24776185 | I67: Anual | J67: =SUM(J55:J66) -> 23512839 | K67: =SUM(K55:K66)/5 -> #DIV/0!
A68: Promedio mens | B68: =B67/6 -> 4129364.2 | I68: Promedio mens | J68: =J67/5 -> 4702567.7
B73: Ganancias | C73: Util/fact
A74: Enero | B74: =B50 -> -8002403.6 | C74: =(B74*100)/B55 -> -51.593676
A75: Febrero | B75: =C50 -> 9265750 | C75: =(B75*100)/B56 -> 100
A76: Marzo | B76: =D50 -> 0 | C76: =(B76*100)/B57 -> #DIV/0!
A77: Abril | B77: =E50 -> 0 | C77: =(B77*100)/B58 -> #DIV/0!
A78: Mayo | B78: =F50 -> 0 | C78: =(B78*100)/B59 -> #DIV/0!
A79: Junio | B79: =G50 -> 0 | C79: =(B79*100)/B60 -> #DIV/0!
A80: Julio | B80: =H50 -> 0 | C80: =(B80*100)/B61 -> #DIV/0!
A81: Agosto | B81: =I50 -> 0 | C81: =(B81*100)/B62 -> #DIV/0!
A82: Septiembre | B82: =J50 -> 0 | C82: =(B82*100)/B63 -> #DIV/0!
A83: Octubre | B83: =K50 -> 0 | C83: =(B83*100)/B64 -> #DIV/0!
A84: Noviembre | B84: =L50 -> 0 | C84: =(B84*100)/B65 -> #DIV/0!
A85: Diciembre | B85: =M50 -> 0 | C85: =(B85*100)/B66 -> #DIV/0!
A86: Anual | B86: =SUM(B74:B85) -> 1263346.4 | C86: =(B86*100)/B67 -> 5.0990351
A87: Promedio mens | B87: =B86/5 -> 252669.28

Sheet DEUDAS, RECAUDADO Y PROYECTADO
A1: ='DEUDAS, RECAUDADO Y PROYECTADO'!AL105='DEUDAS, RECAUDADO Y PROYECTADO'!AL105 -> TRUE
A2: SALDO | R2: RECAUDADO | AI2: PROYECTADO
A3: CONCEPTO | B3: NRO | C3: LOCATARIO | D3: ENERO | E3: FEBRERO | F3: MARZO | G3: ABRIL | H3: MAYO | I3: JUNIO | J3: JULIO | K3: AGOSTO | L3: SEPTIEMBRE | M3: OCTUBRE | N3: NOVIEMBRE | O3: DICIEMBRE | P3: TOTAL | R3: CONCEPTO | S3: NRO | T3: LOCATARIO | U3: ENERO | V3: FEBRERO | W3: MARZO | X3: ABRIL | Y3: MAYO | Z3: JUNIO | AA3: JULIO | AB3: AGOSTO | AC3: SEPTIEMBRE | AD3: OCTUBRE | AE3: NOVIEMBRE | AF3: DICIEMBRE | AG3: TOTAL | AI3: CONCEPTO | AJ3: NRO | AK3: LOCATARIO | AL3: ENERO | AM3: FEBRERO | AN3: MARZO | AO3: ABRIL | AP3: MAYO | AQ3: JUNIO | AR3: JULIO | AS3: AGOSTO | AT3: SEPTIEMBRE | AU3: OCTUBRE | AV3: NOVIEMBRE | AW3: DICIEMBRE | AX3: TOTAL
A4: Puestos | B4: 1 | C4: Hernan Nielsen | D4: =[1]P001!$K$5 -> 0 | E4: =[1]P001!$K$6 -> 0 | P4: =SUM(Tabla6[[#This Row],[ENERO]:[DICIEMBRE]]) -> 0 | R4: Puestos | S4: 1 | T4: Hernan Nielsen | U4: =[1]P001!$L$5 -> 1183800 | V4: =[1]P001!$L$6 -> 1183800 | W4: 0 | X4: 0 | Y4: 0 | Z4: 0 | AA4: 0 | AB4: 0 | AC4: 0 | AD4: 0 | AE4: 0 | AF4: 0 | AG4: =SUM(Tabla63[[#This Row],[ENERO]:[DICIEMBRE]]) -> 2367600 | AI4: Puestos | AJ4: 1 | AK4: Hernan Nielsen | AL4: =[2]P001!$B$5 -> 1183800 | AM4: =[1]P001!$B$6 -> 1183800 | AN4: 0 | AO4: 0 | AP4: 0 | AQ4: 0 | AR4: 0 | AS4: 0 | AT4: 0 | AU4: 0 | AV4: 0 | AW4: 0 | AX4: =SUM(Tabla634[[#This Row],[ENERO]:[DICIEMBRE]]) -> 2367600
A5: Puestos | B5: 2 | D5: =[1]P001!$K$5 -> 0 | E5: =[1]P001!$K$5 -> 0 | P5: =SUM(Tabla6[[#This Row],[ENERO]:[DICIEMBRE]]) -> 0 | R5: Puestos | S5: 2 | U5: =[3]P002!$L$5 -> 0 | V5: =[3]P002!$L$5 -> 0 | X5: =[3]P002!$L$8 -> 0 | Y5: =[3]P002!$L$9 -> 0 | Z5: 0 | AA5: 0 | AB5: 0 | AC5: 0 | AD5: 0 | AE5: 0 | AF5: 0 | AG5: =SUM(Tabla63[[#This Row],[ENERO]:[DICIEMBRE]]) -> 0 | AI5: Puestos | AJ5: 2 | AL5: 0 | AM5: =[1]P001!$B$6 -> 1183800 | AN5: 0 | AO5: 0 | AP5: 0 | AQ5: 0 | AR5: 0 | AS5: 0 | AT5: 0 | AU5: 0 | AV5: 0 | AW5: 0 | AX5: =SUM(Tabla634[[#This Row],[ENERO]:[DICIEMBRE]]) -> 1183800
A6: Puestos | B6: 3 | D6: =[1]P001!$K$5 -> 0 | E6: =[1]P001!$K$5 -> 0 | P6: =SUM(Tabla6[[#This Row],[ENERO]:[DICIEMBRE]]) -> 0 | R6: Puestos | S6: 3 | U6: =[3]P003!$L$5 -> 0 | V6: =[3]P003!$L$5 -> 0 | X6: =[3]P003!$L$8 -> 0 | Y6: =[3]P003!$L$9 -> 0 | Z6: 0 | AA6: 0 | AB6: 0 | AC6: 0 | AD6: 0 | AE6: 0 | AF6: 0 | AG6: =SUM(Tabla63[[#This Row],[ENERO]:[DICIEMBRE]]) -> 0 | AI6: Puestos | AJ6: 3 | AL6: 0 | AM6: =[1]P001!$B$6 -> 1183800 | AN6: 0 | AO6: 0 | AP6: 0 | AQ6: 0 | AR6: 0 | AS6: 0 | AT6: 0 | AU6: 0 | AV6: 0 | AW6: 0 | AX6: =SUM(Tabla634[[#This Row],[ENERO]:[DICIEMBRE]]) -> 1183800
A7: Puestos | B7: 4 | C7: Andrea | D7: =[1]P004!$K$5 -> 0 | E7: =[1]P004!$K$5 -> 0 | P7: =SUM(Tabla6[[#This Row],[ENERO]:[DICIEMBRE]]) -> 0 | R7: Puestos | S7: 4 | T7: Andrea | U7: =[1]P005!$L$5 -> 177600 | V7: =[1]P005!$L$5 -> 177600 | X7: 0 | Y7: 0 | Z7: 0 | AA7: 0 | AB7: 0 | AC7: 0 | AD7: 0 | AE7: 0 | AF7: 0 | AG7: =SUM(Tabla63[[#This Row],[ENERO]:[DICIEMBRE]]) -> 355200 | AI7: Puestos | AJ7: 4 | AK7: Andrea | AL7: 0 | AM7: =[1]P001!$B$6 -> 1183800 | AN7: 0 | AO7: 0 | AP7: 0 | AQ7: 0 | AR7: 0 | AS7: 0 | AT7: 0 | AU7: 0 | AV7: 0 | AW7: 0 | AX7: =SUM(Tabla634[[#This Row],[ENERO]:[DICIEMBRE]]) -> 1183800
A8: Puestos | B8: 5 | C8: Huber Ursula | D8: =[1]P005!$K$5 -> 0 | E8: =[1]P005!$K$6 -> 0 | P8: =SUM(Tabla6[[#This Row],[ENERO]:[DICIEMBRE]]) -> 0 | R8: Puestos | S8: 5 | T8: Huber Ursula | U8: =[1]P005!$L$5 -> 177600 | V8: =[1]P005!$L$6 -> 177600 | X8: 0 | Y8: 0 | Z8: 0 | AA8: 0 | AB8: 0 | AC8: 0 | AD8: 0 | AE8: 0 | AF8: 0 | AG8: =SUM(Tabla63[[#This Row],[ENERO]:[DICIEMBRE]]) -> 355200 | AI8: Puestos | AJ8: 5 | AK8: Huber Ursula | AL8: =[2]P005!$B$5 -> 177600 | AM8: =[1]P005!$B$6 -> 177600 | AN8: 0 | AO8: 0 | AP8: 0 | AQ8: 0 | AR8: 0 | AS8: 0 | AT8: 0 | AU8: 0 | AV8: 0 | AW8: 0 | AX8: =SUM(Tabla634[[#This Row],[ENERO]:[DICIEMBRE]]) -> 355200
A9: Puestos | B9: 6 | C9: Rosalina Paniagua | D9: =[1]P006!$K$5 -> 0 | E9: =[1]P006!$K$6 -> 177600 | P9: =SUM(Tabla6[[#This Row],[ENERO]:[DICIEMBRE]]) -> 177600 | R9: Puestos | S9: 6 | T9: Rosalina Paniagua | U9: =[1]P006!$L$5 -> 177600 | V9: =[1]P006!$L$6 -> 0 | X9: 0 | Y9: 0 | Z9: 0 | AA9: 0 | AB9: 0 | AC9: 0 | AD9: 0 | AE9: 0 | AF9: 0 | AG9: =SUM(Tabla63[[#This Row],[ENERO]:[DICIEMBRE]]) -> 177600 | AI9: Puestos | AJ9: 6 | AK9: Rosalina Paniagua | AL9: =[2]P006!$B$5 -> 177600 | AM9: =[1]P006!$B$6 -> 177600 | AN9: 0 | AO9: 0 | AP9: 0 | AQ9: 0 | AR9: 0 | AS9: 0 | AT9: 0 | AU9: 0 | AV9: 0 | AW9: 0 | AX9: =SUM(Tabla634[[#This Row],[ENERO]:[DICIEMBRE]]) -> 355200
A10: Puestos | B10: 7 | D10: =[1]P001!$K$5 -> 0 | E10: =[1]P001!$K$5 -> 0 | P10: =SUM(Tabla6[[#This Row],[ENERO]:[DICIEMBRE]]) -> 0 | R10: Puestos | S10: 7 | U10: =[3]P007!$L$5 -> 0 | V10: =[3]P007!$L$5 -> 0 | X10: =[3]P007!$L$8 -> 0 | Y10: =[3]P007!$L$9 -> 0 | Z10: 0 | AA10: 0 | AB10: 0 | AC10: 0 | AD10: 0 | AE10: 0 | AF10: 0 | AG10: =SUM(Tabla63[[#This Row],[ENERO]:[DICIEMBRE]]) -> 0 | AI10: Puestos | AJ10: 7 | AL10: 0 | AM10: =[1]P005!$B$6 -> 177600 | AN10: 0 | AO10: 0 | AP10: 0 | AQ10: 0 | AR10: 0 | AS10: 0 | AT10: 0 | AU10: 0 | AV10: 0 | AW10: 0 | AX10: =SUM(Tabla634[[#This Row],[ENERO]:[DICIEMBRE]]) -> 177600
A11: Puestos | B11: 8 | C11: Ruiz Dia Paola | D11: =[1]P008!$K$5 -> 0 | E11: =[1]P008!$K$6 -> 0 | P11: =SUM(Tabla6[[#This Row],[ENERO]:[DICIEMBRE]]) -> 0 | R11: Puestos | S11: 8 | T11: Ruiz Dia Paola | U11: =[1]P008!$L$5 -> 355300 | V11: =[1]P008!$L$6 -> 355300 | X11: 0 | Y11: 0 | Z11: 0 | AA11: 0 | AB11: 0 | AC11: 0 | AD11: 0 | AE11: 0 | AF11: 0 | AG11: =SUM(Tabla63[[#This Row],[ENERO]:[DICIEMBRE]]) -> 710600 | AI11: Puestos | AJ11: 8 | AK11: Ruiz Dia Paola | AL11: =[2]P008!$B$5 -> 355300 | AM11: =[1]P008!$B$6 -> 355300 | AN11: 0 | AO11: 0 | AP11: 0 | AQ11: 0 | AR11: 0 | AS11: 0 | AT11: 0 | AU11: 0 | AV11: 0 | AW11: 0 | AX11: =SUM(Tabla634[[#This Row],[ENERO]:[DICIEMBRE]]) -> 710600
A12: Puestos | B12: 9 | D12: =[1]P001!$K$5 -> 0 | E12: =[1]P001!$K$5 -> 0 | P12: =SUM(Tabla6[[#This Row],[ENERO]:[DICIEMBRE]]) -> 0 | R12: Puestos | S12: 9 | U12: =[3]P009!$L$5 -> 0 | V12: =[3]P009!$L$5 -> 0 | X12: =[3]P009!$L$8 -> 0 | Y12: =[3]P009!$L$9 -> 0 | Z12: 0 | AA12: 0 | AB12: 0 | AC12: 0 | AD12: 0 | AE12: 0 | AF12: 0 | AG12: =SUM(Tabla63[[#This Row],[ENERO]:[DICIEMBRE]]) -> 0 | AI12: Puestos | AJ12: 9 | AK12: Benitez nestor | AL12: 0 | AM12: =[1]P005!$B$6 -> 177600 | AN12: 0 | AO12: 0 | AP12: 0 | AQ12: 0 | AR12: 0 | AS12: 0 | AT12: 0 | AU12: 0 | AV12: 0 | AW12: 0 | AX12: =SUM(Tabla634[[#This Row],[ENERO]:[DICIEMBRE]]) -> 177600
A13: Puestos | B13: 10 | C13: Ferreira Isabella | D13: =[1]P010!$K$5 -> 532800 | E13: =[1]P010!$K$5 -> 532800 | P13: =SUM(Tabla6[[#This Row],[ENERO]:[DICIEMBRE]]) -> 1065600 | R13: Puestos | S13: 10 | T13: Ferreira Isabella | U13: =[1]P010!$L$5 -> 0 | V13: =[1]P010!$L$6 -> 0 | X13: 0 | Y13: 0 | Z13: 0 | AA13: 0 | AB13: 0 | AC13: 0 | AD13: 0 | AE13: 0 | AF13: 0 | AG13: =SUM(Tabla63[[#This Row],[ENERO]:[DICIEMBRE]]) -> 0 | AI13: Puestos | AJ13: 10 | AK13: Ferreira Isabella | AL13: =[2]P010!$B$5 -> 532800 | AM13: =[1]P010!$B$6 -> 532800 | AN13: 0 | AO13: 0 | AP13: 0 | AQ13: 0 | AR13: 0 | AS13: 0 | AT13: 0 | AU13: 0 | AV13: 0 | AW13: 0 | AX13: =SUM(Tabla634[[#This Row],[ENERO]:[DICIEMBRE]]) -> 1065600
A14: Puestos | B14: 11 | D14: =[1]P001!$K$5 -> 0 | E14: =[1]P001!$K$5 -> 0 | P14: =SUM(Tabla6[[#This Row],[ENERO]:[DICIEMBRE]]) -> 0 | R14: Puestos | S14: 11 | U14: =[3]P011!$L$5 -> 0 | V14: =[3]P011!$L$5 -> 0 | X14: =[3]P011!$L$8 -> 0 | Y14: =[3]P011!$L$9 -> 0 | Z14: 0 | AA14: 0 | AB14: 0 | AC14: 0 | AD14: 0 | AE14: 0 | AF14: 0 | AG14: =SUM(Tabla63[[#This Row],[ENERO]:[DICIEMBRE]]) -> 0 | AI14: Puestos | AJ14: 11 | AL14: 0 | AM14: =[1]P005!$B$6 -> 177600 | AN14: 0 | AO14: 0 | AP14: 0 | AQ14: 0 | AR14: 0 | AS14: 0 | AT14: 0 | AU14: 0 | AV14: 0 | AW14: 0 | AX14: =SUM(Tabla634[[#This Row],[ENERO]:[DICIEMBRE]]) -> 177600
A15: Puestos | B15: 12 | C15: Chuchi | D15: =[1]P012!$K$5 -> 0 | E15: =[1]P012!$K$6 -> 0 | P15: =SUM(Tabla6[[#This Row],[ENERO]:[DICIEMBRE]]) -> 0 | R15: Puestos | S15: 12 | T15: Chuchi | U15: =[1]P012!$L$5 -> 1821900 | V15: =[1]P012!$L$6 -> 1821900 | X15: 0 | Y15: 0 | Z15: 0 | AA15: 0 | AB15: 0 | AC15: 0 | AD15: 0 | AE15: 0 | AF15: 0 | AG15: =SUM(Tabla63[[#This Row],[ENERO]:[DICIEMBRE]]) -> 3643800 | AI15: Puestos | AJ15: 12 | AK15: Chuchi | AL15: =[2]P012!$B$5 -> 1821900 | AM15: =[1]P012!$B$6 -> 1821900 | AN15: 0 | AO15: 0 | AP15: 0 | AQ15: 0 | AR15: 0 | AS15: 0 | AT15: 0 | AU15: 0 | AV15: 0 | AW15: 0 | AX15: =SUM(Tabla634[[#This Row],[ENERO]:[DICIEMBRE]]) -> 3643800
A16: Puestos | B16: 13 | C16: Fabiana | D16: =[1]P001!$K$5 -> 0 | E16: =[1]P001!$K$5 -> 0 | P16: =SUM(Tabla6[[#This Row],[ENERO]:[DICIEMBRE]]) -> 0 | R16: Puestos | S16: 13 | T16: Fabiana | U16: =[3]P013!$L$5 -> 163200 | V16: =[3]P013!$L$5 -> 163200 | X16: =[3]P013!$L$8 -> 257500 | Y16: =[3]P013!$L$9 -> 257500 | Z16: 0 | AA16: 0 | AB16: 0 | AC16: 0 | AD16: 0 | AE16: 0 | AF16: 0 | AG16: =SUM(Tabla63[[#This Row],[ENERO]:[DICIEMBRE]]) -> 841400 | AI16: Puestos | AJ16: 13 | AK16: Fabiana | AL16: 0 | AM16: =[1]P005!$B$6 -> 177600 | AN16: 0 | AO16: 0 | AP16: 0 | AQ16: 0 | AR16: 0 | AS16: 0 | AT16: 0 | AU16: 0 | AV16: 0 | AW16: 0 | AX16: =SUM(Tabla634[[#This Row],[ENERO]:[DICIEMBRE]]) -> 177600
A17: Puestos | B17: 14 | D17: =[1]P001!$K$5 -> 0 | E17: =[1]P001!$K$5 -> 0 | P17: =SUM(Tabla6[[#This Row],[ENERO]:[DICIEMBRE]]) -> 0 | R17: Puestos | S17: 14 | U17: =[3]P014!$L$5 -> 0 | V17: =[3]P014!$L$5 -> 0 | X17: =[3]P014!$L$8 -> 0 | Y17: =[3]P014!$L$9 -> 0 | Z17: 0 | AA17: 0 | AB17: 0 | AC17: 0 | AD17: 0 | AE17: 0 | AF17: 0 | AG17: =SUM(Tabla63[[#This Row],[ENERO]:[DICIEMBRE]]) -> 0 | AI17: Puestos | AJ17: 14 | AL17: 0 | AM17: =[1]P005!$B$6 -> 177600 | AN17: 0 | AO17: 0 | AP17: 0 | AQ17: 0 | AR17: 0 | AS17: 0 | AT17: 0 | AU17: 0 | AV17: 0 | AW17: 0 | AX17: =SUM(Tabla634[[#This Row],[ENERO]:[DICIEMBRE]]) -> 177600
A18: Puestos | B18: 15 | D18: =[1]P001!$K$5 -> 0 | E18: =[1]P001!$K$5 -> 0 | P18: =SUM(Tabla6[[#This Row],[ENERO]:[DICIEMBRE]]) -> 0 | R18: Puestos | S18: 15 | U18: =[3]P015!$L$5 -> 22750 | V18: =[3]P015!$L$5 -> 22750 | X18: =[3]P015!$L$8 -> 0 | Y18: =[3]P015!$L$9 -> 0 | Z18: 0 | AA18: 0 | AB18: 0 | AC18: 0 | AD18: 0 | AE18: 0 | AF18: 0 | AG18: =SUM(Tabla63[[#This Row],[ENERO]:[DICIEMBRE]]) -> 45500 | AI18: Puestos | AJ18: 15 | AL18: 0 | AM18: =[1]P005!$B$6 -> 177600 | AN18: 0 | AO18: 0 | AP18: 0 | AQ18: 0 | AR18: 0 | AS18: 0 | AT18: 0 | AU18: 0 | AV18: 0 | AW18: 0 | AX18: =SUM(Tabla634[[#This Row],[ENERO]:[DICIEMBRE]]) -> 177600
A19: Puestos | B19: 16 | C19: Maiadana Norberto | D19: =[1]PO16!$K$5 -> 710600 | E19: =[1]PO16!$K$6 -> 710600 | P19: =SUM(Tabla6[[#This Row],[ENERO]:[DICIEMBRE]]) -> 1421200 | R19: Puestos | S19: 16 | T19: Maiadana Norberto | U19: =[1]PO16!$L$5 -> 0 | V19: =[1]PO16!$L$6 -> 0 | X19: 0 | Y19: 0 | Z19: 0 | AA19: 0 | AB19: 0 | AC19: 0 | AD19: 0 | AE19: 0 | AF19: 0 | AG19: =SUM(Tabla63[[#This Row],[ENERO]:[DICIEMBRE]]) -> 0 | AI19: Puestos | AJ19: 16 | AK19: Maiadana Norberto | AL19: =[2]PO16!$B$5 -> 710600 | AM19: =[1]PO16!$B$6 -> 710600 | AN19: 0 | AO19: 0 | AP19: 0 | AQ19: 0 | AR19: 0 | AS19: 0 | AT19: 0 | AU19: 0 | AV19: 0 | AW19: 0 | AX19: =SUM(Tabla634[[#This Row],[ENERO]:[DICIEMBRE]]) -> 1421200
A20: Puestos | B20: 17 | C20: Yilda Franco | D20: =[1]P017!$K$5 -> 177600 | E20: =[1]P017!$K$6 -> 177600 | P20: =SUM(Tabla6[[#This Row],[ENERO]:[DICIEMBRE]]) -> 355200 | R20: Puestos | S20: 17 | T20: Yilda Franco | U20: =[1]P017!$L$5 -> 0 | V20: =[1]P017!$L$6 -> 0 | X20: 0 | Y20: 0 | Z20: 0 | AA20: 0 | AB20: 0 | AC20: 0 | AD20: 0 | AE20: 0 | AF20: 0 | AG20: =SUM(Tabla63[[#This Row],[ENERO]:[DICIEMBRE]]) -> 0 | AI20: Puestos | AJ20: 17 | AK20: Yilda Franco | AL20: =[2]P017!$B$5 -> 177600 | AM20: =[1]P017!$B$6 -> 177600 | AN20: 0 | AO20: 0 | AP20: 0 | AQ20: 0 | AR20: 0 | AS20: 0 | AT20: 0 | AU20: 0 | AV20: 0 | AW20: 0 | AX20: =SUM(Tabla634[[#This Row],[ENERO]:[DICIEMBRE]]) -> 355200
A21: Puestos | B21: 18 | D21: =[1]P001!$K$5 -> 0 | E21: =[1]P001!$K$5 -> 0 | P21: =SUM(Tabla6[[#This Row],[ENERO]:[DICIEMBRE]]) -> 0 | R21: Puestos | S21: 18 | U21: =[3]P018!$L$5 -> 0 | V21: =[3]P018!$L$5 -> 0 | X21: =[3]P018!$L$8 -> 0 | Y21: =[3]P018!$L$9 -> 0 | Z21: 0 | AA21: 0 | AB21: 0 | AC21: 0 | AD21: 0 | AE21: 0 | AF21: 0 | AG21: =SUM(Tabla63[[#This Row],[ENERO]:[DICIEMBRE]]) -> 0 | AI21: Puestos | AJ21: 18 | AL21: 0 | AM21: =[1]P005!$B$6 -> 177600 | AN21: 0 | AO21: 0 | AP21: 0 | AQ21: 0 | AR21: 0 | AS21: 0 | AT21: 0 | AU21: 0 | AV21: 0 | AW21: 0 | AX21: =SUM(Tabla634[[#This Row],[ENERO]:[DICIEMBRE]]) -> 177600
A22: Puestos | B22: 19 | D22: =[1]P001!$K$5 -> 0 | E22: =[1]P001!$K$5 -> 0 | P22: =SUM(Tabla6[[#This Row],[ENERO]:[DICIEMBRE]]) -> 0 | R22: Puestos | S22: 19 | U22: =[3]P019!$L$5 -> 0 | V22: =[3]P019!$L$5 -> 0 | X22: =[3]P019!$L$8 -> 0 | Y22: =[3]P019!$L$9 -> 0 | Z22: 0 | AA22: 0 | AB22: 0 | AC22: 0 | AD22: 0 | AE22: 0 | AF22: 0 | AG22: =SUM(Tabla63[[#This Row],[ENERO]:[DICIEMBRE]]) -> 0 | AI22: Puestos | AJ22: 19 | AL22: 0 | AM22: =[1]P005!$B$6 -> 177600 | AN22: 0 | AO22: 0 | AP22: 0 | AQ22: 0 | AR22: 0 | AS22: 0 | AT22: 0 | AU22: 0 | AV22: 0 | AW22: 0 | AX22: =SUM(Tabla634[[#This Row],[ENERO]:[DICIEMBRE]]) -> 177600
A23: Puestos | B23: 20 | D23: =[1]P001!$K$5 -> 0 | E23: =[1]P001!$K$5 -> 0 | P23: =SUM(Tabla6[[#This Row],[ENERO]:[DICIEMBRE]]) -> 0 | R23: Puestos | S23: 20 | U23: =[3]P020!$L$5 -> 0 | V23: =[3]P020!$L$5 -> 0 | X23: =[3]P020!$L$8 -> 0 | Y23: =[3]P020!$L$9 -> 0 | Z23: 0 | AA23: 0 | AB23: 0 | AC23: 0 | AD23: 0 | AE23: 0 | AF23: 0 | AG23: =SUM(Tabla63[[#This Row],[ENERO]:[DICIEMBRE]]) -> 0 | AI23: Puestos | AJ23: 20 | AL23: 0 | AM23: =[1]P005!$B$6 -> 177600 | AN23: 0 | AO23: 0 | AP23: 0 | AQ23: 0 | AR23: 0 | AS23: 0 | AT23: 0 | AU23: 0 | AV23: 0 | AW23: 0 | AX23: =SUM(Tabla634[[#This Row],[ENERO]:[DICIEMBRE]]) -> 177600
A24: Puestos | B24: 21 | C24: Osmar Gonzales | D24: =[1]P021!$K$5 -> 710435 | E24: =[1]P021!$K$6 -> 710435 | P24: =SUM(Tabla6[[#This Row],[ENERO]:[DICIEMBRE]]) -> 1420870 | R24: Puestos | S24: 21 | T24: Osmar Gonzales | U24: =[1]P021!$L$5 -> 710435 | V24: =[1]P021!$L$6 -> 0 | X24: 0 | Y24: 0 | Z24: 0 | AA24: 0 | AB24: 0 | AC24: 0 | AD24: 0 | AE24: 0 | AF24: 0 | AG24: =SUM(Tabla63[[#This Row],[ENERO]:[DICIEMBRE]]) -> 710435 | AI24: Puestos | AJ24: 21 | AK24: Osmar Gonzales | AL24: =[2]P021!$B$5 -> 710435 | AM24: =[1]P021!$B$6 -> 710435 | AN24: 0 | AO24: 0 | AP24: 0 | AQ24: 0 | AR24: 0 | AS24: 0 | AT24: 0 | AU24: 0 | AV24: 0 | AW24: 0 | AX24: =SUM(Tabla634[[#This Row],[ENERO]:[DICIEMBRE]]) -> 1420870
A25: Puestos | B25: 22 | D25: =[1]P001!$K$5 -> 0 | E25: =[1]P001!$K$5 -> 0 | P25: =SUM(Tabla6[[#This Row],[ENERO]:[DICIEMBRE]]) -> 0 | R25: Puestos | S25: 22 | U25: =[3]P022!$L$5 -> 0 | V25: =[3]P022!$L$5 -> 0 | X25: =[3]P022!$L$8 -> 0 | Y25: =[3]P022!$L$9 -> 0 | Z25: 0 | AA25: 0 | AB25: 0 | AC25: 0 | AD25: 0 | AE25: 0 | AF25: 0 | AG25: =SUM(Tabla63[[#This Row],[ENERO]:[DICIEMBRE]]) -> 0 | AI25: Puestos | AJ25: 22 | AL25: 0 | AM25: =[1]P005!$B$6 -> 177600 | AN25: 0 | AO25: 0 | AP25: 0 | AQ25: 0 | AR25: 0 | AS25: 0 | AT25: 0 | AU25: 0 | AV25: 0 | AW25: 0 | AX25: =SUM(Tabla634[[#This Row],[ENERO]:[DICIEMBRE]]) -> 177600
A26: Puestos | B26: 23 | D26: =[1]P001!$K$5 -> 0 | E26: =[1]P001!$K$5 -> 0 | P26: =SUM(Tabla6[[#This Row],[ENERO]:[DICIEMBRE]]) -> 0 | R26: Puestos | S26: 23 | U26: =[3]P023!$L$5 -> 110500 | V26: =[3]P023!$L$5 -> 110500 | X26: =[3]P023!$L$8 -> 110500 | Y26: =[3]P023!$L$9 -> 0 | Z26: 0 | AA26: 0 | AB26: 0 | AC26: 0 | AD26: 0 | AE26: 0 | AF26: 0 | AG26: =SUM(Tabla63[[#This Row],[ENERO]:[DICIEMBRE]]) -> 331500 | AI26: Puestos | AJ26: 23 | AL26: 0 | AM26: =[1]P005!$B$6 -> 177600 | AN26: 0 | AO26: 0 | AP26: 0 | AQ26: 0 | AR26: 0 | AS26: 0 | AT26: 0 | AU26: 0 | AV26: 0 | AW26: 0 | AX26: =SUM(Tabla634[[#This Row],[ENERO]:[DICIEMBRE]]) -> 177600
A27: Puestos | B27: 24 | C27: Riveros Mabel | D27: =[1]P024!$K$5 -> 0 | E27: =[1]P024!$K$6 -> 355200 | P27: =SUM(Tabla6[[#This Row],[ENERO]:[DICIEMBRE]]) -> 355200 | R27: Puestos | S27: 24 | T27: Riveros Mabel | U27: =[1]P024!$L$5 -> 13500 | V27: =[1]P024!$L$6 -> 0 | X27: 0 | Y27: 0 | Z27: 0 | AA27: 0 | AB27: 0 | AC27: 0 | AD27: 0 | AE27: 0 | AF27: 0 | AG27: =SUM(Tabla63[[#This Row],[ENERO]:[DICIEMBRE]]) -> 13500 | AI27: Puestos | AJ27: 24 | AK27: Riveros Mabel | AL27: =[2]P024!$B$5 -> 355200 | AM27: =[1]P024!$B$6 -> 355200 | AN27: 0 | AO27: 0 | AP27: 0 | AQ27: 0 | AR27: 0 | AS27: 0 | AT27: 0 | AU27: 0 | AV27: 0 | AW27: 0 | AX27: =SUM(Tabla634[[#This Row],[ENERO]:[DICIEMBRE]]) -> 710400
A28: Puestos | B28: 25 | C28: China | D28: =[1]P025!$K$5 -> 0 | E28: =[1]P025!$K$6 -> 177600 | P28: =SUM(Tabla6[[#This Row],[ENERO]:[DICIEMBRE]]) -> 177600 | R28: Puestos | S28: 25 | T28: China | U28: =[1]P025!$L$5 -> 177600 | V28: =[1]P025!$L$6 -> 0 | X28: 0 | Y28: 0 | Z28: 0 | AA28: 0 | AB28: 0 | AC28: 0 | AD28: 0 | AE28: 0 | AF28: 0 | AG28: =SUM(Tabla63[[#This Row],[ENERO]:[DICIEMBRE]]) -> 177600 | AI28: Puestos | AJ28: 25 | AK28: China | AL28: =[2]P025!$B$5 -> 177600 | AM28: =[1]P025!$B$6 -> 177600 | AN28: 0 | AO28: 0 | AP28: 0 | AQ28: 0 | AR28: 0 | AS28: 0 | AT28: 0 | AU28: 0 | AV28: 0 | AW28: 0 | AX28: =SUM(Tabla634[[#This Row],[ENERO]:[DICIEMBRE]]) -> 355200
A29: Puestos | B29: 26 | D29: =[1]P001!$K$5 -> 0 | E29: =[1]P001!$K$5 -> 0 | P29: =SUM(Tabla6[[#This Row],[ENERO]:[DICIEMBRE]]) -> 0 | R29: Puestos | S29: 26 | U29: =[3]P026!$L$5 -> 0 | X29: =[3]P026!$L$8 -> 0 | Y29: =[3]P026!$L$9 -> 0 | Z29: 0 | AA29: 0 | AB29: 0 | AC29: 0 | AD29: 0 | AE29: 0 | AF29: 0 | AG29: =SUM(Tabla63[[#This Row],[ENERO]:[DICIEMBRE]]) -> 0 | AI29: Puestos | AJ29: 26 | AL29: 0 | AM29: =[1]P005!$B$6 -> 177600 | AN29: 0 | AO29: 0 | AP29: 0 | AQ29: 0 | AR29: 0 | AS29: 0 | AT29: 0 | AU29: 0 | AV29: 0 | AW29: 0 | AX29: =SUM(Tabla634[[#This Row],[ENERO]:[DICIEMBRE]]) -> 177600
A30: Puestos | B30: 27 | D30: =[1]P001!$K$5 -> 0 | E30: =[1]P001!$K$5 -> 0 | P30: =SUM(Tabla6[[#This Row],[ENERO]:[DICIEMBRE]]) -> 0 | R30: Puestos | S30: 27 | U30: =[3]P027!$L$5 -> 0 | X30: =[3]P027!$L$8 -> 0 | Y30: =[3]P027!$L$9 -> 0 | Z30: 0 | AA30: 0 | AB30: 0 | AC30: 0 | AD30: 0 | AE30: 0 | AF30: 0 | AG30: =SUM(Tabla63[[#This Row],[ENERO]:[DICIEMBRE]]) -> 0 | AI30: Puestos | AJ30: 27 | AL30: 0 | AM30: =[1]P005!$B$6 -> 177600 | AN30: 0 | AO30: 0 | AP30: 0 | AQ30: 0 | AR30: 0 | AS30: 0 | AT30: 0 | AU30: 0 | AV30: 0 | AW30: 0 | AX30: =SUM(Tabla634[[#This Row],[ENERO]:[DICIEMBRE]]) -> 177600
A31: Puestos | B31: 28 | D31: =[1]P001!$K$5 -> 0 | E31: =[1]P001!$K$5 -> 0 | P31: =SUM(Tabla6[[#This Row],[ENERO]:[DICIEMBRE]]) -> 0 | R31: Puestos | S31: 28 | U31: =[3]P028!$L$5 -> 0 | X31: =[3]P028!$L$8 -> 0 | Y31: =[3]P028!$L$9 -> 0 | Z31: 0 | AA31: 0 | AB31: 0 | AC31: 0 | AD31: 0 | AE31: 0 | AF31: 0 | AG31: =SUM(Tabla63[[#This Row],[ENERO]:[DICIEMBRE]]) -> 0 | AI31: Puestos | AJ31: 28 | AL31: 0 | AM31: =[1]P005!$B$6 -> 177600 | AN31: 0 | AO31: 0 | AP31: 0 | AQ31: 0 | AR31: 0 | AS31: 0 | AT31: 0 | AU31: 0 | AV31: 0 | AW31: 0 | AX31: =SUM(Tabla634[[#This Row],[ENERO]:[DICIEMBRE]]) -> 177600
A32: Puestos | B32: 29 | D32: =[1]P001!$K$5 -> 0 | E32: =[1]P001!$K$5 -> 0 | P32: =SUM(Tabla6[[#This Row],[ENERO]:[DICIEMBRE]]) -> 0 | R32: Puestos | S32: 29 | U32: =[3]P029!$L$5 -> 0 | X32: =[3]P029!$L$8 -> 0 | Y32: =[3]P029!$L$9 -> 0 | Z32: 0 | AA32: 0 | AB32: 0 | AC32: 0 | AD32: 0 | AE32: 0 | AF32: 0 | AG32: =SUM(Tabla63[[#This Row],[ENERO]:[DICIEMBRE]]) -> 0 | AI32: Puestos | AJ32: 29 | AL32: 0 | AM32: =[1]P005!$B$6 -> 177600 | AN32: 0 | AO32: 0 | AP32: 0 | AQ32: 0 | AR32: 0 | AS32: 0 | AT32: 0 | AU32: 0 | AV32: 0 | AW32: 0 | AX32: =SUM(Tabla634[[#This Row],[ENERO]:[DICIEMBRE]]) -> 177600
A33: Puestos | B33: 30 | D33: =[1]P001!$K$5 -> 0 | E33: =[1]P001!$K$5 -> 0 | P33: =SUM(Tabla6[[#This Row],[ENERO]:[DICIEMBRE]]) -> 0 | R33: Puestos | S33: 30 | U33: =[3]P030!$L$5 -> 0 | X33: =[3]P030!$L$8 -> 0 | Y33: =[3]P030!$L$9 -> 0 | Z33: 0 | AA33: 0 | AB33: 0 | AC33: 0 | AD33: 0 | AE33: 0 | AF33: 0 | AG33: =SUM(Tabla63[[#This Row],[ENERO]:[DICIEMBRE]]) -> 0 | AI33: Puestos | AJ33: 30 | AL33: 0 | AM33: =[1]P005!$B$6 -> 177600 | AN33: 0 | AO33: 0 | AP33: 0 | AQ33: 0 | AR33: 0 | AS33: 0 | AT33: 0 | AU33: 0 | AV33: 0 | AW33: 0 | AX33: =SUM(Tabla634[[#This Row],[ENERO]:[DICIEMBRE]]) -> 177600
A34: Puestos | B34: 31 | C34: Ruben Camargo | D34: =[1]P031!$K$5 -> 0 | E34: =[1]P031!$K$6 -> 794200 | P34: =SUM(Tabla6[[#This Row],[ENERO]:[DICIEMBRE]]) -> 794200 | R34: Puestos | S34: 31 | T34: Ruben Camargo | U34: =[1]P031!$L$5 -> 2294100 | V34: =[1]P031!$L$6 -> 1499900 | X34: 0 | Y34: 0 | Z34: 0 | AA34: 0 | AB34: 0 | AC34: 0 | AD34: 0 | AE34: 0 | AF34: 0 | AG34: =SUM(Tabla63[[#This Row],[ENERO]:[DICIEMBRE]]) -> 3794000 | AI34: Puestos | AJ34: 31 | AK34: Ruben Camargo | AL34: =[2]P031!$B$5 -> 2294100 | AM34: =[1]P031!$B$6 -> 2294100 | AN34: 0 | AO34: 0 | AP34: 0 | AQ34: 0 | AR34: 0 | AS34: 0 | AT34: 0 | AU34: 0 | AV34: 0 | AW34: 0 | AX34: =SUM(Tabla634[[#This Row],[ENERO]:[DICIEMBRE]]) -> 4588200
A35: Puestos | B35: 32 | D35: =[1]P001!$K$5 -> 0 | E35: =[1]P001!$K$5 -> 0 | P35: =SUM(Tabla6[[#This Row],[ENERO]:[DICIEMBRE]]) -> 0 | R35: Puestos | S35: 32 | U35: =[3]P032!$L$5 -> 0 | V35: =[3]P032!$L$5 -> 0 | X35: =[3]P032!$L$8 -> 0 | Y35: =[3]P032!$L$9 -> 0 | Z35: 0 | AA35: 0 | AB35: 0 | AC35: 0 | AD35: 0 | AE35: 0 | AF35: 0 | AG35: =SUM(Tabla63[[#This Row],[ENERO]:[DICIEMBRE]]) -> 0 | AI35: Puestos | AJ35: 32 | AL35: 0 | AM35: =[1]P005!$B$6 -> 177600 | AN35: 0 | AO35: 0 | AP35: 0 | AQ35: 0 | AR35: 0 | AS35: 0 | AT35: 0 | AU35: 0 | AV35: 0 | AW35: 0 | AX35: =SUM(Tabla634[[#This Row],[ENERO]:[DICIEMBRE]]) -> 177600
A36: Puestos | B36: 33 | D36: =[1]P001!$K$5 -> 0 | E36: =[1]P001!$K$5 -> 0 | P36: =SUM(Tabla6[[#This Row],[ENERO]:[DICIEMBRE]]) -> 0 | R36: Puestos | S36: 33 | U36: =[3]P033!$L$5 -> 0 | V36: =[3]P033!$L$5 -> 0 | X36: =[3]P033!$L$8 -> 0 | Y36: =[3]P033!$L$9 -> 0 | Z36: 0 | AA36: 0 | AB36: 0 | AC36: 0 | AD36: 0 | AE36: 0 | AF36: 0 | AG36: =SUM(Tabla63[[#This Row],[ENERO]:[DICIEMBRE]]) -> 0 | AI36: Puestos | AJ36: 33 | AL36: 0 | AM36: =[1]P005!$B$6 -> 177600 | AN36: 0 | AO36: 0 | AP36: 0 | AQ36: 0 | AR36: 0 | AS36: 0 | AT36: 0 | AU36: 0 | AV36: 0 | AW36: 0 | AX36: =SUM(Tabla634[[#This Row],[ENERO]:[DICIEMBRE]]) -> 177600
A37: Puestos | B37: 34 | D37: =[1]P001!$K$5 -> 0 | E37: =[1]P001!$K$5 -> 0 | P37: =SUM(Tabla6[[#This Row],[ENERO]:[DICIEMBRE]]) -> 0 | R37: Puestos | S37: 34 | U37: =[3]P034!$L$5 -> 0 | V37: =[3]P034!$L$5 -> 0 | X37: =[3]P034!$L$8 -> 0 | Y37: =[3]P034!$L$9 -> 0 | Z37: 0 | AA37: 0 | AB37: 0 | AC37: 0 | AD37: 0 | AE37: 0 | AF37: 0 | AG37: =SUM(Tabla63[[#This Row],[ENERO]:[DICIEMBRE]]) -> 0 | AI37: Puestos | AJ37: 34 | AL37: 0 | AM37: =[1]P005!$B$6 -> 177600 | AN37: 0 | AO37: 0 | AP37: 0 | AQ37: 0 | AR37: 0 | AS37: 0 | AT37: 0 | AU37: 0 | AV37: 0 | AW37: 0 | AX37: =SUM(Tabla634[[#This Row],[ENERO]:[DICIEMBRE]]) -> 177600
A38: Puestos | B38: 35 | C38: Agurto Luis | D38: =[1]P001!$K$5 -> 0 | E38: =[1]P001!$K$5 -> 0 | P38: =SUM(Tabla6[[#This Row],[ENERO]:[DICIEMBRE]]) -> 0 | R38: Puestos | S38: 35 | T38: Agurto Luis | U38: =[3]P035!$L$5 -> 279300 | V38: =[3]P035!$L$5 -> 279300 | X38: =[3]P035!$L$8 -> 425000 | Y38: =[3]P035!$L$9 -> 276000 | Z38: 0 | AA38: 0 | AB38: 0 | AC38: 0 | AD38: 0 | AE38: 0 | AF38: 0 | AG38: =SUM(Tabla63[[#This Row],[ENERO]:[DICIEMBRE]]) -> 1259600 | AI38: Puestos | AJ38: 35 | AK38: Agurto Luis | AL38: 0 | AM38: =[1]P005!$B$6 -> 177600 | AN38: 0 | AO38: 0 | AP38: 0 | AQ38: 0 | AR38: 0 | AS38: 0 | AT38: 0 | AU38: 0 | AV38: 0 | AW38: 0 | AX38: =SUM(Tabla634[[#This Row],[ENERO]:[DICIEMBRE]]) -> 177600
A39: Puestos | B39: 36 | C39: Penayo Mariela | D39: =[1]PO37!$K$5 -> 177600 | E39: =[1]PO37!$K$6 -> 177600 | P39: =SUM(Tabla6[[#This Row],[ENERO]:[DICIEMBRE]]) -> 355200 | R39: Puestos | S39: 36 | T39: Cabrera Milka | U39: =[1]PO36!$L$5 -> 313000 | V39: =[1]PO36!$L$6 -> 0 | X39: 0 | Y39: 0 | Z39: 0 | AA39: 0 | AB39: 0 | AC39: 0 | AD39: 0 | AE39: 0 | AF39: 0 | AG39: =SUM(Tabla63[[#This Row],[ENERO]:[DICIEMBRE]]) -> 313000 | AI39: Puestos | AJ39: 36 | AK39: Cabrera Milka | AL39: =[2]PO36!$B$5 -> 355200 | AM39: =[1]P005!$B$6 -> 177600 | AN39: 0 | AO39: 0 | AP39: 0 | AQ39: 0 | AR39: 0 | AS39: 0 | AT39: 0 | AU39: 0 | AV39: 0 | AW39: 0 | AX39: =SUM(Tabla634[[#This Row],[ENERO]:[DICIEMBRE]]) -> 532800
A40: Puestos | B40: 37 | C40: Cabrera Milka | D40: =[1]PO36!$K$5 -> 42200 | E40: =[1]PO36!$K$6 -> 355200 | P40: =SUM(Tabla6[[#This Row],[ENERO]:[DICIEMBRE]]) -> 397400 | R40: Puestos | S40: 37 | T40: Penayo Gabriela | U40: =[1]PO37!$L$5 -> 0 | V40: =[1]PO37!$L$6 -> 0 | X40: 0 | Y40: 0 | Z40: 0 | AA40: 0 | AB40: 0 | AC40: 0 | AD40: 0 | AE40: 0 | AF40: 0 | AG40: =SUM(Tabla63[[#This Row],[ENERO]:[DICIEMBRE]]) -> 0 | AI40: Puestos | AJ40: 37 | AK40: Penayo Mariela | AL40: =[2]PO37!$B$5 -> 177600 | AM40: =[1]PO37!$B$6 -> 177600 | AN40: 0 | AO40: 0 | AP40: 0 | AQ40: 0 | AR40: 0 | AS40: 0 | AT40: 0 | AU40: 0 | AV40: 0 | AW40: 0 | AX40: =SUM(Tabla634[[#This Row],[ENERO]:[DICIEMBRE]]) -> 355200
A41: Puestos | B41: 38 | D41: =[1]P001!$K$5 -> 0 | E41: =[1]P001!$K$5 -> 0 | P41: =SUM(Tabla6[[#This Row],[ENERO]:[DICIEMBRE]]) -> 0 | R41: Puestos | S41: 38 | U41: =[3]P038!$L$5 -> 0 | V41: =[3]P038!$L$5 -> 0 | X41: =[3]P038!$L$8 -> 0 | Y41: =[3]P038!$L$9 -> 0 | Z41: 0 | AA41: 0 | AB41: 0 | AC41: 0 | AD41: 0 | AE41: 0 | AF41: 0 | AG41: =SUM(Tabla63[[#This Row],[ENERO]:[DICIEMBRE]]) -> 0 | AI41: Puestos | AJ41: 38 | AL41: 0 | AM41: =[1]P005!$B$6 -> 177600 | AN41: 0 | AO41: 0 | AP41: 0 | AQ41: 0 | AR41: 0 | AS41: 0 | AT41: 0 | AU41: 0 | AV41: 0 | AW41: 0 | AX41: =SUM(Tabla634[[#This Row],[ENERO]:[DICIEMBRE]]) -> 177600
A42: Puestos | B42: 39 | C42: Camargo Delia | D42: =[1]P039!$K$5 -> 1421200 | E42: =[1]P039!$K$6 -> 1421200 | P42: =SUM(Tabla6[[#This Row],[ENERO]:[DICIEMBRE]]) -> 2842400 | R42: Puestos | S42: 39 | T42: Camargo Delia | U42: =[1]P039!$L$5 -> 0 | V42: =[1]P039!$L$6 -> 0 | X42: 0 | Y42: 0 | Z42: 0 | AA42: 0 | AB42: 0 | AC42: 0 | AD42: 0 | AE42: 0 | AF42: 0 | AG42: =SUM(Tabla63[[#This Row],[ENERO]:[DICIEMBRE]]) -> 0 | AI42: Puestos | AJ42: 39 | AK42: Camargo Delia | AL42: =[2]P039!$B$5 -> 1421200 | AM42: =[1]P039!$B$6 -> 1421200 | AN42: 0 | AO42: 0 | AP42: 0 | AQ42: 0 | AR42: 0 | AS42: 0 | AT42: 0 | AU42: 0 | AV42: 0 | AW42: 0 | AX42: =SUM(Tabla634[[#This Row],[ENERO]:[DICIEMBRE]]) -> 2842400
A43: Puestos | B43: 40 | D43: =[1]P001!$K$5 -> 0 | E43: =[1]P001!$K$5 -> 0 | P43: =SUM(Tabla6[[#This Row],[ENERO]:[DICIEMBRE]]) -> 0 | R43: Puestos | S43: 40 | U43: =[3]P040!$L$5 -> 0 | V43: =[3]P040!$L$5 -> 0 | X43: =[3]P040!$L$8 -> 0 | Y43: =[3]P040!$L$9 -> 0 | Z43: 0 | AA43: 0 | AB43: 0 | AC43: 0 | AD43: 0 | AE43: 0 | AF43: 0 | AG43: =SUM(Tabla63[[#This Row],[ENERO]:[DICIEMBRE]]) -> 0 | AI43: Puestos | AJ43: 40 | AL43: 0 | AM43: =[1]P005!$B$6 -> 177600 | AN43: 0 | AO43: 0 | AP43: 0 | AQ43: 0 | AR43: 0 | AS43: 0 | AT43: 0 | AU43: 0 | AV43: 0 | AW43: 0 | AX43: =SUM(Tabla634[[#This Row],[ENERO]:[DICIEMBRE]]) -> 177600
A44: Puestos | B44: 41 | D44: =[1]P001!$K$5 -> 0 | E44: =[1]P001!$K$5 -> 0 | P44: =SUM(Tabla6[[#This Row],[ENERO]:[DICIEMBRE]]) -> 0 | R44: Puestos | S44: 41 | U44: =[3]P041!$L$5 -> 0 | V44: =[3]P041!$L$5 -> 0 | X44: =[3]P041!$L$8 -> 0 | Y44: =[3]P041!$L$9 -> 0 | Z44: 0 | AA44: 0 | AB44: 0 | AC44: 0 | AD44: 0 | AE44: 0 | AF44: 0 | AG44: =SUM(Tabla63[[#This Row],[ENERO]:[DICIEMBRE]]) -> 0 | AI44: Puestos | AJ44: 41 | AL44: 0 | AM44: =[1]P005!$B$6 -> 177600 | AN44: 0 | AO44: 0 | AP44: 0 | AQ44: 0 | AR44: 0 | AS44: 0 | AT44: 0 | AU44: 0 | AV44: 0 | AW44: 0 | AX44: =SUM(Tabla634[[#This Row],[ENERO]:[DICIEMBRE]]) -> 177600
A45: Puestos | B45: 42 | D45: =[1]P001!$K$5 -> 0 | E45: =[1]P001!$K$5 -> 0 | P45: =SUM(Tabla6[[#This Row],[ENERO]:[DICIEMBRE]]) -> 0 | R45: Puestos | S45: 42 | U45: =[3]P042!$L$5 -> 0 | V45: =[3]P042!$L$5 -> 0 | X45: =[3]P042!$L$8 -> 0 | Y45: =[3]P042!$L$9 -> 0 | Z45: 0 | AA45: 0 | AB45: 0 | AC45: 0 | AD45: 0 | AE45: 0 | AF45: 0 | AG45: =SUM(Tabla63[[#This Row],[ENERO]:[DICIEMBRE]]) -> 0 | AI45: Puestos | AJ45: 42 | AL45: 0 | AM45: =[1]P005!$B$6 -> 177600 | AN45: 0 | AO45: 0 | AP45: 0 | AQ45: 0 | AR45: 0 | AS45: 0 | AT45: 0 | AU45: 0 | AV45: 0 | AW45: 0 | AX45: =SUM(Tabla634[[#This Row],[ENERO]:[DICIEMBRE]]) -> 177600
A46: Puestos | B46: 43 | D46: =[1]P001!$K$5 -> 0 | E46: =[1]P001!$K$5 -> 0 | P46: =SUM(Tabla6[[#This Row],[ENERO]:[DICIEMBRE]]) -> 0 | R46: Puestos | S46: 43 | U46: =[3]P043!$L$5 -> 0 | V46: =[3]P043!$L$5 -> 0 | X46: =[3]P043!$L$8 -> 0 | Y46: =[3]P043!$L$9 -> 0 | Z46: 0 | AA46: 0 | AB46: 0 | AC46: 0 | AD46: 0 | AE46: 0 | AF46: 0 | AG46: =SUM(Tabla63[[#This Row],[ENERO]:[DICIEMBRE]]) -> 0 | AI46: Puestos | AJ46: 43 | AL46: 0 | AM46: =[1]P005!$B$6 -> 177600 | AN46: 0 | AO46: 0 | AP46: 0 | AQ46: 0 | AR46: 0 | AS46: 0 | AT46: 0 | AU46: 0 | AV46: 0 | AW46: 0 | AX46: =SUM(Tabla634[[#This Row],[ENERO]:[DICIEMBRE]]) -> 177600
A47: Puestos | B47: 44 | C47: Becker Sergio | D47: =[1]P001!$K$5 -> 0 | E47: =[1]P001!$K$5 -> 0 | P47: =SUM(Tabla6[[#This Row],[ENERO]:[DICIEMBRE]]) -> 0 | R47: Puestos | S47: 44 | T47: Becker Sergio | U47: =[3]P044!$L$5 -> 135800 | V47: =[3]P044!$L$5 -> 135800 | X47: =[3]P044!$L$8 -> 146000 | Y47: =[3]P044!$L$9 -> 138000 | Z47: 0 | AA47: 0 | AB47: 0 | AC47: 0 | AD47: 0 | AE47: 0 | AF47: 0 | AG47: =SUM(Tabla63[[#This Row],[ENERO]:[DICIEMBRE]]) -> 555600 | AI47: Puestos | AJ47: 44 | AK47: Benitez Margarita | AL47: 0 | AM47: =[1]P005!$B$6 -> 177600 | AN47: 0 | AO47: 0 | AP47: 0 | AQ47: 0 | AR47: 0 | AS47: 0 | AT47: 0 | AU47: 0 | AV47: 0 | AW47: 0 | AX47: =SUM(Tabla634[[#This Row],[ENERO]:[DICIEMBRE]]) -> 177600
A48: Puestos | B48: 45 | D48: =[1]P001!$K$5 -> 0 | E48: =[1]P001!$K$5 -> 0 | P48: =SUM(Tabla6[[#This Row],[ENERO]:[DICIEMBRE]]) -> 0 | R48: Puestos | S48: 45 | U48: =[3]P045!$L$5 -> 0 | V48: =[3]P045!$L$5 -> 0 | X48: =[3]P045!$L$8 -> 0 | Y48: =[3]P045!$L$9 -> 0 | Z48: 0 | AA48: 0 | AB48: 0 | AC48: 0 | AD48: 0 | AE48: 0 | AF48: 0 | AG48: =SUM(Tabla63[[#This Row],[ENERO]:[DICIEMBRE]]) -> 0 | AI48: Puestos | AJ48: 45 | AL48: 0 | AM48: =[1]P005!$B$6 -> 177600 | AN48: 0 | AO48: 0 | AP48: 0 | AQ48: 0 | AR48: 0 | AS48: 0 | AT48: 0 | AU48: 0 | AV48: 0 | AW48: 0 | AX48: =SUM(Tabla634[[#This Row],[ENERO]:[DICIEMBRE]]) -> 177600
A49: Puestos | B49: 46 | C49: Fernando | D49: =[1]P046!$K$5 -> 0 | E49: =[1]P046!$K$6 -> 535900 | P49: =SUM(Tabla6[[#This Row],[ENERO]:[DICIEMBRE]]) -> 535900 | R49: Puestos | S49: 46 | T49: Fernando | U49: =[1]P046!$L$5 -> 535900 | V49: =[1]P046!$L$6 -> 0 | X49: 0 | Y49: 0 | Z49: 0 | AA49: 0 | AB49: 0 | AC49: 0 | AD49: 0 | AE49: 0 | AF49: 0 | AG49: =SUM(Tabla63[[#This Row],[ENERO]:[DICIEMBRE]]) -> 535900 | AI49: Puestos | AJ49: 46 | AK49: Fernando | AL49: =[2]P046!$B$5 -> 535900 | AM49: =[1]P046!$B$6 -> 535900 | AN49: 0 | AO49: 0 | AP49: 0 | AQ49: 0 | AR49: 0 | AS49: 0 | AT49: 0 | AU49: 0 | AV49: 0 | AW49: 0 | AX49: =SUM(Tabla634[[#This Row],[ENERO]:[DICIEMBRE]]) -> 1071800
A50: Puestos | B50: 47 | D50: =[1]P001!$K$5 -> 0 | E50: =[1]P001!$K$5 -> 0 | P50: =SUM(Tabla6[[#This Row],[ENERO]:[DICIEMBRE]]) -> 0 | R50: Puestos | S50: 47 | U50: =[3]P047!$L$5 -> 0 | V50: =[3]P047!$L$5 -> 0 | X50: =[3]P047!$L$8 -> 0 | Y50: =[3]P047!$L$9 -> 0 | Z50: 0 | AA50: 0 | AB50: 0 | AC50: 0 | AD50: 0 | AE50: 0 | AF50: 0 | AG50: =SUM(Tabla63[[#This Row],[ENERO]:[DICIEMBRE]]) -> 0 | AI50: Puestos | AJ50: 47 | AL50: 0 | AM50: =[1]P005!$B$6 -> 177600 | AN50: 0 | AO50: 0 | AP50: 0 | AQ50: 0 | AR50: 0 | AS50: 0 | AT50: 0 | AU50: 0 | AV50: 0 | AW50: 0 | AX50: =SUM(Tabla634[[#This Row],[ENERO]:[DICIEMBRE]]) -> 177600
A51: Puestos | B51: 48 | C51: Paniagua Cristian | D51: =[1]P048!$K$5 -> 355200 | E51: =[1]P048!$K$6 -> 355200 | P51: =SUM(Tabla6[[#This Row],[ENERO]:[DICIEMBRE]]) -> 710400 | R51: Puestos | S51: 48 | T51: Paniagua Cristian | U51: =[1]P048!$L$5 -> 0 | V51: =[1]P048!$L$6 -> 0 | X51: 0 | Y51: 0 | Z51: 0 | AA51: 0 | AB51: 0 | AC51: 0 | AD51: 0 | AE51: 0 | AF51: 0 | AG51: =SUM(Tabla63[[#This Row],[ENERO]:[DICIEMBRE]]) -> 0 | AI51: Puestos | AJ51: 48 | AK51: Paniagua Cristian | AL51: =[2]P048!$B$5 -> 355200 | AM51: =[1]P048!$B$6 -> 355200 | AN51: 0 | AO51: 0 | AP51: 0 | AQ51: 0 | AR51: 0 | AS51: 0 | AT51: 0 | AU51: 0 | AV51: 0 | AW51: 0 | AX51: =SUM(Tabla634[[#This Row],[ENERO]:[DICIEMBRE]]) -> 710400
A52: Puestos | B52: 49 | D52: =[1]P001!$K$5 -> 0 | E52: =[1]P001!$K$5 -> 0 | P52: =SUM(Tabla6[[#This Row],[ENERO]:[DICIEMBRE]]) -> 0 | R52: Puestos | S52: 49 | U52: =[3]P049!$L$5 -> 0 | V52: =[3]P049!$L$5 -> 0 | X52: =[3]P049!$L$8 -> 0 | Y52: =[3]P049!$L$9 -> 0 | Z52: 0 | AA52: 0 | AB52: 0 | AC52: 0 | AD52: 0 | AE52: 0 | AF52: 0 | AG52: =SUM(Tabla63[[#This Row],[ENERO]:[DICIEMBRE]]) -> 0 | AI52: Puestos | AJ52: 49 | AL52: 0 | AM52: =[1]P005!$B$6 -> 177600 | AN52: 0 | AO52: 0 | AP52: 0 | AQ52: 0 | AR52: 0 | AS52: 0 | AT52: 0 | AU52: 0 | AV52: 0 | AW52: 0 | AX52: =SUM(Tabla634[[#This Row],[ENERO]:[DICIEMBRE]]) -> 177600
A53: Puestos | B53: 50 | D53: =[1]P001!$K$5 -> 0 | E53: =[1]P001!$K$5 -> 0 | P53: =SUM(Tabla6[[#This Row],[ENERO]:[DICIEMBRE]]) -> 0 | R53: Puestos | S53: 50 | U53: =[3]P050!$L$5 -> 0 | V53: =[3]P050!$L$5 -> 0 | X53: =[3]P050!$L$8 -> 0 | Y53: =[3]P050!$L$9 -> 0 | Z53: 0 | AA53: 0 | AB53: 0 | AC53: 0 | AD53: 0 | AE53: 0 | AF53: 0 | AG53: =SUM(Tabla63[[#This Row],[ENERO]:[DICIEMBRE]]) -> 0 | AI53: Puestos | AJ53: 50 | AL53: 0 | AM53: =[1]P005!$B$6 -> 177600 | AN53: 0 | AO53: 0 | AP53: 0 | AQ53: 0 | AR53: 0 | AS53: 0 | AT53: 0 | AU53: 0 | AV53: 0 | AW53: 0 | AX53: =SUM(Tabla634[[#This Row],[ENERO]:[DICIEMBRE]]) -> 177600
A54: Puestos | B54: 51 | D54: =[1]P001!$K$5 -> 0 | E54: =[1]P001!$K$5 -> 0 | P54: =SUM(Tabla6[[#This Row],[ENERO]:[DICIEMBRE]]) -> 0 | R54: Puestos | S54: 51 | U54: =[3]P051!$L$5 -> 0 | V54: =[3]P051!$L$5 -> 0 | X54: =[3]P051!$L$8 -> 0 | Y54: =[3]P051!$L$9 -> 0 | Z54: 0 | AA54: 0 | AB54: 0 | AC54: 0 | AD54: 0 | AE54: 0 | AF54: 0 | AG54: =SUM(Tabla63[[#This Row],[ENERO]:[DICIEMBRE]]) -> 0 | AI54: Puestos | AJ54: 51 | AL54: 0 | AM54: =[1]P005!$B$6 -> 177600 | AN54: 0 | AO54: 0 | AP54: 0 | AQ54: 0 | AR54: 0 | AS54: 0 | AT54: 0 | AU54: 0 | AV54: 0 | AW54: 0 | AX54: =SUM(Tabla634[[#This Row],[ENERO]:[DICIEMBRE]]) -> 177600
A55: Puestos | B55: 52 | D55: =[1]P001!$K$5 -> 0 | E55: =[1]P001!$K$5 -> 0 | P55: =SUM(Tabla6[[#This Row],[ENERO]:[DICIEMBRE]]) -> 0 | R55: Puestos | S55: 52 | U55: =[3]P052!$L$5 -> 0 | V55: =[3]P052!$L$5 -> 0 | X55: =[3]P052!$L$8 -> 0 | Y55: =[3]P052!$L$9 -> 0 | Z55: 0 | AA55: 0 | AB55: 0 | AC55: 0 | AD55: 0 | AE55: 0 | AF55: 0 | AG55: =SUM(Tabla63[[#This Row],[ENERO]:[DICIEMBRE]]) -> 0 | AI55: Puestos | AJ55: 52 | AL55: 0 | AM55: =[1]P005!$B$6 -> 177600 | AN55: 0 | AO55: 0 | AP55: 0 | AQ55: 0 | AR55: 0 | AS55: 0 | AT55: 0 | AU55: 0 | AV55: 0 | AW55: 0 | AX55: =SUM(Tabla634[[#This Row],[ENERO]:[DICIEMBRE]]) -> 177600
A56: Puestos | B56: 53 | C56: Becker Matias | D56: =[1]P001!$K$5 -> 0 | E56: =[1]P001!$K$5 -> 0 | P56: =SUM(Tabla6[[#This Row],[ENERO]:[DICIEMBRE]]) -> 0 | R56: Puestos | S56: 53 | T56: Becker Matias | U56: =[3]P053!$L$5 -> 95200 | V56: =[3]P053!$L$5 -> 95200 | X56: =[3]P053!$L$8 -> 0 | Y56: =[3]P053!$L$9 -> 0 | Z56: 0 | AA56: 0 | AB56: 0 | AC56: 0 | AD56: 0 | AE56: 0 | AF56: 0 | AG56: =SUM(Tabla63[[#This Row],[ENERO]:[DICIEMBRE]]) -> 190400 | AI56: Puestos | AJ56: 53 | AK56: Becker Matias | AL56: 0 | AM56: =[1]P005!$B$6 -> 177600 | AN56: 0 | AO56: 0 | AP56: 0 | AQ56: 0 | AR56: 0 | AS56: 0 | AT56: 0 | AU56: 0 | AV56: 0 | AW56: 0 | AX56: =SUM(Tabla634[[#This Row],[ENERO]:[DICIEMBRE]]) -> 177600
A57: Puestos | B57: 54 | C57: Da Costa Gaston | D57: =[1]P001!$K$5 -> 0 | E57: =[1]P001!$K$5 -> 0 | P57: =SUM(Tabla6[[#This Row],[ENERO]:[DICIEMBRE]]) -> 0 | R57: Puestos | S57: 54 | T57: Da Costa Gaston | U57: =[3]P054!$L$5 -> 47600 | V57: =[3]P054!$L$5 -> 47600 | X57: =[3]P054!$L$8 -> 73000 | Y57: =[3]P054!$L$9 -> 69000 | Z57: 0 | AA57: 0 | AB57: 0 | AC57: 0 | AD57: 0 | AE57: 0 | AF57: 0 | AG57: =SUM(Tabla63[[#This Row],[ENERO]:[DICIEMBRE]]) -> 237200 | AI57: Puestos | AJ57: 54 | AK57: Da Costa Gaston | AL57: 0 | AM57: =[1]P005!$B$6 -> 177600 | AN57: 0 | AO57: 0 | AP57: 0 | AQ57: 0 | AR57: 0 | AS57: 0 | AT57: 0 | AU57: 0 | AV57: 0 | AW57: 0 | AX57: =SUM(Tabla634[[#This Row],[ENERO]:[DICIEMBRE]]) -> 177600
A58: Puestos | B58: 55 | C58: Busquetti Agustin | D58: =[1]P054!$K$5 -> 0 | E58: =[1]P054!$K$6 -> 0 | P58: =SUM(Tabla6[[#This Row],[ENERO]:[DICIEMBRE]]) -> 0 | R58: Puestos | S58: 55 | T58: Busquetti Agustin | U58: =[1]P054!$L$5 -> 355200 | V58: =[1]P054!$L$6 -> 355200 | X58: 0 | Y58: 0 | Z58: 0 | AA58: 0 | AB58: 0 | AC58: 0 | AD58: 0 | AE58: 0 | AF58: 0 | AG58: =SUM(Tabla63[[#This Row],[ENERO]:[DICIEMBRE]]) -> 710400 | AI58: Puestos | AJ58: 55 | AK58: Busquetti Agustin | AL58: =[2]P054!$B$5 -> 355200 | AM58: =[1]P054!$B$6 -> 355200 | AN58: 0 | AO58: 0 | AP58: 0 | AQ58: 0 | AR58: 0 | AS58: 0 | AT58: 0 | AU58: 0 | AV58: 0 | AW58: 0 | AX58: =SUM(Tabla634[[#This Row],[ENERO]:[DICIEMBRE]]) -> 710400
A59: Puestos | B59: 56 | D59: =[1]P001!$K$5 -> 0 | E59: =[1]P001!$K$5 -> 0 | P59: =SUM(Tabla6[[#This Row],[ENERO]:[DICIEMBRE]]) -> 0 | R59: Puestos | S59: 56 | U59: =[3]P056!$L$5 -> 0 | V59: =[3]P056!$L$5 -> 0 | X59: =[3]P056!$L$8 -> 0 | Y59: =[3]P056!$L$9 -> 0 | Z59: 0 | AA59: 0 | AB59: 0 | AC59: 0 | AD59: 0 | AE59: 0 | AF59: 0 | AG59: =SUM(Tabla63[[#This Row],[ENERO]:[DICIEMBRE]]) -> 0 | AI59: Puestos | AJ59: 56 | AL59: 0 | AM59: =[1]P005!$B$6 -> 177600 | AN59: 0 | AO59: 0 | AP59: 0 | AQ59: 0 | AR59: 0 | AS59: 0 | AT59: 0 | AU59: 0 | AV59: 0 | AW59: 0 | AX59: =SUM(Tabla634[[#This Row],[ENERO]:[DICIEMBRE]]) -> 177600
A60: Puestos | B60: 57 | D60: =[1]P001!$K$5 -> 0 | E60: =[1]P001!$K$5 -> 0 | P60: =SUM(Tabla6[[#This Row],[ENERO]:[DICIEMBRE]]) -> 0 | R60: Puestos | S60: 57 | U60: =[3]P057!$L$5 -> 0 | V60: =[3]P057!$L$5 -> 0 | X60: =[3]P057!$L$8 -> 0 | Y60: =[3]P057!$L$9 -> 0 | Z60: 0 | AA60: 0 | AB60: 0 | AC60: 0 | AD60: 0 | AE60: 0 | AF60: 0 | AG60: =SUM(Tabla63[[#This Row],[ENERO]:[DICIEMBRE]]) -> 0 | AI60: Puestos | AJ60: 57 | AL60: 0 | AM60: =[1]P005!$B$6 -> 177600 | AN60: 0 | AO60: 0 | AP60: 0 | AQ60: 0 | AR60: 0 | AS60: 0 | AT60: 0 | AU60: 0 | AV60: 0 | AW60: 0 | AX60: =SUM(Tabla634[[#This Row],[ENERO]:[DICIEMBRE]]) -> 177600
A61: Puestos | B61: 58 | D61: =[1]P001!$K$5 -> 0 | E61: =[1]P001!$K$5 -> 0 | P61: =SUM(Tabla6[[#This Row],[ENERO]:[DICIEMBRE]]) -> 0 | R61: Puestos | S61: 58 | U61: =[3]P058!$L$5 -> 0 | V61: =[3]P058!$L$5 -> 0 | X61: =[3]P058!$L$8 -> 0 | Y61: =[3]P058!$L$9 -> 0 | Z61: 0 | AA61: 0 | AB61: 0 | AC61: 0 | AD61: 0 | AE61: 0 | AF61: 0 | AG61: =SUM(Tabla63[[#This Row],[ENERO]:[DICIEMBRE]]) -> 0 | AI61: Puestos | AJ61: 58 | AL61: 0 | AM61: =[1]P005!$B$6 -> 177600 | AN61: 0 | AO61: 0 | AP61: 0 | AQ61: 0 | AR61: 0 | AS61: 0 | AT61: 0 | AU61: 0 | AV61: 0 | AW61: 0 | AX61: =SUM(Tabla634[[#This Row],[ENERO]:[DICIEMBRE]]) -> 177600
A62: Puestos | B62: 59 | C62: Burgos Federico | D62: =[1]P059!$K$5 -> 688100 | E62: =[1]P059!$K$6 -> 988100 | P62: =SUM(Tabla6[[#This Row],[ENERO]:[DICIEMBRE]]) -> 1676200 | R62: Puestos | S62: 59 | T62: Burgos Federico | U62: =[1]P059!$L$5 -> 40500 | V62: =[1]P059!$L$6 -> 0 | X62: 0 | Y62: 0 | Z62: 0 | AA62: 0 | AB62: 0 | AC62: 0 | AD62: 0 | AE62: 0 | AF62: 0 | AG62: =SUM(Tabla63[[#This Row],[ENERO]:[DICIEMBRE]]) -> 40500 | AI62: Puestos | AJ62: 59 | AK62: Burgos Federico | AL62: =[2]P059!$B$5 -> 988100 | AM62: =[1]P059!$B$6 -> 988100 | AN62: 0 | AO62: 0 | AP62: 0 | AQ62: 0 | AR62: 0 | AS62: 0 | AT62: 0 | AU62: 0 | AV62: 0 | AW62: 0 | AX62: =SUM(Tabla634[[#This Row],[ENERO]:[DICIEMBRE]]) -> 1976200
A63: Puestos | B63: 60 | D63: =[1]P001!$K$5 -> 0 | E63: =[1]P001!$K$5 -> 0 | P63: =SUM(Tabla6[[#This Row],[ENERO]:[DICIEMBRE]]) -> 0 | R63: Puestos | S63: 60 | U63: =[3]P060!$L$5 -> 0 | V63: =[3]P060!$L$5 -> 0 | X63: =[3]P060!$L$8 -> 0 | Y63: =[3]P060!$L$9 -> 0 | Z63: 0 | AA63: 0 | AB63: 0 | AC63: 0 | AD63: 0 | AE63: 0 | AF63: 0 | AG63: =SUM(Tabla63[[#This Row],[ENERO]:[DICIEMBRE]]) -> 0 | AI63: Puestos | AJ63: 60 | AL63: 0 | AM63: =[1]P005!$B$6 -> 177600 | AN63: 0 | AO63: 0 | AP63: 0 | AQ63: 0 | AR63: 0 | AS63: 0 | AT63: 0 | AU63: 0 | AV63: 0 | AW63: 0 | AX63: =SUM(Tabla634[[#This Row],[ENERO]:[DICIEMBRE]]) -> 177600
A64: Puestos | B64: 61 | D64: =[1]P001!$K$5 -> 0 | E64: =[1]P001!$K$5 -> 0 | P64: =SUM(Tabla6[[#This Row],[ENERO]:[DICIEMBRE]]) -> 0 | R64: Puestos | S64: 61 | U64: =[3]P061!$L$5 -> 0 | V64: =[3]P061!$L$5 -> 0 | X64: =[3]P061!$L$8 -> 0 | Y64: =[3]P061!$L$9 -> 0 | Z64: 0 | AA64: 0 | AB64: 0 | AC64: 0 | AD64: 0 | AE64: 0 | AF64: 0 | AG64: =SUM(Tabla63[[#This Row],[ENERO]:[DICIEMBRE]]) -> 0 | AI64: Puestos | AJ64: 61 | AL64: 0 | AM64: =[1]P005!$B$6 -> 177600 | AN64: 0 | AO64: 0 | AP64: 0 | AQ64: 0 | AR64: 0 | AS64: 0 | AT64: 0 | AU64: 0 | AV64: 0 | AW64: 0 | AX64: =SUM(Tabla634[[#This Row],[ENERO]:[DICIEMBRE]]) -> 177600
A65: Puestos | B65: 62 | C65: Cabral Maricris | D65: =[1]P001!$K$5 -> 0 | E65: =[1]P001!$K$5 -> 0 | P65: =SUM(Tabla6[[#This Row],[ENERO]:[DICIEMBRE]]) -> 0 | R65: Puestos | S65: 62 | T65: Cabral Maricris | U65: =[3]P062!$L$5 -> 58000 | V65: =[3]P062!$L$5 -> 58000 | X65: =[3]P062!$L$8 -> 90100 | Y65: =[3]P062!$L$9 -> 84100 | Z65: 0 | AA65: 0 | AB65: 0 | AC65: 0 | AD65: 0 | AE65: 0 | AF65: 0 | AG65: =SUM(Tabla63[[#This Row],[ENERO]:[DICIEMBRE]]) -> 290200 | AI65: Puestos | AJ65: 62 | AK65: Cabral Maricris | AL65: 0 | AM65: =[1]P005!$B$6 -> 177600 | AN65: 0 | AO65: 0 | AP65: 0 | AQ65: 0 | AR65: 0 | AS65: 0 | AT65: 0 | AU65: 0 | AV65: 0 | AW65: 0 | AX65: =SUM(Tabla634[[#This Row],[ENERO]:[DICIEMBRE]]) -> 177600
A66: Puestos | B66: 63 | D66: =[1]P001!$K$5 -> 0 | E66: =[1]P001!$K$5 -> 0 | P66: =SUM(Tabla6[[#This Row],[ENERO]:[DICIEMBRE]]) -> 0 | R66: Puestos | S66: 63 | U66: =[3]P063!$L$5 -> 0 | V66: =[3]P063!$L$5 -> 0 | X66: =[3]P063!$L$8 -> 0 | Y66: =[3]P063!$L$9 -> 0 | Z66: 0 | AA66: 0 | AB66: 0 | AC66: 0 | AD66: 0 | AE66: 0 | AF66: 0 | AG66: =SUM(Tabla63[[#This Row],[ENERO]:[DICIEMBRE]]) -> 0 | AI66: Puestos | AJ66: 63 | AL66: 0 | AM66: =[1]P005!$B$6 -> 177600 | AN66: 0 | AO66: 0 | AP66: 0 | AQ66: 0 | AR66: 0 | AS66: 0 | AT66: 0 | AU66: 0 | AV66: 0 | AW66: 0 | AX66: =SUM(Tabla634[[#This Row],[ENERO]:[DICIEMBRE]]) -> 177600
A67: Puestos | B67: 64 | D67: =[1]P001!$K$5 -> 0 | E67: =[1]P001!$K$5 -> 0 | P67: =SUM(Tabla6[[#This Row],[ENERO]:[DICIEMBRE]]) -> 0 | R67: Puestos | S67: 64 | U67: =[3]P064!$L$5 -> 0 | V67: =[3]P064!$L$5 -> 0 | X67: =[3]P064!$L$8 -> 0 | Y67: =[3]P064!$L$9 -> 0 | Z67: 0 | AA67: 0 | AB67: 0 | AC67: 0 | AD67: 0 | AE67: 0 | AF67: 0 | AG67: =SUM(Tabla63[[#This Row],[ENERO]:[DICIEMBRE]]) -> 0 | AI67: Puestos | AJ67: 64 | AL67: 0 | AM67: =[1]P005!$B$6 -> 177600 | AN67: 0 | AO67: 0 | AP67: 0 | AQ67: 0 | AR67: 0 | AS67: 0 | AT67: 0 | AU67: 0 | AV67: 0 | AW67: 0 | AX67: =SUM(Tabla634[[#This Row],[ENERO]:[DICIEMBRE]]) -> 177600
A68: Puestos | B68: 65 | D68: =[1]P001!$K$5 -> 0 | E68: =[1]P001!$K$5 -> 0 | P68: =SUM(Tabla6[[#This Row],[ENERO]:[DICIEMBRE]]) -> 0 | R68: Puestos | S68: 65 | U68: =[3]P065!$L$5 -> 0 | V68: =[3]P065!$L$5 -> 0 | X68: =[3]P065!$L$8 -> 0 | Y68: =[3]P065!$L$9 -> 0 | Z68: 0 | AA68: 0 | AB68: 0 | AC68: 0 | AD68: 0 | AE68: 0 | AF68: 0 | AG68: =SUM(Tabla63[[#This Row],[ENERO]:[DICIEMBRE]]) -> 0 | AI68: Puestos | AJ68: 65 | AL68: 0 | AM68: =[1]P005!$B$6 -> 177600 | AN68: 0 | AO68: 0 | AP68: 0 | AQ68: 0 | AR68: 0 | AS68: 0 | AT68: 0 | AU68: 0 | AV68: 0 | AW68: 0 | AX68: =SUM(Tabla634[[#This Row],[ENERO]:[DICIEMBRE]]) -> 177600
A69: Puestos | B69: 66 | D69: =[1]P001!$K$5 -> 0 | E69: =[1]P001!$K$5 -> 0 | P69: =SUM(Tabla6[[#This Row],[ENERO]:[DICIEMBRE]]) -> 0 | R69: Puestos | S69: 66 | U69: =[3]P066!$L$5 -> 0 | V69: =[3]P066!$L$5 -> 0 | X69: =[3]P066!$L$8 -> 0 | Y69: =[3]P066!$L$9 -> 0 | Z69: 0 | AA69: 0 | AB69: 0 | AC69: 0 | AD69: 0 | AE69: 0 | AF69: 0 | AG69: =SUM(Tabla63[[#This Row],[ENERO]:[DICIEMBRE]]) -> 0 | AI69: Puestos | AJ69: 66 | AL69: 0 | AM69: =[1]P005!$B$6 -> 177600 | AN69: 0 | AO69: 0 | AP69: 0 | AQ69: 0 | AR69: 0 | AS69: 0 | AT69: 0 | AU69: 0 | AV69: 0 | AW69: 0 | AX69: =SUM(Tabla634[[#This Row],[ENERO]:[DICIEMBRE]]) -> 177600
A70: Puestos | B70: 67 | D70: =[1]P001!$K$5 -> 0 | E70: =[1]P001!$K$5 -> 0 | P70: =SUM(Tabla6[[#This Row],[ENERO]:[DICIEMBRE]]) -> 0 | R70: Puestos | S70: 67 | U70: =[3]P067!$L$5 -> 0 | V70: =[3]P067!$L$5 -> 0 | X70: =[3]P067!$L$8 -> 0 | Y70: =[3]P067!$L$9 -> 0 | Z70: 0 | AA70: 0 | AB70: 0 | AC70: 0 | AD70: 0 | AE70: 0 | AF70: 0 | AG70: =SUM(Tabla63[[#This Row],[ENERO]:[DICIEMBRE]]) -> 0 | AI70: Puestos | AJ70: 67 | AL70: 0 | AM70: =[1]P005!$B$6 -> 177600 | AN70: 0 | AO70: 0 | AP70: 0 | AQ70: 0 | AR70: 0 | AS70: 0 | AT70: 0 | AU70: 0 | AV70: 0 | AW70: 0 | AX70: =SUM(Tabla634[[#This Row],[ENERO]:[DICIEMBRE]]) -> 177600
A71: Puestos | B71: 68 | D71: =[1]P001!$K$5 -> 0 | E71: =[1]P001!$K$5 -> 0 | P71: =SUM(Tabla6[[#This Row],[ENERO]:[DICIEMBRE]]) -> 0 | R71: Puestos | S71: 68 | U71: =[3]P068!$L$5 -> 0 | V71: =[3]P068!$L$5 -> 0 | X71: =[3]P068!$L$8 -> 0 | Y71: =[3]P068!$L$9 -> 0 | Z71: 0 | AA71: 0 | AB71: 0 | AC71: 0 | AD71: 0 | AE71: 0 | AF71: 0 | AG71: =SUM(Tabla63[[#This Row],[ENERO]:[DICIEMBRE]]) -> 0 | AI71: Puestos | AJ71: 68 | AL71: 0 | AM71: =[1]P005!$B$6 -> 177600 | AN71: 0 | AO71: 0 | AP71: 0 | AQ71: 0 | AR71: 0 | AS71: 0 | AT71: 0 | AU71: 0 | AV71: 0 | AW71: 0 | AX71: =SUM(Tabla634[[#This Row],[ENERO]:[DICIEMBRE]]) -> 177600
A72: Puestos | B72: 69 | D72: =[1]P001!$K$5 -> 0 | E72: =[1]P001!$K$5 -> 0 | P72: =SUM(Tabla6[[#This Row],[ENERO]:[DICIEMBRE]]) -> 0 | R72: Puestos | S72: 69 | U72: =[3]P069!$L$5 -> 0 | V72: =[3]P069!$L$5 -> 0 | X72: =[3]P069!$L$8 -> 0 | Y72: =[3]P069!$L$9 -> 0 | Z72: 0 | AA72: 0 | AB72: 0 | AC72: 0 | AD72: 0 | AE72: 0 | AF72: 0 | AG72: =SUM(Tabla63[[#This Row],[ENERO]:[DICIEMBRE]]) -> 0 | AI72: Puestos | AJ72: 69 | AL72: 0 | AM72: =[1]P005!$B$6 -> 177600 | AN72: 0 | AO72: 0 | AP72: 0 | AQ72: 0 | AR72: 0 | AS72: 0 | AT72: 0 | AU72: 0 | AV72: 0 | AW72: 0 | AX72: =SUM(Tabla634[[#This Row],[ENERO]:[DICIEMBRE]]) -> 177600
A73: Puestos | B73: 70 | C73: Paniagua Lucia | D73: =[1]P070!$K$5 -> 0 | E73: =[1]P070!$K$6 -> 0 | P73: =SUM(Tabla6[[#This Row],[ENERO]:[DICIEMBRE]]) -> 0 | R73: Puestos | S73: 70 | T73: Paniagua Lucia | U73: =[1]P070!$L$5 -> 857300 | V73: =[1]P070!$L$6 -> 857300 | X73: 0 | Y73: 0 | Z73: 0 | AA73: 0 | AB73: 0 | AC73: 0 | AD73: 0 | AE73: 0 | AF73: 0 | AG73: =SUM(Tabla63[[#This Row],[ENERO]:[DICIEMBRE]]) -> 1714600 | AI73: Puestos | AJ73: 70 | AK73: Paniagua Lucia | AL73: =[2]P070!$B$5 -> 857300 | AM73: =[1]P070!$B$6 -> 857300 | AN73: 0 | AO73: 0 | AP73: 0 | AQ73: 0 | AR73: 0 | AS73: 0 | AT73: 0 | AU73: 0 | AV73: 0 | AW73: 0 | AX73: =SUM(Tabla634[[#This Row],[ENERO]:[DICIEMBRE]]) -> 1714600
A74: Puestos | B74: 71 | D74: =[1]P001!$K$5 -> 0 | E74: =[1]P001!$K$5 -> 0 | P74: =SUM(Tabla6[[#This Row],[ENERO]:[DICIEMBRE]]) -> 0 | R74: Puestos | S74: 71 | U74: =[3]P071!$L$5 -> 0 | V74: =[3]P071!$L$5 -> 0 | X74: =[3]P071!$L$8 -> 0 | Y74: =[3]P071!$L$9 -> 0 | Z74: 0 | AA74: 0 | AB74: 0 | AC74: 0 | AD74: 0 | AE74: 0 | AF74: 0 | AG74: =SUM(Tabla63[[#This Row],[ENERO]:[DICIEMBRE]]) -> 0 | AI74: Puestos | AJ74: 71 | AL74: 0 | AM74: =[1]P005!$B$6 -> 177600 | AN74: 0 | AO74: 0 | AP74: 0 | AQ74: 0 | AR74: 0 | AS74: 0 | AT74: 0 | AU74: 0 | AV74: 0 | AW74: 0 | AX74: =SUM(Tabla634[[#This Row],[ENERO]:[DICIEMBRE]]) -> 177600
A75: Puestos | B75: 72 | D75: =[1]P001!$K$5 -> 0 | E75: =[1]P001!$K$5 -> 0 | P75: =SUM(Tabla6[[#This Row],[ENERO]:[DICIEMBRE]]) -> 0 | R75: Puestos | S75: 72 | U75: =[3]P072!$L$5 -> 0 | V75: =[3]P072!$L$5 -> 0 | X75: =[3]P072!$L$8 -> 0 | Y75: =[3]P072!$L$9 -> 0 | Z75: 0 | AA75: 0 | AB75: 0 | AC75: 0 | AD75: 0 | AE75: 0 | AF75: 0 | AG75: =SUM(Tabla63[[#This Row],[ENERO]:[DICIEMBRE]]) -> 0 | AI75: Puestos | AJ75: 72 | AL75: 0 | AM75: =[1]P005!$B$6 -> 177600 | AN75: 0 | AO75: 0 | AP75: 0 | AQ75: 0 | AR75: 0 | AS75: 0 | AT75: 0 | AU75: 0 | AV75: 0 | AW75: 0 | AX75: =SUM(Tabla634[[#This Row],[ENERO]:[DICIEMBRE]]) -> 177600
A76: Puestos | B76: 73 | D76: =[1]P001!$K$5 -> 0 | E76: =[1]P001!$K$5 -> 0 | P76: =SUM(Tabla6[[#This Row],[ENERO]:[DICIEMBRE]]) -> 0 | R76: Puestos | S76: 73 | U76: =[3]P073!$L$5 -> 0 | V76: =[3]P073!$L$5 -> 0 | X76: =[3]P073!$L$8 -> 0 | Y76: =[3]P073!$L$9 -> 0 | Z76: 0 | AA76: 0 | AB76: 0 | AC76: 0 | AD76: 0 | AE76: 0 | AF76: 0 | AG76: =SUM(Tabla63[[#This Row],[ENERO]:[DICIEMBRE]]) -> 0 | AI76: Puestos | AJ76: 73 | AL76: 0 | AM76: =[1]P005!$B$6 -> 177600 | AN76: 0 | AO76: 0 | AP76: 0 | AQ76: 0 | AR76: 0 | AS76: 0 | AT76: 0 | AU76: 0 | AV76: 0 | AW76: 0 | AX76: =SUM(Tabla634[[#This Row],[ENERO]:[DICIEMBRE]]) -> 177600
A77: Puestos | B77: 74 | C77: Cazapava Yolanda | D77: =[1]PO73!$K$5 -> 0 | E77: =[1]PO73!$K$6 -> 0 | P77: =SUM(Tabla6[[#This Row],[ENERO]:[DICIEMBRE]]) -> 0 | R77: Puestos | S77: 74 | T77: Lezcano Yoana | U77: =[1]PO73!$L$5 -> 266400 | V77: =[1]PO73!$L$6 -> 266400 | X77: 0 | Y77: 0 | Z77: 0 | AA77: 0 | AB77: 0 | AC77: 0 | AD77: 0 | AE77: 0 | AF77: 0 | AG77: =SUM(Tabla63[[#This Row],[ENERO]:[DICIEMBRE]]) -> 532800 | AI77: Puestos | AJ77: 74 | AK77: Lezcano Yoana | AL77: =[2]PO73!$B$5 -> 266400 | AM77: =[1]PO73!$B$6 -> 266400 | AN77: 0 | AO77: 0 | AP77: 0 | AQ77: 0 | AR77: 0 | AS77: 0 | AT77: 0 | AU77: 0 | AV77: 0 | AW77: 0 | AX77: =SUM(Tabla634[[#This Row],[ENERO]:[DICIEMBRE]]) -> 532800
A78: Puestos | B78: 75 | C78: Garcia Lucio | D78: =[1]P075!$K$5 -> 204300 | E78: =[1]P075!$K$6 -> 204300 | P78: =SUM(Tabla6[[#This Row],[ENERO]:[DICIEMBRE]]) -> 408600 | R78: Puestos | S78: 75 | T78: Garcia Lucio | U78: =[1]P075!$L$5 -> 0 | V78: =[1]P075!$L$6 -> 0 | X78: 0 | Y78: 0 | Z78: 0 | AA78: 0 | AB78: 0 | AC78: 0 | AD78: 0 | AE78: 0 | AF78: 0 | AG78: =SUM(Tabla63[[#This Row],[ENERO]:[DICIEMBRE]]) -> 0 | AI78: Puestos | AJ78: 75 | AK78: Garcia Lucio | AL78: =[2]P075!$B$5 -> 204300 | AM78: =[1]P075!$B$6 -> 204300 | AN78: 0 | AO78: 0 | AP78: 0 | AQ78: 0 | AR78: 0 | AS78: 0 | AT78: 0 | AU78: 0 | AV78: 0 | AW78: 0 | AX78: =SUM(Tabla634[[#This Row],[ENERO]:[DICIEMBRE]]) -> 408600
A79: Puestos | B79: 76 | D79: =[1]P001!$K$5 -> 0 | E79: =[1]P001!$K$5 -> 0 | P79: =SUM(Tabla6[[#This Row],[ENERO]:[DICIEMBRE]]) -> 0 | R79: Puestos | S79: 76 | U79: =[3]P076!$L$5 -> 0 | V79: =[3]P076!$L$5 -> 0 | X79: =[3]P076!$L$8 -> 0 | Y79: =[3]P076!$L$9 -> 0 | Z79: 0 | AA79: 0 | AB79: 0 | AC79: 0 | AD79: 0 | AE79: 0 | AF79: 0 | AG79: =SUM(Tabla63[[#This Row],[ENERO]:[DICIEMBRE]]) -> 0 | AI79: Puestos | AJ79: 76 | AL79: 0 | AM79: =[1]P005!$B$6 -> 177600 | AN79: 0 | AO79: 0 | AP79: 0 | AQ79: 0 | AR79: 0 | AS79: 0 | AT79: 0 | AU79: 0 | AV79: 0 | AW79: 0 | AX79: =SUM(Tabla634[[#This Row],[ENERO]:[DICIEMBRE]]) -> 177600
A80: Puestos | B80: 77 | D80: =[1]P001!$K$5 -> 0 | E80: =[1]P001!$K$5 -> 0 | P80: =SUM(Tabla6[[#This Row],[ENERO]:[DICIEMBRE]]) -> 0 | R80: Puestos | S80: 77 | U80: =[3]P077!$L$5 -> 0 | V80: =[3]P077!$L$5 -> 0 | X80: =[3]P077!$L$8 -> 0 | Y80: =[3]P077!$L$9 -> 0 | Z80: 0 | AA80: 0 | AB80: 0 | AC80: 0 | AD80: 0 | AE80: 0 | AF80: 0 | AG80: =SUM(Tabla63[[#This Row],[ENERO]:[DICIEMBRE]]) -> 0 | AI80: Puestos | AJ80: 77 | AL80: 0 | AM80: =[1]P005!$B$6 -> 177600 | AN80: 0 | AO80: 0 | AP80: 0 | AQ80: 0 | AR80: 0 | AS80: 0 | AT80: 0 | AU80: 0 | AV80: 0 | AW80: 0 | AX80: =SUM(Tabla634[[#This Row],[ENERO]:[DICIEMBRE]]) -> 177600
A81: Puestos | B81: 78 | D81: =[1]P001!$K$5 -> 0 | E81: =[1]P001!$K$5 -> 0 | P81: =SUM(Tabla6[[#This Row],[ENERO]:[DICIEMBRE]]) -> 0 | R81: Puestos | S81: 78 | U81: =[3]P078!$L$5 -> 0 | V81: =[3]P078!$L$5 -> 0 | X81: =[3]P078!$L$8 -> 0 | Y81: =[3]P078!$L$9 -> 0 | Z81: 0 | AA81: 0 | AB81: 0 | AC81: 0 | AD81: 0 | AE81: 0 | AF81: 0 | AG81: =SUM(Tabla63[[#This Row],[ENERO]:[DICIEMBRE]]) -> 0 | AI81: Puestos | AJ81: 78 | AL81: 0 | AM81: =[1]P005!$B$6 -> 177600 | AN81: 0 | AO81: 0 | AP81: 0 | AQ81: 0 | AR81: 0 | AS81: 0 | AT81: 0 | AU81: 0 | AV81: 0 | AW81: 0 | AX81: =SUM(Tabla634[[#This Row],[ENERO]:[DICIEMBRE]]) -> 177600
A82: Puestos | B82: 79 | D82: =[1]P001!$K$5 -> 0 | E82: =[1]P001!$K$5 -> 0 | P82: =SUM(Tabla6[[#This Row],[ENERO]:[DICIEMBRE]]) -> 0 | R82: Puestos | S82: 79 | U82: =[3]P079!$L$5 -> 0 | V82: =[3]P079!$L$5 -> 0 | X82: =[3]P079!$L$8 -> 0 | Y82: =[3]P079!$L$9 -> 0 | Z82: 0 | AA82: 0 | AB82: 0 | AC82: 0 | AD82: 0 | AE82: 0 | AF82: 0 | AG82: =SUM(Tabla63[[#This Row],[ENERO]:[DICIEMBRE]]) -> 0 | AI82: Puestos | AJ82: 79 | AL82: 0 | AM82: =[1]P005!$B$6 -> 177600 | AN82: 0 | AO82: 0 | AP82: 0 | AQ82: 0 | AR82: 0 | AS82: 0 | AT82: 0 | AU82: 0 | AV82: 0 | AW82: 0 | AX82: =SUM(Tabla634[[#This Row],[ENERO]:[DICIEMBRE]]) -> 177600
A83: Puestos | B83: 80 | C83: Benitez Evelin | D83: =[1]P080!$K$5 -> 0 | E83: =[1]P080!$K$6 -> 250 | P83: =SUM(Tabla6[[#This Row],[ENERO]:[DICIEMBRE]]) -> 250 | R83: Puestos | S83: 80 | T83: Benitez Evelin | U83: =[1]P080!$L$5 -> 907500 | V83: =[1]P080!$L$6 -> 615750 | X83: 0 | Y83: 0 | Z83: 0 | AA83: 0 | AB83: 0 | AC83: 0 | AD83: 0 | AE83: 0 | AF83: 0 | AG83: =SUM(Tabla63[[#This Row],[ENERO]:[DICIEMBRE]]) -> 1523250 | AI83: Puestos | AJ83: 80 | AK83: Benitez Evelin | AL83: =[1]P080!$B$5 -> 907500 | AM83: =[1]P080!$B$6 -> 616000 | AN83: 0 | AO83: 0 | AP83: 0 | AQ83: 0 | AR83: 0 | AS83: 0 | AT83: 0 | AU83: 0 | AV83: 0 | AW83: 0 | AX83: =SUM(Tabla634[[#This Row],[ENERO]:[DICIEMBRE]]) -> 1523500
A84: Puestos | B84: 81 | D84: =[1]P001!$K$5 -> 0 | E84: =[1]P001!$K$5 -> 0 | P84: =SUM(Tabla6[[#This Row],[ENERO]:[DICIEMBRE]]) -> 0 | R84: Puestos | S84: 81 | U84: =[3]P081!$L$5 -> 0 | V84: =[3]P081!$L$5 -> 0 | X84: =[3]P081!$L$8 -> 0 | Y84: =[3]P081!$L$9 -> 0 | Z84: 0 | AA84: 0 | AB84: 0 | AC84: 0 | AD84: 0 | AE84: 0 | AF84: 0 | AG84: =SUM(Tabla63[[#This Row],[ENERO]:[DICIEMBRE]]) -> 0 | AI84: Puestos | AJ84: 81 | AL84: 0 | AM84: =[1]P005!$B$6 -> 177600 | AN84: 0 | AO84: 0 | AP84: 0 | AQ84: 0 | AR84: 0 | AS84: 0 | AT84: 0 | AU84: 0 | AV84: 0 | AW84: 0 | AX84: =SUM(Tabla634[[#This Row],[ENERO]:[DICIEMBRE]]) -> 177600
A85: Puestos | B85: 82 | D85: =[1]P001!$K$5 -> 0 | E85: =[1]P001!$K$5 -> 0 | P85: =SUM(Tabla6[[#This Row],[ENERO]:[DICIEMBRE]]) -> 0 | R85: Puestos | S85: 82 | U85: =[3]P082!$L$5 -> 0 | V85: =[3]P082!$L$5 -> 0 | X85: =[3]P082!$L$8 -> 0 | Y85: =[3]P082!$L$9 -> 0 | Z85: 0 | AA85: 0 | AB85: 0 | AC85: 0 | AD85: 0 | AE85: 0 | AF85: 0 | AG85: =SUM(Tabla63[[#This Row],[ENERO]:[DICIEMBRE]]) -> 0 | AI85: Puestos | AJ85: 82 | AL85: 0 | AM85: =[1]P005!$B$6 -> 177600 | AN85: 0 | AO85: 0 | AP85: 0 | AQ85: 0 | AR85: 0 | AS85: 0 | AT85: 0 | AU85: 0 | AV85: 0 | AW85: 0 | AX85: =SUM(Tabla634[[#This Row],[ENERO]:[DICIEMBRE]]) -> 177600
A86: Puestos | B86: 83 | D86: =[1]P001!$K$5 -> 0 | E86: =[1]P001!$K$5 -> 0 | P86: =SUM(Tabla6[[#This Row],[ENERO]:[DICIEMBRE]]) -> 0 | R86: Puestos | S86: 83 | U86: =[3]P083!$L$5 -> 0 | V86: =[3]P083!$L$5 -> 0 | X86: =[3]P083!$L$8 -> 0 | Y86: =[3]P083!$L$9 -> 0 | Z86: 0 | AA86: 0 | AB86: 0 | AC86: 0 | AD86: 0 | AE86: 0 | AF86: 0 | AG86: =SUM(Tabla63[[#This Row],[ENERO]:[DICIEMBRE]]) -> 0 | AI86: Puestos | AJ86: 83 | AL86: 0 | AM86: =[1]P005!$B$6 -> 177600 | AN86: 0 | AO86: 0 | AP86: 0 | AQ86: 0 | AR86: 0 | AS86: 0 | AT86: 0 | AU86: 0 | AV86: 0 | AW86: 0 | AX86: =SUM(Tabla634[[#This Row],[ENERO]:[DICIEMBRE]]) -> 177600
A87: Puestos | B87: 84 | C87: Ramirez Ricardo | D87: =[1]P084!$K$5 -> 0 | E87: =[1]P084!$K$6 -> 0 | P87: =SUM(Tabla6[[#This Row],[ENERO]:[DICIEMBRE]]) -> 0 | R87: Puestos | S87: 84 | T87: Ramirez Ricardo | U87: =[1]P084!$L$5 -> 177600 | V87: =[1]P084!$L$6 -> 177600 | X87: 0 | Y87: 0 | Z87: 0 | AA87: 0 | AB87: 0 | AC87: 0 | AD87: 0 | AE87: 0 | AF87: 0 | AG87: =SUM(Tabla63[[#This Row],[ENERO]:[DICIEMBRE]]) -> 355200 | AI87: Puestos | AJ87: 84 | AK87: Ramirez Ricardo | AL87: =[2]P084!$B$5 -> 177600 | AM87: =[1]P084!$B$6 -> 177600 | AN87: 0 | AO87: 0 | AP87: 0 | AQ87: 0 | AR87: 0 | AS87: 0 | AT87: 0 | AU87: 0 | AV87: 0 | AW87: 0 | AX87: =SUM(Tabla634[[#This Row],[ENERO]:[DICIEMBRE]]) -> 355200
A88: Puestos | B88: 85 | C88: Benitez Ariel | D88: =[1]P085!$K$5 -> 177600 | E88: =[1]P085!$K$6 -> 177600 | P88: =SUM(Tabla6[[#This Row],[ENERO]:[DICIEMBRE]]) -> 355200 | R88: Puestos | S88: 85 | T88: Benitez Ariel | U88: =[2]P085!$L$5 -> 0 | V88: =[2]P085!$L$6 -> 0 | X88: 0 | Y88: 0 | Z88: 0 | AA88: 0 | AB88: 0 | AC88: 0 | AD88: 0 | AE88: 0 | AF88: 0 | AG88: =SUM(Tabla63[[#This Row],[ENERO]:[DICIEMBRE]]) -> 0 | AI88: Puestos | AJ88: 85 | AK88: Benitez Ariel | AL88: =[2]P085!$B$5 -> 177600 | AM88: =[1]P085!$B$6 -> 177600 | AN88: 0 | AO88: 0 | AP88: 0 | AQ88: 0 | AR88: 0 | AS88: 0 | AT88: 0 | AU88: 0 | AV88: 0 | AW88: 0 | AX88: =SUM(Tabla634[[#This Row],[ENERO]:[DICIEMBRE]]) -> 355200
A89: Puestos | B89: 86 | C89: Da Silva Raquel | D89: =[1]P086!$K$5 -> 518900 | E89: =[1]P086!$K$6 -> 518900 | P89: =SUM(Tabla6[[#This Row],[ENERO]:[DICIEMBRE]]) -> 1037800 | R89: Puestos | S89: 86 | T89: Da Silva Raquel | U89: =[1]P086!$L$5 -> 0 | V89: =[1]P086!$L$6 -> 0 | X89: 0 | Y89: 0 | Z89: 0 | AA89: 0 | AB89: 0 | AC89: 0 | AD89: 0 | AE89: 0 | AF89: 0 | AG89: =SUM(Tabla63[[#This Row],[ENERO]:[DICIEMBRE]]) -> 0 | AI89: Puestos | AJ89: 86 | AK89: Da Silva Raquel | AL89: =[2]P086!$B$5 -> 518900 | AM89: =[1]P086!$B$6 -> 518900 | AN89: 0 | AO89: 0 | AP89: 0 | AQ89: 0 | AR89: 0 | AS89: 0 | AT89: 0 | AU89: 0 | AV89: 0 | AW89: 0 | AX89: =SUM(Tabla634[[#This Row],[ENERO]:[DICIEMBRE]]) -> 1037800
A90: Puestos | B90: 87 | D90: =[1]P001!$K$5 -> 0 | E90: =[1]P001!$K$5 -> 0 | P90: =SUM(Tabla6[[#This Row],[ENERO]:[DICIEMBRE]]) -> 0 | R90: Puestos | S90: 87 | U90: =[3]P087!$L$5 -> 0 | V90: =[3]P087!$L$5 -> 0 | X90: =[3]P087!$L$8 -> 0 | Y90: =[3]P087!$L$9 -> 0 | Z90: 0 | AA90: 0 | AB90: 0 | AC90: 0 | AD90: 0 | AE90: 0 | AF90: 0 | AG90: =SUM(Tabla63[[#This Row],[ENERO]:[DICIEMBRE]]) -> 0 | AI90: Puestos | AJ90: 87 | AL90: 0 | AM90: =[1]P005!$B$6 -> 177600 | AN90: 0 | AO90: 0 | AP90: 0 | AQ90: 0 | AR90: 0 | AS90: 0 | AT90: 0 | AU90: 0 | AV90: 0 | AW90: 0 | AX90: =SUM(Tabla634[[#This Row],[ENERO]:[DICIEMBRE]]) -> 177600
A91: Puestos | B91: 88 | D91: =[1]P001!$K$5 -> 0 | E91: =[1]P001!$K$5 -> 0 | P91: =SUM(Tabla6[[#This Row],[ENERO]:[DICIEMBRE]]) -> 0 | R91: Puestos | S91: 88 | U91: =[3]P088!$L$5 -> 0 | V91: =[3]P088!$L$5 -> 0 | X91: =[3]P088!$L$8 -> 0 | Y91: =[3]P088!$L$9 -> 0 | Z91: 0 | AA91: 0 | AB91: 0 | AC91: 0 | AD91: 0 | AE91: 0 | AF91: 0 | AG91: =SUM(Tabla63[[#This Row],[ENERO]:[DICIEMBRE]]) -> 0 | AI91: Puestos | AJ91: 88 | AL91: 0 | AM91: =[1]P005!$B$6 -> 177600 | AN91: 0 | AO91: 0 | AP91: 0 | AQ91: 0 | AR91: 0 | AS91: 0 | AT91: 0 | AU91: 0 | AV91: 0 | AW91: 0 | AX91: =SUM(Tabla634[[#This Row],[ENERO]:[DICIEMBRE]]) -> 177600
A92: Puestos | B92: 89 | D92: =[1]P001!$K$5 -> 0 | E92: =[1]P001!$K$5 -> 0 | P92: =SUM(Tabla6[[#This Row],[ENERO]:[DICIEMBRE]]) -> 0 | R92: Puestos | S92: 89 | U92: =[3]P089!$L$5 -> 0 | V92: =[3]P089!$L$5 -> 0 | X92: =[3]P089!$L$8 -> 0 | Y92: =[3]P089!$L$9 -> 0 | Z92: 0 | AA92: 0 | AB92: 0 | AC92: 0 | AD92: 0 | AE92: 0 | AF92: 0 | AG92: =SUM(Tabla63[[#This Row],[ENERO]:[DICIEMBRE]]) -> 0 | AI92: Puestos | AJ92: 89 | AL92: 0 | AM92: =[1]P005!$B$6 -> 177600 | AN92: 0 | AO92: 0 | AP92: 0 | AQ92: 0 | AR92: 0 | AS92: 0 | AT92: 0 | AU92: 0 | AV92: 0 | AW92: 0 | AX92: =SUM(Tabla634[[#This Row],[ENERO]:[DICIEMBRE]]) -> 177600
A93: Puestos | B93: 90 | D93: =[1]P001!$K$5 -> 0 | E93: =[1]P001!$K$5 -> 0 | P93: =SUM(Tabla6[[#This Row],[ENERO]:[DICIEMBRE]]) -> 0 | R93: Puestos | S93: 90 | U93: =[3]P090!$L$5 -> 0 | V93: =[3]P090!$L$5 -> 0 | X93: =[3]P090!$L$8 -> 0 | Y93: =[3]P090!$L$9 -> 0 | Z93: 0 | AA93: 0 | AB93: 0 | AC93: 0 | AD93: 0 | AE93: 0 | AF93: 0 | AG93: =SUM(Tabla63[[#This Row],[ENERO]:[DICIEMBRE]]) -> 0 | AI93: Puestos | AJ93: 90 | AL93: 0 | AM93: =[1]P005!$B$6 -> 177600 | AN93: 0 | AO93: 0 | AP93: 0 | AQ93: 0 | AR93: 0 | AS93: 0 | AT93: 0 | AU93: 0 | AV93: 0 | AW93: 0 | AX93: =SUM(Tabla634[[#This Row],[ENERO]:[DICIEMBRE]]) -> 177600
A94: Puestos | B94: 91 | D94: =[1]P001!$K$5 -> 0 | E94: =[1]P001!$K$5 -> 0 | P94: =SUM(Tabla6[[#This Row],[ENERO]:[DICIEMBRE]]) -> 0 | R94: Puestos | S94: 91 | U94: =[3]P091!$L$5 -> 0 | V94: =[3]P091!$L$5 -> 0 | X94: =[3]P091!$L$8 -> 0 | Y94: =[3]P091!$L$9 -> 0 | Z94: 0 | AA94: 0 | AB94: 0 | AC94: 0 | AD94: 0 | AE94: 0 | AF94: 0 | AG94: =SUM(Tabla63[[#This Row],[ENERO]:[DICIEMBRE]]) -> 0 | AI94: Puestos | AJ94: 91 | AL94: 0 | AM94: =[1]P005!$B$6 -> 177600 | AN94: 0 | AO94: 0 | AP94: 0 | AQ94: 0 | AR94: 0 | AS94: 0 | AT94: 0 | AU94: 0 | AV94: 0 | AW94: 0 | AX94: =SUM(Tabla634[[#This Row],[ENERO]:[DICIEMBRE]]) -> 177600
A95: Puestos | B95: 92 | D95: =[1]P001!$K$5 -> 0 | E95: =[1]P001!$K$5 -> 0 | P95: =SUM(Tabla6[[#This Row],[ENERO]:[DICIEMBRE]]) -> 0 | R95: Puestos | S95: 92 | U95: =[3]P092!$L$5 -> 0 | V95: =[3]P092!$L$5 -> 0 | X95: =[3]P092!$L$8 -> 0 | Y95: =[3]P092!$L$9 -> 0 | Z95: 0 | AA95: 0 | AB95: 0 | AC95: 0 | AD95: 0 | AE95: 0 | AF95: 0 | AG95: =SUM(Tabla63[[#This Row],[ENERO]:[DICIEMBRE]]) -> 0 | AI95: Puestos | AJ95: 92 | AL95: 0 | AM95: =[1]P005!$B$6 -> 177600 | AN95: 0 | AO95: 0 | AP95: 0 | AQ95: 0 | AR95: 0 | AS95: 0 | AT95: 0 | AU95: 0 | AV95: 0 | AW95: 0 | AX95: =SUM(Tabla634[[#This Row],[ENERO]:[DICIEMBRE]]) -> 177600
A96: Puestos | B96: 93 | D96: =[1]P001!$K$5 -> 0 | E96: =[1]P001!$K$5 -> 0 | P96: =SUM(Tabla6[[#This Row],[ENERO]:[DICIEMBRE]]) -> 0 | R96: Puestos | S96: 93 | U96: =[3]P093!$L$5 -> 0 | V96: =[3]P093!$L$5 -> 0 | X96: =[3]P093!$L$8 -> 0 | Y96: =[3]P093!$L$9 -> 0 | Z96: 0 | AA96: 0 | AB96: 0 | AC96: 0 | AD96: 0 | AE96: 0 | AF96: 0 | AG96: =SUM(Tabla63[[#This Row],[ENERO]:[DICIEMBRE]]) -> 0 | AI96: Puestos | AJ96: 93 | AL96: 0 | AM96: =[1]P005!$B$6 -> 177600 | AN96: 0 | AO96: 0 | AP96: 0 | AQ96: 0 | AR96: 0 | AS96: 0 | AT96: 0 | AU96: 0 | AV96: 0 | AW96: 0 | AX96: =SUM(Tabla634[[#This Row],[ENERO]:[DICIEMBRE]]) -> 177600
A97: Puestos | B97: 94 | D97: =[1]P001!$K$5 -> 0 | E97: =[1]P001!$K$5 -> 0 | P97: =SUM(Tabla6[[#This Row],[ENERO]:[DICIEMBRE]]) -> 0 | R97: Puestos | S97: 94 | U97: =[3]P094!$L$5 -> 0 | V97: =[3]P094!$L$5 -> 0 | X97: =[3]P094!$L$8 -> 0 | Y97: =[3]P094!$L$9 -> 0 | Z97: 0 | AA97: 0 | AB97: 0 | AC97: 0 | AD97: 0 | AE97: 0 | AF97: 0 | AG97: =SUM(Tabla63[[#This Row],[ENERO]:[DICIEMBRE]]) -> 0 | AI97: Puestos | AJ97: 94 | AL97: 0 | AM97: =[1]P005!$B$6 -> 177600 | AN97: 0 | AO97: 0 | AP97: 0 | AQ97: 0 | AR97: 0 | AS97: 0 | AT97: 0 | AU97: 0 | AV97: 0 | AW97: 0 | AX97: =SUM(Tabla634[[#This Row],[ENERO]:[DICIEMBRE]]) -> 177600
A98: Puestos | B98: 95 | D98: =[1]P001!$K$5 -> 0 | E98: =[1]P001!$K$5 -> 0 | P98: =SUM(Tabla6[[#This Row],[ENERO]:[DICIEMBRE]]) -> 0 | R98: Puestos | S98: 95 | U98: =[3]P095!$L$5 -> 0 | V98: =[3]P095!$L$5 -> 0 | X98: =[3]P095!$L$8 -> 0 | Y98: =[3]P095!$L$9 -> 0 | Z98: 0 | AA98: 0 | AB98: 0 | AC98: 0 | AD98: 0 | AE98: 0 | AF98: 0 | AG98: =SUM(Tabla63[[#This Row],[ENERO]:[DICIEMBRE]]) -> 0 | AI98: Puestos | AJ98: 95 | AL98: 0 | AM98: =[1]P005!$B$6 -> 177600 | AN98: 0 | AO98: 0 | AP98: 0 | AQ98: 0 | AR98: 0 | AS98: 0 | AT98: 0 | AU98: 0 | AV98: 0 | AW98: 0 | AX98: =SUM(Tabla634[[#This Row],[ENERO]:[DICIEMBRE]]) -> 177600
A99: Puestos | B99: 96 | D99: =[1]P001!$K$5 -> 0 | E99: =[1]P001!$K$5 -> 0 | P99: =SUM(Tabla6[[#This Row],[ENERO]:[DICIEMBRE]]) -> 0 | R99: Puestos | S99: 96 | U99: =[3]P096!$L$5 -> 0 | V99: =[3]P096!$L$5 -> 0 | X99: =[3]P096!$L$8 -> 0 | Y99: =[3]P096!$L$9 -> 0 | Z99: 0 | AA99: 0 | AB99: 0 | AC99: 0 | AD99: 0 | AE99: 0 | AF99: 0 | AG99: =SUM(Tabla63[[#This Row],[ENERO]:[DICIEMBRE]]) -> 0 | AI99: Puestos | AJ99: 96 | AL99: 0 | AM99: =[1]P005!$B$6 -> 177600 | AN99: 0 | AO99: 0 | AP99: 0 | AQ99: 0 | AR99: 0 | AS99: 0 | AT99: 0 | AU99: 0 | AV99: 0 | AW99: 0 | AX99: =SUM(Tabla634[[#This Row],[ENERO]:[DICIEMBRE]]) -> 177600
A100: Puestos | B100: 97 | D100: =[1]P001!$K$5 -> 0 | E100: =[1]P001!$K$5 -> 0 | P100: =SUM(Tabla6[[#This Row],[ENERO]:[DICIEMBRE]]) -> 0 | R100: Puestos | S100: 97 | U100: =[3]P097!$L$5 -> 0 | V100: =[3]P097!$L$5 -> 0 | X100: =[3]P097!$L$8 -> 0 | Y100: =[3]P097!$L$9 -> 0 | Z100: 0 | AA100: 0 | AB100: 0 | AC100: 0 | AD100: 0 | AE100: 0 | AF100: 0 | AG100: =SUM(Tabla63[[#This Row],[ENERO]:[DICIEMBRE]]) -> 0 | AI100: Puestos | AJ100: 97 | AL100: 0 | AM100: =[1]P005!$B$6 -> 177600 | AN100: 0 | AO100: 0 | AP100: 0 | AQ100: 0 | AR100: 0 | AS100: 0 | AT100: 0 | AU100: 0 | AV100: 0 | AW100: 0 | AX100: =SUM(Tabla634[[#This Row],[ENERO]:[DICIEMBRE]]) -> 177600
...

Sheet PERSONALES
D1: enero | F1: febrero | H1: marzo | J1: abril | L1: mayo | N1: junio | P1: julio | R1: agosto | T1: septiembre | V1: octubre | X1: noviembre | Z1: diciembre
A2: AREA | B2: PERSONAL | C2: MODALIDAD | D2: ene-01 | E2: ene-02 | F2: feb-01 | G2: feb-02 | H2: mar-01 | I2: mar-02 | J2: abr-01 | K2: abr-02 | L2: may-01 | M2: may-02 | N2: jun-01 | O2: jun-02 | P2: jul-01 | Q2: jul-02 | R2: ago-01 | S2: ago-02 | T2: sept-01 | U2: sept-02 | V2: oct-01 | W2: oct-02 | X2: nov-01 | Y2: nov-02 | Z2: dic-01 | AA2: dic-02 | AB2: AGUINALDO | AC2: TOTAL FUNCIONARIO
A3: SEGURIDAD | B3: Leandro Rodriguez | C3: Quincenal | D3: 30000 | E3: 30000 | F3: 30000 | G3: 30000 | AC3: =SUM(Tabla4[[#This Row],[ene-01]:[AGUINALDO]]) -> 120000
A4: SEGURIDAD | B4: Luis Rodriguez | C4: Quincenal | D4: 30000 | E4: 30000 | F4: 30000 | G4: 30000 | AC4: =SUM(Tabla4[[#This Row],[ene-01]:[AGUINALDO]]) -> 120000
A5: SEGURIDAD | B5: Marcos | C5: Quincenal | D5: 30000 | E5: 30000 | AC5: =SUM(Tabla4[[#This Row],[ene-01]:[AGUINALDO]]) -> 60000
A6: SEGURIDAD | B6: Eduardo Medina | C6: Quincenal | D6: 30000 | E6: 30000 | F6: 30000 | G6: 30000 | AC6: =SUM(Tabla4[[#This Row],[ene-01]:[AGUINALDO]]) -> 120000
A7: SEGURIDAD | B7: Agustin | C7: Quincenal | D7: 30000 | E7: 30000 | F7: 30000 | G7: 30000 | AC7: =SUM(Tabla4[[#This Row],[ene-01]:[AGUINALDO]]) -> 120000
A8: LIMPIEZA | B8: Jonathan | C8: Quincenal | D8: 30000 | E8: 30000 | AC8: =SUM(Tabla4[[#This Row],[ene-01]:[AGUINALDO]]) -> 60000
A9: LIMPIEZA | B9: Valeria Ortiz | C9: Quincenal | D9: 30000 | E9: 30000 | F9: 30000 | G9: 30000 | AC9: =SUM(Tabla4[[#This Row],[ene-01]:[AGUINALDO]]) -> 120000
A10: LIMPIEZA | B10: Zulma Garay | C10: Quincenal | D10: 30000 | E10: 30000 | F10: 30000 | G10: 30000 | AC10: =SUM(Tabla4[[#This Row],[ene-01]:[AGUINALDO]]) -> 120000
A11: LIMPIEZA | B11: Lucia Fagunde | C11: Quincenal | D11: 30000 | E11: 30000 | F11: 30000 | G11: 30000 | AC11: =SUM(Tabla4[[#This Row],[ene-01]:[AGUINALDO]]) -> 120000
A12: ADMINISTRACION | B12: Miguel Ortiz | C12: Quincenal | D12: 40000 | E12: 40000 | F12: 40000 | G12: 40000 | AC12: =SUM(Tabla4[[#This Row],[ene-01]:[AGUINALDO]]) -> 160000
A13: ADMINISTRACION | B13: Cordoba | C13: Quincenal | AC13: =SUM(Tabla4[[#This Row],[ene-01]:[AGUINALDO]]) -> 0
A14: ADMINISTRACION | B14: Valentino Casares | C14: Quincenal | AC14: =SUM(Tabla4[[#This Row],[ene-01]:[AGUINALDO]]) -> 0
A15: ADMINISTRACION | B15: Ezequiel Casares | C15: Quincenal | AC15: =SUM(Tabla4[[#This Row],[ene-01]:[AGUINALDO]]) -> 0
A16: ADMINISTRACION | B16: Alejandro Casares | C16: Quincenal | AC16: =SUM(Tabla4[[#This Row],[ene-01]:[AGUINALDO]]) -> 0
A17: ADMINISTRACION | B17: Francisco Casares | C17: Quincenal | D17: 50000 | E17: 50000 | F17: 50000 | G17: 50000 | AC17: =SUM(Tabla4[[#This Row],[ene-01]:[AGUINALDO]]) -> 200000
A18: ADMINISTRACION | B18: Elias Ramírez | C18: Quincenal | D18: 30000 | E18: 30000 | F18: 30000 | G18: 30000 | AC18: =SUM(Tabla4[[#This Row],[ene-01]:[AGUINALDO]]) -> 120000
A19: MANTENIMIENTO | B19: Hector Agüero | C19: Diario | D19: 30000 | E19: 30000 | F19: 30000 | G19: 30000
A20: MANTENIMIENTO | C20: Diario
B21: Total | D21: =SUBTOTAL(109,Tabla4[ene-01]) -> 420000 | E21: =SUBTOTAL(109,Tabla4[ene-02]) -> 420000 | F21: =SUBTOTAL(109,Tabla4[feb-01]) -> 360000 | G21: =SUBTOTAL(109,Tabla4[feb-02]) -> 360000 | H21: =SUBTOTAL(109,Tabla4[mar-01]) -> 0 | I21: =SUBTOTAL(109,Tabla4[mar-02]) -> 0 | J21: =SUBTOTAL(109,Tabla4[abr-01]) -> 0 | K21: =SUBTOTAL(109,Tabla4[abr-02]) -> 0 | L21: =SUBTOTAL(109,Tabla4[may-01]) -> 0 | M21: =SUBTOTAL(109,Tabla4[may-02]) -> 0 | N21: =SUBTOTAL(109,Tabla4[jun-01]) -> 0 | O21: =SUBTOTAL(109,Tabla4[jun-02]) -> 0 | P21: =SUBTOTAL(109,Tabla4[jul-01]) -> 0 | Q21: =SUBTOTAL(109,Tabla4[jul-02]) -> 0 | R21: =SUBTOTAL(109,Tabla4[ago-01]) -> 0 | S21: =SUBTOTAL(109,Tabla4[ago-02]) -> 0 | T21: =SUBTOTAL(109,Tabla4[sept-01]) -> 0 | U21: =SUBTOTAL(109,Tabla4[sept-02]) -> 0 | V21: =SUBTOTAL(109,Tabla4[oct-01]) -> 0 | W21: =SUBTOTAL(109,Tabla4[oct-02]) -> 0 | X21: =SUBTOTAL(109,Tabla4[nov-01]) -> 0 | Y21: =SUBTOTAL(109,Tabla4[nov-02]) -> 0 | Z21: =SUBTOTAL(109,Tabla4[dic-01]) -> 0 | AA21: =SUBTOTAL(109,Tabla4[dic-02]) -> 0 | AB21: =SUBTOTAL(109,Tabla4[AGUINALDO]) -> 0

Sheet GASTOS
A3: ENERO
A6: Costos Estructura | E6: ALMUERZOS | H6: OFICINA | K6: VEHICULOS | N6: IMP. | Q6: GASTOS EXTRAORDIANRIOS
A7: Alq | B7: 6230415 | F7: 447000 | I7: 424172 | L7: 50000 | O7: 800000 | R7: 1400000
A8: Luz | B8: 4209789.9
A9: Agua | B9: 731461.7
A10: Internet | B10: 20000
A11: Mantenimiento | B11: =L36 -> 0
A12: Total | B12: =SUM(B7:B11) -> 11191667 | O12: =SUM(O7:O11) -> 800000 | R12: =SUM(R7:R11) -> 1400000
F14: =SUM(F7:F13) -> 447000 | I14: =SUM(I7:I13) -> 424172 | L14: =SUM(L7:L13) -> 50000
A15: Otros Gastos
A16: Publicidad | B16: =F35 -> 0
A17: Impuestos | B17: =O12 -> 800000 | E17: OFICINA | H17: SEGURIDA Y MANTENIMIENTO | K17: LIMPIEZA
A18: Gastos extraord | B18: =R12 -> 1400000 | E18: FRANCISCO | F18: 1000000 | H18: RICARDO | I18: 600000 | K18: TAMARA | L18: 400000
A19: Oficina | B19: =I14+F14 -> 871172 | E19: EZEQUIEL | F19: 1000000 | H19: FABIAN | I19: 500000 | K19: LUCIA | L19: 400000
A20: Vehiculos | B20: =L14 -> 50000 | E20: ALEJANDRO | F20: 1000000 | H20: LUCAS | I20: 300000 | K20: VALERIA | L20: 400000
A21: Total | B21: =SUM(B16:B20) -> 3121172 | E21: CORDOBA | F21: 1000000 | H21: PEDRO | I21: 400000 | K21: ZULMA | L21: 400000
E22: ELIAS | F22: 400000 | H22: MARCELO | I22: 400000
A23: Sueldos | H23: HECTOR | I23: 600000
A24: Seguridad | B24: =I27 -> 3200000 | H24: EZEQUIEL | I24: 400000
A25: Limpieza | B25: =L27 -> 1600000
A26: Mantenimiento | B26: =I36 -> 0 | F26: =SUM(F18:F25) -> 4400000
A27: Administracion | B27: =F26 -> 4400000 | I27: =SUM(I18:I26) -> 3200000 | L27: =SUM(L18:L26) -> 1600000
B28: =B27+B26+B25+B24 -> 9200000
K31: GASTOS MANTENIMIENTO
A32: Resumen de Gastos | K32: FERRETERIA
A33: C E | B33: =B12 -> 11191667 | K33: LIMPIEZA | L33: 128360
A34: Gastos Ad | B34: =F14 -> 447000
A35: Otros | B35: =B21 -> 3121172
A36: Total | B36: =B28+B21+B12 -> 23512839

Sheet Hoja2
A4: Costos Estructura | B4: ENERO | C4: FEBRERO | D4: MARZO | E4: ABRIL | F4: MAYO | G4: JUNIO | H4: JULIO | I4: AGOSTO
A5: Alq | B5: 1953000 | C5: 1953000 | D5: 3000000 | E5: 3000000 | F5: 3000000 | G5: 3775788 | H5: 3775788 | I5: 3775788
A6: Luz | B6: 817500 | C6: 1507969 | D6: 1341729.6 | E6: 2029579.6 | F6: 1677467.1 | G6: 2086042 | H6: 1706825.1 | I6: 2544372
A7: Agua | B7: 122336 | C7: 164385 | D7: 105340 | E7: 164385.77 | F7: 255376 | G7: 250376.61 | H7: 157373.08 | I7: 226195
A8: Internet | B8: 34000 | C8: 34000 | D8: 12300 | E8: 20000 | F8: 20000 | G8: 40000 | H8: 40000 | I8: 19000
A9: Mantenimiento | B9: 36090 | C9: 216247 | D9: 393010 | E9: 214900 | F9: 212887 | G9: 470651 | H9: 328094 | I9: 369500
A10: Total | B10: 2962926 | C10: 3875601 | D10: 4852379.6 | E10: 5428865.4 | F10: 5165730.2 | G10: 6622857.6 | H10: 5998080.1 | I10: =SUM(I5:I9) -> 6934855
A13: Otros Gastos | B13: ENERO | C13: FEBRERO | D13: MARZO | E13: ABRIL | F13: MAYO | G13: JUNIO | H13: JULIO | I13: AGOSTO
A14: Publicidad | B14: 8000 | C14: 8000 | D14: 0 | E14: 0 | F14: 0 | G14: 0 | H14: 0 | I14: 0
A15: Impuestos | B15: 5000 | C15: 5000 | D15: 5000 | E15: 700000 | F15: 5000 | G15: 600000 | H15: 600000 | I15: 600000
A16: Gastos extraord | B16: 0 | C16: 0 | D16: 38900 | E16: 0 | F16: 800000 | G16: 27000 | H16: 0 | I16: 0
A17: Oficina | B17: 98975 | C17: 148700 | D17: 256850 | E17: 468000 | F17: 461666 | G17: 165750 | H17: 985063 | I17: 508223
A18: Vehiculos | B18: 40000 | C18: 83300 | D18: 50000 | E18: 53000 | F18: 84000 | G18: 290500 | H18: 66000 | I18: 52500
A19: Total | B19: 151975 | C19: 245000 | D19: 350750 | E19: 1221000 | F19: 1350666 | G19: 1083250 | H19: 1651063 | I19: =SUM(I14:I18) -> 1160723
A21: Sueldos | B21: ENERO | C21: FEBRERO | D21: MARZO | E21: ABRIL | F21: MAYO | G21: JUNIO | H21: JULIO | I21: AGOSTO
A22: Seguridad | B22: 812000 | C22: 812000 | D22: 1173000 | E22: 740000 | F22: 740000 | G22: 1110000 | H22: 1000000 | I22: 910000
A23: Limpieza | B23: 560000 | C23: 700000 | D23: 800000 | E23: 1000000 | F23: 1000000 | G23: 1500000 | H23: 1000000 | I23: 1000000
A24: Mantenimiento | B24: 340000 | C24: 340000 | D24: 500000 | E24: 550000 | F24: 700000 | G24: 900000 | H24: 700000 | I24: 700000
A25: Administracion | B25: 1670000 | C25: 2160000 | D25: 2620000 | E25: 2500000 | F25: 2120000 | G25: 2120000 | H25: 2520000 | I25: 2350000
A26: Total | B26: 3382000 | C26: 4012000 | D26: 5093000 | E26: 4790000 | F26: 4560000 | G26: 5630000 | H26: 5220000 | I26: =SUM(I22:I25) -> 4960000
A30: Resumen de Gastos | B30: ENERO | C30: FEBRERO | D30: MARZO | E30: ABRIL | F30: MAYO | G30: JUNIO | H30: JULIO | I30: AGOSTO
A31: C E | B31: 2962926 | C31: 3875601 | D31: 4852379.6 | E31: 5428865.4 | F31: 5165730.2 | G31: 6622857.6 | H31: 5998080.1 | I31: =I10 -> 6934855
A32: Gastos Ad | B32: 3575392 | C32: 4012000 | D32: 5093000 | E32: 4790000 | F32: 4560000 | G32: 5630000 | H32: 0 | I32: 0
A33: Otros | B33: 151975 | C33: 245000 | D33: 350750 | E33: 1221000 | F33: 1350666 | G33: 1083250 | H33: 1651063 | I33: =I19 -> 1160723
A34: Total | B34: 6690293 | C34: 8132601 | D34: 10296130 | E34: 11439865 | F34: 11076396 | G34: 13336108 | H34: =SUM(H31:H33) -> 7649143.1 | I34: =SUM(I31:I33) -> 8095578
