Workbook

Sheet INTERESES
A1: FECHA | B1: PUESTO | C1: NOMBRE | D1: RECIBO | E1: MONTO | F1: DETALLE

Sheet MATRIZ
A3: PAGOS DEL ALQUILER
B4: COSTO | C4: PAGO 1 | D4: PAGO 2 | E4: PAGO 3 | F4: PAGO 4 | G4: PAGO 5 | H4: PAGO 6 | I4: PAGO 7 | J4: PAGO 8 | K4: SALDO | L4: RECAUDADO
A5: Enero | K5: =MATRIZ!$B5-(MATRIZ!$C5+MATRIZ!$D5+MATRIZ!$E5+MATRIZ!$F5+MATRIZ!$G5+MATRIZ!$H5+MATRIZ!$I5+MATRIZ!$J5) -> 0 | L5: =MATRIZ!$B5-MATRIZ!$K5 -> 0
A6: Febrero | K6: =MATRIZ!$B6-(MATRIZ!$C6+MATRIZ!$D6+MATRIZ!$E6+MATRIZ!$F6+MATRIZ!$G6+MATRIZ!$H6+MATRIZ!$I6+MATRIZ!$J6) -> 0 | L6: =MATRIZ!$B6-MATRIZ!$K6 -> 0
A7: Marzo | K7: =MATRIZ!$B7-(MATRIZ!$C7+MATRIZ!$D7+MATRIZ!$E7+MATRIZ!$F7+MATRIZ!$G7+MATRIZ!$H7+MATRIZ!$I7+MATRIZ!$J7) -> 0 | L7: =MATRIZ!$B7-MATRIZ!$K7 -> 0
A8: Abril | K8: =MATRIZ!$B8-(MATRIZ!$C8+MATRIZ!$D8+MATRIZ!$E8+MATRIZ!$F8+MATRIZ!$G8+MATRIZ!$H8+MATRIZ!$I8+MATRIZ!$J8) -> 0 | L8: =MATRIZ!$B8-MATRIZ!$K8 -> 0
A9: Mayo | K9: =MATRIZ!$B9-(MATRIZ!$C9+MATRIZ!$D9+MATRIZ!$E9+MATRIZ!$F9+MATRIZ!$G9+MATRIZ!$H9+MATRIZ!$I9+MATRIZ!$J9) -> 0 | L9: =MATRIZ!$B9-MATRIZ!$K9 -> 0
A10: Junio | K10: =MATRIZ!$B10-(MATRIZ!$C10+MATRIZ!$D10+MATRIZ!$E10+MATRIZ!$F10+MATRIZ!$G10+MATRIZ!$H10+MATRIZ!$I10+MATRIZ!$J10) -> 0 | L10: =MATRIZ!$B10-MATRIZ!$K10 -> 0
A11: Julio | K11: =MATRIZ!$B11-(MATRIZ!$C11+MATRIZ!$D11+MATRIZ!$E11+MATRIZ!$F11+MATRIZ!$G11+MATRIZ!$H11+MATRIZ!$I11+MATRIZ!$J11) -> 0 | L11: =MATRIZ!$B11-MATRIZ!$K11 -> 0
A12: Agosto | K12: =MATRIZ!$B12-(MATRIZ!$C12+MATRIZ!$D12+MATRIZ!$E12+MATRIZ!$F12+MATRIZ!$G12+MATRIZ!$H12+MATRIZ!$I12+MATRIZ!$J12) -> 0 | L12: =MATRIZ!$B12-MATRIZ!$K12 -> 0
A13: Septiembre | K13: =MATRIZ!$B13-(MATRIZ!$C13+MATRIZ!$D13+MATRIZ!$E13+MATRIZ!$F13+MATRIZ!$G13+MATRIZ!$H13+MATRIZ!$I13+MATRIZ!$J13) -> 0 | L13: =MATRIZ!$B13-MATRIZ!$K13 -> 0
A14: Octubre | K14: =MATRIZ!$B14-(MATRIZ!$C14+MATRIZ!$D14+MATRIZ!$E14+MATRIZ!$F14+MATRIZ!$G14+MATRIZ!$H14+MATRIZ!$I14+MATRIZ!$J14) -> 0 | L14: =MATRIZ!$B14-MATRIZ!$K14 -> 0
A15: Noviembre | K15: =MATRIZ!$B15-(MATRIZ!$C15+MATRIZ!$D15+MATRIZ!$E15+MATRIZ!$F15+MATRIZ!$G15+MATRIZ!$H15+MATRIZ!$I15+MATRIZ!$J15) -> 0 | L15: =MATRIZ!$B15-MATRIZ!$K15 -> 0
A16: Diciembre | K16: =MATRIZ!$B16-(MATRIZ!$C16+MATRIZ!$D16+MATRIZ!$E16+MATRIZ!$F16+MATRIZ!$G16+MATRIZ!$H16+MATRIZ!$I16+MATRIZ!$J16) -> 0 | L16: =MATRIZ!$B16-MATRIZ!$K16 -> 0
A18: NRO DE RECIBOS DE LOS PAGOS
C19: RECIBO 1 | D19: RECIBO 2 | E19: RECIBO 3 | F19: RECIBO 4 | G19: RECIBO 5 | H19: RECIBO 6 | I19: RECIBO 7 | J19: RECIBO 8
A20: Enero
A21: Febrero
A22: Marzo
A23: Abril
A24: Mayo
A25: Junio
A26: Julio
A27: Agosto
A28: Septiembre
A29: Octubre
A30: Noviembre
A31: Diciembre

Sheet P001
A1: Pto.1/2/3/21/22/23/loc23 | C1: HERNAN NIELSEN
A3: PAGOS DEL ALQUILER
B4: 1183800 | C4: PAGO 1 | D4: PAGO 2 | E4: PAGO 3 | F4: PAGO 4 | G4: PAGO 5 | H4: PAGO 6 | I4: PAGO 7 | J4: PAGO 8 | K4: SALDO | L4: RECAUDADO
A5: Enero | B5: 1183800 | C5: 1183800 | K5: ='P001'!$B5-('P001'!$C5+'P001'!$D5+'P001'!$E5+'P001'!$F5+'P001'!$G5+'P001'!$H5+'P001'!$I5+'P001'!$J5) -> 0 | L5: ='P001'!$B5-'P001'!$K5 -> 1183800 | M5: 54000
A6: Febrero | B6: 1183800 | C6: 1183800 | K6: ='P001'!$B6-('P001'!$C6+'P001'!$D6+'P001'!$E6+'P001'!$F6+'P001'!$G6+'P001'!$H6+'P001'!$I6+'P001'!$J6) -> 0 | L6: ='P001'!$B6-'P001'!$K6 -> 1183800 | M6: 54000
A7: Marzo | B7: 1287900 | C7: 1287900 | K7: ='P001'!$B7-('P001'!$C7+'P001'!$D7+'P001'!$E7+'P001'!$F7+'P001'!$G7+'P001'!$H7+'P001'!$I7+'P001'!$J7) -> 0 | L7: ='P001'!$B7-'P001'!$K7 -> 1287900 | M7: 54000
A8: Abril | K8: ='P001'!$B8-('P001'!$C8+'P001'!$D8+'P001'!$E8+'P001'!$F8+'P001'!$G8+'P001'!$H8+'P001'!$I8+'P001'!$J8) -> 0 | L8: ='P001'!$B8-'P001'!$K8 -> 0
A9: Mayo | K9: ='P001'!$B9-('P001'!$C9+'P001'!$D9+'P001'!$E9+'P001'!$F9+'P001'!$G9+'P001'!$H9+'P001'!$I9+'P001'!$J9) -> 0 | L9: ='P001'!$B9-'P001'!$K9 -> 0
A10: Junio | K10: ='P001'!$B10-('P001'!$C10+'P001'!$D10+'P001'!$E10+'P001'!$F10+'P001'!$G10+'P001'!$H10+'P001'!$I10+'P001'!$J10) -> 0 | L10: ='P001'!$B10-'P001'!$K10 -> 0
A11: Julio | K11: ='P001'!$B11-('P001'!$C11+'P001'!$D11+'P001'!$E11+'P001'!$F11+'P001'!$G11+'P001'!$H11+'P001'!$I11+'P001'!$J11) -> 0 | L11: ='P001'!$B11-'P001'!$K11 -> 0
A12: Agosto | K12: ='P001'!$B12-('P001'!$C12+'P001'!$D12+'P001'!$E12+'P001'!$F12+'P001'!$G12+'P001'!$H12+'P001'!$I12+'P001'!$J12) -> 0 | L12: ='P001'!$B12-'P001'!$K12 -> 0
A13: Septiembre | K13: ='P001'!$B13-('P001'!$C13+'P001'!$D13+'P001'!$E13+'P001'!$F13+'P001'!$G13+'P001'!$H13+'P001'!$I13+'P001'!$J13) -> 0 | L13: ='P001'!$B13-'P001'!$K13 -> 0
A14: Octubre | K14: ='P001'!$B14-('P001'!$C14+'P001'!$D14+'P001'!$E14+'P001'!$F14+'P001'!$G14+'P001'!$H14+'P001'!$I14+'P001'!$J14) -> 0 | L14: ='P001'!$B14-'P001'!$K14 -> 0
A15: Noviembre | K15: ='P001'!$B15-('P001'!$C15+'P001'!$D15+'P001'!$E15+'P001'!$F15+'P001'!$G15+'P001'!$H15+'P001'!$I15+'P001'!$J15) -> 0 | L15: ='P001'!$B15-'P001'!$K15 -> 0
A16: Diciembre | K16: ='P001'!$B16-('P001'!$C16+'P001'!$D16+'P001'!$E16+'P001'!$F16+'P001'!$G16+'P001'!$H16+'P001'!$I16+'P001'!$J16) -> 0 | L16: ='P001'!$B16-'P001'!$K16 -> 0
A18: NRO DE RECIBOS DE LOS PAGOS
C19: RECIBO 1 | D19: RECIBO 2 | E19: RECIBO 3 | F19: RECIBO 4 | G19: RECIBO 5 | H19: RECIBO 6 | I19: RECIBO 7 | J19: RECIBO 8
A20: Enero | C20: 9594
A21: Febrero | C21: 9664
A22: Marzo | C22: 9756
A23: Abril
A24: Mayo
A25: Junio
A26: Julio
A27: Agosto
A28: Septiembre
A29: Octubre
A30: Noviembre
A31: Diciembre

Sheet P004
A1: P004 | C1: DIAS DE FREITAS ADRIAN
A3: PAGOS DEL ALQUILER
B4: COSTO | C4: PAGO 1 | D4: PAGO 2 | E4: PAGO 3 | F4: PAGO 4 | G4: PAGO 5 | H4: PAGO 6 | I4: PAGO 7 | J4: PAGO 8 | K4: SALDO | L4: RECAUDADO
A5: Enero | B5: 128600 | C5: 128600 | K5: ='P004'!$B5-('P004'!$C5+'P004'!$D5+'P004'!$E5+'P004'!$F5+'P004'!$G5+'P004'!$H5+'P004'!$I5+'P004'!$J5) -> 0 | L5: ='P004'!$B5-'P004'!$K5 -> 128600
A6: Febrero | B6: 175000 | C6: 161500 | D6: 13500 | K6: ='P004'!$B6-('P004'!$C6+'P004'!$D6+'P004'!$E6+'P004'!$F6+'P004'!$G6+'P004'!$H6+'P004'!$I6+'P004'!$J6) -> 0 | L6: ='P004'!$B6-'P004'!$K6 -> 175000
A7: Marzo | B7: 175000 | C7: 161500 | D7: 13500 | K7: ='P004'!$B7-('P004'!$C7+'P004'!$D7+'P004'!$E7+'P004'!$F7+'P004'!$G7+'P004'!$H7+'P004'!$I7+'P004'!$J7) -> 0 | L7: ='P004'!$B7-'P004'!$K7 -> 175000
A8: Abril | B8: 175000 | C8: 161500 | D8: 13500 | K8: ='P004'!$B8-('P004'!$C8+'P004'!$D8+'P004'!$E8+'P004'!$F8+'P004'!$G8+'P004'!$H8+'P004'!$I8+'P004'!$J8) -> 0 | L8: ='P004'!$B8-'P004'!$K8 -> 175000
A9: Mayo | B9: 175000 | C9: 115500 | D9: 46000 | E9: 13500 | K9: ='P004'!$B9-('P004'!$C9+'P004'!$D9+'P004'!$E9+'P004'!$F9+'P004'!$G9+'P004'!$H9+'P004'!$I9+'P004'!$J9) -> 0 | L9: ='P004'!$B9-'P004'!$K9 -> 175000
A10: Junio | B10: 175000 | C10: 54000 | D10: 107500 | E10: 13500 | K10: ='P004'!$B10-('P004'!$C10+'P004'!$D10+'P004'!$E10+'P004'!$F10+'P004'!$G10+'P004'!$H10+'P004'!$I10+'P004'!$J10) -> 0 | L10: ='P004'!$B10-'P004'!$K10 -> 175000
A11: Julio | B11: 175000 | C11: 161500 | D11: 13500 | K11: ='P004'!$B11-('P004'!$C11+'P004'!$D11+'P004'!$E11+'P004'!$F11+'P004'!$G11+'P004'!$H11+'P004'!$I11+'P004'!$J11) -> 0 | L11: ='P004'!$B11-'P004'!$K11 -> 175000
A12: Agosto | B12: 175000 | C12: 161500 | D12: 13500 | K12: ='P004'!$B12-('P004'!$C12+'P004'!$D12+'P004'!$E12+'P004'!$F12+'P004'!$G12+'P004'!$H12+'P004'!$I12+'P004'!$J12) -> 0 | L12: ='P004'!$B12-'P004'!$K12 -> 175000
A13: Septiembre | B13: 175000 | C13: 161500 | D13: 13500 | K13: ='P004'!$B13-('P004'!$C13+'P004'!$D13+'P004'!$E13+'P004'!$F13+'P004'!$G13+'P004'!$H13+'P004'!$I13+'P004'!$J13) -> 0 | L13: ='P004'!$B13-'P004'!$K13 -> 175000
A14: Octubre | B14: 175000 | C14: 8000 | D14: 153500 | E14: 13500 | K14: ='P004'!$B14-('P004'!$C14+'P004'!$D14+'P004'!$E14+'P004'!$F14+'P004'!$G14+'P004'!$H14+'P004'!$I14+'P004'!$J14) -> 0 | L14: ='P004'!$B14-'P004'!$K14 -> 175000
A15: Noviembre | B15: 175000 | C15: 11500 | D15: 163500 | K15: ='P004'!$B15-('P004'!$C15+'P004'!$D15+'P004'!$E15+'P004'!$F15+'P004'!$G15+'P004'!$H15+'P004'!$I15+'P004'!$J15) -> 0 | L15: ='P004'!$B15-'P004'!$K15 -> 175000
A16: Diciembre | K16: ='P004'!$B16-('P004'!$C16+'P004'!$D16+'P004'!$E16+'P004'!$F16+'P004'!$G16+'P004'!$H16+'P004'!$I16+'P004'!$J16) -> 0 | L16: ='P004'!$B16-'P004'!$K16 -> 0
A18: NRO DE RECIBOS DE LOS PAGOS
C19: RECIBO 1 | D19: RECIBO 2 | E19: RECIBO 3 | F19: RECIBO 4 | G19: RECIBO 5 | H19: RECIBO 6 | I19: RECIBO 7 | J19: RECIBO 8
A20: Enero | C20: 8708 | D20: 9486
A21: Febrero | C21: 9426 | D21: 9486
A22: Marzo | C22: 9426 | D22: 9486
A23: Abril | C23: 9426 | D23: 9486
A24: Mayo | C24: 9426 | D24: 9436 | E24: 9486
A25: Junio | C25: 9436 | D25: 9476 | E25: 9486
A26: Julio | C26: 9476 | D26: 9486
A27: Agosto | C27: 9476 | D27: 9486
A28: Septiembre | C28: 9476 | D28: 9486
A29: Octubre | C29: 9476 | D29: 9486
A30: Noviembre | C30: 9486
A31: Diciembre
N44: 2900
N46: 3400
N49: 34600
N64: 7602

Sheet P002
A3: PAGOS DEL ALQUILER
B4: COSTO | C4: PAGO 1 | D4: PAGO 2 | E4: PAGO 3 | F4: PAGO 4 | G4: PAGO 5 | H4: PAGO 6 | I4: PAGO 7 | J4: PAGO 8 | K4: SALDO | L4: RECAUDADO
A5: Enero | K5: ='P002'!$B5-('P002'!$C5+'P002'!$D5+'P002'!$E5+'P002'!$F5+'P002'!$G5+'P002'!$H5+'P002'!$I5+'P002'!$J5) -> 0 | L5: ='P002'!$B5-'P002'!$K5 -> 0
A6: Febrero | K6: ='P002'!$B6-('P002'!$C6+'P002'!$D6+'P002'!$E6+'P002'!$F6+'P002'!$G6+'P002'!$H6+'P002'!$I6+'P002'!$J6) -> 0 | L6: ='P002'!$B6-'P002'!$K6 -> 0
A7: Marzo | K7: ='P002'!$B7-('P002'!$C7+'P002'!$D7+'P002'!$E7+'P002'!$F7+'P002'!$G7+'P002'!$H7+'P002'!$I7+'P002'!$J7) -> 0 | L7: ='P002'!$B7-'P002'!$K7 -> 0
A8: Abril | K8: ='P002'!$B8-('P002'!$C8+'P002'!$D8+'P002'!$E8+'P002'!$F8+'P002'!$G8+'P002'!$H8+'P002'!$I8+'P002'!$J8) -> 0 | L8: ='P002'!$B8-'P002'!$K8 -> 0
A9: Mayo | K9: ='P002'!$B9-('P002'!$C9+'P002'!$D9+'P002'!$E9+'P002'!$F9+'P002'!$G9+'P002'!$H9+'P002'!$I9+'P002'!$J9) -> 0 | L9: ='P002'!$B9-'P002'!$K9 -> 0
A10: Junio | K10: ='P002'!$B10-('P002'!$C10+'P002'!$D10+'P002'!$E10+'P002'!$F10+'P002'!$G10+'P002'!$H10+'P002'!$I10+'P002'!$J10) -> 0 | L10: ='P002'!$B10-'P002'!$K10 -> 0
A11: Julio | K11: ='P002'!$B11-('P002'!$C11+'P002'!$D11+'P002'!$E11+'P002'!$F11+'P002'!$G11+'P002'!$H11+'P002'!$I11+'P002'!$J11) -> 0 | L11: ='P002'!$B11-'P002'!$K11 -> 0
A12: Agosto | K12: ='P002'!$B12-('P002'!$C12+'P002'!$D12+'P002'!$E12+'P002'!$F12+'P002'!$G12+'P002'!$H12+'P002'!$I12+'P002'!$J12) -> 0 | L12: ='P002'!$B12-'P002'!$K12 -> 0
A13: Septiembre | K13: ='P002'!$B13-('P002'!$C13+'P002'!$D13+'P002'!$E13+'P002'!$F13+'P002'!$G13+'P002'!$H13+'P002'!$I13+'P002'!$J13) -> 0 | L13: ='P002'!$B13-'P002'!$K13 -> 0
A14: Octubre | K14: ='P002'!$B14-('P002'!$C14+'P002'!$D14+'P002'!$E14+'P002'!$F14+'P002'!$G14+'P002'!$H14+'P002'!$I14+'P002'!$J14) -> 0 | L14: ='P002'!$B14-'P002'!$K14 -> 0
A15: Noviembre | K15: ='P002'!$B15-('P002'!$C15+'P002'!$D15+'P002'!$E15+'P002'!$F15+'P002'!$G15+'P002'!$H15+'P002'!$I15+'P002'!$J15) -> 0 | L15: ='P002'!$B15-'P002'!$K15 -> 0
A16: Diciembre | K16: ='P002'!$B16-('P002'!$C16+'P002'!$D16+'P002'!$E16+'P002'!$F16+'P002'!$G16+'P002'!$H16+'P002'!$I16+'P002'!$J16) -> 0 | L16: ='P002'!$B16-'P002'!$K16 -> 0
A18: NRO DE RECIBOS DE LOS PAGOS
C19: RECIBO 1 | D19: RECIBO 2 | E19: RECIBO 3 | F19: RECIBO 4 | G19: RECIBO 5 | H19: RECIBO 6 | I19: RECIBO 7 | J19: RECIBO 8
A20: Enero
A21: Febrero
A22: Marzo
A23: Abril
A24: Mayo
A25: Junio
A26: Julio
A27: Agosto
A28: Septiembre
A29: Octubre
A30: Noviembre
A31: Diciembre

Sheet P003
A3: PAGOS DEL ALQUILER
B4: COSTO | C4: PAGO 1 | D4: PAGO 2 | E4: PAGO 3 | F4: PAGO 4 | G4: PAGO 5 | H4: PAGO 6 | I4: PAGO 7 | J4: PAGO 8 | K4: SALDO | L4: RECAUDADO
A5: Enero | K5: ='P003'!$B5-('P003'!$C5+'P003'!$D5+'P003'!$E5+'P003'!$F5+'P003'!$G5+'P003'!$H5+'P003'!$I5+'P003'!$J5) -> 0 | L5: ='P003'!$B5-'P003'!$K5 -> 0
A6: Febrero | K6: ='P003'!$B6-('P003'!$C6+'P003'!$D6+'P003'!$E6+'P003'!$F6+'P003'!$G6+'P003'!$H6+'P003'!$I6+'P003'!$J6) -> 0 | L6: ='P003'!$B6-'P003'!$K6 -> 0
A7: Marzo | K7: ='P003'!$B7-('P003'!$C7+'P003'!$D7+'P003'!$E7+'P003'!$F7+'P003'!$G7+'P003'!$H7+'P003'!$I7+'P003'!$J7) -> 0 | L7: ='P003'!$B7-'P003'!$K7 -> 0
A8: Abril | K8: ='P003'!$B8-('P003'!$C8+'P003'!$D8+'P003'!$E8+'P003'!$F8+'P003'!$G8+'P003'!$H8+'P003'!$I8+'P003'!$J8) -> 0 | L8: ='P003'!$B8-'P003'!$K8 -> 0
A9: Mayo | K9: ='P003'!$B9-('P003'!$C9+'P003'!$D9+'P003'!$E9+'P003'!$F9+'P003'!$G9+'P003'!$H9+'P003'!$I9+'P003'!$J9) -> 0 | L9: ='P003'!$B9-'P003'!$K9 -> 0
A10: Junio | K10: ='P003'!$B10-('P003'!$C10+'P003'!$D10+'P003'!$E10+'P003'!$F10+'P003'!$G10+'P003'!$H10+'P003'!$I10+'P003'!$J10) -> 0 | L10: ='P003'!$B10-'P003'!$K10 -> 0
A11: Julio | K11: ='P003'!$B11-('P003'!$C11+'P003'!$D11+'P003'!$E11+'P003'!$F11+'P003'!$G11+'P003'!$H11+'P003'!$I11+'P003'!$J11) -> 0 | L11: ='P003'!$B11-'P003'!$K11 -> 0
A12: Agosto | K12: ='P003'!$B12-('P003'!$C12+'P003'!$D12+'P003'!$E12+'P003'!$F12+'P003'!$G12+'P003'!$H12+'P003'!$I12+'P003'!$J12) -> 0 | L12: ='P003'!$B12-'P003'!$K12 -> 0
A13: Septiembre | K13: ='P003'!$B13-('P003'!$C13+'P003'!$D13+'P003'!$E13+'P003'!$F13+'P003'!$G13+'P003'!$H13+'P003'!$I13+'P003'!$J13) -> 0 | L13: ='P003'!$B13-'P003'!$K13 -> 0
A14: Octubre | K14: ='P003'!$B14-('P003'!$C14+'P003'!$D14+'P003'!$E14+'P003'!$F14+'P003'!$G14+'P003'!$H14+'P003'!$I14+'P003'!$J14) -> 0 | L14: ='P003'!$B14-'P003'!$K14 -> 0
A15: Noviembre | K15: ='P003'!$B15-('P003'!$C15+'P003'!$D15+'P003'!$E15+'P003'!$F15+'P003'!$G15+'P003'!$H15+'P003'!$I15+'P003'!$J15) -> 0 | L15: ='P003'!$B15-'P003'!$K15 -> 0
A16: Diciembre | K16: ='P003'!$B16-('P003'!$C16+'P003'!$D16+'P003'!$E16+'P003'!$F16+'P003'!$G16+'P003'!$H16+'P003'!$I16+'P003'!$J16) -> 0 | L16: ='P003'!$B16-'P003'!$K16 -> 0
A18: NRO DE RECIBOS DE LOS PAGOS
C19: RECIBO 1 | D19: RECIBO 2 | E19: RECIBO 3 | F19: RECIBO 4 | G19: RECIBO 5 | H19: RECIBO 6 | I19: RECIBO 7 | J19: RECIBO 8
A20: Enero
A21: Febrero
A22: Marzo
A23: Abril
A24: Mayo
A25: Junio
A26: Julio
A27: Agosto
A28: Septiembre
A29: Octubre
A30: Noviembre
A31: Diciembre

Sheet P005
A1: P005 | C1: URSULA HUBER
A3: PAGOS DEL ALQUILER
B4: 177600 | C4: PAGO 1 | D4: PAGO 2 | E4: PAGO 3 | F4: PAGO 4 | G4: PAGO 5 | H4: PAGO 6 | I4: PAGO 7 | J4: PAGO 8 | K4: SALDO | L4: RECAUDADO
A5: Enero | B5: 177600 | C5: 177600 | K5: ='P005'!$B5-('P005'!$C5+'P005'!$D5+'P005'!$E5+'P005'!$F5+'P005'!$G5+'P005'!$H5+'P005'!$I5+'P005'!$J5) -> 0 | L5: ='P005'!$B5-'P005'!$K5 -> 177600 | M5: 13500
A6: Febrero | B6: 177600 | C6: 177600 | K6: ='P005'!$B6-('P005'!$C6+'P005'!$D6+'P005'!$E6+'P005'!$F6+'P005'!$G6+'P005'!$H6+'P005'!$I6+'P005'!$J6) -> 0 | L6: ='P005'!$B6-'P005'!$K6 -> 177600 | M6: 13500
A7: Marzo | K7: ='P005'!$B7-('P005'!$C7+'P005'!$D7+'P005'!$E7+'P005'!$F7+'P005'!$G7+'P005'!$H7+'P005'!$I7+'P005'!$J7) -> 0 | L7: ='P005'!$B7-'P005'!$K7 -> 0
A8: Abril | K8: ='P005'!$B8-('P005'!$C8+'P005'!$D8+'P005'!$E8+'P005'!$F8+'P005'!$G8+'P005'!$H8+'P005'!$I8+'P005'!$J8) -> 0 | L8: ='P005'!$B8-'P005'!$K8 -> 0
A9: Mayo | K9: ='P005'!$B9-('P005'!$C9+'P005'!$D9+'P005'!$E9+'P005'!$F9+'P005'!$G9+'P005'!$H9+'P005'!$I9+'P005'!$J9) -> 0 | L9: ='P005'!$B9-'P005'!$K9 -> 0
A10: Junio | K10: ='P005'!$B10-('P005'!$C10+'P005'!$D10+'P005'!$E10+'P005'!$F10+'P005'!$G10+'P005'!$H10+'P005'!$I10+'P005'!$J10) -> 0 | L10: ='P005'!$B10-'P005'!$K10 -> 0
A11: Julio | K11: ='P005'!$B11-('P005'!$C11+'P005'!$D11+'P005'!$E11+'P005'!$F11+'P005'!$G11+'P005'!$H11+'P005'!$I11+'P005'!$J11) -> 0 | L11: ='P005'!$B11-'P005'!$K11 -> 0
A12: Agosto | K12: ='P005'!$B12-('P005'!$C12+'P005'!$D12+'P005'!$E12+'P005'!$F12+'P005'!$G12+'P005'!$H12+'P005'!$I12+'P005'!$J12) -> 0 | L12: ='P005'!$B12-'P005'!$K12 -> 0
A13: Septiembre | K13: ='P005'!$B13-('P005'!$C13+'P005'!$D13+'P005'!$E13+'P005'!$F13+'P005'!$G13+'P005'!$H13+'P005'!$I13+'P005'!$J13) -> 0 | L13: ='P005'!$B13-'P005'!$K13 -> 0
A14: Octubre | K14: ='P005'!$B14-('P005'!$C14+'P005'!$D14+'P005'!$E14+'P005'!$F14+'P005'!$G14+'P005'!$H14+'P005'!$I14+'P005'!$J14) -> 0 | L14: ='P005'!$B14-'P005'!$K14 -> 0
A15: Noviembre | K15: ='P005'!$B15-('P005'!$C15+'P005'!$D15+'P005'!$E15+'P005'!$F15+'P005'!$G15+'P005'!$H15+'P005'!$I15+'P005'!$J15) -> 0 | L15: ='P005'!$B15-'P005'!$K15 -> 0
A16: Diciembre | K16: ='P005'!$B16-('P005'!$C16+'P005'!$D16+'P005'!$E16+'P005'!$F16+'P005'!$G16+'P005'!$H16+'P005'!$I16+'P005'!$J16) -> 0 | L16: ='P005'!$B16-'P005'!$K16 -> 0
A18: NRO DE RECIBOS DE LOS PAGOS
C19: RECIBO 1 | D19: RECIBO 2 | E19: RECIBO 3 | F19: RECIBO 4 | G19: RECIBO 5 | H19: RECIBO 6 | I19: RECIBO 7 | J19: RECIBO 8
A20: Enero | C20: 9598
A21: Febrero | C21: 9703
A22: Marzo
A23: Abril
A24: Mayo
A25: Junio
A26: Julio
A27: Agosto
A28: Septiembre
A29: Octubre
A30: Noviembre
A31: Diciembre

Sheet P006
A1: P6 | C1: ROSALINA FERNANDEZ
A3: PAGOS DEL ALQUILER
B4: 177600 | C4: PAGO 1 | D4: PAGO 2 | E4: PAGO 3 | F4: PAGO 4 | G4: PAGO 5 | H4: PAGO 6 | I4: PAGO 7 | J4: PAGO 8 | K4: SALDO | L4: RECAUDADO
A5: Enero | B5: 177600 | C5: 177600 | K5: ='P006'!$B5-('P006'!$C5+'P006'!$D5+'P006'!$E5+'P006'!$F5+'P006'!$G5+'P006'!$H5+'P006'!$I5+'P006'!$J5) -> 0 | L5: ='P006'!$B5-'P006'!$K5 -> 177600 | M5: 13500
A6: Febrero | B6: 177600 | C6: 177600 | K6: ='P006'!$B6-('P006'!$C6+'P006'!$D6+'P006'!$E6+'P006'!$F6+'P006'!$G6+'P006'!$H6+'P006'!$I6+'P006'!$J6) -> 0 | L6: ='P006'!$B6-'P006'!$K6 -> 177600 | M6: 13500
A7: Marzo | K7: ='P006'!$B7-('P006'!$C7+'P006'!$D7+'P006'!$E7+'P006'!$F7+'P006'!$G7+'P006'!$H7+'P006'!$I7+'P006'!$J7) -> 0 | L7: ='P006'!$B7-'P006'!$K7 -> 0
A8: Abril | K8: ='P006'!$B8-('P006'!$C8+'P006'!$D8+'P006'!$E8+'P006'!$F8+'P006'!$G8+'P006'!$H8+'P006'!$I8+'P006'!$J8) -> 0 | L8: ='P006'!$B8-'P006'!$K8 -> 0
A9: Mayo | K9: ='P006'!$B9-('P006'!$C9+'P006'!$D9+'P006'!$E9+'P006'!$F9+'P006'!$G9+'P006'!$H9+'P006'!$I9+'P006'!$J9) -> 0 | L9: ='P006'!$B9-'P006'!$K9 -> 0
A10: Junio | K10: ='P006'!$B10-('P006'!$C10+'P006'!$D10+'P006'!$E10+'P006'!$F10+'P006'!$G10+'P006'!$H10+'P006'!$I10+'P006'!$J10) -> 0 | L10: ='P006'!$B10-'P006'!$K10 -> 0
A11: Julio | K11: ='P006'!$B11-('P006'!$C11+'P006'!$D11+'P006'!$E11+'P006'!$F11+'P006'!$G11+'P006'!$H11+'P006'!$I11+'P006'!$J11) -> 0 | L11: ='P006'!$B11-'P006'!$K11 -> 0
A12: Agosto | K12: ='P006'!$B12-('P006'!$C12+'P006'!$D12+'P006'!$E12+'P006'!$F12+'P006'!$G12+'P006'!$H12+'P006'!$I12+'P006'!$J12) -> 0 | L12: ='P006'!$B12-'P006'!$K12 -> 0
A13: Septiembre | K13: ='P006'!$B13-('P006'!$C13+'P006'!$D13+'P006'!$E13+'P006'!$F13+'P006'!$G13+'P006'!$H13+'P006'!$I13+'P006'!$J13) -> 0 | L13: ='P006'!$B13-'P006'!$K13 -> 0
A14: Octubre | K14: ='P006'!$B14-('P006'!$C14+'P006'!$D14+'P006'!$E14+'P006'!$F14+'P006'!$G14+'P006'!$H14+'P006'!$I14+'P006'!$J14) -> 0 | L14: ='P006'!$B14-'P006'!$K14 -> 0
A15: Noviembre | K15: ='P006'!$B15-('P006'!$C15+'P006'!$D15+'P006'!$E15+'P006'!$F15+'P006'!$G15+'P006'!$H15+'P006'!$I15+'P006'!$J15) -> 0 | L15: ='P006'!$B15-'P006'!$K15 -> 0
A16: Diciembre | K16: ='P006'!$B16-('P006'!$C16+'P006'!$D16+'P006'!$E16+'P006'!$F16+'P006'!$G16+'P006'!$H16+'P006'!$I16+'P006'!$J16) -> 0 | L16: ='P006'!$B16-'P006'!$K16 -> 0
A18: NRO DE RECIBOS DE LOS PAGOS
C19: RECIBO 1 | D19: RECIBO 2 | E19: RECIBO 3 | F19: RECIBO 4 | G19: RECIBO 5 | H19: RECIBO 6 | I19: RECIBO 7 | J19: RECIBO 8
A20: Enero | C20: 9636
A21: Febrero | C21: 9706
A22: Marzo
A23: Abril
A24: Mayo
A25: Junio
A26: Julio
A27: Agosto
A28: Septiembre
A29: Octubre
A30: Noviembre
A31: Diciembre

Sheet P007
A3: PAGOS DEL ALQUILER
B4: COSTO | C4: PAGO 1 | D4: PAGO 2 | E4: PAGO 3 | F4: PAGO 4 | G4: PAGO 5 | H4: PAGO 6 | I4: PAGO 7 | J4: PAGO 8 | K4: SALDO | L4: RECAUDADO
A5: Enero | K5: ='P007'!$B5-('P007'!$C5+'P007'!$D5+'P007'!$E5+'P007'!$F5+'P007'!$G5+'P007'!$H5+'P007'!$I5+'P007'!$J5) -> 0 | L5: ='P007'!$B5-'P007'!$K5 -> 0
A6: Febrero | K6: ='P007'!$B6-('P007'!$C6+'P007'!$D6+'P007'!$E6+'P007'!$F6+'P007'!$G6+'P007'!$H6+'P007'!$I6+'P007'!$J6) -> 0 | L6: ='P007'!$B6-'P007'!$K6 -> 0
A7: Marzo | K7: ='P007'!$B7-('P007'!$C7+'P007'!$D7+'P007'!$E7+'P007'!$F7+'P007'!$G7+'P007'!$H7+'P007'!$I7+'P007'!$J7) -> 0 | L7: ='P007'!$B7-'P007'!$K7 -> 0
A8: Abril | K8: ='P007'!$B8-('P007'!$C8+'P007'!$D8+'P007'!$E8+'P007'!$F8+'P007'!$G8+'P007'!$H8+'P007'!$I8+'P007'!$J8) -> 0 | L8: ='P007'!$B8-'P007'!$K8 -> 0
A9: Mayo | K9: ='P007'!$B9-('P007'!$C9+'P007'!$D9+'P007'!$E9+'P007'!$F9+'P007'!$G9+'P007'!$H9+'P007'!$I9+'P007'!$J9) -> 0 | L9: ='P007'!$B9-'P007'!$K9 -> 0
A10: Junio | K10: ='P007'!$B10-('P007'!$C10+'P007'!$D10+'P007'!$E10+'P007'!$F10+'P007'!$G10+'P007'!$H10+'P007'!$I10+'P007'!$J10) -> 0 | L10: ='P007'!$B10-'P007'!$K10 -> 0
A11: Julio | K11: ='P007'!$B11-('P007'!$C11+'P007'!$D11+'P007'!$E11+'P007'!$F11+'P007'!$G11+'P007'!$H11+'P007'!$I11+'P007'!$J11) -> 0 | L11: ='P007'!$B11-'P007'!$K11 -> 0
A12: Agosto | K12: ='P007'!$B12-('P007'!$C12+'P007'!$D12+'P007'!$E12+'P007'!$F12+'P007'!$G12+'P007'!$H12+'P007'!$I12+'P007'!$J12) -> 0 | L12: ='P007'!$B12-'P007'!$K12 -> 0
A13: Septiembre | K13: ='P007'!$B13-('P007'!$C13+'P007'!$D13+'P007'!$E13+'P007'!$F13+'P007'!$G13+'P007'!$H13+'P007'!$I13+'P007'!$J13) -> 0 | L13: ='P007'!$B13-'P007'!$K13 -> 0
A14: Octubre | K14: ='P007'!$B14-('P007'!$C14+'P007'!$D14+'P007'!$E14+'P007'!$F14+'P007'!$G14+'P007'!$H14+'P007'!$I14+'P007'!$J14) -> 0 | L14: ='P007'!$B14-'P007'!$K14 -> 0
A15: Noviembre | K15: ='P007'!$B15-('P007'!$C15+'P007'!$D15+'P007'!$E15+'P007'!$F15+'P007'!$G15+'P007'!$H15+'P007'!$I15+'P007'!$J15) -> 0 | L15: ='P007'!$B15-'P007'!$K15 -> 0
A16: Diciembre | K16: ='P007'!$B16-('P007'!$C16+'P007'!$D16+'P007'!$E16+'P007'!$F16+'P007'!$G16+'P007'!$H16+'P007'!$I16+'P007'!$J16) -> 0 | L16: ='P007'!$B16-'P007'!$K16 -> 0
A18: NRO DE RECIBOS DE LOS PAGOS
C19: RECIBO 1 | D19: RECIBO 2 | E19: RECIBO 3 | F19: RECIBO 4 | G19: RECIBO 5 | H19: RECIBO 6 | I19: RECIBO 7 | J19: RECIBO 8
A20: Enero
A21: Febrero
A22: Marzo
A23: Abril
A24: Mayo
A25: Junio
A26: Julio
A27: Agosto
A28: Septiembre
A29: Octubre
A30: Noviembre
A31: Diciembre

Sheet P009
A1: P.9 | C1: ACOSTA EVANY
A3: PAGOS DEL ALQUILER
B4: 177600 | C4: PAGO 1 | D4: PAGO 2 | E4: PAGO 3 | F4: PAGO 4 | G4: PAGO 5 | H4: PAGO 6 | I4: PAGO 7 | J4: PAGO 8 | K4: SALDO | L4: RECAUDADO
A5: Enero | B5: 177600 | C5: 177600 | K5: ='P009'!$B5-('P009'!$C5+'P009'!$D5+'P009'!$E5+'P009'!$F5+'P009'!$G5+'P009'!$H5+'P009'!$I5+'P009'!$J5) -> 0 | L5: ='P009'!$B5-'P009'!$K5 -> 177600 | M5: 13500
A6: Febrero | B6: 177600 | C6: 177600 | K6: ='P009'!$B6-('P009'!$C6+'P009'!$D6+'P009'!$E6+'P009'!$F6+'P009'!$G6+'P009'!$H6+'P009'!$I6+'P009'!$J6) -> 0 | L6: ='P009'!$B6-'P009'!$K6 -> 177600 | M6: 13500
A7: Marzo | B7: 193200 | C7: 193200 | K7: ='P009'!$B7-('P009'!$C7+'P009'!$D7+'P009'!$E7+'P009'!$F7+'P009'!$G7+'P009'!$H7+'P009'!$I7+'P009'!$J7) -> 0 | L7: ='P009'!$B7-'P009'!$K7 -> 193200 | M7: 13500
A8: Abril | B8: 193200 | K8: ='P009'!$B8-('P009'!$C8+'P009'!$D8+'P009'!$E8+'P009'!$F8+'P009'!$G8+'P009'!$H8+'P009'!$I8+'P009'!$J8) -> 193200 | L8: ='P009'!$B8-'P009'!$K8 -> 0
A9: Mayo | K9: ='P009'!$B9-('P009'!$C9+'P009'!$D9+'P009'!$E9+'P009'!$F9+'P009'!$G9+'P009'!$H9+'P009'!$I9+'P009'!$J9) -> 0 | L9: ='P009'!$B9-'P009'!$K9 -> 0
A10: Junio | K10: ='P009'!$B10-('P009'!$C10+'P009'!$D10+'P009'!$E10+'P009'!$F10+'P009'!$G10+'P009'!$H10+'P009'!$I10+'P009'!$J10) -> 0 | L10: ='P009'!$B10-'P009'!$K10 -> 0
A11: Julio | K11: ='P009'!$B11-('P009'!$C11+'P009'!$D11+'P009'!$E11+'P009'!$F11+'P009'!$G11+'P009'!$H11+'P009'!$I11+'P009'!$J11) -> 0 | L11: ='P009'!$B11-'P009'!$K11 -> 0
A12: Agosto | K12: ='P009'!$B12-('P009'!$C12+'P009'!$D12+'P009'!$E12+'P009'!$F12+'P009'!$G12+'P009'!$H12+'P009'!$I12+'P009'!$J12) -> 0 | L12: ='P009'!$B12-'P009'!$K12 -> 0
A13: Septiembre | K13: ='P009'!$B13-('P009'!$C13+'P009'!$D13+'P009'!$E13+'P009'!$F13+'P009'!$G13+'P009'!$H13+'P009'!$I13+'P009'!$J13) -> 0 | L13: ='P009'!$B13-'P009'!$K13 -> 0
A14: Octubre | K14: ='P009'!$B14-('P009'!$C14+'P009'!$D14+'P009'!$E14+'P009'!$F14+'P009'!$G14+'P009'!$H14+'P009'!$I14+'P009'!$J14) -> 0 | L14: ='P009'!$B14-'P009'!$K14 -> 0
A15: Noviembre | K15: ='P009'!$B15-('P009'!$C15+'P009'!$D15+'P009'!$E15+'P009'!$F15+'P009'!$G15+'P009'!$H15+'P009'!$I15+'P009'!$J15) -> 0 | L15: ='P009'!$B15-'P009'!$K15 -> 0
A16: Diciembre | K16: ='P009'!$B16-('P009'!$C16+'P009'!$D16+'P009'!$E16+'P009'!$F16+'P009'!$G16+'P009'!$H16+'P009'!$I16+'P009'!$J16) -> 0 | L16: ='P009'!$B16-'P009'!$K16 -> 0
A18: NRO DE RECIBOS DE LOS PAGOS
C19: RECIBO 1 | D19: RECIBO 2 | E19: RECIBO 3 | F19: RECIBO 4 | G19: RECIBO 5 | H19: RECIBO 6 | I19: RECIBO 7 | J19: RECIBO 8
A20: Enero | C20: 9627
A21: Febrero | C21: 9679
A22: Marzo | C22: 6757
A23: Abril
A24: Mayo
A25: Junio
A26: Julio
A27: Agosto
A28: Septiembre
A29: Octubre
A30: Noviembre
A31: Diciembre

Sheet P008
A1: 8 | C1: RUIZ PAOLA
A3: PAGOS DEL ALQUILER
B4: COSTO | C4: PAGO 1 | D4: PAGO 2 | E4: PAGO 3 | F4: PAGO 4 | G4: PAGO 5 | H4: PAGO 6 | I4: PAGO 7 | J4: PAGO 8 | K4: SALDO | L4: RECAUDADO
A5: Enero | B5: 355300 | C5: 355300 | K5: ='P008'!$B5-('P008'!$C5+'P008'!$D5+'P008'!$E5+'P008'!$F5+'P008'!$G5+'P008'!$H5+'P008'!$I5+'P008'!$J5) -> 0 | L5: ='P008'!$B5-'P008'!$K5 -> 355300 | M5: 13500
A6: Febrero | B6: 355300 | C6: 355300 | K6: ='P008'!$B6-('P008'!$C6+'P008'!$D6+'P008'!$E6+'P008'!$F6+'P008'!$G6+'P008'!$H6+'P008'!$I6+'P008'!$J6) -> 0 | L6: ='P008'!$B6-'P008'!$K6 -> 355300 | M6: 13500
A7: Marzo | B7: 386600 | C7: 346500 | K7: ='P008'!$B7-('P008'!$C7+'P008'!$D7+'P008'!$E7+'P008'!$F7+'P008'!$G7+'P008'!$H7+'P008'!$I7+'P008'!$J7) -> 40100 | L7: ='P008'!$B7-'P008'!$K7 -> 346500 | M7: 13500
A8: Abril | K8: ='P008'!$B8-('P008'!$C8+'P008'!$D8+'P008'!$E8+'P008'!$F8+'P008'!$G8+'P008'!$H8+'P008'!$I8+'P008'!$J8) -> 0 | L8: ='P008'!$B8-'P008'!$K8 -> 0
A9: Mayo | K9: ='P008'!$B9-('P008'!$C9+'P008'!$D9+'P008'!$E9+'P008'!$F9+'P008'!$G9+'P008'!$H9+'P008'!$I9+'P008'!$J9) -> 0 | L9: ='P008'!$B9-'P008'!$K9 -> 0
A10: Junio | K10: ='P008'!$B10-('P008'!$C10+'P008'!$D10+'P008'!$E10+'P008'!$F10+'P008'!$G10+'P008'!$H10+'P008'!$I10+'P008'!$J10) -> 0 | L10: ='P008'!$B10-'P008'!$K10 -> 0
A11: Julio | K11: ='P008'!$B11-('P008'!$C11+'P008'!$D11+'P008'!$E11+'P008'!$F11+'P008'!$G11+'P008'!$H11+'P008'!$I11+'P008'!$J11) -> 0 | L11: ='P008'!$B11-'P008'!$K11 -> 0
A12: Agosto | K12: ='P008'!$B12-('P008'!$C12+'P008'!$D12+'P008'!$E12+'P008'!$F12+'P008'!$G12+'P008'!$H12+'P008'!$I12+'P008'!$J12) -> 0 | L12: ='P008'!$B12-'P008'!$K12 -> 0
A13: Septiembre | K13: ='P008'!$B13-('P008'!$C13+'P008'!$D13+'P008'!$E13+'P008'!$F13+'P008'!$G13+'P008'!$H13+'P008'!$I13+'P008'!$J13) -> 0 | L13: ='P008'!$B13-'P008'!$K13 -> 0
A14: Octubre | K14: ='P008'!$B14-('P008'!$C14+'P008'!$D14+'P008'!$E14+'P008'!$F14+'P008'!$G14+'P008'!$H14+'P008'!$I14+'P008'!$J14) -> 0 | L14: ='P008'!$B14-'P008'!$K14 -> 0
A15: Noviembre | K15: ='P008'!$B15-('P008'!$C15+'P008'!$D15+'P008'!$E15+'P008'!$F15+'P008'!$G15+'P008'!$H15+'P008'!$I15+'P008'!$J15) -> 0 | L15: ='P008'!$B15-'P008'!$K15 -> 0
A16: Diciembre | K16: ='P008'!$B16-('P008'!$C16+'P008'!$D16+'P008'!$E16+'P008'!$F16+'P008'!$G16+'P008'!$H16+'P008'!$I16+'P008'!$J16) -> 0 | L16: ='P008'!$B16-'P008'!$K16 -> 0
A18: NRO DE RECIBOS DE LOS PAGOS
C19: RECIBO 1 | D19: RECIBO 2 | E19: RECIBO 3 | F19: RECIBO 4 | G19: RECIBO 5 | H19: RECIBO 6 | I19: RECIBO 7 | J19: RECIBO 8
A20: Enero | C20: 9607
A21: Febrero | C21: 9665
A22: Marzo | C22: 9730
A23: Abril
A24: Mayo
A25: Junio
A26: Julio
A27: Agosto
A28: Septiembre
A29: Octubre
A30: Noviembre
A31: Diciembre

Sheet P010
A1: Pto 10/11/125 | C1: FERREIRA ISABELLA
A3: PAGOS DEL ALQUILER
B4: COSTO | C4: PAGO 1 | D4: PAGO 2 | E4: PAGO 3 | F4: PAGO 4 | G4: PAGO 5 | H4: PAGO 6 | I4: PAGO 7 | J4: PAGO 8 | K4: SALDO | L4: RECAUDADO
A5: Enero | B5: 579700 | K5: ='P010'!$B5-('P010'!$C5+'P010'!$D5+'P010'!$E5+'P010'!$F5+'P010'!$G5+'P010'!$H5+'P010'!$I5+'P010'!$J5) -> 579700 | L5: ='P010'!$B5-'P010'!$K5 -> 0
A6: Febrero | B6: 579700 | K6: ='P010'!$B6-('P010'!$C6+'P010'!$D6+'P010'!$E6+'P010'!$F6+'P010'!$G6+'P010'!$H6+'P010'!$I6+'P010'!$J6) -> 579700 | L6: ='P010'!$B6-'P010'!$K6 -> 0 | O6: 26000
A7: Marzo | B7: 579700 | K7: ='P010'!$B7-('P010'!$C7+'P010'!$D7+'P010'!$E7+'P010'!$F7+'P010'!$G7+'P010'!$H7+'P010'!$I7+'P010'!$J7) -> 579700 | L7: ='P010'!$B7-'P010'!$K7 -> 0
A8: Abril | B8: 579700 | K8: ='P010'!$B8-('P010'!$C8+'P010'!$D8+'P010'!$E8+'P010'!$F8+'P010'!$G8+'P010'!$H8+'P010'!$I8+'P010'!$J8) -> 579700 | L8: ='P010'!$B8-'P010'!$K8 -> 0
A9: Mayo | B9: 579700 | K9: ='P010'!$B9-('P010'!$C9+'P010'!$D9+'P010'!$E9+'P010'!$F9+'P010'!$G9+'P010'!$H9+'P010'!$I9+'P010'!$J9) -> 579700 | L9: ='P010'!$B9-'P010'!$K9 -> 0
A10: Junio | K10: ='P010'!$B10-('P010'!$C10+'P010'!$D10+'P010'!$E10+'P010'!$F10+'P010'!$G10+'P010'!$H10+'P010'!$I10+'P010'!$J10) -> 0 | L10: ='P010'!$B10-'P010'!$K10 -> 0
A11: Julio | K11: ='P010'!$B11-('P010'!$C11+'P010'!$D11+'P010'!$E11+'P010'!$F11+'P010'!$G11+'P010'!$H11+'P010'!$I11+'P010'!$J11) -> 0 | L11: ='P010'!$B11-'P010'!$K11 -> 0
A12: Agosto | K12: ='P010'!$B12-('P010'!$C12+'P010'!$D12+'P010'!$E12+'P010'!$F12+'P010'!$G12+'P010'!$H12+'P010'!$I12+'P010'!$J12) -> 0 | L12: ='P010'!$B12-'P010'!$K12 -> 0
A13: Septiembre | K13: ='P010'!$B13-('P010'!$C13+'P010'!$D13+'P010'!$E13+'P010'!$F13+'P010'!$G13+'P010'!$H13+'P010'!$I13+'P010'!$J13) -> 0 | L13: ='P010'!$B13-'P010'!$K13 -> 0
A14: Octubre | K14: ='P010'!$B14-('P010'!$C14+'P010'!$D14+'P010'!$E14+'P010'!$F14+'P010'!$G14+'P010'!$H14+'P010'!$I14+'P010'!$J14) -> 0 | L14: ='P010'!$B14-'P010'!$K14 -> 0
A15: Noviembre | K15: ='P010'!$B15-('P010'!$C15+'P010'!$D15+'P010'!$E15+'P010'!$F15+'P010'!$G15+'P010'!$H15+'P010'!$I15+'P010'!$J15) -> 0 | L15: ='P010'!$B15-'P010'!$K15 -> 0
A16: Diciembre | K16: ='P010'!$B16-('P010'!$C16+'P010'!$D16+'P010'!$E16+'P010'!$F16+'P010'!$G16+'P010'!$H16+'P010'!$I16+'P010'!$J16) -> 0 | L16: ='P010'!$B16-'P010'!$K16 -> 0
A18: NRO DE RECIBOS DE LOS PAGOS
C19: RECIBO 1 | D19: RECIBO 2 | E19: RECIBO 3 | F19: RECIBO 4 | G19: RECIBO 5 | H19: RECIBO 6 | I19: RECIBO 7 | J19: RECIBO 8
A20: Enero
A21: Febrero
A22: Marzo
A23: Abril
A24: Mayo
A25: Junio
A26: Julio
A27: Agosto
A28: Septiembre
A29: Octubre
A30: Noviembre
A31: Diciembre

Sheet P011
A3: PAGOS DEL ALQUILER
B4: COSTO | C4: PAGO 1 | D4: PAGO 2 | E4: PAGO 3 | F4: PAGO 4 | G4: PAGO 5 | H4: PAGO 6 | I4: PAGO 7 | J4: PAGO 8 | K4: SALDO | L4: RECAUDADO
A5: Enero | K5: ='P011'!$B5-('P011'!$C5+'P011'!$D5+'P011'!$E5+'P011'!$F5+'P011'!$G5+'P011'!$H5+'P011'!$I5+'P011'!$J5) -> 0 | L5: ='P011'!$B5-'P011'!$K5 -> 0
A6: Febrero | K6: ='P011'!$B6-('P011'!$C6+'P011'!$D6+'P011'!$E6+'P011'!$F6+'P011'!$G6+'P011'!$H6+'P011'!$I6+'P011'!$J6) -> 0 | L6: ='P011'!$B6-'P011'!$K6 -> 0
A7: Marzo | K7: ='P011'!$B7-('P011'!$C7+'P011'!$D7+'P011'!$E7+'P011'!$F7+'P011'!$G7+'P011'!$H7+'P011'!$I7+'P011'!$J7) -> 0 | L7: ='P011'!$B7-'P011'!$K7 -> 0
A8: Abril | K8: ='P011'!$B8-('P011'!$C8+'P011'!$D8+'P011'!$E8+'P011'!$F8+'P011'!$G8+'P011'!$H8+'P011'!$I8+'P011'!$J8) -> 0 | L8: ='P011'!$B8-'P011'!$K8 -> 0
A9: Mayo | K9: ='P011'!$B9-('P011'!$C9+'P011'!$D9+'P011'!$E9+'P011'!$F9+'P011'!$G9+'P011'!$H9+'P011'!$I9+'P011'!$J9) -> 0 | L9: ='P011'!$B9-'P011'!$K9 -> 0
A10: Junio | K10: ='P011'!$B10-('P011'!$C10+'P011'!$D10+'P011'!$E10+'P011'!$F10+'P011'!$G10+'P011'!$H10+'P011'!$I10+'P011'!$J10) -> 0 | L10: ='P011'!$B10-'P011'!$K10 -> 0
A11: Julio | K11: ='P011'!$B11-('P011'!$C11+'P011'!$D11+'P011'!$E11+'P011'!$F11+'P011'!$G11+'P011'!$H11+'P011'!$I11+'P011'!$J11) -> 0 | L11: ='P011'!$B11-'P011'!$K11 -> 0
A12: Agosto | K12: ='P011'!$B12-('P011'!$C12+'P011'!$D12+'P011'!$E12+'P011'!$F12+'P011'!$G12+'P011'!$H12+'P011'!$I12+'P011'!$J12) -> 0 | L12: ='P011'!$B12-'P011'!$K12 -> 0
A13: Septiembre | K13: ='P011'!$B13-('P011'!$C13+'P011'!$D13+'P011'!$E13+'P011'!$F13+'P011'!$G13+'P011'!$H13+'P011'!$I13+'P011'!$J13) -> 0 | L13: ='P011'!$B13-'P011'!$K13 -> 0
A14: Octubre | K14: ='P011'!$B14-('P011'!$C14+'P011'!$D14+'P011'!$E14+'P011'!$F14+'P011'!$G14+'P011'!$H14+'P011'!$I14+'P011'!$J14) -> 0 | L14: ='P011'!$B14-'P011'!$K14 -> 0
A15: Noviembre | K15: ='P011'!$B15-('P011'!$C15+'P011'!$D15+'P011'!$E15+'P011'!$F15+'P011'!$G15+'P011'!$H15+'P011'!$I15+'P011'!$J15) -> 0 | L15: ='P011'!$B15-'P011'!$K15 -> 0
A16: Diciembre | K16: ='P011'!$B16-('P011'!$C16+'P011'!$D16+'P011'!$E16+'P011'!$F16+'P011'!$G16+'P011'!$H16+'P011'!$I16+'P011'!$J16) -> 0 | L16: ='P011'!$B16-'P011'!$K16 -> 0
A18: NRO DE RECIBOS DE LOS PAGOS
C19: RECIBO 1 | D19: RECIBO 2 | E19: RECIBO 3 | F19: RECIBO 4 | G19: RECIBO 5 | H19: RECIBO 6 | I19: RECIBO 7 | J19: RECIBO 8
A20: Enero
A21: Febrero
A22: Marzo
A23: Abril
A24: Mayo
A25: Junio
A26: Julio
A27: Agosto
A28: Septiembre
A29: Octubre
A30: Noviembre
A31: Diciembre

Sheet P012
A1: P012 | C1: CHUCHI
A3: PAGOS DEL ALQUILER
B4: COSTO | C4: PAGO 1 | D4: PAGO 2 | E4: PAGO 3 | F4: PAGO 4 | G4: PAGO 5 | H4: PAGO 6 | I4: PAGO 7 | J4: PAGO 8 | K4: SALDO | L4: RECAUDADO
A5: Enero | B5: 1821900 | C5: 1821900 | K5: ='P012'!$B5-('P012'!$C5+'P012'!$D5+'P012'!$E5+'P012'!$F5+'P012'!$G5+'P012'!$H5+'P012'!$I5+'P012'!$J5) -> 0 | L5: ='P012'!$B5-'P012'!$K5 -> 1821900 | M5: 40500
A6: Febrero | B6: 1821900 | C6: 1821900 | K6: ='P012'!$B6-('P012'!$C6+'P012'!$D6+'P012'!$E6+'P012'!$F6+'P012'!$G6+'P012'!$H6+'P012'!$I6+'P012'!$J6) -> 0 | L6: ='P012'!$B6-'P012'!$K6 -> 1821900 | M6: 40500
A7: Marzo | K7: ='P012'!$B7-('P012'!$C7+'P012'!$D7+'P012'!$E7+'P012'!$F7+'P012'!$G7+'P012'!$H7+'P012'!$I7+'P012'!$J7) -> 0 | L7: ='P012'!$B7-'P012'!$K7 -> 0
A8: Abril | K8: ='P012'!$B8-('P012'!$C8+'P012'!$D8+'P012'!$E8+'P012'!$F8+'P012'!$G8+'P012'!$H8+'P012'!$I8+'P012'!$J8) -> 0 | L8: ='P012'!$B8-'P012'!$K8 -> 0
A9: Mayo | K9: ='P012'!$B9-('P012'!$C9+'P012'!$D9+'P012'!$E9+'P012'!$F9+'P012'!$G9+'P012'!$H9+'P012'!$I9+'P012'!$J9) -> 0 | L9: ='P012'!$B9-'P012'!$K9 -> 0
A10: Junio | K10: ='P012'!$B10-('P012'!$C10+'P012'!$D10+'P012'!$E10+'P012'!$F10+'P012'!$G10+'P012'!$H10+'P012'!$I10+'P012'!$J10) -> 0 | L10: ='P012'!$B10-'P012'!$K10 -> 0
A11: Julio | K11: ='P012'!$B11-('P012'!$C11+'P012'!$D11+'P012'!$E11+'P012'!$F11+'P012'!$G11+'P012'!$H11+'P012'!$I11+'P012'!$J11) -> 0 | L11: ='P012'!$B11-'P012'!$K11 -> 0
A12: Agosto | K12: ='P012'!$B12-('P012'!$C12+'P012'!$D12+'P012'!$E12+'P012'!$F12+'P012'!$G12+'P012'!$H12+'P012'!$I12+'P012'!$J12) -> 0 | L12: ='P012'!$B12-'P012'!$K12 -> 0
A13: Septiembre | K13: ='P012'!$B13-('P012'!$C13+'P012'!$D13+'P012'!$E13+'P012'!$F13+'P012'!$G13+'P012'!$H13+'P012'!$I13+'P012'!$J13) -> 0 | L13: ='P012'!$B13-'P012'!$K13 -> 0
A14: Octubre | L14: ='P012'!$B14-'P012'!$K14 -> 0
A15: Noviembre | K15: ='P012'!$B15-('P012'!$C15+'P012'!$D15+'P012'!$E15+'P012'!$F15+'P012'!$G15+'P012'!$H15+'P012'!$I15+'P012'!$J15) -> 0 | L15: ='P012'!$B15-'P012'!$K15 -> 0
A16: Diciembre | K16: ='P012'!$B16-('P012'!$C16+'P012'!$D16+'P012'!$E16+'P012'!$F16+'P012'!$G16+'P012'!$H16+'P012'!$I16+'P012'!$J16) -> 0 | L16: ='P012'!$B16-'P012'!$K16 -> 0
A18: NRO DE RECIBOS DE LOS PAGOS
C19: RECIBO 1 | D19: RECIBO 2 | E19: RECIBO 3 | F19: RECIBO 4 | G19: RECIBO 5 | H19: RECIBO 6 | I19: RECIBO 7 | J19: RECIBO 8
A20: Enero | C20: 9625
A21: Febrero | C21: 9690
A22: Marzo
A23: Abril
A24: Mayo
A25: Junio
A26: Julio
A27: Agosto | K27: 9283
A28: Septiembre
A29: Octubre | K29: 9419
A30: Noviembre
A31: Diciembre

Sheet PO16
A1: 15/16/122/123 | C1: NORBERTO MAIDANA
A3: PAGOS DEL ALQUILER
B4: COSTO | C4: PAGO 1 | D4: PAGO 2 | E4: PAGO 3 | F4: PAGO 4 | G4: PAGO 5 | H4: PAGO 6 | I4: PAGO 7 | J4: PAGO 8 | K4: SALDO | L4: RECAUDADO | M4: interes | O4: impuesto | S4: DNI | T4: 24,572,126
A5: Enero | B5: 773200 | C5: 600 | K5: ='PO16'!$B5-('PO16'!$C5+'PO16'!$D5+'PO16'!$E5+'PO16'!$F5+'PO16'!$G5+'PO16'!$H5+'PO16'!$I5+'PO16'!$J5)+N5 -> 772600 | L5: ='PO16'!$B5-'PO16'!$K5 -> 600 | S5: DIRECCION | T5: 63a Cocomarola Oeste 9258 posadas
A6: Febrero | B6: 773200 | K6: ='PO16'!$B6-('PO16'!$C6+'PO16'!$D6+'PO16'!$E6+'PO16'!$F6+'PO16'!$G6+'PO16'!$H6+'PO16'!$I6+'PO16'!$J6)+N6 -> 773200 | L6: ='PO16'!$B6-'PO16'!$K6 -> 0 | S6: mail | T6: MPOLACO428-GMAIL.COM
A7: Marzo | B7: 773200 | K7: ='PO16'!$B7-('PO16'!$C7+'PO16'!$D7+'PO16'!$E7+'PO16'!$F7+'PO16'!$G7+'PO16'!$H7+'PO16'!$I7+'PO16'!$J7)+N7 -> 773200 | L7: ='PO16'!$B7-'PO16'!$K7 -> 0
A8: Abril | B8: 773200 | K8: ='PO16'!$B8-('PO16'!$C8+'PO16'!$D8+'PO16'!$E8+'PO16'!$F8+'PO16'!$G8+'PO16'!$H8+'PO16'!$I8+'PO16'!$J8)+N8 -> 773200 | L8: ='PO16'!$B8-'PO16'!$K8 -> 0
A9: Mayo | B9: 773200 | K9: ='PO16'!$B9-('PO16'!$C9+'PO16'!$D9+'PO16'!$E9+'PO16'!$F9+'PO16'!$G9+'PO16'!$H9+'PO16'!$I9+'PO16'!$J9)+N9 -> 773200 | L9: ='PO16'!$B9-'PO16'!$K9 -> 0
A10: Junio | K10: ='PO16'!$B10-('PO16'!$C10+'PO16'!$D10+'PO16'!$E10+'PO16'!$F10+'PO16'!$G10+'PO16'!$H10+'PO16'!$I10+'PO16'!$J10)+N10 -> 0 | L10: ='PO16'!$B10-'PO16'!$K10 -> 0
A11: Julio | K11: ='PO16'!$B11-('PO16'!$C11+'PO16'!$D11+'PO16'!$E11+'PO16'!$F11+'PO16'!$G11+'PO16'!$H11+'PO16'!$I11+'PO16'!$J11)+N11 -> 0 | L11: ='PO16'!$B11-'PO16'!$K11 -> 0
A12: Agosto | K12: ='PO16'!$B12-('PO16'!$C12+'PO16'!$D12+'PO16'!$E12+'PO16'!$F12+'PO16'!$G12+'PO16'!$H12+'PO16'!$I12+'PO16'!$J12)+N12 -> 0 | L12: ='PO16'!$B12-'PO16'!$K12 -> 0
A13: Septiembre | K13: ='PO16'!$B13-('PO16'!$C13+'PO16'!$D13+'PO16'!$E13+'PO16'!$F13+'PO16'!$G13+'PO16'!$H13+'PO16'!$I13+'PO16'!$J13)+N13 -> 0 | L13: ='PO16'!$B13-'PO16'!$K13 -> 0
A14: Octubre | K14: ='PO16'!$B14-('PO16'!$C14+'PO16'!$D14+'PO16'!$E14+'PO16'!$F14+'PO16'!$G14+'PO16'!$H14+'PO16'!$I14+'PO16'!$J14)+N14 -> 0 | L14: ='PO16'!$B14-'PO16'!$K14 -> 0
A15: Noviembre | K15: ='PO16'!$B15-('PO16'!$C15+'PO16'!$D15+'PO16'!$E15+'PO16'!$F15+'PO16'!$G15+'PO16'!$H15+'PO16'!$I15+'PO16'!$J15)+N15 -> 0 | L15: ='PO16'!$B15-'PO16'!$K15 -> 0
A16: Diciembre | K16: ='PO16'!$B16-('PO16'!$C16+'PO16'!$D16+'PO16'!$E16+'PO16'!$F16+'PO16'!$G16+'PO16'!$H16+'PO16'!$I16+'PO16'!$J16)+N16 -> 0 | L16: ='PO16'!$B16-'PO16'!$K16 -> 0
A18: NRO DE RECIBOS DE LOS PAGOS
C19: RECIBO 1 | D19: RECIBO 2 | E19: RECIBO 3 | F19: RECIBO 4 | G19: RECIBO 5 | H19: RECIBO 6 | I19: RECIBO 7 | J19: RECIBO 8
A20: Enero
A21: Febrero
A22: Marzo
A23: Abril
A24: Mayo
A25: Junio
A26: Julio
A27: Agosto
A28: Septiembre
A29: Octubre
A30: Noviembre
A31: Diciembre
N39: 12100
N40: 23350
N41: 13550
N42: 13550
N43: 3550
N44: 18500
N45: 16000
N46: 19500
N47: 14400
N48: 13400

Sheet Hoja 1

Sheet P014
A3: PAGOS DEL ALQUILER
B4: COSTO | C4: PAGO 1 | D4: PAGO 2 | E4: PAGO 3 | F4: PAGO 4 | G4: PAGO 5 | H4: PAGO 6 | I4: PAGO 7 | J4: PAGO 8 | K4: SALDO | L4: RECAUDADO
A5: Enero | K5: ='P014'!$B5-('P014'!$C5+'P014'!$D5+'P014'!$E5+'P014'!$F5+'P014'!$G5+'P014'!$H5+'P014'!$I5+'P014'!$J5) -> 0 | L5: ='P014'!$B5-'P014'!$K5 -> 0
A6: Febrero | K6: ='P014'!$B6-('P014'!$C6+'P014'!$D6+'P014'!$E6+'P014'!$F6+'P014'!$G6+'P014'!$H6+'P014'!$I6+'P014'!$J6) -> 0 | L6: ='P014'!$B6-'P014'!$K6 -> 0
A7: Marzo | K7: ='P014'!$B7-('P014'!$C7+'P014'!$D7+'P014'!$E7+'P014'!$F7+'P014'!$G7+'P014'!$H7+'P014'!$I7+'P014'!$J7) -> 0 | L7: ='P014'!$B7-'P014'!$K7 -> 0
A8: Abril | K8: ='P014'!$B8-('P014'!$C8+'P014'!$D8+'P014'!$E8+'P014'!$F8+'P014'!$G8+'P014'!$H8+'P014'!$I8+'P014'!$J8) -> 0 | L8: ='P014'!$B8-'P014'!$K8 -> 0
A9: Mayo | K9: ='P014'!$B9-('P014'!$C9+'P014'!$D9+'P014'!$E9+'P014'!$F9+'P014'!$G9+'P014'!$H9+'P014'!$I9+'P014'!$J9) -> 0 | L9: ='P014'!$B9-'P014'!$K9 -> 0
A10: Junio | K10: ='P014'!$B10-('P014'!$C10+'P014'!$D10+'P014'!$E10+'P014'!$F10+'P014'!$G10+'P014'!$H10+'P014'!$I10+'P014'!$J10) -> 0 | L10: ='P014'!$B10-'P014'!$K10 -> 0
A11: Julio | K11: ='P014'!$B11-('P014'!$C11+'P014'!$D11+'P014'!$E11+'P014'!$F11+'P014'!$G11+'P014'!$H11+'P014'!$I11+'P014'!$J11) -> 0 | L11: ='P014'!$B11-'P014'!$K11 -> 0
A12: Agosto | K12: ='P014'!$B12-('P014'!$C12+'P014'!$D12+'P014'!$E12+'P014'!$F12+'P014'!$G12+'P014'!$H12+'P014'!$I12+'P014'!$J12) -> 0 | L12: ='P014'!$B12-'P014'!$K12 -> 0
A13: Septiembre | K13: ='P014'!$B13-('P014'!$C13+'P014'!$D13+'P014'!$E13+'P014'!$F13+'P014'!$G13+'P014'!$H13+'P014'!$I13+'P014'!$J13) -> 0 | L13: ='P014'!$B13-'P014'!$K13 -> 0
A14: Octubre | K14: ='P014'!$B14-('P014'!$C14+'P014'!$D14+'P014'!$E14+'P014'!$F14+'P014'!$G14+'P014'!$H14+'P014'!$I14+'P014'!$J14) -> 0 | L14: ='P014'!$B14-'P014'!$K14 -> 0
A15: Noviembre | K15: ='P014'!$B15-('P014'!$C15+'P014'!$D15+'P014'!$E15+'P014'!$F15+'P014'!$G15+'P014'!$H15+'P014'!$I15+'P014'!$J15) -> 0 | L15: ='P014'!$B15-'P014'!$K15 -> 0
A16: Diciembre | K16: ='P014'!$B16-('P014'!$C16+'P014'!$D16+'P014'!$E16+'P014'!$F16+'P014'!$G16+'P014'!$H16+'P014'!$I16+'P014'!$J16) -> 0 | L16: ='P014'!$B16-'P014'!$K16 -> 0
A18: NRO DE RECIBOS DE LOS PAGOS
C19: RECIBO 1 | D19: RECIBO 2 | E19: RECIBO 3 | F19: RECIBO 4 | G19: RECIBO 5 | H19: RECIBO 6 | I19: RECIBO 7 | J19: RECIBO 8
A20: Enero
A21: Febrero
A22: Marzo
A23: Abril
A24: Mayo
A25: Junio
A26: Julio
A27: Agosto
A28: Septiembre
A29: Octubre
A30: Noviembre
A31: Diciembre

Sheet P015
A1: P015 | C1: PADILLA MARIA
A3: PAGOS DEL ALQUILER
B4: COSTO | C4: PAGO 1 | D4: PAGO 2 | E4: PAGO 3 | F4: PAGO 4 | G4: PAGO 5 | H4: PAGO 6 | I4: PAGO 7 | J4: PAGO 8 | K4: SALDO | L4: RECAUDADO
A5: Enero | B5: 22750 | C5: 22750 | K5: ='P015'!$B5-('P015'!$C5+'P015'!$D5+'P015'!$E5+'P015'!$F5+'P015'!$G5+'P015'!$H5+'P015'!$I5+'P015'!$J5) -> 0 | L5: ='P015'!$B5-'P015'!$K5 -> 22750
A6: Febrero | B6: 22750 | C6: 10000 | D6: 6000 | E6: 6750 | K6: ='P015'!$B6-('P015'!$C6+'P015'!$D6+'P015'!$E6+'P015'!$F6+'P015'!$G6+'P015'!$H6+'P015'!$I6+'P015'!$J6) -> 0 | L6: ='P015'!$B6-'P015'!$K6 -> 22750
A7: Marzo | K7: ='P015'!$B7-('P015'!$C7+'P015'!$D7+'P015'!$E7+'P015'!$F7+'P015'!$G7+'P015'!$H7+'P015'!$I7+'P015'!$J7) -> 0 | L7: ='P015'!$B7-'P015'!$K7 -> 0
A8: Abril | K8: ='P015'!$B8-('P015'!$C8+'P015'!$D8+'P015'!$E8+'P015'!$F8+'P015'!$G8+'P015'!$H8+'P015'!$I8+'P015'!$J8) -> 0 | L8: ='P015'!$B8-'P015'!$K8 -> 0
A9: Mayo | K9: ='P015'!$B9-('P015'!$C9+'P015'!$D9+'P015'!$E9+'P015'!$F9+'P015'!$G9+'P015'!$H9+'P015'!$I9+'P015'!$J9) -> 0 | L9: ='P015'!$B9-'P015'!$K9 -> 0
A10: Junio | K10: ='P015'!$B10-('P015'!$C10+'P015'!$D10+'P015'!$E10+'P015'!$F10+'P015'!$G10+'P015'!$H10+'P015'!$I10+'P015'!$J10) -> 0 | L10: ='P015'!$B10-'P015'!$K10 -> 0
A11: Julio | K11: ='P015'!$B11-('P015'!$C11+'P015'!$D11+'P015'!$E11+'P015'!$F11+'P015'!$G11+'P015'!$H11+'P015'!$I11+'P015'!$J11) -> 0 | L11: ='P015'!$B11-'P015'!$K11 -> 0
A12: Agosto | K12: ='P015'!$B12-('P015'!$C12+'P015'!$D12+'P015'!$E12+'P015'!$F12+'P015'!$G12+'P015'!$H12+'P015'!$I12+'P015'!$J12) -> 0 | L12: ='P015'!$B12-'P015'!$K12 -> 0
A13: Septiembre | K13: ='P015'!$B13-('P015'!$C13+'P015'!$D13+'P015'!$E13+'P015'!$F13+'P015'!$G13+'P015'!$H13+'P015'!$I13+'P015'!$J13) -> 0 | L13: ='P015'!$B13-'P015'!$K13 -> 0
A14: Octubre | K14: ='P015'!$B14-('P015'!$C14+'P015'!$D14+'P015'!$E14+'P015'!$F14+'P015'!$G14+'P015'!$H14+'P015'!$I14+'P015'!$J14) -> 0 | L14: ='P015'!$B14-'P015'!$K14 -> 0
A15: Noviembre | K15: ='P015'!$B15-('P015'!$C15+'P015'!$D15+'P015'!$E15+'P015'!$F15+'P015'!$G15+'P015'!$H15+'P015'!$I15+'P015'!$J15) -> 0 | L15: ='P015'!$B15-'P015'!$K15 -> 0
A16: Diciembre | K16: ='P015'!$B16-('P015'!$C16+'P015'!$D16+'P015'!$E16+'P015'!$F16+'P015'!$G16+'P015'!$H16+'P015'!$I16+'P015'!$J16) -> 0 | L16: ='P015'!$B16-'P015'!$K16 -> 0
A18: NRO DE RECIBOS DE LOS PAGOS
C19: RECIBO 1 | D19: RECIBO 2 | E19: RECIBO 3 | F19: RECIBO 4 | G19: RECIBO 5 | H19: RECIBO 6 | I19: RECIBO 7 | J19: RECIBO 8
A20: Enero | C20: 6537
A21: Febrero | C21: 6626 | D21: 6638 | E21: 6676
A22: Marzo
A23: Abril
A24: Mayo
A25: Junio
A26: Julio
A27: Agosto
A28: Septiembre
A29: Octubre
A30: Noviembre
A31: Diciembre

Sheet P017
A1: P17 | C1: GILDA FRANCO
A3: PAGOS DEL ALQUILER
B4: COSTO | C4: PAGO 1 | D4: PAGO 2 | E4: PAGO 3 | F4: PAGO 4 | G4: PAGO 5 | H4: PAGO 6 | I4: PAGO 7 | J4: PAGO 8 | K4: SALDO | L4: RECAUDADO
A5: Enero | B5: 177600 | K5: ='P017'!$B5-('P017'!$C5+'P017'!$D5+'P017'!$E5+'P017'!$F5+'P017'!$G5+'P017'!$H5+'P017'!$I5+'P017'!$J5) -> 177600 | L5: ='P017'!$B5-'P017'!$K5 -> 0
A6: Febrero | B6: 177600 | K6: ='P017'!$B6-('P017'!$C6+'P017'!$D6+'P017'!$E6+'P017'!$F6+'P017'!$G6+'P017'!$H6+'P017'!$I6+'P017'!$J6) -> 177600 | L6: ='P017'!$B6-'P017'!$K6 -> 0
A7: Marzo | B7: 193200 | K7: ='P017'!$B7-('P017'!$C7+'P017'!$D7+'P017'!$E7+'P017'!$F7+'P017'!$G7+'P017'!$H7+'P017'!$I7+'P017'!$J7) -> 193200 | L7: ='P017'!$B7-'P017'!$K7 -> 0
A8: Abril | B8: 193200 | K8: ='P017'!$B8-('P017'!$C8+'P017'!$D8+'P017'!$E8+'P017'!$F8+'P017'!$G8+'P017'!$H8+'P017'!$I8+'P017'!$J8) -> 193200 | L8: ='P017'!$B8-'P017'!$K8 -> 0
A9: Mayo | B9: 193200 | K9: ='P017'!$B9-('P017'!$C9+'P017'!$D9+'P017'!$E9+'P017'!$F9+'P017'!$G9+'P017'!$H9+'P017'!$I9+'P017'!$J9) -> 193200 | L9: ='P017'!$B9-'P017'!$K9 -> 0
A10: Junio | K10: ='P017'!$B10-('P017'!$C10+'P017'!$D10+'P017'!$E10+'P017'!$F10+'P017'!$G10+'P017'!$H10+'P017'!$I10+'P017'!$J10) -> 0 | L10: ='P017'!$B10-'P017'!$K10 -> 0
A11: Julio | K11: ='P017'!$B11-('P017'!$C11+'P017'!$D11+'P017'!$E11+'P017'!$F11+'P017'!$G11+'P017'!$H11+'P017'!$I11+'P017'!$J11) -> 0 | L11: ='P017'!$B11-'P017'!$K11 -> 0
A12: Agosto | K12: ='P017'!$B12-('P017'!$C12+'P017'!$D12+'P017'!$E12+'P017'!$F12+'P017'!$G12+'P017'!$H12+'P017'!$I12+'P017'!$J12) -> 0 | L12: ='P017'!$B12-'P017'!$K12 -> 0
A13: Septiembre | K13: ='P017'!$B13-('P017'!$C13+'P017'!$D13+'P017'!$E13+'P017'!$F13+'P017'!$G13+'P017'!$H13+'P017'!$I13+'P017'!$J13) -> 0 | L13: ='P017'!$B13-'P017'!$K13 -> 0
A14: Octubre | K14: ='P017'!$B14-('P017'!$C14+'P017'!$D14+'P017'!$E14+'P017'!$F14+'P017'!$G14+'P017'!$H14+'P017'!$I14+'P017'!$J14) -> 0 | L14: ='P017'!$B14-'P017'!$K14 -> 0
A15: Noviembre | K15: ='P017'!$B15-('P017'!$C15+'P017'!$D15+'P017'!$E15+'P017'!$F15+'P017'!$G15+'P017'!$H15+'P017'!$I15+'P017'!$J15) -> 0 | L15: ='P017'!$B15-'P017'!$K15 -> 0
A16: Diciembre | K16: ='P017'!$B16-('P017'!$C16+'P017'!$D16+'P017'!$E16+'P017'!$F16+'P017'!$G16+'P017'!$H16+'P017'!$I16+'P017'!$J16) -> 0 | L16: ='P017'!$B16-'P017'!$K16 -> 0
A18: NRO DE RECIBOS DE LOS PAGOS
C19: RECIBO 1 | D19: RECIBO 2 | E19: RECIBO 3 | F19: RECIBO 4 | G19: RECIBO 5 | H19: RECIBO 6 | I19: RECIBO 7 | J19: RECIBO 8
A20: Enero
A21: Febrero
A22: Marzo
A23: Abril
A24: Mayo
A25: Junio
A26: Julio
A27: Agosto
A28: Septiembre
A29: Octubre
A30: Noviembre
A31: Diciembre

Sheet P018
A3: PAGOS DEL ALQUILER
B4: COSTO | C4: PAGO 1 | D4: PAGO 2 | E4: PAGO 3 | F4: PAGO 4 | G4: PAGO 5 | H4: PAGO 6 | I4: PAGO 7 | J4: PAGO 8 | K4: SALDO | L4: RECAUDADO
A5: Enero | K5: ='P018'!$B5-('P018'!$C5+'P018'!$D5+'P018'!$E5+'P018'!$F5+'P018'!$G5+'P018'!$H5+'P018'!$I5+'P018'!$J5) -> 0 | L5: ='P018'!$B5-'P018'!$K5 -> 0
A6: Febrero | K6: ='P018'!$B6-('P018'!$C6+'P018'!$D6+'P018'!$E6+'P018'!$F6+'P018'!$G6+'P018'!$H6+'P018'!$I6+'P018'!$J6) -> 0 | L6: ='P018'!$B6-'P018'!$K6 -> 0
A7: Marzo | K7: ='P018'!$B7-('P018'!$C7+'P018'!$D7+'P018'!$E7+'P018'!$F7+'P018'!$G7+'P018'!$H7+'P018'!$I7+'P018'!$J7) -> 0 | L7: ='P018'!$B7-'P018'!$K7 -> 0
A8: Abril | K8: ='P018'!$B8-('P018'!$C8+'P018'!$D8+'P018'!$E8+'P018'!$F8+'P018'!$G8+'P018'!$H8+'P018'!$I8+'P018'!$J8) -> 0 | L8: ='P018'!$B8-'P018'!$K8 -> 0
A9: Mayo | K9: ='P018'!$B9-('P018'!$C9+'P018'!$D9+'P018'!$E9+'P018'!$F9+'P018'!$G9+'P018'!$H9+'P018'!$I9+'P018'!$J9) -> 0 | L9: ='P018'!$B9-'P018'!$K9 -> 0
A10: Junio | K10: ='P018'!$B10-('P018'!$C10+'P018'!$D10+'P018'!$E10+'P018'!$F10+'P018'!$G10+'P018'!$H10+'P018'!$I10+'P018'!$J10) -> 0 | L10: ='P018'!$B10-'P018'!$K10 -> 0
A11: Julio | K11: ='P018'!$B11-('P018'!$C11+'P018'!$D11+'P018'!$E11+'P018'!$F11+'P018'!$G11+'P018'!$H11+'P018'!$I11+'P018'!$J11) -> 0 | L11: ='P018'!$B11-'P018'!$K11 -> 0
A12: Agosto | K12: ='P018'!$B12-('P018'!$C12+'P018'!$D12+'P018'!$E12+'P018'!$F12+'P018'!$G12+'P018'!$H12+'P018'!$I12+'P018'!$J12) -> 0 | L12: ='P018'!$B12-'P018'!$K12 -> 0
A13: Septiembre | K13: ='P018'!$B13-('P018'!$C13+'P018'!$D13+'P018'!$E13+'P018'!$F13+'P018'!$G13+'P018'!$H13+'P018'!$I13+'P018'!$J13) -> 0 | L13: ='P018'!$B13-'P018'!$K13 -> 0
A14: Octubre | K14: ='P018'!$B14-('P018'!$C14+'P018'!$D14+'P018'!$E14+'P018'!$F14+'P018'!$G14+'P018'!$H14+'P018'!$I14+'P018'!$J14) -> 0 | L14: ='P018'!$B14-'P018'!$K14 -> 0
A15: Noviembre | K15: ='P018'!$B15-('P018'!$C15+'P018'!$D15+'P018'!$E15+'P018'!$F15+'P018'!$G15+'P018'!$H15+'P018'!$I15+'P018'!$J15) -> 0 | L15: ='P018'!$B15-'P018'!$K15 -> 0
A16: Diciembre | K16: ='P018'!$B16-('P018'!$C16+'P018'!$D16+'P018'!$E16+'P018'!$F16+'P018'!$G16+'P018'!$H16+'P018'!$I16+'P018'!$J16) -> 0 | L16: ='P018'!$B16-'P018'!$K16 -> 0
A18: NRO DE RECIBOS DE LOS PAGOS
C19: RECIBO 1 | D19: RECIBO 2 | E19: RECIBO 3 | F19: RECIBO 4 | G19: RECIBO 5 | H19: RECIBO 6 | I19: RECIBO 7 | J19: RECIBO 8
A20: Enero
A21: Febrero
A22: Marzo
A23: Abril
A24: Mayo
A25: Junio
A26: Julio
A27: Agosto
A28: Septiembre
A29: Octubre
A30: Noviembre
A31: Diciembre

Sheet P019
A3: PAGOS DEL ALQUILER
B4: COSTO | C4: PAGO 1 | D4: PAGO 2 | E4: PAGO 3 | F4: PAGO 4 | G4: PAGO 5 | H4: PAGO 6 | I4: PAGO 7 | J4: PAGO 8 | K4: SALDO | L4: RECAUDADO
A5: Enero | K5: ='P019'!$B5-('P019'!$C5+'P019'!$D5+'P019'!$E5+'P019'!$F5+'P019'!$G5+'P019'!$H5+'P019'!$I5+'P019'!$J5) -> 0 | L5: ='P019'!$B5-'P019'!$K5 -> 0
A6: Febrero | K6: ='P019'!$B6-('P019'!$C6+'P019'!$D6+'P019'!$E6+'P019'!$F6+'P019'!$G6+'P019'!$H6+'P019'!$I6+'P019'!$J6) -> 0 | L6: ='P019'!$B6-'P019'!$K6 -> 0
A7: Marzo | K7: ='P019'!$B7-('P019'!$C7+'P019'!$D7+'P019'!$E7+'P019'!$F7+'P019'!$G7+'P019'!$H7+'P019'!$I7+'P019'!$J7) -> 0 | L7: ='P019'!$B7-'P019'!$K7 -> 0
A8: Abril | K8: ='P019'!$B8-('P019'!$C8+'P019'!$D8+'P019'!$E8+'P019'!$F8+'P019'!$G8+'P019'!$H8+'P019'!$I8+'P019'!$J8) -> 0 | L8: ='P019'!$B8-'P019'!$K8 -> 0
A9: Mayo | K9: ='P019'!$B9-('P019'!$C9+'P019'!$D9+'P019'!$E9+'P019'!$F9+'P019'!$G9+'P019'!$H9+'P019'!$I9+'P019'!$J9) -> 0 | L9: ='P019'!$B9-'P019'!$K9 -> 0
A10: Junio | K10: ='P019'!$B10-('P019'!$C10+'P019'!$D10+'P019'!$E10+'P019'!$F10+'P019'!$G10+'P019'!$H10+'P019'!$I10+'P019'!$J10) -> 0 | L10: ='P019'!$B10-'P019'!$K10 -> 0
A11: Julio | K11: ='P019'!$B11-('P019'!$C11+'P019'!$D11+'P019'!$E11+'P019'!$F11+'P019'!$G11+'P019'!$H11+'P019'!$I11+'P019'!$J11) -> 0 | L11: ='P019'!$B11-'P019'!$K11 -> 0
A12: Agosto | K12: ='P019'!$B12-('P019'!$C12+'P019'!$D12+'P019'!$E12+'P019'!$F12+'P019'!$G12+'P019'!$H12+'P019'!$I12+'P019'!$J12) -> 0 | L12: ='P019'!$B12-'P019'!$K12 -> 0
A13: Septiembre | K13: ='P019'!$B13-('P019'!$C13+'P019'!$D13+'P019'!$E13+'P019'!$F13+'P019'!$G13+'P019'!$H13+'P019'!$I13+'P019'!$J13) -> 0 | L13: ='P019'!$B13-'P019'!$K13 -> 0
A14: Octubre | K14: ='P019'!$B14-('P019'!$C14+'P019'!$D14+'P019'!$E14+'P019'!$F14+'P019'!$G14+'P019'!$H14+'P019'!$I14+'P019'!$J14) -> 0 | L14: ='P019'!$B14-'P019'!$K14 -> 0
A15: Noviembre | K15: ='P019'!$B15-('P019'!$C15+'P019'!$D15+'P019'!$E15+'P019'!$F15+'P019'!$G15+'P019'!$H15+'P019'!$I15+'P019'!$J15) -> 0 | L15: ='P019'!$B15-'P019'!$K15 -> 0
A16: Diciembre | K16: ='P019'!$B16-('P019'!$C16+'P019'!$D16+'P019'!$E16+'P019'!$F16+'P019'!$G16+'P019'!$H16+'P019'!$I16+'P019'!$J16) -> 0 | L16: ='P019'!$B16-'P019'!$K16 -> 0
A18: NRO DE RECIBOS DE LOS PAGOS
C19: RECIBO 1 | D19: RECIBO 2 | E19: RECIBO 3 | F19: RECIBO 4 | G19: RECIBO 5 | H19: RECIBO 6 | I19: RECIBO 7 | J19: RECIBO 8
A20: Enero
A21: Febrero
A22: Marzo
A23: Abril
A24: Mayo
A25: Junio
A26: Julio
A27: Agosto
A28: Septiembre
A29: Octubre
A30: Noviembre
A31: Diciembre

Sheet P020
A3: PAGOS DEL ALQUILER
B4: COSTO | C4: PAGO 1 | D4: PAGO 2 | E4: PAGO 3 | F4: PAGO 4 | G4: PAGO 5 | H4: PAGO 6 | I4: PAGO 7 | J4: PAGO 8 | K4: SALDO | L4: RECAUDADO
A5: Enero | K5: ='P020'!$B5-('P020'!$C5+'P020'!$D5+'P020'!$E5+'P020'!$F5+'P020'!$G5+'P020'!$H5+'P020'!$I5+'P020'!$J5) -> 0 | L5: ='P020'!$B5-'P020'!$K5 -> 0
A6: Febrero | K6: ='P020'!$B6-('P020'!$C6+'P020'!$D6+'P020'!$E6+'P020'!$F6+'P020'!$G6+'P020'!$H6+'P020'!$I6+'P020'!$J6) -> 0 | L6: ='P020'!$B6-'P020'!$K6 -> 0
A7: Marzo | K7: ='P020'!$B7-('P020'!$C7+'P020'!$D7+'P020'!$E7+'P020'!$F7+'P020'!$G7+'P020'!$H7+'P020'!$I7+'P020'!$J7) -> 0 | L7: ='P020'!$B7-'P020'!$K7 -> 0
A8: Abril | K8: ='P020'!$B8-('P020'!$C8+'P020'!$D8+'P020'!$E8+'P020'!$F8+'P020'!$G8+'P020'!$H8+'P020'!$I8+'P020'!$J8) -> 0 | L8: ='P020'!$B8-'P020'!$K8 -> 0
A9: Mayo | K9: ='P020'!$B9-('P020'!$C9+'P020'!$D9+'P020'!$E9+'P020'!$F9+'P020'!$G9+'P020'!$H9+'P020'!$I9+'P020'!$J9) -> 0 | L9: ='P020'!$B9-'P020'!$K9 -> 0
A10: Junio | K10: ='P020'!$B10-('P020'!$C10+'P020'!$D10+'P020'!$E10+'P020'!$F10+'P020'!$G10+'P020'!$H10+'P020'!$I10+'P020'!$J10) -> 0 | L10: ='P020'!$B10-'P020'!$K10 -> 0
A11: Julio | K11: ='P020'!$B11-('P020'!$C11+'P020'!$D11+'P020'!$E11+'P020'!$F11+'P020'!$G11+'P020'!$H11+'P020'!$I11+'P020'!$J11) -> 0 | L11: ='P020'!$B11-'P020'!$K11 -> 0
A12: Agosto | K12: ='P020'!$B12-('P020'!$C12+'P020'!$D12+'P020'!$E12+'P020'!$F12+'P020'!$G12+'P020'!$H12+'P020'!$I12+'P020'!$J12) -> 0 | L12: ='P020'!$B12-'P020'!$K12 -> 0
A13: Septiembre | K13: ='P020'!$B13-('P020'!$C13+'P020'!$D13+'P020'!$E13+'P020'!$F13+'P020'!$G13+'P020'!$H13+'P020'!$I13+'P020'!$J13) -> 0 | L13: ='P020'!$B13-'P020'!$K13 -> 0
A14: Octubre | K14: ='P020'!$B14-('P020'!$C14+'P020'!$D14+'P020'!$E14+'P020'!$F14+'P020'!$G14+'P020'!$H14+'P020'!$I14+'P020'!$J14) -> 0 | L14: ='P020'!$B14-'P020'!$K14 -> 0
A15: Noviembre | K15: ='P020'!$B15-('P020'!$C15+'P020'!$D15+'P020'!$E15+'P020'!$F15+'P020'!$G15+'P020'!$H15+'P020'!$I15+'P020'!$J15) -> 0 | L15: ='P020'!$B15-'P020'!$K15 -> 0
A16: Diciembre | K16: ='P020'!$B16-('P020'!$C16+'P020'!$D16+'P020'!$E16+'P020'!$F16+'P020'!$G16+'P020'!$H16+'P020'!$I16+'P020'!$J16) -> 0 | L16: ='P020'!$B16-'P020'!$K16 -> 0
A18: NRO DE RECIBOS DE LOS PAGOS
C19: RECIBO 1 | D19: RECIBO 2 | E19: RECIBO 3 | F19: RECIBO 4 | G19: RECIBO 5 | H19: RECIBO 6 | I19: RECIBO 7 | J19: RECIBO 8
A20: Enero
A21: Febrero
A22: Marzo
A23: Abril
A24: Mayo
A25: Junio
A26: Julio
A27: Agosto
A28: Septiembre
A29: Octubre
A30: Noviembre
A31: Diciembre

Sheet P022
A3: PAGOS DEL ALQUILER
B4: COSTO | C4: PAGO 1 | D4: PAGO 2 | E4: PAGO 3 | F4: PAGO 4 | G4: PAGO 5 | H4: PAGO 6 | I4: PAGO 7 | J4: PAGO 8 | K4: SALDO | L4: RECAUDADO
A5: Enero | K5: ='P022'!$B5-('P022'!$C5+'P022'!$D5+'P022'!$E5+'P022'!$F5+'P022'!$G5+'P022'!$H5+'P022'!$I5+'P022'!$J5) -> 0 | L5: ='P022'!$B5-'P022'!$K5 -> 0
A6: Febrero | K6: ='P022'!$B6-('P022'!$C6+'P022'!$D6+'P022'!$E6+'P022'!$F6+'P022'!$G6+'P022'!$H6+'P022'!$I6+'P022'!$J6) -> 0 | L6: ='P022'!$B6-'P022'!$K6 -> 0
A7: Marzo | K7: ='P022'!$B7-('P022'!$C7+'P022'!$D7+'P022'!$E7+'P022'!$F7+'P022'!$G7+'P022'!$H7+'P022'!$I7+'P022'!$J7) -> 0 | L7: ='P022'!$B7-'P022'!$K7 -> 0
A8: Abril | K8: ='P022'!$B8-('P022'!$C8+'P022'!$D8+'P022'!$E8+'P022'!$F8+'P022'!$G8+'P022'!$H8+'P022'!$I8+'P022'!$J8) -> 0 | L8: ='P022'!$B8-'P022'!$K8 -> 0
A9: Mayo | K9: ='P022'!$B9-('P022'!$C9+'P022'!$D9+'P022'!$E9+'P022'!$F9+'P022'!$G9+'P022'!$H9+'P022'!$I9+'P022'!$J9) -> 0 | L9: ='P022'!$B9-'P022'!$K9 -> 0
A10: Junio | K10: ='P022'!$B10-('P022'!$C10+'P022'!$D10+'P022'!$E10+'P022'!$F10+'P022'!$G10+'P022'!$H10+'P022'!$I10+'P022'!$J10) -> 0 | L10: ='P022'!$B10-'P022'!$K10 -> 0
A11: Julio | K11: ='P022'!$B11-('P022'!$C11+'P022'!$D11+'P022'!$E11+'P022'!$F11+'P022'!$G11+'P022'!$H11+'P022'!$I11+'P022'!$J11) -> 0 | L11: ='P022'!$B11-'P022'!$K11 -> 0
A12: Agosto | K12: ='P022'!$B12-('P022'!$C12+'P022'!$D12+'P022'!$E12+'P022'!$F12+'P022'!$G12+'P022'!$H12+'P022'!$I12+'P022'!$J12) -> 0 | L12: ='P022'!$B12-'P022'!$K12 -> 0
A13: Septiembre | K13: ='P022'!$B13-('P022'!$C13+'P022'!$D13+'P022'!$E13+'P022'!$F13+'P022'!$G13+'P022'!$H13+'P022'!$I13+'P022'!$J13) -> 0 | L13: ='P022'!$B13-'P022'!$K13 -> 0
A14: Octubre | K14: ='P022'!$B14-('P022'!$C14+'P022'!$D14+'P022'!$E14+'P022'!$F14+'P022'!$G14+'P022'!$H14+'P022'!$I14+'P022'!$J14) -> 0 | L14: ='P022'!$B14-'P022'!$K14 -> 0
A15: Noviembre | K15: ='P022'!$B15-('P022'!$C15+'P022'!$D15+'P022'!$E15+'P022'!$F15+'P022'!$G15+'P022'!$H15+'P022'!$I15+'P022'!$J15) -> 0 | L15: ='P022'!$B15-'P022'!$K15 -> 0
A16: Diciembre | K16: ='P022'!$B16-('P022'!$C16+'P022'!$D16+'P022'!$E16+'P022'!$F16+'P022'!$G16+'P022'!$H16+'P022'!$I16+'P022'!$J16) -> 0 | L16: ='P022'!$B16-'P022'!$K16 -> 0
A18: NRO DE RECIBOS DE LOS PAGOS
C19: RECIBO 1 | D19: RECIBO 2 | E19: RECIBO 3 | F19: RECIBO 4 | G19: RECIBO 5 | H19: RECIBO 6 | I19: RECIBO 7 | J19: RECIBO 8
A20: Enero
A21: Febrero
A22: Marzo
A23: Abril
A24: Mayo
A25: Junio
A26: Julio
A27: Agosto
A28: Septiembre
A29: Octubre
A30: Noviembre
A31: Diciembre

Sheet P023
A1: P023 | C1: NIELSEN HERNAN
A3: PAGOS DEL ALQUILER
B4: COSTO | C4: PAGO 1 | D4: PAGO 2 | E4: PAGO 3 | F4: PAGO 4 | G4: PAGO 5 | H4: PAGO 6 | I4: PAGO 7 | J4: PAGO 8 | K4: SALDO | L4: RECAUDADO
A5: Enero | B5: 110500 | C5: 110500 | K5: ='P023'!$B5-('P023'!$C5+'P023'!$D5+'P023'!$E5+'P023'!$F5+'P023'!$G5+'P023'!$H5+'P023'!$I5+'P023'!$J5) -> 0 | L5: ='P023'!$B5-'P023'!$K5 -> 110500
A6: Febrero | B6: 110500 | C6: 60000 | D6: 50500 | K6: ='P023'!$B6-('P023'!$C6+'P023'!$D6+'P023'!$E6+'P023'!$F6+'P023'!$G6+'P023'!$H6+'P023'!$I6+'P023'!$J6) -> 0 | L6: ='P023'!$B6-'P023'!$K6 -> 110500
A7: Marzo | B7: 110500 | C7: 80000 | D7: 30500 | K7: ='P023'!$B7-('P023'!$C7+'P023'!$D7+'P023'!$E7+'P023'!$F7+'P023'!$G7+'P023'!$H7+'P023'!$I7+'P023'!$J7) -> 0 | L7: ='P023'!$B7-'P023'!$K7 -> 110500
A8: Abril | B8: 110500 | C8: 78400 | D8: 32100 | K8: ='P023'!$B8-('P023'!$C8+'P023'!$D8+'P023'!$E8+'P023'!$F8+'P023'!$G8+'P023'!$H8+'P023'!$I8+'P023'!$J8) -> 0 | L8: ='P023'!$B8-'P023'!$K8 -> 110500
A9: Mayo | K9: ='P023'!$B9-('P023'!$C9+'P023'!$D9+'P023'!$E9+'P023'!$F9+'P023'!$G9+'P023'!$H9+'P023'!$I9+'P023'!$J9) -> 0 | L9: ='P023'!$B9-'P023'!$K9 -> 0
A10: Junio | K10: ='P023'!$B10-('P023'!$C10+'P023'!$D10+'P023'!$E10+'P023'!$F10+'P023'!$G10+'P023'!$H10+'P023'!$I10+'P023'!$J10) -> 0 | L10: ='P023'!$B10-'P023'!$K10 -> 0
A11: Julio | K11: ='P023'!$B11-('P023'!$C11+'P023'!$D11+'P023'!$E11+'P023'!$F11+'P023'!$G11+'P023'!$H11+'P023'!$I11+'P023'!$J11) -> 0 | L11: ='P023'!$B11-'P023'!$K11 -> 0
A12: Agosto | K12: ='P023'!$B12-('P023'!$C12+'P023'!$D12+'P023'!$E12+'P023'!$F12+'P023'!$G12+'P023'!$H12+'P023'!$I12+'P023'!$J12) -> 0 | L12: ='P023'!$B12-'P023'!$K12 -> 0
A13: Septiembre | K13: ='P023'!$B13-('P023'!$C13+'P023'!$D13+'P023'!$E13+'P023'!$F13+'P023'!$G13+'P023'!$H13+'P023'!$I13+'P023'!$J13) -> 0 | L13: ='P023'!$B13-'P023'!$K13 -> 0
A14: Octubre | K14: ='P023'!$B14-('P023'!$C14+'P023'!$D14+'P023'!$E14+'P023'!$F14+'P023'!$G14+'P023'!$H14+'P023'!$I14+'P023'!$J14) -> 0 | L14: ='P023'!$B14-'P023'!$K14 -> 0
A15: Noviembre | K15: ='P023'!$B15-('P023'!$C15+'P023'!$D15+'P023'!$E15+'P023'!$F15+'P023'!$G15+'P023'!$H15+'P023'!$I15+'P023'!$J15) -> 0 | L15: ='P023'!$B15-'P023'!$K15 -> 0
A16: Diciembre | K16: ='P023'!$B16-('P023'!$C16+'P023'!$D16+'P023'!$E16+'P023'!$F16+'P023'!$G16+'P023'!$H16+'P023'!$I16+'P023'!$J16) -> 0 | L16: ='P023'!$B16-'P023'!$K16 -> 0
A18: NRO DE RECIBOS DE LOS PAGOS
C19: RECIBO 1 | D19: RECIBO 2 | E19: RECIBO 3 | F19: RECIBO 4 | G19: RECIBO 5 | H19: RECIBO 6 | I19: RECIBO 7 | J19: RECIBO 8
A20: Enero | C20: 6588
A21: Febrero | C21: 6668 | D21: 6695
A22: Marzo | C22: 6771 | D22: 6792
A23: Abril | C23: 6848 | D23: 6869
A24: Mayo
A25: Junio
A26: Julio
A27: Agosto
A28: Septiembre
A29: Octubre
A30: Noviembre
A31: Diciembre

Sheet P021
A1: 645850 | C1: OSMAR GONZANLEZ
A3: PAGOS DEL ALQUILER
B4: COSTO | C4: PAGO 1 | D4: PAGO 2 | E4: PAGO 3 | F4: PAGO 4 | G4: PAGO 5 | H4: PAGO 6 | I4: PAGO 7 | J4: PAGO 8 | K4: SALDO | L4: RECAUDADO
A5: Enero | B5: 710435 | C5: 710435 | K5: ='P021'!$B5-('P021'!$C5+'P021'!$D5+'P021'!$E5+'P021'!$F5+'P021'!$G5+'P021'!$H5+'P021'!$I5+'P021'!$J5) -> 0 | L5: 710435 | M5: 13500
A6: Febrero | B6: 710435 | C6: 710435 | K6: ='P021'!$B6-('P021'!$C6+'P021'!$D6+'P021'!$E6+'P021'!$F6+'P021'!$G6+'P021'!$H6+'P021'!$I6+'P021'!$J6) -> 0 | L6: ='P021'!$B6-'P021'!$K6 -> 710435 | M6: 13500
A7: Marzo | B7: 772950 | K7: ='P021'!$B7-('P021'!$C7+'P021'!$D7+'P021'!$E7+'P021'!$F7+'P021'!$G7+'P021'!$H7+'P021'!$I7+'P021'!$J7) -> 772950 | L7: ='P021'!$B7-'P021'!$K7 -> 0
A8: Abril | B8: 772950 | K8: ='P021'!$B8-('P021'!$C8+'P021'!$D8+'P021'!$E8+'P021'!$F8+'P021'!$G8+'P021'!$H8+'P021'!$I8+'P021'!$J8) -> 772950 | L8: ='P021'!$B8-'P021'!$K8 -> 0
A9: Mayo | B9: 772950 | K9: ='P021'!$B9-('P021'!$C9+'P021'!$D9+'P021'!$E9+'P021'!$F9+'P021'!$G9+'P021'!$H9+'P021'!$I9+'P021'!$J9) -> 772950 | L9: ='P021'!$B9-'P021'!$K9 -> 0
A10: Junio | K10: ='P021'!$B10-('P021'!$C10+'P021'!$D10+'P021'!$E10+'P021'!$F10+'P021'!$G10+'P021'!$H10+'P021'!$I10+'P021'!$J10) -> 0 | L10: ='P021'!$B10-'P021'!$K10 -> 0
A11: Julio | K11: ='P021'!$B11-('P021'!$C11+'P021'!$D11+'P021'!$E11+'P021'!$F11+'P021'!$G11+'P021'!$H11+'P021'!$I11+'P021'!$J11) -> 0 | L11: ='P021'!$B11-'P021'!$K11 -> 0
A12: Agosto | K12: ='P021'!$B12-('P021'!$C12+'P021'!$D12+'P021'!$E12+'P021'!$F12+'P021'!$G12+'P021'!$H12+'P021'!$I12+'P021'!$J12) -> 0 | L12: ='P021'!$B12-'P021'!$K12 -> 0
A13: Septiembre | K13: ='P021'!$B13-('P021'!$C13+'P021'!$D13+'P021'!$E13+'P021'!$F13+'P021'!$G13+'P021'!$H13+'P021'!$I13+'P021'!$J13) -> 0 | L13: ='P021'!$B13-'P021'!$K13 -> 0
A14: Octubre | K14: ='P021'!$B14-('P021'!$C14+'P021'!$D14+'P021'!$E14+'P021'!$F14+'P021'!$G14+'P021'!$H14+'P021'!$I14+'P021'!$J14) -> 0 | L14: ='P021'!$B14-'P021'!$K14 -> 0
A15: Noviembre | K15: ='P021'!$B15-('P021'!$C15+'P021'!$D15+'P021'!$E15+'P021'!$F15+'P021'!$G15+'P021'!$H15+'P021'!$I15+'P021'!$J15) -> 0 | L15: ='P021'!$B15-'P021'!$K15 -> 0
A16: Diciembre | K16: ='P021'!$B16-('P021'!$C16+'P021'!$D16+'P021'!$E16+'P021'!$F16+'P021'!$G16+'P021'!$H16+'P021'!$I16+'P021'!$J16) -> 0 | L16: ='P021'!$B16-'P021'!$K16 -> 0
A18: NRO DE RECIBOS DE LOS PAGOS
C19: RECIBO 1 | D19: RECIBO 2 | E19: RECIBO 3 | F19: RECIBO 4 | G19: RECIBO 5 | H19: RECIBO 6 | I19: RECIBO 7 | J19: RECIBO 8
A20: Enero | C20: 9635
A21: Febrero | C21: 9710
A22: Marzo
A23: Abril
A24: Mayo
A25: Junio
A26: Julio
A27: Agosto
A28: Septiembre
A29: Octubre
A30: Noviembre
A31: Diciembre

Sheet P024
A1: Po24/26 | C1: BRITEZ SAMUEL
A3: PAGOS DEL ALQUILER
B4: COSTO | C4: PAGO 1 | D4: PAGO 2 | E4: PAGO 3 | F4: PAGO 4 | G4: PAGO 5 | H4: PAGO 6 | I4: PAGO 7 | J4: PAGO 8 | K4: SALDO | L4: RECAUDADO
A5: Enero | B5: 355200 | C5: 100000 | D5: 255200 | K5: ='P024'!$B5-('P024'!$C5+'P024'!$D5+'P024'!$E5+'P024'!$F5+'P024'!$G5+'P024'!$H5+'P024'!$I5+'P024'!$J5) -> 0 | L5: =B5 -> 355200 | M5: 13500
A6: Febrero | B6: 355200 | C6: 236500 | D6: 118700 | K6: ='P024'!$B6-('P024'!$C6+'P024'!$D6+'P024'!$E6+'P024'!$F6+'P024'!$G6+'P024'!$H6+'P024'!$I6+'P024'!$J6) -> 0 | L6: ='P024'!$B6-'P024'!$K6 -> 355200 | M6: 13500
A7: Marzo | B7: 386500 | K7: ='P024'!$B7-('P024'!$C7+'P024'!$D7+'P024'!$E7+'P024'!$F7+'P024'!$G7+'P024'!$H7+'P024'!$I7+'P024'!$J7) -> 386500 | L7: ='P024'!$B7-'P024'!$K7 -> 0
A8: Abril | B8: 386460 | K8: ='P024'!$B8-('P024'!$C8+'P024'!$D8+'P024'!$E8+'P024'!$F8+'P024'!$G8+'P024'!$H8+'P024'!$I8+'P024'!$J8) -> 386460 | L8: ='P024'!$B8-'P024'!$K8 -> 0
A9: Mayo | B9: 386460 | K9: ='P024'!$B9-('P024'!$C9+'P024'!$D9+'P024'!$E9+'P024'!$F9+'P024'!$G9+'P024'!$H9+'P024'!$I9+'P024'!$J9) -> 386460 | L9: ='P024'!$B9-'P024'!$K9 -> 0
A10: Junio | K10: ='P024'!$B10-('P024'!$C10+'P024'!$D10+'P024'!$E10+'P024'!$F10+'P024'!$G10+'P024'!$H10+'P024'!$I10+'P024'!$J10) -> 0 | L10: ='P024'!$B10-'P024'!$K10 -> 0
A11: Julio | K11: ='P024'!$B11-('P024'!$C11+'P024'!$D11+'P024'!$E11+'P024'!$F11+'P024'!$G11+'P024'!$H11+'P024'!$I11+'P024'!$J11) -> 0 | L11: ='P024'!$B11-'P024'!$K11 -> 0
A12: Agosto | K12: ='P024'!$B12-('P024'!$C12+'P024'!$D12+'P024'!$E12+'P024'!$F12+'P024'!$G12+'P024'!$H12+'P024'!$I12+'P024'!$J12) -> 0 | L12: ='P024'!$B12-'P024'!$K12 -> 0
A13: Septiembre | K13: ='P024'!$B13-('P024'!$C13+'P024'!$D13+'P024'!$E13+'P024'!$F13+'P024'!$G13+'P024'!$H13+'P024'!$I13+'P024'!$J13) -> 0 | L13: ='P024'!$B13-'P024'!$K13 -> 0
A14: Octubre | K14: ='P024'!$B14-('P024'!$C14+'P024'!$D14+'P024'!$E14+'P024'!$F14+'P024'!$G14+'P024'!$H14+'P024'!$I14+'P024'!$J14) -> 0 | L14: ='P024'!$B14-'P024'!$K14 -> 0
A15: Noviembre | K15: ='P024'!$B15-('P024'!$C15+'P024'!$D15+'P024'!$E15+'P024'!$F15+'P024'!$G15+'P024'!$H15+'P024'!$I15+'P024'!$J15) -> 0 | L15: ='P024'!$B15-'P024'!$K15 -> 0
A16: Diciembre | K16: ='P024'!$B16-('P024'!$C16+'P024'!$D16+'P024'!$E16+'P024'!$F16+'P024'!$G16+'P024'!$H16+'P024'!$I16+'P024'!$J16) -> 0 | L16: ='P024'!$B16-'P024'!$K16 -> 0
A18: NRO DE RECIBOS DE LOS PAGOS
C19: RECIBO 1 | D19: RECIBO 2 | E19: RECIBO 3 | F19: RECIBO 4 | G19: RECIBO 5 | H19: RECIBO 6 | I19: RECIBO 7 | J19: RECIBO 8
A20: Enero | D20: 9648
A21: Febrero | C21: 9712
A22: Marzo
A23: Abril
A24: Mayo
A25: Junio
A26: Julio
A27: Agosto
A28: Septiembre
A29: Octubre
A30: Noviembre
A31: Diciembre

Sheet P025
A1: P025 | C1: MABEL RIVERO(CH)
A3: PAGOS DEL ALQUILER
B4: COSTO | C4: PAGO 1 | D4: PAGO 2 | E4: PAGO 3 | F4: PAGO 4 | G4: PAGO 5 | H4: PAGO 6 | I4: PAGO 7 | J4: PAGO 8 | K4: SALDO | L4: RECAUDADO
A5: Enero | B5: 177600 | C5: 177600 | K5: ='P025'!$B5-('P025'!$C5+'P025'!$D5+'P025'!$E5+'P025'!$F5+'P025'!$G5+'P025'!$H5+'P025'!$I5+'P025'!$J5) -> 0 | L5: ='P025'!$B5-'P025'!$K5 -> 177600 | M5: 13500
A6: Febrero | B6: 177600 | C6: 177600 | K6: ='P025'!$B6-('P025'!$C6+'P025'!$D6+'P025'!$E6+'P025'!$F6+'P025'!$G6+'P025'!$H6+'P025'!$I6+'P025'!$J6) -> 0 | L6: ='P025'!$B6-'P025'!$K6 -> 177600 | M6: 13500
A7: Marzo | B7: 193200 | K7: ='P025'!$B7-('P025'!$C7+'P025'!$D7+'P025'!$E7+'P025'!$F7+'P025'!$G7+'P025'!$H7+'P025'!$I7+'P025'!$J7) -> 193200 | L7: ='P025'!$B7-'P025'!$K7 -> 0
A8: Abril | B8: 193200 | K8: ='P025'!$B8-('P025'!$C8+'P025'!$D8+'P025'!$E8+'P025'!$F8+'P025'!$G8+'P025'!$H8+'P025'!$I8+'P025'!$J8) -> 193200 | L8: ='P025'!$B8-'P025'!$K8 -> 0
A9: Mayo | B9: 193200 | K9: ='P025'!$B9-('P025'!$C9+'P025'!$D9+'P025'!$E9+'P025'!$F9+'P025'!$G9+'P025'!$H9+'P025'!$I9+'P025'!$J9) -> 193200 | L9: ='P025'!$B9-'P025'!$K9 -> 0
A10: Junio | K10: ='P025'!$B10-('P025'!$C10+'P025'!$D10+'P025'!$E10+'P025'!$F10+'P025'!$G10+'P025'!$H10+'P025'!$I10+'P025'!$J10) -> 0 | L10: ='P025'!$B10-'P025'!$K10 -> 0
A11: Julio | K11: ='P025'!$B11-('P025'!$C11+'P025'!$D11+'P025'!$E11+'P025'!$F11+'P025'!$G11+'P025'!$H11+'P025'!$I11+'P025'!$J11) -> 0 | L11: ='P025'!$B11-'P025'!$K11 -> 0
A12: Agosto | K12: ='P025'!$B12-('P025'!$C12+'P025'!$D12+'P025'!$E12+'P025'!$F12+'P025'!$G12+'P025'!$H12+'P025'!$I12+'P025'!$J12) -> 0 | L12: ='P025'!$B12-'P025'!$K12 -> 0
A13: Septiembre | K13: ='P025'!$B13-('P025'!$C13+'P025'!$D13+'P025'!$E13+'P025'!$F13+'P025'!$G13+'P025'!$H13+'P025'!$I13+'P025'!$J13) -> 0 | L13: ='P025'!$B13-'P025'!$K13 -> 0
A14: Octubre | K14: ='P025'!$B14-('P025'!$C14+'P025'!$D14+'P025'!$E14+'P025'!$F14+'P025'!$G14+'P025'!$H14+'P025'!$I14+'P025'!$J14) -> 0 | L14: ='P025'!$B14-'P025'!$K14 -> 0
A15: Noviembre | K15: ='P025'!$B15-('P025'!$C15+'P025'!$D15+'P025'!$E15+'P025'!$F15+'P025'!$G15+'P025'!$H15+'P025'!$I15+'P025'!$J15) -> 0 | L15: ='P025'!$B15-'P025'!$K15 -> 0
A16: Diciembre | K16: ='P025'!$B16-('P025'!$C16+'P025'!$D16+'P025'!$E16+'P025'!$F16+'P025'!$G16+'P025'!$H16+'P025'!$I16+'P025'!$J16) -> 0 | L16: ='P025'!$B16-'P025'!$K16 -> 0
A18: NRO DE RECIBOS DE LOS PAGOS
C19: RECIBO 1 | D19: RECIBO 2 | E19: RECIBO 3 | F19: RECIBO 4 | G19: RECIBO 5 | H19: RECIBO 6 | I19: RECIBO 7 | J19: RECIBO 8
A20: Enero | C20: 9669
A21: Febrero | C21: 9738
A22: Marzo
A23: Abril
A24: Mayo
A25: Junio
A26: Julio
A27: Agosto
A28: Septiembre
A29: Octubre
A30: Noviembre
A31: Diciembre
N40: 1250
N41: 3750
N42: 2250
N43: 4550
N46: 2955
N48: 6400
N49: 3000
N50: 3000

Sheet P031
A1: pto 29/31/53/56/96 | C1: CAMARGO RUBEN
A3: PAGOS DEL ALQUILER
B4: COSTO | C4: PAGO 1 | D4: PAGO 2 | E4: PAGO 3 | F4: PAGO 4 | G4: PAGO 5 | H4: PAGO 6 | I4: PAGO 7 | J4: PAGO 8 | K4: SALDO | L4: RECAUDADO
A5: Enero | B5: 2294100 | C5: 1242000 | D5: 1052100 | K5: ='P031'!$B5-('P031'!$C5+'P031'!$D5+'P031'!$E5+'P031'!$F5+'P031'!$G5+'P031'!$H5+'P031'!$I5+'P031'!$J5) -> 0 | L5: ='P031'!$B5-'P031'!$K51 -> 2294100 | M5: 108000
A6: Febrero | B6: 2294100 | C6: 107900 | D6: 1392000 | E6: 794200 | K6: ='P031'!$B6-('P031'!$C6+'P031'!$D6+'P031'!$E6+'P031'!$F6+'P031'!$G6+'P031'!$H6+'P031'!$I6+'P031'!$J6) -> 0 | L6: ='P031'!$B6-'P031'!$K6 -> 2294100 | M6: 108000
A7: Marzo | B7: 2496000 | C7: 1000000 | K7: ='P031'!$B7-('P031'!$C7+'P031'!$D7+'P031'!$E7+'P031'!$F7+'P031'!$G7+'P031'!$H7+'P031'!$I7+'P031'!$J7) -> 1496000 | L7: ='P031'!$B7-'P031'!$K7 -> 1000000
A8: Abril | K8: ='P031'!$B8-('P031'!$C8+'P031'!$D8+'P031'!$E8+'P031'!$F8+'P031'!$G8+'P031'!$H8+'P031'!$I8+'P031'!$J8) -> 0 | L8: ='P031'!$B8-'P031'!$K8 -> 0
A9: Mayo | K9: ='P031'!$B9-('P031'!$C9+'P031'!$D9+'P031'!$E9+'P031'!$F9+'P031'!$G9+'P031'!$H9+'P031'!$I9+'P031'!$J9) -> 0 | L9: ='P031'!$B9-'P031'!$K9 -> 0
A10: Junio | K10: ='P031'!$B10-('P031'!$C10+'P031'!$D10+'P031'!$E10+'P031'!$F10+'P031'!$G10+'P031'!$H10+'P031'!$I10+'P031'!$J10) -> 0 | L10: ='P031'!$B10-'P031'!$K10 -> 0
A11: Julio | K11: ='P031'!$B11-('P031'!$C11+'P031'!$D11+'P031'!$E11+'P031'!$F11+'P031'!$G11+'P031'!$H11+'P031'!$I11+'P031'!$J11) -> 0 | L11: ='P031'!$B11-'P031'!$K11 -> 0
A12: Agosto | K12: ='P031'!$B12-('P031'!$C12+'P031'!$D12+'P031'!$E12+'P031'!$F12+'P031'!$G12+'P031'!$H12+'P031'!$I12+'P031'!$J12) -> 0 | L12: ='P031'!$B12-'P031'!$K12 -> 0
A13: Septiembre | K13: ='P031'!$B13-('P031'!$C13+'P031'!$D13+'P031'!$E13+'P031'!$F13+'P031'!$G13+'P031'!$H13+'P031'!$I13+'P031'!$J13) -> 0 | L13: ='P031'!$B13-'P031'!$K13 -> 0
A14: Octubre | K14: ='P031'!$B14-('P031'!$C14+'P031'!$D14+'P031'!$E14+'P031'!$F14+'P031'!$G14+'P031'!$H14+'P031'!$I14+'P031'!$J14) -> 0 | L14: ='P031'!$B14-'P031'!$K14 -> 0
A15: Noviembre | K15: ='P031'!$B15-('P031'!$C15+'P031'!$D15+'P031'!$E15+'P031'!$F15+'P031'!$G15+'P031'!$H15+'P031'!$I15+'P031'!$J15) -> 0 | L15: ='P031'!$B15-'P031'!$K15 -> 0
A16: Diciembre | K16: ='P031'!$B16-('P031'!$C16+'P031'!$D16+'P031'!$E16+'P031'!$F16+'P031'!$G16+'P031'!$H16+'P031'!$I16+'P031'!$J16) -> 0 | L16: ='P031'!$B16-'P031'!$K16 -> 0
A18: NRO DE RECIBOS DE LOS PAGOS
C19: RECIBO 1 | D19: RECIBO 2 | E19: RECIBO 3 | F19: RECIBO 4 | G19: RECIBO 5 | H19: RECIBO 6 | I19: RECIBO 7 | J19: RECIBO 8 | K19: RECIBO 9 | L19: RECIBO 10
A20: Enero | C20: 9612 | D20: 9627
A21: Febrero | C21: 9627 | D21: 9689 | E21: 9705 | P21: 0
A22: Marzo | C22: 9752
A23: Abril
A24: Mayo
A25: Junio
A26: Julio
A27: Agosto
A28: Septiembre
A29: Octubre
A30: Noviembre
A31: Diciembre

Sheet P026
A3: PAGOS DEL ALQUILER
B4: COSTO | C4: PAGO 1 | D4: PAGO 2 | E4: PAGO 3 | F4: PAGO 4 | G4: PAGO 5 | H4: PAGO 6 | I4: PAGO 7 | J4: PAGO 8 | K4: SALDO | L4: RECAUDADO
A5: Enero | K5: ='P026'!$B5-('P026'!$C5+'P026'!$D5+'P026'!$E5+'P026'!$F5+'P026'!$G5+'P026'!$H5+'P026'!$I5+'P026'!$J5) -> 0 | L5: ='P026'!$B5-'P026'!$K5 -> 0
A6: Febrero | K6: ='P026'!$B6-('P026'!$C6+'P026'!$D6+'P026'!$E6+'P026'!$F6+'P026'!$G6+'P026'!$H6+'P026'!$I6+'P026'!$J6) -> 0 | L6: ='P026'!$B6-'P026'!$K6 -> 0
A7: Marzo | K7: ='P026'!$B7-('P026'!$C7+'P026'!$D7+'P026'!$E7+'P026'!$F7+'P026'!$G7+'P026'!$H7+'P026'!$I7+'P026'!$J7) -> 0 | L7: ='P026'!$B7-'P026'!$K7 -> 0
A8: Abril | K8: ='P026'!$B8-('P026'!$C8+'P026'!$D8+'P026'!$E8+'P026'!$F8+'P026'!$G8+'P026'!$H8+'P026'!$I8+'P026'!$J8) -> 0 | L8: ='P026'!$B8-'P026'!$K8 -> 0
A9: Mayo | K9: ='P026'!$B9-('P026'!$C9+'P026'!$D9+'P026'!$E9+'P026'!$F9+'P026'!$G9+'P026'!$H9+'P026'!$I9+'P026'!$J9) -> 0 | L9: ='P026'!$B9-'P026'!$K9 -> 0
A10: Junio | K10: ='P026'!$B10-('P026'!$C10+'P026'!$D10+'P026'!$E10+'P026'!$F10+'P026'!$G10+'P026'!$H10+'P026'!$I10+'P026'!$J10) -> 0 | L10: ='P026'!$B10-'P026'!$K10 -> 0
A11: Julio | K11: ='P026'!$B11-('P026'!$C11+'P026'!$D11+'P026'!$E11+'P026'!$F11+'P026'!$G11+'P026'!$H11+'P026'!$I11+'P026'!$J11) -> 0 | L11: ='P026'!$B11-'P026'!$K11 -> 0
A12: Agosto | K12: ='P026'!$B12-('P026'!$C12+'P026'!$D12+'P026'!$E12+'P026'!$F12+'P026'!$G12+'P026'!$H12+'P026'!$I12+'P026'!$J12) -> 0 | L12: ='P026'!$B12-'P026'!$K12 -> 0
A13: Septiembre | K13: ='P026'!$B13-('P026'!$C13+'P026'!$D13+'P026'!$E13+'P026'!$F13+'P026'!$G13+'P026'!$H13+'P026'!$I13+'P026'!$J13) -> 0 | L13: ='P026'!$B13-'P026'!$K13 -> 0
A14: Octubre | K14: ='P026'!$B14-('P026'!$C14+'P026'!$D14+'P026'!$E14+'P026'!$F14+'P026'!$G14+'P026'!$H14+'P026'!$I14+'P026'!$J14) -> 0 | L14: ='P026'!$B14-'P026'!$K14 -> 0
A15: Noviembre | K15: ='P026'!$B15-('P026'!$C15+'P026'!$D15+'P026'!$E15+'P026'!$F15+'P026'!$G15+'P026'!$H15+'P026'!$I15+'P026'!$J15) -> 0 | L15: ='P026'!$B15-'P026'!$K15 -> 0
A16: Diciembre | K16: ='P026'!$B16-('P026'!$C16+'P026'!$D16+'P026'!$E16+'P026'!$F16+'P026'!$G16+'P026'!$H16+'P026'!$I16+'P026'!$J16) -> 0 | L16: ='P026'!$B16-'P026'!$K16 -> 0
A18: NRO DE RECIBOS DE LOS PAGOS
C19: RECIBO 1 | D19: RECIBO 2 | E19: RECIBO 3 | F19: RECIBO 4 | G19: RECIBO 5 | H19: RECIBO 6 | I19: RECIBO 7 | J19: RECIBO 8
A20: Enero
A21: Febrero
A22: Marzo
A23: Abril
A24: Mayo
A25: Junio
A26: Julio
A27: Agosto
A28: Septiembre
A29: Octubre
A30: Noviembre
A31: Diciembre

Sheet P027
A3: PAGOS DEL ALQUILER
B4: COSTO | C4: PAGO 1 | D4: PAGO 2 | E4: PAGO 3 | F4: PAGO 4 | G4: PAGO 5 | H4: PAGO 6 | I4: PAGO 7 | J4: PAGO 8 | K4: SALDO | L4: RECAUDADO
A5: Enero | K5: ='P027'!$B5-('P027'!$C5+'P027'!$D5+'P027'!$E5+'P027'!$F5+'P027'!$G5+'P027'!$H5+'P027'!$I5+'P027'!$J5) -> 0 | L5: ='P027'!$B5-'P027'!$K5 -> 0
A6: Febrero | K6: ='P027'!$B6-('P027'!$C6+'P027'!$D6+'P027'!$E6+'P027'!$F6+'P027'!$G6+'P027'!$H6+'P027'!$I6+'P027'!$J6) -> 0 | L6: ='P027'!$B6-'P027'!$K6 -> 0
A7: Marzo | K7: ='P027'!$B7-('P027'!$C7+'P027'!$D7+'P027'!$E7+'P027'!$F7+'P027'!$G7+'P027'!$H7+'P027'!$I7+'P027'!$J7) -> 0 | L7: ='P027'!$B7-'P027'!$K7 -> 0
A8: Abril | K8: ='P027'!$B8-('P027'!$C8+'P027'!$D8+'P027'!$E8+'P027'!$F8+'P027'!$G8+'P027'!$H8+'P027'!$I8+'P027'!$J8) -> 0 | L8: ='P027'!$B8-'P027'!$K8 -> 0
A9: Mayo | K9: ='P027'!$B9-('P027'!$C9+'P027'!$D9+'P027'!$E9+'P027'!$F9+'P027'!$G9+'P027'!$H9+'P027'!$I9+'P027'!$J9) -> 0 | L9: ='P027'!$B9-'P027'!$K9 -> 0
A10: Junio | K10: ='P027'!$B10-('P027'!$C10+'P027'!$D10+'P027'!$E10+'P027'!$F10+'P027'!$G10+'P027'!$H10+'P027'!$I10+'P027'!$J10) -> 0 | L10: ='P027'!$B10-'P027'!$K10 -> 0
A11: Julio | K11: ='P027'!$B11-('P027'!$C11+'P027'!$D11+'P027'!$E11+'P027'!$F11+'P027'!$G11+'P027'!$H11+'P027'!$I11+'P027'!$J11) -> 0 | L11: ='P027'!$B11-'P027'!$K11 -> 0
A12: Agosto | K12: ='P027'!$B12-('P027'!$C12+'P027'!$D12+'P027'!$E12+'P027'!$F12+'P027'!$G12+'P027'!$H12+'P027'!$I12+'P027'!$J12) -> 0 | L12: ='P027'!$B12-'P027'!$K12 -> 0
A13: Septiembre | K13: ='P027'!$B13-('P027'!$C13+'P027'!$D13+'P027'!$E13+'P027'!$F13+'P027'!$G13+'P027'!$H13+'P027'!$I13+'P027'!$J13) -> 0 | L13: ='P027'!$B13-'P027'!$K13 -> 0
A14: Octubre | K14: ='P027'!$B14-('P027'!$C14+'P027'!$D14+'P027'!$E14+'P027'!$F14+'P027'!$G14+'P027'!$H14+'P027'!$I14+'P027'!$J14) -> 0 | L14: ='P027'!$B14-'P027'!$K14 -> 0
A15: Noviembre | K15: ='P027'!$B15-('P027'!$C15+'P027'!$D15+'P027'!$E15+'P027'!$F15+'P027'!$G15+'P027'!$H15+'P027'!$I15+'P027'!$J15) -> 0 | L15: ='P027'!$B15-'P027'!$K15 -> 0
A16: Diciembre | K16: ='P027'!$B16-('P027'!$C16+'P027'!$D16+'P027'!$E16+'P027'!$F16+'P027'!$G16+'P027'!$H16+'P027'!$I16+'P027'!$J16) -> 0 | L16: ='P027'!$B16-'P027'!$K16 -> 0
A18: NRO DE RECIBOS DE LOS PAGOS
C19: RECIBO 1 | D19: RECIBO 2 | E19: RECIBO 3 | F19: RECIBO 4 | G19: RECIBO 5 | H19: RECIBO 6 | I19: RECIBO 7 | J19: RECIBO 8
A20: Enero
A21: Febrero
A22: Marzo
A23: Abril
A24: Mayo
A25: Junio
A26: Julio
A27: Agosto
A28: Septiembre
A29: Octubre
A30: Noviembre
A31: Diciembre

Sheet P028
A3: PAGOS DEL ALQUILER
B4: COSTO | C4: PAGO 1 | D4: PAGO 2 | E4: PAGO 3 | F4: PAGO 4 | G4: PAGO 5 | H4: PAGO 6 | I4: PAGO 7 | J4: PAGO 8 | K4: SALDO | L4: RECAUDADO
A5: Enero | K5: ='P028'!$B5-('P028'!$C5+'P028'!$D5+'P028'!$E5+'P028'!$F5+'P028'!$G5+'P028'!$H5+'P028'!$I5+'P028'!$J5) -> 0 | L5: ='P028'!$B5-'P028'!$K5 -> 0
A6: Febrero | K6: ='P028'!$B6-('P028'!$C6+'P028'!$D6+'P028'!$E6+'P028'!$F6+'P028'!$G6+'P028'!$H6+'P028'!$I6+'P028'!$J6) -> 0 | L6: ='P028'!$B6-'P028'!$K6 -> 0
A7: Marzo | K7: ='P028'!$B7-('P028'!$C7+'P028'!$D7+'P028'!$E7+'P028'!$F7+'P028'!$G7+'P028'!$H7+'P028'!$I7+'P028'!$J7) -> 0 | L7: ='P028'!$B7-'P028'!$K7 -> 0
A8: Abril | K8: ='P028'!$B8-('P028'!$C8+'P028'!$D8+'P028'!$E8+'P028'!$F8+'P028'!$G8+'P028'!$H8+'P028'!$I8+'P028'!$J8) -> 0 | L8: ='P028'!$B8-'P028'!$K8 -> 0
A9: Mayo | K9: ='P028'!$B9-('P028'!$C9+'P028'!$D9+'P028'!$E9+'P028'!$F9+'P028'!$G9+'P028'!$H9+'P028'!$I9+'P028'!$J9) -> 0 | L9: ='P028'!$B9-'P028'!$K9 -> 0
A10: Junio | K10: ='P028'!$B10-('P028'!$C10+'P028'!$D10+'P028'!$E10+'P028'!$F10+'P028'!$G10+'P028'!$H10+'P028'!$I10+'P028'!$J10) -> 0 | L10: ='P028'!$B10-'P028'!$K10 -> 0
A11: Julio | K11: ='P028'!$B11-('P028'!$C11+'P028'!$D11+'P028'!$E11+'P028'!$F11+'P028'!$G11+'P028'!$H11+'P028'!$I11+'P028'!$J11) -> 0 | L11: ='P028'!$B11-'P028'!$K11 -> 0
A12: Agosto | K12: ='P028'!$B12-('P028'!$C12+'P028'!$D12+'P028'!$E12+'P028'!$F12+'P028'!$G12+'P028'!$H12+'P028'!$I12+'P028'!$J12) -> 0 | L12: ='P028'!$B12-'P028'!$K12 -> 0
A13: Septiembre | K13: ='P028'!$B13-('P028'!$C13+'P028'!$D13+'P028'!$E13+'P028'!$F13+'P028'!$G13+'P028'!$H13+'P028'!$I13+'P028'!$J13) -> 0 | L13: ='P028'!$B13-'P028'!$K13 -> 0
A14: Octubre | K14: ='P028'!$B14-('P028'!$C14+'P028'!$D14+'P028'!$E14+'P028'!$F14+'P028'!$G14+'P028'!$H14+'P028'!$I14+'P028'!$J14) -> 0 | L14: ='P028'!$B14-'P028'!$K14 -> 0
A15: Noviembre | K15: ='P028'!$B15-('P028'!$C15+'P028'!$D15+'P028'!$E15+'P028'!$F15+'P028'!$G15+'P028'!$H15+'P028'!$I15+'P028'!$J15) -> 0 | L15: ='P028'!$B15-'P028'!$K15 -> 0
A16: Diciembre | K16: ='P028'!$B16-('P028'!$C16+'P028'!$D16+'P028'!$E16+'P028'!$F16+'P028'!$G16+'P028'!$H16+'P028'!$I16+'P028'!$J16) -> 0 | L16: ='P028'!$B16-'P028'!$K16 -> 0
A18: NRO DE RECIBOS DE LOS PAGOS
C19: RECIBO 1 | D19: RECIBO 2 | E19: RECIBO 3 | F19: RECIBO 4 | G19: RECIBO 5 | H19: RECIBO 6 | I19: RECIBO 7 | J19: RECIBO 8
A20: Enero
A21: Febrero
A22: Marzo
A23: Abril
A24: Mayo
A25: Junio
A26: Julio
A27: Agosto
A28: Septiembre
A29: Octubre
A30: Noviembre
A31: Diciembre

Sheet P029
A3: PAGOS DEL ALQUILER
B4: COSTO | C4: PAGO 1 | D4: PAGO 2 | E4: PAGO 3 | F4: PAGO 4 | G4: PAGO 5 | H4: PAGO 6 | I4: PAGO 7 | J4: PAGO 8 | K4: SALDO | L4: RECAUDADO
A5: Enero | K5: ='P029'!$B5-('P029'!$C5+'P029'!$D5+'P029'!$E5+'P029'!$F5+'P029'!$G5+'P029'!$H5+'P029'!$I5+'P029'!$J5) -> 0 | L5: ='P029'!$B5-'P029'!$K5 -> 0
A6: Febrero | K6: ='P029'!$B6-('P029'!$C6+'P029'!$D6+'P029'!$E6+'P029'!$F6+'P029'!$G6+'P029'!$H6+'P029'!$I6+'P029'!$J6) -> 0 | L6: ='P029'!$B6-'P029'!$K6 -> 0
A7: Marzo | K7: ='P029'!$B7-('P029'!$C7+'P029'!$D7+'P029'!$E7+'P029'!$F7+'P029'!$G7+'P029'!$H7+'P029'!$I7+'P029'!$J7) -> 0 | L7: ='P029'!$B7-'P029'!$K7 -> 0
A8: Abril | K8: ='P029'!$B8-('P029'!$C8+'P029'!$D8+'P029'!$E8+'P029'!$F8+'P029'!$G8+'P029'!$H8+'P029'!$I8+'P029'!$J8) -> 0 | L8: ='P029'!$B8-'P029'!$K8 -> 0
A9: Mayo | K9: ='P029'!$B9-('P029'!$C9+'P029'!$D9+'P029'!$E9+'P029'!$F9+'P029'!$G9+'P029'!$H9+'P029'!$I9+'P029'!$J9) -> 0 | L9: ='P029'!$B9-'P029'!$K9 -> 0
A10: Junio | K10: ='P029'!$B10-('P029'!$C10+'P029'!$D10+'P029'!$E10+'P029'!$F10+'P029'!$G10+'P029'!$H10+'P029'!$I10+'P029'!$J10) -> 0 | L10: ='P029'!$B10-'P029'!$K10 -> 0
A11: Julio | K11: ='P029'!$B11-('P029'!$C11+'P029'!$D11+'P029'!$E11+'P029'!$F11+'P029'!$G11+'P029'!$H11+'P029'!$I11+'P029'!$J11) -> 0 | L11: ='P029'!$B11-'P029'!$K11 -> 0
A12: Agosto | K12: ='P029'!$B12-('P029'!$C12+'P029'!$D12+'P029'!$E12+'P029'!$F12+'P029'!$G12+'P029'!$H12+'P029'!$I12+'P029'!$J12) -> 0 | L12: ='P029'!$B12-'P029'!$K12 -> 0
A13: Septiembre | K13: ='P029'!$B13-('P029'!$C13+'P029'!$D13+'P029'!$E13+'P029'!$F13+'P029'!$G13+'P029'!$H13+'P029'!$I13+'P029'!$J13) -> 0 | L13: ='P029'!$B13-'P029'!$K13 -> 0
A14: Octubre | K14: ='P029'!$B14-('P029'!$C14+'P029'!$D14+'P029'!$E14+'P029'!$F14+'P029'!$G14+'P029'!$H14+'P029'!$I14+'P029'!$J14) -> 0 | L14: ='P029'!$B14-'P029'!$K14 -> 0
A15: Noviembre | K15: ='P029'!$B15-('P029'!$C15+'P029'!$D15+'P029'!$E15+'P029'!$F15+'P029'!$G15+'P029'!$H15+'P029'!$I15+'P029'!$J15) -> 0 | L15: ='P029'!$B15-'P029'!$K15 -> 0
A16: Diciembre | K16: ='P029'!$B16-('P029'!$C16+'P029'!$D16+'P029'!$E16+'P029'!$F16+'P029'!$G16+'P029'!$H16+'P029'!$I16+'P029'!$J16) -> 0 | L16: ='P029'!$B16-'P029'!$K16 -> 0
A18: NRO DE RECIBOS DE LOS PAGOS
C19: RECIBO 1 | D19: RECIBO 2 | E19: RECIBO 3 | F19: RECIBO 4 | G19: RECIBO 5 | H19: RECIBO 6 | I19: RECIBO 7 | J19: RECIBO 8
A20: Enero
A21: Febrero
A22: Marzo
A23: Abril
A24: Mayo
A25: Junio
A26: Julio
A27: Agosto
A28: Septiembre
A29: Octubre
A30: Noviembre
A31: Diciembre

Sheet P030
A3: PAGOS DEL ALQUILER
B4: COSTO | C4: PAGO 1 | D4: PAGO 2 | E4: PAGO 3 | F4: PAGO 4 | G4: PAGO 5 | H4: PAGO 6 | I4: PAGO 7 | J4: PAGO 8 | K4: SALDO | L4: RECAUDADO
A5: Enero | K5: ='P030'!$B5-('P030'!$C5+'P030'!$D5+'P030'!$E5+'P030'!$F5+'P030'!$G5+'P030'!$H5+'P030'!$I5+'P030'!$J5) -> 0 | L5: ='P030'!$B5-'P030'!$K5 -> 0
A6: Febrero | K6: ='P030'!$B6-('P030'!$C6+'P030'!$D6+'P030'!$E6+'P030'!$F6+'P030'!$G6+'P030'!$H6+'P030'!$I6+'P030'!$J6) -> 0 | L6: ='P030'!$B6-'P030'!$K6 -> 0
A7: Marzo | K7: ='P030'!$B7-('P030'!$C7+'P030'!$D7+'P030'!$E7+'P030'!$F7+'P030'!$G7+'P030'!$H7+'P030'!$I7+'P030'!$J7) -> 0 | L7: ='P030'!$B7-'P030'!$K7 -> 0
A8: Abril | K8: ='P030'!$B8-('P030'!$C8+'P030'!$D8+'P030'!$E8+'P030'!$F8+'P030'!$G8+'P030'!$H8+'P030'!$I8+'P030'!$J8) -> 0 | L8: ='P030'!$B8-'P030'!$K8 -> 0
A9: Mayo | K9: ='P030'!$B9-('P030'!$C9+'P030'!$D9+'P030'!$E9+'P030'!$F9+'P030'!$G9+'P030'!$H9+'P030'!$I9+'P030'!$J9) -> 0 | L9: ='P030'!$B9-'P030'!$K9 -> 0
A10: Junio | K10: ='P030'!$B10-('P030'!$C10+'P030'!$D10+'P030'!$E10+'P030'!$F10+'P030'!$G10+'P030'!$H10+'P030'!$I10+'P030'!$J10) -> 0 | L10: ='P030'!$B10-'P030'!$K10 -> 0
A11: Julio | K11: ='P030'!$B11-('P030'!$C11+'P030'!$D11+'P030'!$E11+'P030'!$F11+'P030'!$G11+'P030'!$H11+'P030'!$I11+'P030'!$J11) -> 0 | L11: ='P030'!$B11-'P030'!$K11 -> 0
A12: Agosto | K12: ='P030'!$B12-('P030'!$C12+'P030'!$D12+'P030'!$E12+'P030'!$F12+'P030'!$G12+'P030'!$H12+'P030'!$I12+'P030'!$J12) -> 0 | L12: ='P030'!$B12-'P030'!$K12 -> 0
A13: Septiembre | K13: ='P030'!$B13-('P030'!$C13+'P030'!$D13+'P030'!$E13+'P030'!$F13+'P030'!$G13+'P030'!$H13+'P030'!$I13+'P030'!$J13) -> 0 | L13: ='P030'!$B13-'P030'!$K13 -> 0
A14: Octubre | K14: ='P030'!$B14-('P030'!$C14+'P030'!$D14+'P030'!$E14+'P030'!$F14+'P030'!$G14+'P030'!$H14+'P030'!$I14+'P030'!$J14) -> 0 | L14: ='P030'!$B14-'P030'!$K14 -> 0
A15: Noviembre | K15: ='P030'!$B15-('P030'!$C15+'P030'!$D15+'P030'!$E15+'P030'!$F15+'P030'!$G15+'P030'!$H15+'P030'!$I15+'P030'!$J15) -> 0 | L15: ='P030'!$B15-'P030'!$K15 -> 0
A16: Diciembre | K16: ='P030'!$B16-('P030'!$C16+'P030'!$D16+'P030'!$E16+'P030'!$F16+'P030'!$G16+'P030'!$H16+'P030'!$I16+'P030'!$J16) -> 0 | L16: ='P030'!$B16-'P030'!$K16 -> 0
A18: NRO DE RECIBOS DE LOS PAGOS
C19: RECIBO 1 | D19: RECIBO 2 | E19: RECIBO 3 | F19: RECIBO 4 | G19: RECIBO 5 | H19: RECIBO 6 | I19: RECIBO 7 | J19: RECIBO 8
A20: Enero
A21: Febrero
A22: Marzo
A23: Abril
A24: Mayo
A25: Junio
A26: Julio
A27: Agosto
A28: Septiembre
A29: Octubre
A30: Noviembre
A31: Diciembre

Sheet P032
A3: PAGOS DEL ALQUILER
B4: COSTO | C4: PAGO 1 | D4: PAGO 2 | E4: PAGO 3 | F4: PAGO 4 | G4: PAGO 5 | H4: PAGO 6 | I4: PAGO 7 | J4: PAGO 8 | K4: SALDO | L4: RECAUDADO
A5: Enero | K5: ='P032'!$B5-('P032'!$C5+'P032'!$D5+'P032'!$E5+'P032'!$F5+'P032'!$G5+'P032'!$H5+'P032'!$I5+'P032'!$J5) -> 0 | L5: ='P032'!$B5-'P032'!$K5 -> 0
A6: Febrero | K6: ='P032'!$B6-('P032'!$C6+'P032'!$D6+'P032'!$E6+'P032'!$F6+'P032'!$G6+'P032'!$H6+'P032'!$I6+'P032'!$J6) -> 0 | L6: ='P032'!$B6-'P032'!$K6 -> 0
A7: Marzo | K7: ='P032'!$B7-('P032'!$C7+'P032'!$D7+'P032'!$E7+'P032'!$F7+'P032'!$G7+'P032'!$H7+'P032'!$I7+'P032'!$J7) -> 0 | L7: ='P032'!$B7-'P032'!$K7 -> 0
A8: Abril | K8: ='P032'!$B8-('P032'!$C8+'P032'!$D8+'P032'!$E8+'P032'!$F8+'P032'!$G8+'P032'!$H8+'P032'!$I8+'P032'!$J8) -> 0 | L8: ='P032'!$B8-'P032'!$K8 -> 0
A9: Mayo | K9: ='P032'!$B9-('P032'!$C9+'P032'!$D9+'P032'!$E9+'P032'!$F9+'P032'!$G9+'P032'!$H9+'P032'!$I9+'P032'!$J9) -> 0 | L9: ='P032'!$B9-'P032'!$K9 -> 0
A10: Junio | K10: ='P032'!$B10-('P032'!$C10+'P032'!$D10+'P032'!$E10+'P032'!$F10+'P032'!$G10+'P032'!$H10+'P032'!$I10+'P032'!$J10) -> 0 | L10: ='P032'!$B10-'P032'!$K10 -> 0
A11: Julio | K11: ='P032'!$B11-('P032'!$C11+'P032'!$D11+'P032'!$E11+'P032'!$F11+'P032'!$G11+'P032'!$H11+'P032'!$I11+'P032'!$J11) -> 0 | L11: ='P032'!$B11-'P032'!$K11 -> 0
A12: Agosto | K12: ='P032'!$B12-('P032'!$C12+'P032'!$D12+'P032'!$E12+'P032'!$F12+'P032'!$G12+'P032'!$H12+'P032'!$I12+'P032'!$J12) -> 0 | L12: ='P032'!$B12-'P032'!$K12 -> 0
A13: Septiembre | K13: ='P032'!$B13-('P032'!$C13+'P032'!$D13+'P032'!$E13+'P032'!$F13+'P032'!$G13+'P032'!$H13+'P032'!$I13+'P032'!$J13) -> 0 | L13: ='P032'!$B13-'P032'!$K13 -> 0
A14: Octubre | K14: ='P032'!$B14-('P032'!$C14+'P032'!$D14+'P032'!$E14+'P032'!$F14+'P032'!$G14+'P032'!$H14+'P032'!$I14+'P032'!$J14) -> 0 | L14: ='P032'!$B14-'P032'!$K14 -> 0
A15: Noviembre | K15: ='P032'!$B15-('P032'!$C15+'P032'!$D15+'P032'!$E15+'P032'!$F15+'P032'!$G15+'P032'!$H15+'P032'!$I15+'P032'!$J15) -> 0 | L15: ='P032'!$B15-'P032'!$K15 -> 0
A16: Diciembre | K16: ='P032'!$B16-('P032'!$C16+'P032'!$D16+'P032'!$E16+'P032'!$F16+'P032'!$G16+'P032'!$H16+'P032'!$I16+'P032'!$J16) -> 0 | L16: ='P032'!$B16-'P032'!$K16 -> 0
A18: NRO DE RECIBOS DE LOS PAGOS
C19: RECIBO 1 | D19: RECIBO 2 | E19: RECIBO 3 | F19: RECIBO 4 | G19: RECIBO 5 | H19: RECIBO 6 | I19: RECIBO 7 | J19: RECIBO 8
A20: Enero
A21: Febrero
A22: Marzo
A23: Abril
A24: Mayo
A25: Junio
A26: Julio
A27: Agosto
A28: Septiembre
A29: Octubre
A30: Noviembre
A31: Diciembre

Sheet P033
A3: PAGOS DEL ALQUILER
B4: COSTO | C4: PAGO 1 | D4: PAGO 2 | E4: PAGO 3 | F4: PAGO 4 | G4: PAGO 5 | H4: PAGO 6 | I4: PAGO 7 | J4: PAGO 8 | K4: SALDO | L4: RECAUDADO
A5: Enero | K5: ='P033'!$B5-('P033'!$C5+'P033'!$D5+'P033'!$E5+'P033'!$F5+'P033'!$G5+'P033'!$H5+'P033'!$I5+'P033'!$J5) -> 0 | L5: ='P033'!$B5-'P033'!$K5 -> 0
A6: Febrero | K6: ='P033'!$B6-('P033'!$C6+'P033'!$D6+'P033'!$E6+'P033'!$F6+'P033'!$G6+'P033'!$H6+'P033'!$I6+'P033'!$J6) -> 0 | L6: ='P033'!$B6-'P033'!$K6 -> 0
A7: Marzo | K7: ='P033'!$B7-('P033'!$C7+'P033'!$D7+'P033'!$E7+'P033'!$F7+'P033'!$G7+'P033'!$H7+'P033'!$I7+'P033'!$J7) -> 0 | L7: ='P033'!$B7-'P033'!$K7 -> 0
A8: Abril | K8: ='P033'!$B8-('P033'!$C8+'P033'!$D8+'P033'!$E8+'P033'!$F8+'P033'!$G8+'P033'!$H8+'P033'!$I8+'P033'!$J8) -> 0 | L8: ='P033'!$B8-'P033'!$K8 -> 0
A9: Mayo | K9: ='P033'!$B9-('P033'!$C9+'P033'!$D9+'P033'!$E9+'P033'!$F9+'P033'!$G9+'P033'!$H9+'P033'!$I9+'P033'!$J9) -> 0 | L9: ='P033'!$B9-'P033'!$K9 -> 0
A10: Junio | K10: ='P033'!$B10-('P033'!$C10+'P033'!$D10+'P033'!$E10+'P033'!$F10+'P033'!$G10+'P033'!$H10+'P033'!$I10+'P033'!$J10) -> 0 | L10: ='P033'!$B10-'P033'!$K10 -> 0
A11: Julio | K11: ='P033'!$B11-('P033'!$C11+'P033'!$D11+'P033'!$E11+'P033'!$F11+'P033'!$G11+'P033'!$H11+'P033'!$I11+'P033'!$J11) -> 0 | L11: ='P033'!$B11-'P033'!$K11 -> 0
A12: Agosto | K12: ='P033'!$B12-('P033'!$C12+'P033'!$D12+'P033'!$E12+'P033'!$F12+'P033'!$G12+'P033'!$H12+'P033'!$I12+'P033'!$J12) -> 0 | L12: ='P033'!$B12-'P033'!$K12 -> 0
A13: Septiembre | K13: ='P033'!$B13-('P033'!$C13+'P033'!$D13+'P033'!$E13+'P033'!$F13+'P033'!$G13+'P033'!$H13+'P033'!$I13+'P033'!$J13) -> 0 | L13: ='P033'!$B13-'P033'!$K13 -> 0
A14: Octubre | K14: ='P033'!$B14-('P033'!$C14+'P033'!$D14+'P033'!$E14+'P033'!$F14+'P033'!$G14+'P033'!$H14+'P033'!$I14+'P033'!$J14) -> 0 | L14: ='P033'!$B14-'P033'!$K14 -> 0
A15: Noviembre | K15: ='P033'!$B15-('P033'!$C15+'P033'!$D15+'P033'!$E15+'P033'!$F15+'P033'!$G15+'P033'!$H15+'P033'!$I15+'P033'!$J15) -> 0 | L15: ='P033'!$B15-'P033'!$K15 -> 0
A16: Diciembre | K16: ='P033'!$B16-('P033'!$C16+'P033'!$D16+'P033'!$E16+'P033'!$F16+'P033'!$G16+'P033'!$H16+'P033'!$I16+'P033'!$J16) -> 0 | L16: ='P033'!$B16-'P033'!$K16 -> 0
A18: NRO DE RECIBOS DE LOS PAGOS
C19: RECIBO 1 | D19: RECIBO 2 | E19: RECIBO 3 | F19: RECIBO 4 | G19: RECIBO 5 | H19: RECIBO 6 | I19: RECIBO 7 | J19: RECIBO 8
A20: Enero
A21: Febrero
A22: Marzo
A23: Abril
A24: Mayo
A25: Junio
A26: Julio
A27: Agosto
A28: Septiembre
A29: Octubre
A30: Noviembre
A31: Diciembre

Sheet P034
A3: PAGOS DEL ALQUILER
B4: COSTO | C4: PAGO 1 | D4: PAGO 2 | E4: PAGO 3 | F4: PAGO 4 | G4: PAGO 5 | H4: PAGO 6 | I4: PAGO 7 | J4: PAGO 8 | K4: SALDO | L4: RECAUDADO
A5: Enero | K5: ='P034'!$B5-('P034'!$C5+'P034'!$D5+'P034'!$E5+'P034'!$F5+'P034'!$G5+'P034'!$H5+'P034'!$I5+'P034'!$J5) -> 0 | L5: ='P034'!$B5-'P034'!$K5 -> 0
A6: Febrero | K6: ='P034'!$B6-('P034'!$C6+'P034'!$D6+'P034'!$E6+'P034'!$F6+'P034'!$G6+'P034'!$H6+'P034'!$I6+'P034'!$J6) -> 0 | L6: ='P034'!$B6-'P034'!$K6 -> 0
A7: Marzo | K7: ='P034'!$B7-('P034'!$C7+'P034'!$D7+'P034'!$E7+'P034'!$F7+'P034'!$G7+'P034'!$H7+'P034'!$I7+'P034'!$J7) -> 0 | L7: ='P034'!$B7-'P034'!$K7 -> 0
A8: Abril | K8: ='P034'!$B8-('P034'!$C8+'P034'!$D8+'P034'!$E8+'P034'!$F8+'P034'!$G8+'P034'!$H8+'P034'!$I8+'P034'!$J8) -> 0 | L8: ='P034'!$B8-'P034'!$K8 -> 0
A9: Mayo | K9: ='P034'!$B9-('P034'!$C9+'P034'!$D9+'P034'!$E9+'P034'!$F9+'P034'!$G9+'P034'!$H9+'P034'!$I9+'P034'!$J9) -> 0 | L9: ='P034'!$B9-'P034'!$K9 -> 0
A10: Junio | K10: ='P034'!$B10-('P034'!$C10+'P034'!$D10+'P034'!$E10+'P034'!$F10+'P034'!$G10+'P034'!$H10+'P034'!$I10+'P034'!$J10) -> 0 | L10: ='P034'!$B10-'P034'!$K10 -> 0
A11: Julio | K11: ='P034'!$B11-('P034'!$C11+'P034'!$D11+'P034'!$E11+'P034'!$F11+'P034'!$G11+'P034'!$H11+'P034'!$I11+'P034'!$J11) -> 0 | L11: ='P034'!$B11-'P034'!$K11 -> 0
A12: Agosto | K12: ='P034'!$B12-('P034'!$C12+'P034'!$D12+'P034'!$E12+'P034'!$F12+'P034'!$G12+'P034'!$H12+'P034'!$I12+'P034'!$J12) -> 0 | L12: ='P034'!$B12-'P034'!$K12 -> 0
A13: Septiembre | K13: ='P034'!$B13-('P034'!$C13+'P034'!$D13+'P034'!$E13+'P034'!$F13+'P034'!$G13+'P034'!$H13+'P034'!$I13+'P034'!$J13) -> 0 | L13: ='P034'!$B13-'P034'!$K13 -> 0
A14: Octubre | K14: ='P034'!$B14-('P034'!$C14+'P034'!$D14+'P034'!$E14+'P034'!$F14+'P034'!$G14+'P034'!$H14+'P034'!$I14+'P034'!$J14) -> 0 | L14: ='P034'!$B14-'P034'!$K14 -> 0
A15: Noviembre | K15: ='P034'!$B15-('P034'!$C15+'P034'!$D15+'P034'!$E15+'P034'!$F15+'P034'!$G15+'P034'!$H15+'P034'!$I15+'P034'!$J15) -> 0 | L15: ='P034'!$B15-'P034'!$K15 -> 0
A16: Diciembre | K16: ='P034'!$B16-('P034'!$C16+'P034'!$D16+'P034'!$E16+'P034'!$F16+'P034'!$G16+'P034'!$H16+'P034'!$I16+'P034'!$J16) -> 0 | L16: ='P034'!$B16-'P034'!$K16 -> 0
A18: NRO DE RECIBOS DE LOS PAGOS
C19: RECIBO 1 | D19: RECIBO 2 | E19: RECIBO 3 | F19: RECIBO 4 | G19: RECIBO 5 | H19: RECIBO 6 | I19: RECIBO 7 | J19: RECIBO 8
A20: Enero
A21: Febrero
A22: Marzo
A23: Abril
A24: Mayo
A25: Junio
A26: Julio
A27: Agosto
A28: Septiembre
A29: Octubre
A30: Noviembre
A31: Diciembre

Sheet P035
A1: Pto.42/51/35/35b | C1: AGURTO LUIS
A3: PAGOS DEL ALQUILER | T3: NETO | U3: INTERES
B4: COSTO | C4: PAGO 1 | D4: PAGO 2 | E4: PAGO 3 | F4: PAGO 4 | G4: PAGO 5 | H4: PAGO 6 | I4: PAGO 7 | J4: PAGO 8 | K4: SALDO | L4: RECAUDADO | S4: SEP | T4: 420900 | U4: 0.7 | V4: 715530
A5: Enero | B5: 486300 | C5: 486300 | K5: ='P035'!$B5-('P035'!$C5+'P035'!$D5+'P035'!$E5+'P035'!$F5+'P035'!$G5+'P035'!$H5+'P035'!$I5+'P035'!$J5) -> 0 | L5: ='P035'!$B5-'P035'!$K5 -> 486300 | S5: OCT | T5: 420900 | U5: 0.6 | V5: 673440
A6: Febrero | B6: 486300 | C6: 486300 | K6: ='P035'!$B6-('P035'!$C6+'P035'!$D6+'P035'!$E6+'P035'!$F6+'P035'!$G6+'P035'!$H6+'P035'!$I6+'P035'!$J6) -> 0 | L6: ='P035'!$B6-'P035'!$K6 -> 486300 | S6: NOV | T6: 420900 | U6: 0.5 | V6: 631350
A7: Marzo | B7: 537900 | C7: 537900 | K7: ='P035'!$B7-('P035'!$C7+'P035'!$D7+'P035'!$E7+'P035'!$F7+'P035'!$G7+'P035'!$H7+'P035'!$I7+'P035'!$J7) -> 0 | L7: ='P035'!$B7-'P035'!$K7 -> 537900 | S7: DIC | T7: 463100 | U7: 0.4 | V7: 648340
A8: Abril | B8: 537900 | C8: 537900 | K8: ='P035'!$B8-('P035'!$C8+'P035'!$D8+'P035'!$E8+'P035'!$F8+'P035'!$G8+'P035'!$H8+'P035'!$I8+'P035'!$J8) -> 0 | L8: ='P035'!$B8-'P035'!$K8 -> 537900 | S8: ENERO | T8: 486300 | U8: 0.3 | V8: 632190
A9: Mayo | B9: 2655800 | C9: 2655800 | K9: ='P035'!$B9-('P035'!$C9+'P035'!$D9+'P035'!$E9+'P035'!$F9+'P035'!$G9+'P035'!$H9+'P035'!$I9+'P035'!$J9) -> 0 | L9: ='P035'!$B9-'P035'!$K9 -> 2655800 | S9: FEB | T9: 486300 | U9: 0.2 | V9: 583560
A10: Junio | K10: ='P035'!$B10-('P035'!$C10+'P035'!$D10+'P035'!$E10+'P035'!$F10+'P035'!$G10+'P035'!$H10+'P035'!$I10+'P035'!$J10) -> 0 | L10: ='P035'!$B10-'P035'!$K10 -> 0 | S10: MARZO | T10: 537900 | U10: 0.1 | V10: 591690
A11: Julio | K11: ='P035'!$B11-('P035'!$C11+'P035'!$D11+'P035'!$E11+'P035'!$F11+'P035'!$G11+'P035'!$H11+'P035'!$I11+'P035'!$J11) -> 0 | L11: ='P035'!$B11-'P035'!$K11 -> 0 | V11: =SUM(V4:V10) -> 4476100
A12: Agosto | K12: ='P035'!$B12-('P035'!$C12+'P035'!$D12+'P035'!$E12+'P035'!$F12+'P035'!$G12+'P035'!$H12+'P035'!$I12+'P035'!$J12) -> 0 | L12: ='P035'!$B12-'P035'!$K12 -> 0
A13: Septiembre | K13: ='P035'!$B13-('P035'!$C13+'P035'!$D13+'P035'!$E13+'P035'!$F13+'P035'!$G13+'P035'!$H13+'P035'!$I13+'P035'!$J13) -> 0 | L13: ='P035'!$B13-'P035'!$K13 -> 0
A14: Octubre | K14: ='P035'!$B14-('P035'!$C14+'P035'!$D14+'P035'!$E14+'P035'!$F14+'P035'!$G14+'P035'!$H14+'P035'!$I14+'P035'!$J14) -> 0 | L14: ='P035'!$B14-'P035'!$K14 -> 0
A15: Noviembre | K15: ='P035'!$B15-('P035'!$C15+'P035'!$D15+'P035'!$E15+'P035'!$F15+'P035'!$G15+'P035'!$H15+'P035'!$I15+'P035'!$J15) -> 0 | L15: ='P035'!$B15-'P035'!$K15 -> 0 | N15: 2025 | O15: 2024
A16: Diciembre | K16: ='P035'!$B16-('P035'!$C16+'P035'!$D16+'P035'!$E16+'P035'!$F16+'P035'!$G16+'P035'!$H16+'P035'!$I16+'P035'!$J16) -> 0 | L16: ='P035'!$B16-'P035'!$K16 -> 0 | N16: =B5+B6+B7 -> 1510500 | O16: 1725800 | P16: =N16+O16 -> 3236300
A18: NRO DE RECIBOS DE LOS PAGOS
C19: RECIBO 1 | D19: RECIBO 2 | E19: RECIBO 3 | F19: RECIBO 4 | G19: RECIBO 5 | H19: RECIBO 6 | I19: RECIBO 7 | J19: RECIBO 8 | N19: 45683 | O19: 900000 | P19: =P16-O19 -> 2336300
A20: Enero | C20: 9158
A21: Febrero | C21: 9158
A22: Marzo | C22: 9158
A23: Abril | C23: 9158
A24: Mayo | C24: 9158
A25: Junio
A26: Julio
A27: Agosto
A28: Septiembre
A29: Octubre
A30: Noviembre
A31: Diciembre

Sheet PO36
A1: Pto.36/101 | C1: CABRERA RUBEN(MILCA)
A3: PAGOS DEL ALQUILER
B4: COSTO | C4: PAGO 1 | D4: PAGO 2 | E4: PAGO 3 | F4: PAGO 4 | G4: PAGO 5 | H4: PAGO 6 | I4: PAGO 7 | J4: PAGO 8 | K4: SALDO | L4: RECAUDADO
A5: Enero | B5: 355200 | C5: 313000 | K5: ='PO36'!$B5-('PO36'!$C5+'PO36'!$D5+'PO36'!$E5+'PO36'!$F5+'PO36'!$G5+'PO36'!$H5+'PO36'!$I5+'PO36'!$J5) -> 42200 | L5: ='PO36'!$B5-'PO36'!$K5 -> 313000 | M5: 27000
A6: Febrero | B6: 355200 | K6: ='PO36'!$B6-('PO36'!$C6+'PO36'!$D6+'PO36'!$E6+'PO36'!$F6+'PO36'!$G6+'PO36'!$H6+'PO36'!$I6+'PO36'!$J6) -> 355200 | L6: ='PO36'!$B6-'PO36'!$K6 -> 0
A7: Marzo | K7: ='PO36'!$B7-('PO36'!$C7+'PO36'!$D7+'PO36'!$E7+'PO36'!$F7+'PO36'!$G7+'PO36'!$H7+'PO36'!$I7+'PO36'!$J7) -> 0 | L7: ='PO36'!$B7-'PO36'!$K7 -> 0
A8: Abril | K8: ='PO36'!$B8-('PO36'!$C8+'PO36'!$D8+'PO36'!$E8+'PO36'!$F8+'PO36'!$G8+'PO36'!$H8+'PO36'!$I8+'PO36'!$J8) -> 0 | L8: ='PO36'!$B8-'PO36'!$K8 -> 0
A9: Mayo | K9: ='PO36'!$B9-('PO36'!$C9+'PO36'!$D9+'PO36'!$E9+'PO36'!$F9+'PO36'!$G9+'PO36'!$H9+'PO36'!$I9+'PO36'!$J9) -> 0 | L9: ='PO36'!$B9-'PO36'!$K9 -> 0
A10: Junio | K10: ='PO36'!$B10-('PO36'!$C10+'PO36'!$D10+'PO36'!$E10+'PO36'!$F10+'PO36'!$G10+'PO36'!$H10+'PO36'!$I10+'PO36'!$J10) -> 0 | L10: ='PO36'!$B10-'PO36'!$K10 -> 0
A11: Julio | K11: ='PO36'!$B11-('PO36'!$C11+'PO36'!$D11+'PO36'!$E11+'PO36'!$F11+'PO36'!$G11+'PO36'!$H11+'PO36'!$I11+'PO36'!$J11) -> 0 | L11: ='PO36'!$B11-'PO36'!$K11 -> 0
A12: Agosto | K12: ='PO36'!$B12-('PO36'!$C12+'PO36'!$D12+'PO36'!$E12+'PO36'!$F12+'PO36'!$G12+'PO36'!$H12+'PO36'!$I12+'PO36'!$J12) -> 0 | L12: ='PO36'!$B12-'PO36'!$K12 -> 0
A13: Septiembre | K13: ='PO36'!$B13-('PO36'!$C13+'PO36'!$D13+'PO36'!$E13+'PO36'!$F13+'PO36'!$G13+'PO36'!$H13+'PO36'!$I13+'PO36'!$J13) -> 0 | L13: ='PO36'!$B13-'PO36'!$K13 -> 0
A14: Octubre | K14: ='PO36'!$B14-('PO36'!$C14+'PO36'!$D14+'PO36'!$E14+'PO36'!$F14+'PO36'!$G14+'PO36'!$H14+'PO36'!$I14+'PO36'!$J14) -> 0 | L14: ='PO36'!$B14-'PO36'!$K14 -> 0
A15: Noviembre | K15: ='PO36'!$B15-('PO36'!$C15+'PO36'!$D15+'PO36'!$E15+'PO36'!$F15+'PO36'!$G15+'PO36'!$H15+'PO36'!$I15+'PO36'!$J15) -> 0 | L15: ='PO36'!$B15-'PO36'!$K15 -> 0
A16: Diciembre | K16: ='PO36'!$B16-('PO36'!$C16+'PO36'!$D16+'PO36'!$E16+'PO36'!$F16+'PO36'!$G16+'PO36'!$H16+'PO36'!$I16+'PO36'!$J16) -> 0 | L16: ='PO36'!$B16-'PO36'!$K16 -> 0
A18: NRO DE RECIBOS DE LOS PAGOS
C19: RECIBO 1 | D19: RECIBO 2 | E19: RECIBO 3 | F19: RECIBO 4 | G19: RECIBO 5 | H19: RECIBO 6 | I19: RECIBO 7 | J19: RECIBO 8
A20: Enero | C20: 9591
A21: Febrero
A22: Marzo
A23: Abril
A24: Mayo
A25: Junio
A26: Julio
A27: Agosto
A28: Septiembre
A29: Octubre
A30: Noviembre
A31: Diciembre

Sheet PO37
A1: PTO37 | C1: PENAYO LAURA MARIELA
T2: DEUDA
A3: PAGOS DEL ALQUILER | S3: ABRIL | T3: 164600
B4: COSTO | C4: PAGO 1 | D4: PAGO 2 | E4: PAGO 3 | F4: PAGO 4 | G4: PAGO 5 | H4: PAGO 6 | I4: PAGO 7 | J4: PAGO 8 | K4: SALDO | L4: RECAUDADO | S4: MAYO | T4: 177600
A5: Enero | B5: 177600 | K5: ='PO37'!$B5-('PO37'!$C5+'PO37'!$D5+'PO37'!$E5+'PO37'!$F5+'PO37'!$G5+'PO37'!$H5+'PO37'!$I5+'PO37'!$J5) -> 177600 | L5: ='PO37'!$B5-'PO37'!$K5 -> 0 | S5: JUNIO | T5: 177600
A6: Febrero | B6: 177600 | K6: ='PO37'!$B6-('PO37'!$C6+'PO37'!$D6+'PO37'!$E6+'PO37'!$F6+'PO37'!$G6+'PO37'!$H6+'PO37'!$I6+'PO37'!$J6) -> 177600 | L6: ='PO37'!$B6-'PO37'!$K6 -> 0 | S6: JULIO | T6: 177600
A7: Marzo | K7: ='PO37'!$B7-('PO37'!$C7+'PO37'!$D7+'PO37'!$E7+'PO37'!$F7+'PO37'!$G7+'PO37'!$H7+'PO37'!$I7+'PO37'!$J7) -> 0 | L7: ='PO37'!$B7-'PO37'!$K7 -> 0 | S7: AGOSTO | T7: 177600
A8: Abril | K8: ='PO37'!$B8-('PO37'!$C8+'PO37'!$D8+'PO37'!$E8+'PO37'!$F8+'PO37'!$G8+'PO37'!$H8+'PO37'!$I8+'PO37'!$J8) -> 0 | L8: ='PO37'!$B8-'PO37'!$K8 -> 0 | S8: SEPT | T8: 177600
A9: Mayo | K9: ='PO37'!$B9-('PO37'!$C9+'PO37'!$D9+'PO37'!$E9+'PO37'!$F9+'PO37'!$G9+'PO37'!$H9+'PO37'!$I9+'PO37'!$J9) -> 0 | L9: ='PO37'!$B9-'PO37'!$K9 -> 0 | S9: OCTUBRE | T9: 177600
A10: Junio | K10: ='PO37'!$B10-('PO37'!$C10+'PO37'!$D10+'PO37'!$E10+'PO37'!$F10+'PO37'!$G10+'PO37'!$H10+'PO37'!$I10+'PO37'!$J10) -> 0 | L10: ='PO37'!$B10-'PO37'!$K10 -> 0 | S10: NOV | T10: 177600
A11: Julio | K11: ='PO37'!$B11-('PO37'!$C11+'PO37'!$D11+'PO37'!$E11+'PO37'!$F11+'PO37'!$G11+'PO37'!$H11+'PO37'!$I11+'PO37'!$J11) -> 0 | L11: ='PO37'!$B11-'PO37'!$K11 -> 0 | S11: DIC | T11: 177600
A12: Agosto | K12: ='PO37'!$B12-('PO37'!$C12+'PO37'!$D12+'PO37'!$E12+'PO37'!$F12+'PO37'!$G12+'PO37'!$H12+'PO37'!$I12+'PO37'!$J12) -> 0 | L12: ='PO37'!$B12-'PO37'!$K12 -> 0 | T12: =SUM(T3:T11) -> 1585400
A13: Septiembre | K13: ='PO37'!$B13-('PO37'!$C13+'PO37'!$D13+'PO37'!$E13+'PO37'!$F13+'PO37'!$G13+'PO37'!$H13+'PO37'!$I13+'PO37'!$J13) -> 0 | L13: ='PO37'!$B13-'PO37'!$K13 -> 0
A14: Octubre | K14: ='PO37'!$B14-('PO37'!$C14+'PO37'!$D14+'PO37'!$E14+'PO37'!$F14+'PO37'!$G14+'PO37'!$H14+'PO37'!$I14+'PO37'!$J14) -> 0 | L14: ='PO37'!$B14-'PO37'!$K14 -> 0
A15: Noviembre | K15: ='PO37'!$B15-('PO37'!$C15+'PO37'!$D15+'PO37'!$E15+'PO37'!$F15+'PO37'!$G15+'PO37'!$H15+'PO37'!$I15+'PO37'!$J15) -> 0 | L15: ='PO37'!$B15-'PO37'!$K15 -> 0
A16: Diciembre | K16: ='PO37'!$B16-('PO37'!$C16+'PO37'!$D16+'PO37'!$E16+'PO37'!$F16+'PO37'!$G16+'PO37'!$H16+'PO37'!$I16+'PO37'!$J16) -> 0 | L16: ='PO37'!$B16-'PO37'!$K16 -> 0
A18: NRO DE RECIBOS DE LOS PAGOS
C19: RECIBO 1 | D19: RECIBO 2 | E19: RECIBO 3 | F19: RECIBO 4 | G19: RECIBO 5 | H19: RECIBO 6 | I19: RECIBO 7 | J19: RECIBO 8
A20: Enero
A21: Febrero
A22: Marzo
A23: Abril
A24: Mayo
A25: Junio
A26: Julio
A27: Agosto
A28: Septiembre
A29: Octubre
A30: Noviembre
A31: Diciembre

Sheet P039
A1: 34/35/38/39/51/52/82/83 | C1: BUSQUETT SANTIAGO-DELIA CAMARGO
A3: PAGOS DEL ALQUILER
B4: COSTO | C4: PAGO 1 | D4: PAGO 2 | E4: PAGO 3 | F4: PAGO 4 | G4: PAGO 5 | H4: PAGO 6 | I4: PAGO 7 | J4: PAGO 8 | K4: SALDO | L4: RECAUDADO
A5: Enero | B5: 1546270 | K5: ='P039'!$B5-('P039'!$C5+'P039'!$D5+'P039'!$E5+'P039'!$F5+'P039'!$G5+'P039'!$H5+'P039'!$I5+'P039'!$J5) -> 1546270 | L5: ='P039'!$B5-'P039'!$K5 -> 0
A6: Febrero | B6: 1546270 | K6: ='P039'!$B6-('P039'!$C6+'P039'!$D6+'P039'!$E6+'P039'!$F6+'P039'!$G6+'P039'!$H6+'P039'!$I6+'P039'!$J6) -> 1546270 | L6: ='P039'!$B6-'P039'!$K6 -> 0
A7: Marzo | B7: 1546270 | K7: ='P039'!$B7-('P039'!$C7+'P039'!$D7+'P039'!$E7+'P039'!$F7+'P039'!$G7+'P039'!$H7+'P039'!$I7+'P039'!$J7) -> 1546270 | L7: ='P039'!$B7-'P039'!$K7 -> 0
A8: Abril | B8: 1546270 | K8: ='P039'!$B8-('P039'!$C8+'P039'!$D8+'P039'!$E8+'P039'!$F8+'P039'!$G8+'P039'!$H8+'P039'!$I8+'P039'!$J8) -> 1546270 | L8: ='P039'!$B8-'P039'!$K8 -> 0
A9: Mayo | B9: 1546270 | K9: ='P039'!$B9-('P039'!$C9+'P039'!$D9+'P039'!$E9+'P039'!$F9+'P039'!$G9+'P039'!$H9+'P039'!$I9+'P039'!$J9) -> 1546270 | L9: ='P039'!$B9-'P039'!$K9 -> 0
A10: Junio | K10: ='P039'!$B10-('P039'!$C10+'P039'!$D10+'P039'!$E10+'P039'!$F10+'P039'!$G10+'P039'!$H10+'P039'!$I10+'P039'!$J10) -> 0 | L10: ='P039'!$B10-'P039'!$K10 -> 0
A11: Julio | K11: ='P039'!$B11-('P039'!$C11+'P039'!$D11+'P039'!$E11+'P039'!$F11+'P039'!$G11+'P039'!$H11+'P039'!$I11+'P039'!$J11) -> 0 | L11: ='P039'!$B11-'P039'!$K11 -> 0
A12: Agosto | K12: ='P039'!$B12-('P039'!$C12+'P039'!$D12+'P039'!$E12+'P039'!$F12+'P039'!$G12+'P039'!$H12+'P039'!$I12+'P039'!$J12) -> 0 | L12: ='P039'!$B12-'P039'!$K12 -> 0
A13: Septiembre | K13: ='P039'!$B13-('P039'!$C13+'P039'!$D13+'P039'!$E13+'P039'!$F13+'P039'!$G13+'P039'!$H13+'P039'!$I13+'P039'!$J13) -> 0 | L13: ='P039'!$B13-'P039'!$K13 -> 0
A14: Octubre | K14: ='P039'!$B14-('P039'!$C14+'P039'!$D14+'P039'!$E14+'P039'!$F14+'P039'!$G14+'P039'!$H14+'P039'!$I14+'P039'!$J14) -> 0 | L14: ='P039'!$B14-'P039'!$K14 -> 0
A15: Noviembre | K15: ='P039'!$B15-('P039'!$C15+'P039'!$D15+'P039'!$E15+'P039'!$F15+'P039'!$G15+'P039'!$H15+'P039'!$I15+'P039'!$J15) -> 0 | L15: ='P039'!$B15-'P039'!$K15 -> 0
A16: Diciembre | K16: ='P039'!$B16-('P039'!$C16+'P039'!$D16+'P039'!$E16+'P039'!$F16+'P039'!$G16+'P039'!$H16+'P039'!$I16+'P039'!$J16) -> 0 | L16: ='P039'!$B16-'P039'!$K16 -> 0
A18: NRO DE RECIBOS DE LOS PAGOS
C19: RECIBO 1 | D19: RECIBO 2 | E19: RECIBO 3 | F19: RECIBO 4 | G19: RECIBO 5 | H19: RECIBO 6 | I19: RECIBO 7 | J19: RECIBO 8
A20: Enero
A21: Febrero
A22: Marzo
A23: Abril
A24: Mayo
A25: Junio
A26: Julio
A27: Agosto
A28: Septiembre
A29: Octubre
A30: Noviembre
A31: Diciembre
N47: 285600

Sheet P038
A3: PAGOS DEL ALQUILER
B4: COSTO | C4: PAGO 1 | D4: PAGO 2 | E4: PAGO 3 | F4: PAGO 4 | G4: PAGO 5 | H4: PAGO 6 | I4: PAGO 7 | J4: PAGO 8 | K4: SALDO | L4: RECAUDADO
A5: Enero | K5: ='P038'!$B5-('P038'!$C5+'P038'!$D5+'P038'!$E5+'P038'!$F5+'P038'!$G5+'P038'!$H5+'P038'!$I5+'P038'!$J5) -> 0 | L5: ='P038'!$B5-'P038'!$K5 -> 0
A6: Febrero | K6: ='P038'!$B6-('P038'!$C6+'P038'!$D6+'P038'!$E6+'P038'!$F6+'P038'!$G6+'P038'!$H6+'P038'!$I6+'P038'!$J6) -> 0 | L6: ='P038'!$B6-'P038'!$K6 -> 0
A7: Marzo | K7: ='P038'!$B7-('P038'!$C7+'P038'!$D7+'P038'!$E7+'P038'!$F7+'P038'!$G7+'P038'!$H7+'P038'!$I7+'P038'!$J7) -> 0 | L7: ='P038'!$B7-'P038'!$K7 -> 0
A8: Abril | K8: ='P038'!$B8-('P038'!$C8+'P038'!$D8+'P038'!$E8+'P038'!$F8+'P038'!$G8+'P038'!$H8+'P038'!$I8+'P038'!$J8) -> 0 | L8: ='P038'!$B8-'P038'!$K8 -> 0
A9: Mayo | K9: ='P038'!$B9-('P038'!$C9+'P038'!$D9+'P038'!$E9+'P038'!$F9+'P038'!$G9+'P038'!$H9+'P038'!$I9+'P038'!$J9) -> 0 | L9: ='P038'!$B9-'P038'!$K9 -> 0
A10: Junio | K10: ='P038'!$B10-('P038'!$C10+'P038'!$D10+'P038'!$E10+'P038'!$F10+'P038'!$G10+'P038'!$H10+'P038'!$I10+'P038'!$J10) -> 0 | L10: ='P038'!$B10-'P038'!$K10 -> 0
A11: Julio | K11: ='P038'!$B11-('P038'!$C11+'P038'!$D11+'P038'!$E11+'P038'!$F11+'P038'!$G11+'P038'!$H11+'P038'!$I11+'P038'!$J11) -> 0 | L11: ='P038'!$B11-'P038'!$K11 -> 0
A12: Agosto | K12: ='P038'!$B12-('P038'!$C12+'P038'!$D12+'P038'!$E12+'P038'!$F12+'P038'!$G12+'P038'!$H12+'P038'!$I12+'P038'!$J12) -> 0 | L12: ='P038'!$B12-'P038'!$K12 -> 0
A13: Septiembre | K13: ='P038'!$B13-('P038'!$C13+'P038'!$D13+'P038'!$E13+'P038'!$F13+'P038'!$G13+'P038'!$H13+'P038'!$I13+'P038'!$J13) -> 0 | L13: ='P038'!$B13-'P038'!$K13 -> 0
A14: Octubre | K14: ='P038'!$B14-('P038'!$C14+'P038'!$D14+'P038'!$E14+'P038'!$F14+'P038'!$G14+'P038'!$H14+'P038'!$I14+'P038'!$J14) -> 0 | L14: ='P038'!$B14-'P038'!$K14 -> 0
A15: Noviembre | K15: ='P038'!$B15-('P038'!$C15+'P038'!$D15+'P038'!$E15+'P038'!$F15+'P038'!$G15+'P038'!$H15+'P038'!$I15+'P038'!$J15) -> 0 | L15: ='P038'!$B15-'P038'!$K15 -> 0
A16: Diciembre | K16: ='P038'!$B16-('P038'!$C16+'P038'!$D16+'P038'!$E16+'P038'!$F16+'P038'!$G16+'P038'!$H16+'P038'!$I16+'P038'!$J16) -> 0 | L16: ='P038'!$B16-'P038'!$K16 -> 0
A18: NRO DE RECIBOS DE LOS PAGOS
C19: RECIBO 1 | D19: RECIBO 2 | E19: RECIBO 3 | F19: RECIBO 4 | G19: RECIBO 5 | H19: RECIBO 6 | I19: RECIBO 7 | J19: RECIBO 8
A20: Enero
A21: Febrero
A22: Marzo
A23: Abril
A24: Mayo
A25: Junio
A26: Julio
A27: Agosto
A28: Septiembre
A29: Octubre
A30: Noviembre
A31: Diciembre

Sheet P044
A1: Pto43/44 | C1: MARGARITA
A3: PAGOS DEL ALQUILER
B4: COSTO | C4: PAGO 1 | D4: PAGO 2 | E4: PAGO 3 | F4: PAGO 4 | G4: PAGO 5 | H4: PAGO 6 | I4: PAGO 7 | J4: PAGO 8 | K4: SALDO | L4: RECAUDADO
A5: Enero | B5: 243700 | C5: 243700 | K5: ='P044'!$B5-('P044'!$C5+'P044'!$D5+'P044'!$E5+'P044'!$F5+'P044'!$G5+'P044'!$H5+'P044'!$I5+'P044'!$J5) -> 0 | L5: ='P044'!$B5-'P044'!$K5 -> 243700 | M5: BECKER
A6: Febrero | B6: 243700 | C6: 243700 | K6: ='P044'!$B6-('P044'!$C6+'P044'!$D6+'P044'!$E6+'P044'!$F6+'P044'!$G6+'P044'!$H6+'P044'!$I6+'P044'!$J6) -> 0 | L6: ='P044'!$B6-'P044'!$K6 -> 243700
A7: Marzo | B7: 269600 | C7: 100000 | D7: 270800 | L7: ='P044'!$B7-'P044'!$K7 -> 269600 | M7: 101200
A8: Abril | B8: 269600 | C8: 269600 | K8: ='P044'!$B8-('P044'!$C8+'P044'!$D8+'P044'!$E8+'P044'!$F8+'P044'!$G8+'P044'!$H8+'P044'!$I8+'P044'!$J8) -> 0 | L8: ='P044'!$B8-'P044'!$K8 -> 269600
A9: Mayo | B9: 269600 | C9: 300 | D9: 119300 | E9: 150000 | K9: ='P044'!$B9-('P044'!$C9+'P044'!$D9+'P044'!$E9+'P044'!$F9+'P044'!$G9+'P044'!$H9+'P044'!$I9+'P044'!$J9) -> 0 | L9: ='P044'!$B9-'P044'!$K9 -> 269600
A10: Junio | B10: 299000 | C10: 299000 | K10: ='P044'!$B10-('P044'!$C10+'P044'!$D10+'P044'!$E10+'P044'!$F10+'P044'!$G10+'P044'!$H10+'P044'!$I10+'P044'!$J10) -> 0 | L10: ='P044'!$B10-'P044'!$K10 -> 299000
A11: Julio | B11: 299000 | C11: 299000 | K11: ='P044'!$B11-('P044'!$C11+'P044'!$D11+'P044'!$E11+'P044'!$F11+'P044'!$G11+'P044'!$H11+'P044'!$I11+'P044'!$J11) -> 0 | L11: ='P044'!$B11-'P044'!$K11 -> 299000 | M11: 13500
A12: Agosto | B12: 299000 | C12: 32400 | D12: 266600 | K12: ='P044'!$B12-('P044'!$C12+'P044'!$D12+'P044'!$E12+'P044'!$F12+'P044'!$G12+'P044'!$H12+'P044'!$I12+'P044'!$J12) -> 0 | L12: ='P044'!$B12-'P044'!$K12 -> 299000 | M12: 13500
A13: Septiembre | K13: ='P044'!$B13-('P044'!$C13+'P044'!$D13+'P044'!$E13+'P044'!$F13+'P044'!$G13+'P044'!$H13+'P044'!$I13+'P044'!$J13) -> 0 | L13: ='P044'!$B13-'P044'!$K13 -> 0
A14: Octubre | K14: ='P044'!$B14-('P044'!$C14+'P044'!$D14+'P044'!$E14+'P044'!$F14+'P044'!$G14+'P044'!$H14+'P044'!$I14+'P044'!$J14) -> 0 | L14: ='P044'!$B14-'P044'!$K14 -> 0
A15: Noviembre | K15: ='P044'!$B15-('P044'!$C15+'P044'!$D15+'P044'!$E15+'P044'!$F15+'P044'!$G15+'P044'!$H15+'P044'!$I15+'P044'!$J15) -> 0 | L15: ='P044'!$B15-'P044'!$K15 -> 0
A16: Diciembre | K16: ='P044'!$B16-('P044'!$C16+'P044'!$D16+'P044'!$E16+'P044'!$F16+'P044'!$G16+'P044'!$H16+'P044'!$I16+'P044'!$J16) -> 0 | L16: ='P044'!$B16-'P044'!$K16 -> 0
A18: NRO DE RECIBOS DE LOS PAGOS
C19: RECIBO 1 | D19: RECIBO 2 | E19: RECIBO 3 | F19: RECIBO 4 | G19: RECIBO 5 | H19: RECIBO 6 | I19: RECIBO 7 | J19: RECIBO 8
A20: Enero | C20: 8666
A21: Febrero | C21: 8736
A22: Marzo | C22: 8877 | D22: 8880
A23: Abril | C23: 8839
A24: Mayo | C24: 8943 | D24: 9103
A25: Junio | C25: 8970
A26: Julio | C26: 9194 | K26: 9194
A27: Agosto | C27: 9292 | D27: 9302
A28: Septiembre
A29: Octubre
A30: Noviembre
A31: Diciembre

Sheet P040
A3: PAGOS DEL ALQUILER
B4: COSTO | C4: PAGO 1 | D4: PAGO 2 | E4: PAGO 3 | F4: PAGO 4 | G4: PAGO 5 | H4: PAGO 6 | I4: PAGO 7 | J4: PAGO 8 | K4: SALDO | L4: RECAUDADO
A5: Enero | K5: ='P040'!$B5-('P040'!$C5+'P040'!$D5+'P040'!$E5+'P040'!$F5+'P040'!$G5+'P040'!$H5+'P040'!$I5+'P040'!$J5) -> 0 | L5: ='P040'!$B5-'P040'!$K5 -> 0
A6: Febrero | K6: ='P040'!$B6-('P040'!$C6+'P040'!$D6+'P040'!$E6+'P040'!$F6+'P040'!$G6+'P040'!$H6+'P040'!$I6+'P040'!$J6) -> 0 | L6: ='P040'!$B6-'P040'!$K6 -> 0
A7: Marzo | K7: ='P040'!$B7-('P040'!$C7+'P040'!$D7+'P040'!$E7+'P040'!$F7+'P040'!$G7+'P040'!$H7+'P040'!$I7+'P040'!$J7) -> 0 | L7: ='P040'!$B7-'P040'!$K7 -> 0
A8: Abril | K8: ='P040'!$B8-('P040'!$C8+'P040'!$D8+'P040'!$E8+'P040'!$F8+'P040'!$G8+'P040'!$H8+'P040'!$I8+'P040'!$J8) -> 0 | L8: ='P040'!$B8-'P040'!$K8 -> 0
A9: Mayo | K9: ='P040'!$B9-('P040'!$C9+'P040'!$D9+'P040'!$E9+'P040'!$F9+'P040'!$G9+'P040'!$H9+'P040'!$I9+'P040'!$J9) -> 0 | L9: ='P040'!$B9-'P040'!$K9 -> 0
A10: Junio | K10: ='P040'!$B10-('P040'!$C10+'P040'!$D10+'P040'!$E10+'P040'!$F10+'P040'!$G10+'P040'!$H10+'P040'!$I10+'P040'!$J10) -> 0 | L10: ='P040'!$B10-'P040'!$K10 -> 0
A11: Julio | K11: ='P040'!$B11-('P040'!$C11+'P040'!$D11+'P040'!$E11+'P040'!$F11+'P040'!$G11+'P040'!$H11+'P040'!$I11+'P040'!$J11) -> 0 | L11: ='P040'!$B11-'P040'!$K11 -> 0
A12: Agosto | K12: ='P040'!$B12-('P040'!$C12+'P040'!$D12+'P040'!$E12+'P040'!$F12+'P040'!$G12+'P040'!$H12+'P040'!$I12+'P040'!$J12) -> 0 | L12: ='P040'!$B12-'P040'!$K12 -> 0
A13: Septiembre | K13: ='P040'!$B13-('P040'!$C13+'P040'!$D13+'P040'!$E13+'P040'!$F13+'P040'!$G13+'P040'!$H13+'P040'!$I13+'P040'!$J13) -> 0 | L13: ='P040'!$B13-'P040'!$K13 -> 0
A14: Octubre | K14: ='P040'!$B14-('P040'!$C14+'P040'!$D14+'P040'!$E14+'P040'!$F14+'P040'!$G14+'P040'!$H14+'P040'!$I14+'P040'!$J14) -> 0 | L14: ='P040'!$B14-'P040'!$K14 -> 0
A15: Noviembre | K15: ='P040'!$B15-('P040'!$C15+'P040'!$D15+'P040'!$E15+'P040'!$F15+'P040'!$G15+'P040'!$H15+'P040'!$I15+'P040'!$J15) -> 0 | L15: ='P040'!$B15-'P040'!$K15 -> 0
A16: Diciembre | K16: ='P040'!$B16-('P040'!$C16+'P040'!$D16+'P040'!$E16+'P040'!$F16+'P040'!$G16+'P040'!$H16+'P040'!$I16+'P040'!$J16) -> 0 | L16: ='P040'!$B16-'P040'!$K16 -> 0
A18: NRO DE RECIBOS DE LOS PAGOS
C19: RECIBO 1 | D19: RECIBO 2 | E19: RECIBO 3 | F19: RECIBO 4 | G19: RECIBO 5 | H19: RECIBO 6 | I19: RECIBO 7 | J19: RECIBO 8
A20: Enero
A21: Febrero
A22: Marzo
A23: Abril
A24: Mayo
A25: Junio
A26: Julio
A27: Agosto
A28: Septiembre
A29: Octubre
A30: Noviembre
A31: Diciembre

Sheet P041
A3: PAGOS DEL ALQUILER
B4: COSTO | C4: PAGO 1 | D4: PAGO 2 | E4: PAGO 3 | F4: PAGO 4 | G4: PAGO 5 | H4: PAGO 6 | I4: PAGO 7 | J4: PAGO 8 | K4: SALDO | L4: RECAUDADO
A5: Enero | K5: ='P041'!$B5-('P041'!$C5+'P041'!$D5+'P041'!$E5+'P041'!$F5+'P041'!$G5+'P041'!$H5+'P041'!$I5+'P041'!$J5) -> 0 | L5: ='P041'!$B5-'P041'!$K5 -> 0
A6: Febrero | K6: ='P041'!$B6-('P041'!$C6+'P041'!$D6+'P041'!$E6+'P041'!$F6+'P041'!$G6+'P041'!$H6+'P041'!$I6+'P041'!$J6) -> 0 | L6: ='P041'!$B6-'P041'!$K6 -> 0
A7: Marzo | K7: ='P041'!$B7-('P041'!$C7+'P041'!$D7+'P041'!$E7+'P041'!$F7+'P041'!$G7+'P041'!$H7+'P041'!$I7+'P041'!$J7) -> 0 | L7: ='P041'!$B7-'P041'!$K7 -> 0
A8: Abril | K8: ='P041'!$B8-('P041'!$C8+'P041'!$D8+'P041'!$E8+'P041'!$F8+'P041'!$G8+'P041'!$H8+'P041'!$I8+'P041'!$J8) -> 0 | L8: ='P041'!$B8-'P041'!$K8 -> 0
A9: Mayo | K9: ='P041'!$B9-('P041'!$C9+'P041'!$D9+'P041'!$E9+'P041'!$F9+'P041'!$G9+'P041'!$H9+'P041'!$I9+'P041'!$J9) -> 0 | L9: ='P041'!$B9-'P041'!$K9 -> 0
A10: Junio | K10: ='P041'!$B10-('P041'!$C10+'P041'!$D10+'P041'!$E10+'P041'!$F10+'P041'!$G10+'P041'!$H10+'P041'!$I10+'P041'!$J10) -> 0 | L10: ='P041'!$B10-'P041'!$K10 -> 0
A11: Julio | K11: ='P041'!$B11-('P041'!$C11+'P041'!$D11+'P041'!$E11+'P041'!$F11+'P041'!$G11+'P041'!$H11+'P041'!$I11+'P041'!$J11) -> 0 | L11: ='P041'!$B11-'P041'!$K11 -> 0
A12: Agosto | K12: ='P041'!$B12-('P041'!$C12+'P041'!$D12+'P041'!$E12+'P041'!$F12+'P041'!$G12+'P041'!$H12+'P041'!$I12+'P041'!$J12) -> 0 | L12: ='P041'!$B12-'P041'!$K12 -> 0
A13: Septiembre | K13: ='P041'!$B13-('P041'!$C13+'P041'!$D13+'P041'!$E13+'P041'!$F13+'P041'!$G13+'P041'!$H13+'P041'!$I13+'P041'!$J13) -> 0 | L13: ='P041'!$B13-'P041'!$K13 -> 0
A14: Octubre | K14: ='P041'!$B14-('P041'!$C14+'P041'!$D14+'P041'!$E14+'P041'!$F14+'P041'!$G14+'P041'!$H14+'P041'!$I14+'P041'!$J14) -> 0 | L14: ='P041'!$B14-'P041'!$K14 -> 0
A15: Noviembre | K15: ='P041'!$B15-('P041'!$C15+'P041'!$D15+'P041'!$E15+'P041'!$F15+'P041'!$G15+'P041'!$H15+'P041'!$I15+'P041'!$J15) -> 0 | L15: ='P041'!$B15-'P041'!$K15 -> 0
A16: Diciembre | K16: ='P041'!$B16-('P041'!$C16+'P041'!$D16+'P041'!$E16+'P041'!$F16+'P041'!$G16+'P041'!$H16+'P041'!$I16+'P041'!$J16) -> 0 | L16: ='P041'!$B16-'P041'!$K16 -> 0
A18: NRO DE RECIBOS DE LOS PAGOS
C19: RECIBO 1 | D19: RECIBO 2 | E19: RECIBO 3 | F19: RECIBO 4 | G19: RECIBO 5 | H19: RECIBO 6 | I19: RECIBO 7 | J19: RECIBO 8
A20: Enero
A21: Febrero
A22: Marzo
A23: Abril
A24: Mayo
A25: Junio
A26: Julio
A27: Agosto
A28: Septiembre
A29: Octubre
A30: Noviembre
A31: Diciembre

Sheet P042
A3: PAGOS DEL ALQUILER
B4: COSTO | C4: PAGO 1 | D4: PAGO 2 | E4: PAGO 3 | F4: PAGO 4 | G4: PAGO 5 | H4: PAGO 6 | I4: PAGO 7 | J4: PAGO 8 | K4: SALDO | L4: RECAUDADO
A5: Enero | K5: ='P042'!$B5-('P042'!$C5+'P042'!$D5+'P042'!$E5+'P042'!$F5+'P042'!$G5+'P042'!$H5+'P042'!$I5+'P042'!$J5) -> 0 | L5: ='P042'!$B5-'P042'!$K5 -> 0
A6: Febrero | K6: ='P042'!$B6-('P042'!$C6+'P042'!$D6+'P042'!$E6+'P042'!$F6+'P042'!$G6+'P042'!$H6+'P042'!$I6+'P042'!$J6) -> 0 | L6: ='P042'!$B6-'P042'!$K6 -> 0
A7: Marzo | K7: ='P042'!$B7-('P042'!$C7+'P042'!$D7+'P042'!$E7+'P042'!$F7+'P042'!$G7+'P042'!$H7+'P042'!$I7+'P042'!$J7) -> 0 | L7: ='P042'!$B7-'P042'!$K7 -> 0
A8: Abril | K8: ='P042'!$B8-('P042'!$C8+'P042'!$D8+'P042'!$E8+'P042'!$F8+'P042'!$G8+'P042'!$H8+'P042'!$I8+'P042'!$J8) -> 0 | L8: ='P042'!$B8-'P042'!$K8 -> 0
A9: Mayo | K9: ='P042'!$B9-('P042'!$C9+'P042'!$D9+'P042'!$E9+'P042'!$F9+'P042'!$G9+'P042'!$H9+'P042'!$I9+'P042'!$J9) -> 0 | L9: ='P042'!$B9-'P042'!$K9 -> 0
A10: Junio | K10: ='P042'!$B10-('P042'!$C10+'P042'!$D10+'P042'!$E10+'P042'!$F10+'P042'!$G10+'P042'!$H10+'P042'!$I10+'P042'!$J10) -> 0 | L10: ='P042'!$B10-'P042'!$K10 -> 0
A11: Julio | K11: ='P042'!$B11-('P042'!$C11+'P042'!$D11+'P042'!$E11+'P042'!$F11+'P042'!$G11+'P042'!$H11+'P042'!$I11+'P042'!$J11) -> 0 | L11: ='P042'!$B11-'P042'!$K11 -> 0
A12: Agosto | K12: ='P042'!$B12-('P042'!$C12+'P042'!$D12+'P042'!$E12+'P042'!$F12+'P042'!$G12+'P042'!$H12+'P042'!$I12+'P042'!$J12) -> 0 | L12: ='P042'!$B12-'P042'!$K12 -> 0
A13: Septiembre | K13: ='P042'!$B13-('P042'!$C13+'P042'!$D13+'P042'!$E13+'P042'!$F13+'P042'!$G13+'P042'!$H13+'P042'!$I13+'P042'!$J13) -> 0 | L13: ='P042'!$B13-'P042'!$K13 -> 0
A14: Octubre | K14: ='P042'!$B14-('P042'!$C14+'P042'!$D14+'P042'!$E14+'P042'!$F14+'P042'!$G14+'P042'!$H14+'P042'!$I14+'P042'!$J14) -> 0 | L14: ='P042'!$B14-'P042'!$K14 -> 0
A15: Noviembre | K15: ='P042'!$B15-('P042'!$C15+'P042'!$D15+'P042'!$E15+'P042'!$F15+'P042'!$G15+'P042'!$H15+'P042'!$I15+'P042'!$J15) -> 0 | L15: ='P042'!$B15-'P042'!$K15 -> 0
A16: Diciembre | K16: ='P042'!$B16-('P042'!$C16+'P042'!$D16+'P042'!$E16+'P042'!$F16+'P042'!$G16+'P042'!$H16+'P042'!$I16+'P042'!$J16) -> 0 | L16: ='P042'!$B16-'P042'!$K16 -> 0
A18: NRO DE RECIBOS DE LOS PAGOS
C19: RECIBO 1 | D19: RECIBO 2 | E19: RECIBO 3 | F19: RECIBO 4 | G19: RECIBO 5 | H19: RECIBO 6 | I19: RECIBO 7 | J19: RECIBO 8
A20: Enero
A21: Febrero
A22: Marzo
A23: Abril
A24: Mayo
A25: Junio
A26: Julio
A27: Agosto
A28: Septiembre
A29: Octubre
A30: Noviembre
A31: Diciembre

Sheet P043
A3: PAGOS DEL ALQUILER
B4: COSTO | C4: PAGO 1 | D4: PAGO 2 | E4: PAGO 3 | F4: PAGO 4 | G4: PAGO 5 | H4: PAGO 6 | I4: PAGO 7 | J4: PAGO 8 | K4: SALDO | L4: RECAUDADO
A5: Enero | K5: ='P043'!$B5-('P043'!$C5+'P043'!$D5+'P043'!$E5+'P043'!$F5+'P043'!$G5+'P043'!$H5+'P043'!$I5+'P043'!$J5) -> 0 | L5: ='P043'!$B5-'P043'!$K5 -> 0
A6: Febrero | K6: ='P043'!$B6-('P043'!$C6+'P043'!$D6+'P043'!$E6+'P043'!$F6+'P043'!$G6+'P043'!$H6+'P043'!$I6+'P043'!$J6) -> 0 | L6: ='P043'!$B6-'P043'!$K6 -> 0
A7: Marzo | K7: ='P043'!$B7-('P043'!$C7+'P043'!$D7+'P043'!$E7+'P043'!$F7+'P043'!$G7+'P043'!$H7+'P043'!$I7+'P043'!$J7) -> 0 | L7: ='P043'!$B7-'P043'!$K7 -> 0
A8: Abril | K8: ='P043'!$B8-('P043'!$C8+'P043'!$D8+'P043'!$E8+'P043'!$F8+'P043'!$G8+'P043'!$H8+'P043'!$I8+'P043'!$J8) -> 0 | L8: ='P043'!$B8-'P043'!$K8 -> 0
A9: Mayo | K9: ='P043'!$B9-('P043'!$C9+'P043'!$D9+'P043'!$E9+'P043'!$F9+'P043'!$G9+'P043'!$H9+'P043'!$I9+'P043'!$J9) -> 0 | L9: ='P043'!$B9-'P043'!$K9 -> 0
A10: Junio | K10: ='P043'!$B10-('P043'!$C10+'P043'!$D10+'P043'!$E10+'P043'!$F10+'P043'!$G10+'P043'!$H10+'P043'!$I10+'P043'!$J10) -> 0 | L10: ='P043'!$B10-'P043'!$K10 -> 0
A11: Julio | K11: ='P043'!$B11-('P043'!$C11+'P043'!$D11+'P043'!$E11+'P043'!$F11+'P043'!$G11+'P043'!$H11+'P043'!$I11+'P043'!$J11) -> 0 | L11: ='P043'!$B11-'P043'!$K11 -> 0
A12: Agosto | K12: ='P043'!$B12-('P043'!$C12+'P043'!$D12+'P043'!$E12+'P043'!$F12+'P043'!$G12+'P043'!$H12+'P043'!$I12+'P043'!$J12) -> 0 | L12: ='P043'!$B12-'P043'!$K12 -> 0
A13: Septiembre | K13: ='P043'!$B13-('P043'!$C13+'P043'!$D13+'P043'!$E13+'P043'!$F13+'P043'!$G13+'P043'!$H13+'P043'!$I13+'P043'!$J13) -> 0 | L13: ='P043'!$B13-'P043'!$K13 -> 0
A14: Octubre | K14: ='P043'!$B14-('P043'!$C14+'P043'!$D14+'P043'!$E14+'P043'!$F14+'P043'!$G14+'P043'!$H14+'P043'!$I14+'P043'!$J14) -> 0 | L14: ='P043'!$B14-'P043'!$K14 -> 0
A15: Noviembre | K15: ='P043'!$B15-('P043'!$C15+'P043'!$D15+'P043'!$E15+'P043'!$F15+'P043'!$G15+'P043'!$H15+'P043'!$I15+'P043'!$J15) -> 0 | L15: ='P043'!$B15-'P043'!$K15 -> 0
A16: Diciembre | K16: ='P043'!$B16-('P043'!$C16+'P043'!$D16+'P043'!$E16+'P043'!$F16+'P043'!$G16+'P043'!$H16+'P043'!$I16+'P043'!$J16) -> 0 | L16: ='P043'!$B16-'P043'!$K16 -> 0
A18: NRO DE RECIBOS DE LOS PAGOS
C19: RECIBO 1 | D19: RECIBO 2 | E19: RECIBO 3 | F19: RECIBO 4 | G19: RECIBO 5 | H19: RECIBO 6 | I19: RECIBO 7 | J19: RECIBO 8
A20: Enero
A21: Febrero
A22: Marzo
A23: Abril
A24: Mayo
A25: Junio
A26: Julio
A27: Agosto
A28: Septiembre
A29: Octubre
A30: Noviembre
A31: Diciembre

Sheet P045
A3: PAGOS DEL ALQUILER
B4: COSTO | C4: PAGO 1 | D4: PAGO 2 | E4: PAGO 3 | F4: PAGO 4 | G4: PAGO 5 | H4: PAGO 6 | I4: PAGO 7 | J4: PAGO 8 | K4: SALDO | L4: RECAUDADO
A5: Enero | K5: ='P045'!$B5-('P045'!$C5+'P045'!$D5+'P045'!$E5+'P045'!$F5+'P045'!$G5+'P045'!$H5+'P045'!$I5+'P045'!$J5) -> 0 | L5: ='P045'!$B5-'P045'!$K5 -> 0
A6: Febrero | K6: ='P045'!$B6-('P045'!$C6+'P045'!$D6+'P045'!$E6+'P045'!$F6+'P045'!$G6+'P045'!$H6+'P045'!$I6+'P045'!$J6) -> 0 | L6: ='P045'!$B6-'P045'!$K6 -> 0
A7: Marzo | K7: ='P045'!$B7-('P045'!$C7+'P045'!$D7+'P045'!$E7+'P045'!$F7+'P045'!$G7+'P045'!$H7+'P045'!$I7+'P045'!$J7) -> 0 | L7: ='P045'!$B7-'P045'!$K7 -> 0
A8: Abril | K8: ='P045'!$B8-('P045'!$C8+'P045'!$D8+'P045'!$E8+'P045'!$F8+'P045'!$G8+'P045'!$H8+'P045'!$I8+'P045'!$J8) -> 0 | L8: ='P045'!$B8-'P045'!$K8 -> 0
A9: Mayo | K9: ='P045'!$B9-('P045'!$C9+'P045'!$D9+'P045'!$E9+'P045'!$F9+'P045'!$G9+'P045'!$H9+'P045'!$I9+'P045'!$J9) -> 0 | L9: ='P045'!$B9-'P045'!$K9 -> 0
A10: Junio | K10: ='P045'!$B10-('P045'!$C10+'P045'!$D10+'P045'!$E10+'P045'!$F10+'P045'!$G10+'P045'!$H10+'P045'!$I10+'P045'!$J10) -> 0 | L10: ='P045'!$B10-'P045'!$K10 -> 0
A11: Julio | K11: ='P045'!$B11-('P045'!$C11+'P045'!$D11+'P045'!$E11+'P045'!$F11+'P045'!$G11+'P045'!$H11+'P045'!$I11+'P045'!$J11) -> 0 | L11: ='P045'!$B11-'P045'!$K11 -> 0
A12: Agosto | K12: ='P045'!$B12-('P045'!$C12+'P045'!$D12+'P045'!$E12+'P045'!$F12+'P045'!$G12+'P045'!$H12+'P045'!$I12+'P045'!$J12) -> 0 | L12: ='P045'!$B12-'P045'!$K12 -> 0
A13: Septiembre | K13: ='P045'!$B13-('P045'!$C13+'P045'!$D13+'P045'!$E13+'P045'!$F13+'P045'!$G13+'P045'!$H13+'P045'!$I13+'P045'!$J13) -> 0 | L13: ='P045'!$B13-'P045'!$K13 -> 0
A14: Octubre | K14: ='P045'!$B14-('P045'!$C14+'P045'!$D14+'P045'!$E14+'P045'!$F14+'P045'!$G14+'P045'!$H14+'P045'!$I14+'P045'!$J14) -> 0 | L14: ='P045'!$B14-'P045'!$K14 -> 0
A15: Noviembre | K15: ='P045'!$B15-('P045'!$C15+'P045'!$D15+'P045'!$E15+'P045'!$F15+'P045'!$G15+'P045'!$H15+'P045'!$I15+'P045'!$J15) -> 0 | L15: ='P045'!$B15-'P045'!$K15 -> 0
A16: Diciembre | K16: ='P045'!$B16-('P045'!$C16+'P045'!$D16+'P045'!$E16+'P045'!$F16+'P045'!$G16+'P045'!$H16+'P045'!$I16+'P045'!$J16) -> 0 | L16: ='P045'!$B16-'P045'!$K16 -> 0
A18: NRO DE RECIBOS DE LOS PAGOS
C19: RECIBO 1 | D19: RECIBO 2 | E19: RECIBO 3 | F19: RECIBO 4 | G19: RECIBO 5 | H19: RECIBO 6 | I19: RECIBO 7 | J19: RECIBO 8
A20: Enero
A21: Febrero
A22: Marzo
A23: Abril
A24: Mayo
A25: Junio
A26: Julio
A27: Agosto
A28: Septiembre
A29: Octubre
A30: Noviembre
A31: Diciembre

Sheet P046
A1: k.Pto.46/47/49 | C1: RUIZ FERNANDO
A3: PAGOS DEL ALQUILER
B4: COSTO | C4: PAGO 1 | D4: PAGO 2 | E4: PAGO 3 | F4: PAGO 4 | G4: PAGO 5 | H4: PAGO 6 | I4: PAGO 7 | J4: PAGO 8 | K4: SALDO | L4: RECAUDADO | M4: Columna1
A5: Enero | B5: 535900 | C5: 434500 | D5: 101400 | K5: ='P046'!$B5-('P046'!$C5+'P046'!$D5+'P046'!$E5+'P046'!$F5+'P046'!$G5+'P046'!$H5+'P046'!$I5+'P046'!$J5) -> 0 | L5: ='P046'!$B5-'P046'!$K5 -> 535900 | M5: 13500
A6: Febrero | B6: 535900 | C6: 236500 | D6: 150000 | K6: ='P046'!$B6-('P046'!$C6+'P046'!$D6+'P046'!$E6+'P046'!$F6+'P046'!$G6+'P046'!$H6+'P046'!$I6+'P046'!$J6) -> 149400 | L6: ='P046'!$B6-'P046'!$K6 -> 386500 | M6: 13500
A7: Marzo | K7: ='P046'!$B7-('P046'!$C7+'P046'!$D7+'P046'!$E7+'P046'!$F7+'P046'!$G7+'P046'!$H7+'P046'!$I7+'P046'!$J7) -> 0 | L7: ='P046'!$B7-'P046'!$K7 -> 0
A8: Abril | K8: ='P046'!$B8-('P046'!$C8+'P046'!$D8+'P046'!$E8+'P046'!$F8+'P046'!$G8+'P046'!$H8+'P046'!$I8+'P046'!$J8) -> 0 | L8: ='P046'!$B8-'P046'!$K8 -> 0
A9: Mayo | K9: ='P046'!$B9-('P046'!$C9+'P046'!$D9+'P046'!$E9+'P046'!$F9+'P046'!$G9+'P046'!$H9+'P046'!$I9+'P046'!$J9) -> 0 | L9: ='P046'!$B9-'P046'!$K9 -> 0
A10: Junio | K10: ='P046'!$B10-('P046'!$C10+'P046'!$D10+'P046'!$E10+'P046'!$F10+'P046'!$G10+'P046'!$H10+'P046'!$I10+'P046'!$J10) -> 0 | L10: ='P046'!$B10-'P046'!$K10 -> 0
A11: Julio | K11: ='P046'!$B11-('P046'!$C11+'P046'!$D11+'P046'!$E11+'P046'!$F11+'P046'!$G11+'P046'!$H11+'P046'!$I11+'P046'!$J11) -> 0 | L11: ='P046'!$B11-'P046'!$K11 -> 0
A12: Agosto | K12: ='P046'!$B12-('P046'!$C12+'P046'!$D12+'P046'!$E12+'P046'!$F12+'P046'!$G12+'P046'!$H12+'P046'!$I12+'P046'!$J12) -> 0 | L12: ='P046'!$B12-'P046'!$K12 -> 0
A13: Septiembre | K13: ='P046'!$B13-('P046'!$C13+'P046'!$D13+'P046'!$E13+'P046'!$F13+'P046'!$G13+'P046'!$H13+'P046'!$I13+'P046'!$J13) -> 0 | L13: ='P046'!$B13-'P046'!$K13 -> 0
A14: Octubre | K14: ='P046'!$B14-('P046'!$C14+'P046'!$D14+'P046'!$E14+'P046'!$F14+'P046'!$G14+'P046'!$H14+'P046'!$I14+'P046'!$J14) -> 0 | L14: ='P046'!$B14-'P046'!$K14 -> 0
A15: Noviembre | K15: ='P046'!$B15-('P046'!$C15+'P046'!$D15+'P046'!$E15+'P046'!$F15+'P046'!$G15+'P046'!$H15+'P046'!$I15+'P046'!$J15) -> 0 | L15: ='P046'!$B15-'P046'!$K15 -> 0
A16: Diciembre | K16: ='P046'!$B16-('P046'!$C16+'P046'!$D16+'P046'!$E16+'P046'!$F16+'P046'!$G16+'P046'!$H16+'P046'!$I16+'P046'!$J16) -> 0 | L16: ='P046'!$B16-'P046'!$K16 -> 0
A18: NRO DE RECIBOS DE LOS PAGOS
C19: RECIBO 1 | D19: RECIBO 2 | E19: RECIBO 3 | F19: RECIBO 4 | G19: RECIBO 5 | H19: RECIBO 6 | I19: RECIBO 7 | J19: RECIBO 8
A20: Enero | D20: 9688
A21: Febrero | C21: 9713 | D21: 9748
A22: Marzo
A23: Abril
A24: Mayo
A25: Junio
A26: Julio
A27: Agosto
A28: Septiembre
A29: Octubre
A30: Noviembre
A31: Diciembre

Sheet P047

Sheet P048
A1: Pto.45/48 | C1: PANIAGUA CRISTIA
A3: PAGOS DEL ALQUILER
B4: COSTO | C4: PAGO 1 | D4: PAGO 2 | E4: PAGO 3 | F4: PAGO 4 | G4: PAGO 5 | H4: PAGO 6 | I4: PAGO 7 | J4: PAGO 8 | K4: SALDO | L4: RECAUDADO | M4: Columna1
A5: Enero | B5: 386500 | K5: ='P048'!$B5-('P048'!$C5+'P048'!$D5+'P048'!$E5+'P048'!$F5+'P048'!$G5+'P048'!$H5+'P048'!$I5+'P048'!$J5) -> 386500 | L5: ='P048'!$B5-'P048'!$K5 -> 0
A6: Febrero | B6: 386500 | K6: ='P048'!$B6-('P048'!$C6+'P048'!$D6+'P048'!$E6+'P048'!$F6+'P048'!$G6+'P048'!$H6+'P048'!$I6+'P048'!$J6) -> 386500 | L6: ='P048'!$B6-'P048'!$K6 -> 0
A7: Marzo | B7: 386500 | K7: ='P048'!$B7-('P048'!$C7+'P048'!$D7+'P048'!$E7+'P048'!$F7+'P048'!$G7+'P048'!$H7+'P048'!$I7+'P048'!$J7) -> 386500 | L7: ='P048'!$B7-'P048'!$K7 -> 0
A8: Abril | K8: ='P048'!$B8-('P048'!$C8+'P048'!$D8+'P048'!$E8+'P048'!$F8+'P048'!$G8+'P048'!$H8+'P048'!$I8+'P048'!$J8) -> 0 | L8: ='P048'!$B8-'P048'!$K8 -> 0
A9: Mayo | K9: ='P048'!$B9-('P048'!$C9+'P048'!$D9+'P048'!$E9+'P048'!$F9+'P048'!$G9+'P048'!$H9+'P048'!$I9+'P048'!$J9) -> 0 | L9: ='P048'!$B9-'P048'!$K9 -> 0
A10: Junio | K10: ='P048'!$B10-('P048'!$C10+'P048'!$D10+'P048'!$E10+'P048'!$F10+'P048'!$G10+'P048'!$H10+'P048'!$I10+'P048'!$J10) -> 0 | L10: ='P048'!$B10-'P048'!$K10 -> 0
A11: Julio | K11: ='P048'!$B11-('P048'!$C11+'P048'!$D11+'P048'!$E11+'P048'!$F11+'P048'!$G11+'P048'!$H11+'P048'!$I11+'P048'!$J11) -> 0 | L11: ='P048'!$B11-'P048'!$K11 -> 0
A12: Agosto | K12: ='P048'!$B12-('P048'!$C12+'P048'!$D12+'P048'!$E12+'P048'!$F12+'P048'!$G12+'P048'!$H12+'P048'!$I12+'P048'!$J12) -> 0 | L12: ='P048'!$B12-'P048'!$K12 -> 0
A13: Septiembre | K13: ='P048'!$B13-('P048'!$C13+'P048'!$D13+'P048'!$E13+'P048'!$F13+'P048'!$G13+'P048'!$H13+'P048'!$I13+'P048'!$J13) -> 0 | L13: ='P048'!$B13-'P048'!$K13 -> 0
A14: Octubre | K14: ='P048'!$B14-('P048'!$C14+'P048'!$D14+'P048'!$E14+'P048'!$F14+'P048'!$G14+'P048'!$H14+'P048'!$I14+'P048'!$J14) -> 0 | L14: ='P048'!$B14-'P048'!$K14 -> 0
A15: Noviembre | K15: ='P048'!$B15-('P048'!$C15+'P048'!$D15+'P048'!$E15+'P048'!$F15+'P048'!$G15+'P048'!$H15+'P048'!$I15+'P048'!$J15) -> 0 | L15: ='P048'!$B15-'P048'!$K15 -> 0
A16: Diciembre | K16: ='P048'!$B16-('P048'!$C16+'P048'!$D16+'P048'!$E16+'P048'!$F16+'P048'!$G16+'P048'!$H16+'P048'!$I16+'P048'!$J16) -> 0 | L16: ='P048'!$B16-'P048'!$K16 -> 0
A18: NRO DE RECIBOS DE LOS PAGOS
C19: RECIBO 1 | D19: RECIBO 2 | E19: RECIBO 3 | F19: RECIBO 4 | G19: RECIBO 5 | H19: RECIBO 6 | I19: RECIBO 7 | J19: RECIBO 8
A20: Enero
A21: Febrero
A22: Marzo
A23: Abril
A24: Mayo
A25: Junio
A26: Julio
A27: Agosto
A28: Septiembre
A29: Octubre
A30: Noviembre
A31: Diciembre
O44: 31600
O62: 7428

Sheet P049
A3: PAGOS DEL ALQUILER
B4: COSTO | C4: PAGO 1 | D4: PAGO 2 | E4: PAGO 3 | F4: PAGO 4 | G4: PAGO 5 | H4: PAGO 6 | I4: PAGO 7 | J4: PAGO 8 | K4: SALDO | L4: RECAUDADO
A5: Enero | K5: ='P049'!$B5-('P049'!$C5+'P049'!$D5+'P049'!$E5+'P049'!$F5+'P049'!$G5+'P049'!$H5+'P049'!$I5+'P049'!$J5) -> 0 | L5: ='P049'!$B5-'P049'!$K5 -> 0
A6: Febrero | K6: ='P049'!$B6-('P049'!$C6+'P049'!$D6+'P049'!$E6+'P049'!$F6+'P049'!$G6+'P049'!$H6+'P049'!$I6+'P049'!$J6) -> 0 | L6: ='P049'!$B6-'P049'!$K6 -> 0
A7: Marzo | K7: ='P049'!$B7-('P049'!$C7+'P049'!$D7+'P049'!$E7+'P049'!$F7+'P049'!$G7+'P049'!$H7+'P049'!$I7+'P049'!$J7) -> 0 | L7: ='P049'!$B7-'P049'!$K7 -> 0
A8: Abril | K8: ='P049'!$B8-('P049'!$C8+'P049'!$D8+'P049'!$E8+'P049'!$F8+'P049'!$G8+'P049'!$H8+'P049'!$I8+'P049'!$J8) -> 0 | L8: ='P049'!$B8-'P049'!$K8 -> 0
A9: Mayo | K9: ='P049'!$B9-('P049'!$C9+'P049'!$D9+'P049'!$E9+'P049'!$F9+'P049'!$G9+'P049'!$H9+'P049'!$I9+'P049'!$J9) -> 0 | L9: ='P049'!$B9-'P049'!$K9 -> 0
A10: Junio | K10: ='P049'!$B10-('P049'!$C10+'P049'!$D10+'P049'!$E10+'P049'!$F10+'P049'!$G10+'P049'!$H10+'P049'!$I10+'P049'!$J10) -> 0 | L10: ='P049'!$B10-'P049'!$K10 -> 0
A11: Julio | K11: ='P049'!$B11-('P049'!$C11+'P049'!$D11+'P049'!$E11+'P049'!$F11+'P049'!$G11+'P049'!$H11+'P049'!$I11+'P049'!$J11) -> 0 | L11: ='P049'!$B11-'P049'!$K11 -> 0
A12: Agosto | K12: ='P049'!$B12-('P049'!$C12+'P049'!$D12+'P049'!$E12+'P049'!$F12+'P049'!$G12+'P049'!$H12+'P049'!$I12+'P049'!$J12) -> 0 | L12: ='P049'!$B12-'P049'!$K12 -> 0
A13: Septiembre | K13: ='P049'!$B13-('P049'!$C13+'P049'!$D13+'P049'!$E13+'P049'!$F13+'P049'!$G13+'P049'!$H13+'P049'!$I13+'P049'!$J13) -> 0 | L13: ='P049'!$B13-'P049'!$K13 -> 0
A14: Octubre | K14: ='P049'!$B14-('P049'!$C14+'P049'!$D14+'P049'!$E14+'P049'!$F14+'P049'!$G14+'P049'!$H14+'P049'!$I14+'P049'!$J14) -> 0 | L14: ='P049'!$B14-'P049'!$K14 -> 0
A15: Noviembre | K15: ='P049'!$B15-('P049'!$C15+'P049'!$D15+'P049'!$E15+'P049'!$F15+'P049'!$G15+'P049'!$H15+'P049'!$I15+'P049'!$J15) -> 0 | L15: ='P049'!$B15-'P049'!$K15 -> 0
A16: Diciembre | K16: ='P049'!$B16-('P049'!$C16+'P049'!$D16+'P049'!$E16+'P049'!$F16+'P049'!$G16+'P049'!$H16+'P049'!$I16+'P049'!$J16) -> 0 | L16: ='P049'!$B16-'P049'!$K16 -> 0
A18: NRO DE RECIBOS DE LOS PAGOS
C19: RECIBO 1 | D19: RECIBO 2 | E19: RECIBO 3 | F19: RECIBO 4 | G19: RECIBO 5 | H19: RECIBO 6 | I19: RECIBO 7 | J19: RECIBO 8
A20: Enero
A21: Febrero
A22: Marzo
A23: Abril
A24: Mayo
A25: Junio
A26: Julio
A27: Agosto
A28: Septiembre
A29: Octubre
A30: Noviembre
A31: Diciembre

Sheet P050
A3: PAGOS DEL ALQUILER
B4: COSTO | C4: PAGO 1 | D4: PAGO 2 | E4: PAGO 3 | F4: PAGO 4 | G4: PAGO 5 | H4: PAGO 6 | I4: PAGO 7 | J4: PAGO 8 | K4: SALDO | L4: RECAUDADO
A5: Enero | K5: ='P050'!$B5-('P050'!$C5+'P050'!$D5+'P050'!$E5+'P050'!$F5+'P050'!$G5+'P050'!$H5+'P050'!$I5+'P050'!$J5) -> 0 | L5: ='P050'!$B5-'P050'!$K5 -> 0
A6: Febrero | K6: ='P050'!$B6-('P050'!$C6+'P050'!$D6+'P050'!$E6+'P050'!$F6+'P050'!$G6+'P050'!$H6+'P050'!$I6+'P050'!$J6) -> 0 | L6: ='P050'!$B6-'P050'!$K6 -> 0
A7: Marzo | K7: ='P050'!$B7-('P050'!$C7+'P050'!$D7+'P050'!$E7+'P050'!$F7+'P050'!$G7+'P050'!$H7+'P050'!$I7+'P050'!$J7) -> 0 | L7: ='P050'!$B7-'P050'!$K7 -> 0
A8: Abril | K8: ='P050'!$B8-('P050'!$C8+'P050'!$D8+'P050'!$E8+'P050'!$F8+'P050'!$G8+'P050'!$H8+'P050'!$I8+'P050'!$J8) -> 0 | L8: ='P050'!$B8-'P050'!$K8 -> 0
A9: Mayo | K9: ='P050'!$B9-('P050'!$C9+'P050'!$D9+'P050'!$E9+'P050'!$F9+'P050'!$G9+'P050'!$H9+'P050'!$I9+'P050'!$J9) -> 0 | L9: ='P050'!$B9-'P050'!$K9 -> 0
A10: Junio | K10: ='P050'!$B10-('P050'!$C10+'P050'!$D10+'P050'!$E10+'P050'!$F10+'P050'!$G10+'P050'!$H10+'P050'!$I10+'P050'!$J10) -> 0 | L10: ='P050'!$B10-'P050'!$K10 -> 0
A11: Julio | K11: ='P050'!$B11-('P050'!$C11+'P050'!$D11+'P050'!$E11+'P050'!$F11+'P050'!$G11+'P050'!$H11+'P050'!$I11+'P050'!$J11) -> 0 | L11: ='P050'!$B11-'P050'!$K11 -> 0
A12: Agosto | K12: ='P050'!$B12-('P050'!$C12+'P050'!$D12+'P050'!$E12+'P050'!$F12+'P050'!$G12+'P050'!$H12+'P050'!$I12+'P050'!$J12) -> 0 | L12: ='P050'!$B12-'P050'!$K12 -> 0
A13: Septiembre | K13: ='P050'!$B13-('P050'!$C13+'P050'!$D13+'P050'!$E13+'P050'!$F13+'P050'!$G13+'P050'!$H13+'P050'!$I13+'P050'!$J13) -> 0 | L13: ='P050'!$B13-'P050'!$K13 -> 0
A14: Octubre | K14: ='P050'!$B14-('P050'!$C14+'P050'!$D14+'P050'!$E14+'P050'!$F14+'P050'!$G14+'P050'!$H14+'P050'!$I14+'P050'!$J14) -> 0 | L14: ='P050'!$B14-'P050'!$K14 -> 0
A15: Noviembre | K15: ='P050'!$B15-('P050'!$C15+'P050'!$D15+'P050'!$E15+'P050'!$F15+'P050'!$G15+'P050'!$H15+'P050'!$I15+'P050'!$J15) -> 0 | L15: ='P050'!$B15-'P050'!$K15 -> 0
A16: Diciembre | K16: ='P050'!$B16-('P050'!$C16+'P050'!$D16+'P050'!$E16+'P050'!$F16+'P050'!$G16+'P050'!$H16+'P050'!$I16+'P050'!$J16) -> 0 | L16: ='P050'!$B16-'P050'!$K16 -> 0
A18: NRO DE RECIBOS DE LOS PAGOS
C19: RECIBO 1 | D19: RECIBO 2 | E19: RECIBO 3 | F19: RECIBO 4 | G19: RECIBO 5 | H19: RECIBO 6 | I19: RECIBO 7 | J19: RECIBO 8
A20: Enero
A21: Febrero
A22: Marzo
A23: Abril
A24: Mayo
A25: Junio
A26: Julio
A27: Agosto
A28: Septiembre
A29: Octubre
A30: Noviembre
A31: Diciembre

Sheet P051
A3: PAGOS DEL ALQUILER
B4: COSTO | C4: PAGO 1 | D4: PAGO 2 | E4: PAGO 3 | F4: PAGO 4 | G4: PAGO 5 | H4: PAGO 6 | I4: PAGO 7 | J4: PAGO 8 | K4: SALDO | L4: RECAUDADO
A5: Enero | K5: ='P051'!$B5-('P051'!$C5+'P051'!$D5+'P051'!$E5+'P051'!$F5+'P051'!$G5+'P051'!$H5+'P051'!$I5+'P051'!$J5) -> 0 | L5: ='P051'!$B5-'P051'!$K5 -> 0
A6: Febrero | K6: ='P051'!$B6-('P051'!$C6+'P051'!$D6+'P051'!$E6+'P051'!$F6+'P051'!$G6+'P051'!$H6+'P051'!$I6+'P051'!$J6) -> 0 | L6: ='P051'!$B6-'P051'!$K6 -> 0
A7: Marzo | K7: ='P051'!$B7-('P051'!$C7+'P051'!$D7+'P051'!$E7+'P051'!$F7+'P051'!$G7+'P051'!$H7+'P051'!$I7+'P051'!$J7) -> 0 | L7: ='P051'!$B7-'P051'!$K7 -> 0
A8: Abril | K8: ='P051'!$B8-('P051'!$C8+'P051'!$D8+'P051'!$E8+'P051'!$F8+'P051'!$G8+'P051'!$H8+'P051'!$I8+'P051'!$J8) -> 0 | L8: ='P051'!$B8-'P051'!$K8 -> 0
A9: Mayo | K9: ='P051'!$B9-('P051'!$C9+'P051'!$D9+'P051'!$E9+'P051'!$F9+'P051'!$G9+'P051'!$H9+'P051'!$I9+'P051'!$J9) -> 0 | L9: ='P051'!$B9-'P051'!$K9 -> 0
A10: Junio | K10: ='P051'!$B10-('P051'!$C10+'P051'!$D10+'P051'!$E10+'P051'!$F10+'P051'!$G10+'P051'!$H10+'P051'!$I10+'P051'!$J10) -> 0 | L10: ='P051'!$B10-'P051'!$K10 -> 0
A11: Julio | K11: ='P051'!$B11-('P051'!$C11+'P051'!$D11+'P051'!$E11+'P051'!$F11+'P051'!$G11+'P051'!$H11+'P051'!$I11+'P051'!$J11) -> 0 | L11: ='P051'!$B11-'P051'!$K11 -> 0
A12: Agosto | K12: ='P051'!$B12-('P051'!$C12+'P051'!$D12+'P051'!$E12+'P051'!$F12+'P051'!$G12+'P051'!$H12+'P051'!$I12+'P051'!$J12) -> 0 | L12: ='P051'!$B12-'P051'!$K12 -> 0
A13: Septiembre | K13: ='P051'!$B13-('P051'!$C13+'P051'!$D13+'P051'!$E13+'P051'!$F13+'P051'!$G13+'P051'!$H13+'P051'!$I13+'P051'!$J13) -> 0 | L13: ='P051'!$B13-'P051'!$K13 -> 0
A14: Octubre | K14: ='P051'!$B14-('P051'!$C14+'P051'!$D14+'P051'!$E14+'P051'!$F14+'P051'!$G14+'P051'!$H14+'P051'!$I14+'P051'!$J14) -> 0 | L14: ='P051'!$B14-'P051'!$K14 -> 0
A15: Noviembre | K15: ='P051'!$B15-('P051'!$C15+'P051'!$D15+'P051'!$E15+'P051'!$F15+'P051'!$G15+'P051'!$H15+'P051'!$I15+'P051'!$J15) -> 0 | L15: ='P051'!$B15-'P051'!$K15 -> 0
A16: Diciembre | K16: ='P051'!$B16-('P051'!$C16+'P051'!$D16+'P051'!$E16+'P051'!$F16+'P051'!$G16+'P051'!$H16+'P051'!$I16+'P051'!$J16) -> 0 | L16: ='P051'!$B16-'P051'!$K16 -> 0
A18: NRO DE RECIBOS DE LOS PAGOS
C19: RECIBO 1 | D19: RECIBO 2 | E19: RECIBO 3 | F19: RECIBO 4 | G19: RECIBO 5 | H19: RECIBO 6 | I19: RECIBO 7 | J19: RECIBO 8
A20: Enero
A21: Febrero
A22: Marzo
A23: Abril
A24: Mayo
A25: Junio
A26: Julio
A27: Agosto
A28: Septiembre
A29: Octubre
A30: Noviembre
A31: Diciembre

Sheet P052
A3: PAGOS DEL ALQUILER
B4: COSTO | C4: PAGO 1 | D4: PAGO 2 | E4: PAGO 3 | F4: PAGO 4 | G4: PAGO 5 | H4: PAGO 6 | I4: PAGO 7 | J4: PAGO 8 | K4: SALDO | L4: RECAUDADO
A5: Enero | K5: ='P052'!$B5-('P052'!$C5+'P052'!$D5+'P052'!$E5+'P052'!$F5+'P052'!$G5+'P052'!$H5+'P052'!$I5+'P052'!$J5) -> 0 | L5: ='P052'!$B5-'P052'!$K5 -> 0
A6: Febrero | K6: ='P052'!$B6-('P052'!$C6+'P052'!$D6+'P052'!$E6+'P052'!$F6+'P052'!$G6+'P052'!$H6+'P052'!$I6+'P052'!$J6) -> 0 | L6: ='P052'!$B6-'P052'!$K6 -> 0
A7: Marzo | K7: ='P052'!$B7-('P052'!$C7+'P052'!$D7+'P052'!$E7+'P052'!$F7+'P052'!$G7+'P052'!$H7+'P052'!$I7+'P052'!$J7) -> 0 | L7: ='P052'!$B7-'P052'!$K7 -> 0
A8: Abril | K8: ='P052'!$B8-('P052'!$C8+'P052'!$D8+'P052'!$E8+'P052'!$F8+'P052'!$G8+'P052'!$H8+'P052'!$I8+'P052'!$J8) -> 0 | L8: ='P052'!$B8-'P052'!$K8 -> 0
A9: Mayo | K9: ='P052'!$B9-('P052'!$C9+'P052'!$D9+'P052'!$E9+'P052'!$F9+'P052'!$G9+'P052'!$H9+'P052'!$I9+'P052'!$J9) -> 0 | L9: ='P052'!$B9-'P052'!$K9 -> 0
A10: Junio | K10: ='P052'!$B10-('P052'!$C10+'P052'!$D10+'P052'!$E10+'P052'!$F10+'P052'!$G10+'P052'!$H10+'P052'!$I10+'P052'!$J10) -> 0 | L10: ='P052'!$B10-'P052'!$K10 -> 0
A11: Julio | K11: ='P052'!$B11-('P052'!$C11+'P052'!$D11+'P052'!$E11+'P052'!$F11+'P052'!$G11+'P052'!$H11+'P052'!$I11+'P052'!$J11) -> 0 | L11: ='P052'!$B11-'P052'!$K11 -> 0
A12: Agosto | K12: ='P052'!$B12-('P052'!$C12+'P052'!$D12+'P052'!$E12+'P052'!$F12+'P052'!$G12+'P052'!$H12+'P052'!$I12+'P052'!$J12) -> 0 | L12: ='P052'!$B12-'P052'!$K12 -> 0
A13: Septiembre | K13: ='P052'!$B13-('P052'!$C13+'P052'!$D13+'P052'!$E13+'P052'!$F13+'P052'!$G13+'P052'!$H13+'P052'!$I13+'P052'!$J13) -> 0 | L13: ='P052'!$B13-'P052'!$K13 -> 0
A14: Octubre | K14: ='P052'!$B14-('P052'!$C14+'P052'!$D14+'P052'!$E14+'P052'!$F14+'P052'!$G14+'P052'!$H14+'P052'!$I14+'P052'!$J14) -> 0 | L14: ='P052'!$B14-'P052'!$K14 -> 0
A15: Noviembre | K15: ='P052'!$B15-('P052'!$C15+'P052'!$D15+'P052'!$E15+'P052'!$F15+'P052'!$G15+'P052'!$H15+'P052'!$I15+'P052'!$J15) -> 0 | L15: ='P052'!$B15-'P052'!$K15 -> 0
A16: Diciembre | K16: ='P052'!$B16-('P052'!$C16+'P052'!$D16+'P052'!$E16+'P052'!$F16+'P052'!$G16+'P052'!$H16+'P052'!$I16+'P052'!$J16) -> 0 | L16: ='P052'!$B16-'P052'!$K16 -> 0
A18: NRO DE RECIBOS DE LOS PAGOS
C19: RECIBO 1 | D19: RECIBO 2 | E19: RECIBO 3 | F19: RECIBO 4 | G19: RECIBO 5 | H19: RECIBO 6 | I19: RECIBO 7 | J19: RECIBO 8
A20: Enero
A21: Febrero
A22: Marzo
A23: Abril
A24: Mayo
A25: Junio
A26: Julio
A27: Agosto
A28: Septiembre
A29: Octubre
A30: Noviembre
A31: Diciembre

Sheet P053
A1: P053 | C1: BECKER MATIAS
A3: PAGOS DEL ALQUILER
B4: COSTO | C4: PAGO 1 | D4: PAGO 2 | E4: PAGO 3 | F4: PAGO 4 | G4: PAGO 5 | H4: PAGO 6 | I4: PAGO 7 | J4: PAGO 8 | K4: SALDO | L4: RECAUDADO
A5: Enero | B5: 95200 | C5: 95200 | K5: ='P053'!$B5-('P053'!$C5+'P053'!$D5+'P053'!$E5+'P053'!$F5+'P053'!$G5+'P053'!$H5+'P053'!$I5+'P053'!$J5) -> 0 | L5: ='P053'!$B5-'P053'!$K5 -> 95200
A6: Febrero | B6: 102800 | C6: 55000 | D6: 40200 | E6: 7600 | K6: ='P053'!$B6-('P053'!$C6+'P053'!$D6+'P053'!$E6+'P053'!$F6+'P053'!$G6+'P053'!$H6+'P053'!$I6+'P053'!$J6) -> 0 | L6: ='P053'!$B6-'P053'!$K6 -> 102800
A7: Marzo | B7: 138000 | C7: 70000 | D7: 68000 | K7: ='P053'!$B7-('P053'!$C7+'P053'!$D7+'P053'!$E7+'P053'!$F7+'P053'!$G7+'P053'!$H7+'P053'!$I7+'P053'!$J7) -> 0 | L7: ='P053'!$B7-'P053'!$K7 -> 138000
A8: Abril | K8: ='P053'!$B8-('P053'!$C8+'P053'!$D8+'P053'!$E8+'P053'!$F8+'P053'!$G8+'P053'!$H8+'P053'!$I8+'P053'!$J8) -> 0 | L8: ='P053'!$B8-'P053'!$K8 -> 0
A9: Mayo | K9: ='P053'!$B9-('P053'!$C9+'P053'!$D9+'P053'!$E9+'P053'!$F9+'P053'!$G9+'P053'!$H9+'P053'!$I9+'P053'!$J9) -> 0 | L9: ='P053'!$B9-'P053'!$K9 -> 0
A10: Junio | K10: ='P053'!$B10-('P053'!$C10+'P053'!$D10+'P053'!$E10+'P053'!$F10+'P053'!$G10+'P053'!$H10+'P053'!$I10+'P053'!$J10) -> 0 | L10: ='P053'!$B10-'P053'!$K10 -> 0
A11: Julio | K11: ='P053'!$B11-('P053'!$C11+'P053'!$D11+'P053'!$E11+'P053'!$F11+'P053'!$G11+'P053'!$H11+'P053'!$I11+'P053'!$J11) -> 0 | L11: ='P053'!$B11-'P053'!$K11 -> 0
A12: Agosto | K12: ='P053'!$B12-('P053'!$C12+'P053'!$D12+'P053'!$E12+'P053'!$F12+'P053'!$G12+'P053'!$H12+'P053'!$I12+'P053'!$J12) -> 0 | L12: ='P053'!$B12-'P053'!$K12 -> 0
A13: Septiembre | K13: ='P053'!$B13-('P053'!$C13+'P053'!$D13+'P053'!$E13+'P053'!$F13+'P053'!$G13+'P053'!$H13+'P053'!$I13+'P053'!$J13) -> 0 | L13: ='P053'!$B13-'P053'!$K13 -> 0
A14: Octubre | K14: ='P053'!$B14-('P053'!$C14+'P053'!$D14+'P053'!$E14+'P053'!$F14+'P053'!$G14+'P053'!$H14+'P053'!$I14+'P053'!$J14) -> 0 | L14: ='P053'!$B14-'P053'!$K14 -> 0
A15: Noviembre | K15: ='P053'!$B15-('P053'!$C15+'P053'!$D15+'P053'!$E15+'P053'!$F15+'P053'!$G15+'P053'!$H15+'P053'!$I15+'P053'!$J15) -> 0 | L15: ='P053'!$B15-'P053'!$K15 -> 0
A16: Diciembre | K16: ='P053'!$B16-('P053'!$C16+'P053'!$D16+'P053'!$E16+'P053'!$F16+'P053'!$G16+'P053'!$H16+'P053'!$I16+'P053'!$J16) -> 0 | L16: ='P053'!$B16-'P053'!$K16 -> 0
A18: NRO DE RECIBOS DE LOS PAGOS
C19: RECIBO 1 | D19: RECIBO 2 | E19: RECIBO 3 | F19: RECIBO 4 | G19: RECIBO 5 | H19: RECIBO 6 | I19: RECIBO 7 | J19: RECIBO 8
A20: Enero | C20: 7664
A21: Febrero | C21: 7775 | D21: 7785 | E21: 7785
A22: Marzo | C22: 7801 | D22: 7846
A23: Abril
A24: Mayo
A25: Junio
A26: Julio
A27: Agosto
A28: Septiembre
A29: Octubre
A30: Noviembre
A31: Diciembre

Sheet P054
A1: 54/55 | C1: BUSQUETI AGUSTIN
A3: PAGOS DEL ALQUILER
B4: COSTO | C4: PAGO 1 | D4: PAGO 2 | E4: PAGO 3 | F4: PAGO 4 | G4: PAGO 5 | H4: PAGO 6 | I4: PAGO 7 | J4: PAGO 8 | K4: SALDO | L4: RECAUDADO
A5: Enero | B5: 355200 | C5: 355200 | K5: ='P054'!$B5-('P054'!$C5+'P054'!$D5+'P054'!$E5+'P054'!$F5+'P054'!$G5+'P054'!$H5+'P054'!$I5+'P054'!$J5) -> 0 | L5: ='P054'!$B5-'P054'!$K5 -> 355200 | M5: 13500
A6: Febrero | B6: 355200 | C6: 1300 | D6: 353900 | K6: ='P054'!$B6-('P054'!$C6+'P054'!$D6+'P054'!$E6+'P054'!$F6+'P054'!$G6+'P054'!$H6+'P054'!$I6+'P054'!$J6) -> 0 | L6: ='P054'!$B6-'P054'!$K6 -> 355200 | M6: 13500
A7: Marzo | B7: 772800 | C7: 772800 | K7: ='P054'!$B7-('P054'!$C7+'P054'!$D7+'P054'!$E7+'P054'!$F7+'P054'!$G7+'P054'!$H7+'P054'!$I7+'P054'!$J7) -> 0 | L7: ='P054'!$B7-'P054'!$K7 -> 772800 | M7: 13500
A8: Abril | K8: ='P054'!$B8-('P054'!$C8+'P054'!$D8+'P054'!$E8+'P054'!$F8+'P054'!$G8+'P054'!$H8+'P054'!$I8+'P054'!$J8) -> 0 | L8: ='P054'!$B8-'P054'!$K8 -> 0
A9: Mayo | K9: ='P054'!$B9-('P054'!$C9+'P054'!$D9+'P054'!$E9+'P054'!$F9+'P054'!$G9+'P054'!$H9+'P054'!$I9+'P054'!$J9) -> 0 | L9: ='P054'!$B9-'P054'!$K9 -> 0
A10: Junio | K10: ='P054'!$B10-('P054'!$C10+'P054'!$D10+'P054'!$E10+'P054'!$F10+'P054'!$G10+'P054'!$H10+'P054'!$I10+'P054'!$J10) -> 0 | L10: ='P054'!$B10-'P054'!$K10 -> 0
A11: Julio | K11: ='P054'!$B11-('P054'!$C11+'P054'!$D11+'P054'!$E11+'P054'!$F11+'P054'!$G11+'P054'!$H11+'P054'!$I11+'P054'!$J11) -> 0 | L11: ='P054'!$B11-'P054'!$K11 -> 0
A12: Agosto | K12: ='P054'!$B12-('P054'!$C12+'P054'!$D12+'P054'!$E12+'P054'!$F12+'P054'!$G12+'P054'!$H12+'P054'!$I12+'P054'!$J12) -> 0 | L12: ='P054'!$B12-'P054'!$K12 -> 0
A13: Septiembre | K13: ='P054'!$B13-('P054'!$C13+'P054'!$D13+'P054'!$E13+'P054'!$F13+'P054'!$G13+'P054'!$H13+'P054'!$I13+'P054'!$J13) -> 0 | L13: ='P054'!$B13-'P054'!$K13 -> 0
A14: Octubre | K14: ='P054'!$B14-('P054'!$C14+'P054'!$D14+'P054'!$E14+'P054'!$F14+'P054'!$G14+'P054'!$H14+'P054'!$I14+'P054'!$J14) -> 0 | L14: ='P054'!$B14-'P054'!$K14 -> 0
A15: Noviembre | K15: ='P054'!$B15-('P054'!$C15+'P054'!$D15+'P054'!$E15+'P054'!$F15+'P054'!$G15+'P054'!$H15+'P054'!$I15+'P054'!$J15) -> 0 | L15: ='P054'!$B15-'P054'!$K15 -> 0
A16: Diciembre | K16: ='P054'!$B16-('P054'!$C16+'P054'!$D16+'P054'!$E16+'P054'!$F16+'P054'!$G16+'P054'!$H16+'P054'!$I16+'P054'!$J16) -> 0 | L16: ='P054'!$B16-'P054'!$K16 -> 0
A18: NRO DE RECIBOS DE LOS PAGOS
C19: RECIBO 1 | D19: RECIBO 2 | E19: RECIBO 3 | F19: RECIBO 4 | G19: RECIBO 5 | H19: RECIBO 6 | I19: RECIBO 7 | J19: RECIBO 8
A20: Enero | C20: 9605
A21: Febrero | C21: 9605 | D21: 9663
A22: Marzo
A23: Abril
A24: Mayo
A25: Junio
A26: Julio
A27: Agosto
A28: Septiembre
A29: Octubre
A30: Noviembre
A31: Diciembre

Sheet P059
A1: Pto.58/59/60/60b/90/92 | C1: BURGOS FEDERICO
A3: PAGOS DEL ALQUILER
B4: COSTO | C4: PAGO 1 | D4: PAGO 2 | E4: PAGO 3 | F4: PAGO 4 | G4: PAGO 5 | H4: PAGO 6 | I4: PAGO 7 | J4: PAGO 8 | K4: SALDO | L4: RECAUDADO
A5: Enero | B5: 988100 | C5: 300000 | D5: 138100 | E5: 550000 | K5: ='P059'!$B5-('P059'!$C5+'P059'!$D5+'P059'!$E5+'P059'!$F5+'P059'!$G5+'P059'!$H5+'P059'!$I5+'P059'!$J5) -> 0 | L5: =B5 -> 988100 | M5: 40500
A6: Febrero | B6: 988100 | C6: 11900 | D6: 459500 | E6: 516700 | K6: ='P059'!$B6-('P059'!$C6+'P059'!$D6+'P059'!$E6+'P059'!$F6+'P059'!$G6+'P059'!$H6+'P059'!$I6+'P059'!$J6) -> 0 | L6: ='P059'!$B6-'P059'!$K6 -> 988100 | M6: 40500
A7: Marzo | K7: ='P059'!$B7-('P059'!$C7+'P059'!$D7+'P059'!$E7+'P059'!$F7+'P059'!$G7+'P059'!$H7+'P059'!$I7+'P059'!$J7) -> 0 | L7: ='P059'!$B7-'P059'!$K7 -> 0
A8: Abril | K8: ='P059'!$B8-('P059'!$C8+'P059'!$D8+'P059'!$E8+'P059'!$F8+'P059'!$G8+'P059'!$H8+'P059'!$I8+'P059'!$J8) -> 0 | L8: ='P059'!$B8-'P059'!$K8 -> 0
A9: Mayo | K9: ='P059'!$B9-('P059'!$C9+'P059'!$D9+'P059'!$E9+'P059'!$F9+'P059'!$G9+'P059'!$H9+'P059'!$I9+'P059'!$J9) -> 0 | L9: ='P059'!$B9-'P059'!$K9 -> 0
A10: Junio | K10: ='P059'!$B10-('P059'!$C10+'P059'!$D10+'P059'!$E10+'P059'!$F10+'P059'!$G10+'P059'!$H10+'P059'!$I10+'P059'!$J10) -> 0 | L10: ='P059'!$B10-'P059'!$K10 -> 0
A11: Julio | K11: ='P059'!$B11-('P059'!$C11+'P059'!$D11+'P059'!$E11+'P059'!$F11+'P059'!$G11+'P059'!$H11+'P059'!$I11+'P059'!$J11) -> 0 | L11: ='P059'!$B11-'P059'!$K11 -> 0
A12: Agosto | K12: ='P059'!$B12-('P059'!$C12+'P059'!$D12+'P059'!$E12+'P059'!$F12+'P059'!$G12+'P059'!$H12+'P059'!$I12+'P059'!$J12) -> 0 | L12: ='P059'!$B12-'P059'!$K12 -> 0
A13: Septiembre | K13: ='P059'!$B13-('P059'!$C13+'P059'!$D13+'P059'!$E13+'P059'!$F13+'P059'!$G13+'P059'!$H13+'P059'!$I13+'P059'!$J13) -> 0 | L13: ='P059'!$B13-'P059'!$K13 -> 0
A14: Octubre | K14: ='P059'!$B14-('P059'!$C14+'P059'!$D14+'P059'!$E14+'P059'!$F14+'P059'!$G14+'P059'!$H14+'P059'!$I14+'P059'!$J14) -> 0 | L14: ='P059'!$B14-'P059'!$K14 -> 0
A15: Noviembre | K15: ='P059'!$B15-('P059'!$C15+'P059'!$D15+'P059'!$E15+'P059'!$F15+'P059'!$G15+'P059'!$H15+'P059'!$I15+'P059'!$J15) -> 0 | L15: ='P059'!$B15-'P059'!$K15 -> 0
A16: Diciembre | K16: ='P059'!$B16-('P059'!$C16+'P059'!$D16+'P059'!$E16+'P059'!$F16+'P059'!$G16+'P059'!$H16+'P059'!$I16+'P059'!$J16) -> 0 | L16: ='P059'!$B16-'P059'!$K16 -> 0
A18: NRO DE RECIBOS DE LOS PAGOS
C19: RECIBO 1 | D19: RECIBO 2 | E19: RECIBO 3 | F19: RECIBO 4 | G19: RECIBO 5 | H19: RECIBO 6 | I19: RECIBO 7 | J19: RECIBO 8
A20: Enero | C20: 9061 | D20: 9708 | E20: 9708
A21: Febrero | C21: 9708 | D21: 9728 | E21: 9755
A22: Marzo
A23: Abril
A24: Mayo
A25: Junio
A26: Julio
A27: Agosto
A28: Septiembre
A29: Octubre
A30: Noviembre
A31: Diciembre

Sheet P055
A1: P055 | C1: BUSQUETI AGUSTIN (SANTI)
A3: PAGOS DEL ALQUILER
B4: COSTO | C4: PAGO 1 | D4: PAGO 2 | E4: PAGO 3 | F4: PAGO 4 | G4: PAGO 5 | H4: PAGO 6 | I4: PAGO 7 | J4: PAGO 8 | K4: SALDO | L4: RECAUDADO
A5: Enero | K5: ='P055'!$B5-('P055'!$C5+'P055'!$D5+'P055'!$E5+'P055'!$F5+'P055'!$G5+'P055'!$H5+'P055'!$I5+'P055'!$J5) -> 0 | L5: ='P055'!$B5-'P055'!$K5 -> 0
A6: Febrero | K6: ='P055'!$B6-('P055'!$C6+'P055'!$D6+'P055'!$E6+'P055'!$F6+'P055'!$G6+'P055'!$H6+'P055'!$I6+'P055'!$J6) -> 0 | L6: ='P055'!$B6-'P055'!$K6 -> 0
A7: Marzo | K7: ='P055'!$B7-('P055'!$C7+'P055'!$D7+'P055'!$E7+'P055'!$F7+'P055'!$G7+'P055'!$H7+'P055'!$I7+'P055'!$J7) -> 0 | L7: ='P055'!$B7-'P055'!$K7 -> 0
A8: Abril | K8: ='P055'!$B8-('P055'!$C8+'P055'!$D8+'P055'!$E8+'P055'!$F8+'P055'!$G8+'P055'!$H8+'P055'!$I8+'P055'!$J8) -> 0 | L8: ='P055'!$B8-'P055'!$K8 -> 0
A9: Mayo | K9: ='P055'!$B9-('P055'!$C9+'P055'!$D9+'P055'!$E9+'P055'!$F9+'P055'!$G9+'P055'!$H9+'P055'!$I9+'P055'!$J9) -> 0 | L9: ='P055'!$B9-'P055'!$K9 -> 0
A10: Junio | K10: ='P055'!$B10-('P055'!$C10+'P055'!$D10+'P055'!$E10+'P055'!$F10+'P055'!$G10+'P055'!$H10+'P055'!$I10+'P055'!$J10) -> 0 | L10: ='P055'!$B10-'P055'!$K10 -> 0
A11: Julio | K11: ='P055'!$B11-('P055'!$C11+'P055'!$D11+'P055'!$E11+'P055'!$F11+'P055'!$G11+'P055'!$H11+'P055'!$I11+'P055'!$J11) -> 0 | L11: ='P055'!$B11-'P055'!$K11 -> 0
A12: Agosto | K12: ='P055'!$B12-('P055'!$C12+'P055'!$D12+'P055'!$E12+'P055'!$F12+'P055'!$G12+'P055'!$H12+'P055'!$I12+'P055'!$J12) -> 0 | L12: ='P055'!$B12-'P055'!$K12 -> 0
A13: Septiembre | K13: ='P055'!$B13-('P055'!$C13+'P055'!$D13+'P055'!$E13+'P055'!$F13+'P055'!$G13+'P055'!$H13+'P055'!$I13+'P055'!$J13) -> 0 | L13: ='P055'!$B13-'P055'!$K13 -> 0
A14: Octubre | K14: ='P055'!$B14-('P055'!$C14+'P055'!$D14+'P055'!$E14+'P055'!$F14+'P055'!$G14+'P055'!$H14+'P055'!$I14+'P055'!$J14) -> 0 | L14: ='P055'!$B14-'P055'!$K14 -> 0
A15: Noviembre | K15: ='P055'!$B15-('P055'!$C15+'P055'!$D15+'P055'!$E15+'P055'!$F15+'P055'!$G15+'P055'!$H15+'P055'!$I15+'P055'!$J15) -> 0 | L15: ='P055'!$B15-'P055'!$K15 -> 0
A16: Diciembre | K16: ='P055'!$B16-('P055'!$C16+'P055'!$D16+'P055'!$E16+'P055'!$F16+'P055'!$G16+'P055'!$H16+'P055'!$I16+'P055'!$J16) -> 0 | L16: ='P055'!$B16-'P055'!$K16 -> 0
A18: NRO DE RECIBOS DE LOS PAGOS
C19: RECIBO 1 | D19: RECIBO 2 | E19: RECIBO 3 | F19: RECIBO 4 | G19: RECIBO 5 | H19: RECIBO 6 | I19: RECIBO 7 | J19: RECIBO 8
A20: Enero
A21: Febrero
A22: Marzo
A23: Abril
A24: Mayo
A25: Junio
A26: Julio
A27: Agosto
A28: Septiembre
A29: Octubre
A30: Noviembre
A31: Diciembre

Sheet P056
A3: PAGOS DEL ALQUILER
B4: COSTO | C4: PAGO 1 | D4: PAGO 2 | E4: PAGO 3 | F4: PAGO 4 | G4: PAGO 5 | H4: PAGO 6 | I4: PAGO 7 | J4: PAGO 8 | K4: SALDO | L4: RECAUDADO
A5: Enero | K5: ='P056'!$B5-('P056'!$C5+'P056'!$D5+'P056'!$E5+'P056'!$F5+'P056'!$G5+'P056'!$H5+'P056'!$I5+'P056'!$J5) -> 0 | L5: ='P056'!$B5-'P056'!$K5 -> 0
A6: Febrero | K6: ='P056'!$B6-('P056'!$C6+'P056'!$D6+'P056'!$E6+'P056'!$F6+'P056'!$G6+'P056'!$H6+'P056'!$I6+'P056'!$J6) -> 0 | L6: ='P056'!$B6-'P056'!$K6 -> 0
A7: Marzo | K7: ='P056'!$B7-('P056'!$C7+'P056'!$D7+'P056'!$E7+'P056'!$F7+'P056'!$G7+'P056'!$H7+'P056'!$I7+'P056'!$J7) -> 0 | L7: ='P056'!$B7-'P056'!$K7 -> 0
A8: Abril | K8: ='P056'!$B8-('P056'!$C8+'P056'!$D8+'P056'!$E8+'P056'!$F8+'P056'!$G8+'P056'!$H8+'P056'!$I8+'P056'!$J8) -> 0 | L8: ='P056'!$B8-'P056'!$K8 -> 0
A9: Mayo | K9: ='P056'!$B9-('P056'!$C9+'P056'!$D9+'P056'!$E9+'P056'!$F9+'P056'!$G9+'P056'!$H9+'P056'!$I9+'P056'!$J9) -> 0 | L9: ='P056'!$B9-'P056'!$K9 -> 0
A10: Junio | K10: ='P056'!$B10-('P056'!$C10+'P056'!$D10+'P056'!$E10+'P056'!$F10+'P056'!$G10+'P056'!$H10+'P056'!$I10+'P056'!$J10) -> 0 | L10: ='P056'!$B10-'P056'!$K10 -> 0
A11: Julio | K11: ='P056'!$B11-('P056'!$C11+'P056'!$D11+'P056'!$E11+'P056'!$F11+'P056'!$G11+'P056'!$H11+'P056'!$I11+'P056'!$J11) -> 0 | L11: ='P056'!$B11-'P056'!$K11 -> 0
A12: Agosto | K12: ='P056'!$B12-('P056'!$C12+'P056'!$D12+'P056'!$E12+'P056'!$F12+'P056'!$G12+'P056'!$H12+'P056'!$I12+'P056'!$J12) -> 0 | L12: ='P056'!$B12-'P056'!$K12 -> 0
A13: Septiembre | K13: ='P056'!$B13-('P056'!$C13+'P056'!$D13+'P056'!$E13+'P056'!$F13+'P056'!$G13+'P056'!$H13+'P056'!$I13+'P056'!$J13) -> 0 | L13: ='P056'!$B13-'P056'!$K13 -> 0
A14: Octubre | K14: ='P056'!$B14-('P056'!$C14+'P056'!$D14+'P056'!$E14+'P056'!$F14+'P056'!$G14+'P056'!$H14+'P056'!$I14+'P056'!$J14) -> 0 | L14: ='P056'!$B14-'P056'!$K14 -> 0
A15: Noviembre | K15: ='P056'!$B15-('P056'!$C15+'P056'!$D15+'P056'!$E15+'P056'!$F15+'P056'!$G15+'P056'!$H15+'P056'!$I15+'P056'!$J15) -> 0 | L15: ='P056'!$B15-'P056'!$K15 -> 0
A16: Diciembre | K16: ='P056'!$B16-('P056'!$C16+'P056'!$D16+'P056'!$E16+'P056'!$F16+'P056'!$G16+'P056'!$H16+'P056'!$I16+'P056'!$J16) -> 0 | L16: ='P056'!$B16-'P056'!$K16 -> 0
A18: NRO DE RECIBOS DE LOS PAGOS
C19: RECIBO 1 | D19: RECIBO 2 | E19: RECIBO 3 | F19: RECIBO 4 | G19: RECIBO 5 | H19: RECIBO 6 | I19: RECIBO 7 | J19: RECIBO 8
A20: Enero
A21: Febrero
A22: Marzo
A23: Abril
A24: Mayo
A25: Junio
A26: Julio
A27: Agosto
A28: Septiembre
A29: Octubre
A30: Noviembre
A31: Diciembre

Sheet P057
A3: PAGOS DEL ALQUILER
B4: COSTO | C4: PAGO 1 | D4: PAGO 2 | E4: PAGO 3 | F4: PAGO 4 | G4: PAGO 5 | H4: PAGO 6 | I4: PAGO 7 | J4: PAGO 8 | K4: SALDO | L4: RECAUDADO
A5: Enero | K5: ='P057'!$B5-('P057'!$C5+'P057'!$D5+'P057'!$E5+'P057'!$F5+'P057'!$G5+'P057'!$H5+'P057'!$I5+'P057'!$J5) -> 0 | L5: ='P057'!$B5-'P057'!$K5 -> 0
A6: Febrero | K6: ='P057'!$B6-('P057'!$C6+'P057'!$D6+'P057'!$E6+'P057'!$F6+'P057'!$G6+'P057'!$H6+'P057'!$I6+'P057'!$J6) -> 0 | L6: ='P057'!$B6-'P057'!$K6 -> 0
A7: Marzo | K7: ='P057'!$B7-('P057'!$C7+'P057'!$D7+'P057'!$E7+'P057'!$F7+'P057'!$G7+'P057'!$H7+'P057'!$I7+'P057'!$J7) -> 0 | L7: ='P057'!$B7-'P057'!$K7 -> 0
A8: Abril | K8: ='P057'!$B8-('P057'!$C8+'P057'!$D8+'P057'!$E8+'P057'!$F8+'P057'!$G8+'P057'!$H8+'P057'!$I8+'P057'!$J8) -> 0 | L8: ='P057'!$B8-'P057'!$K8 -> 0
A9: Mayo | K9: ='P057'!$B9-('P057'!$C9+'P057'!$D9+'P057'!$E9+'P057'!$F9+'P057'!$G9+'P057'!$H9+'P057'!$I9+'P057'!$J9) -> 0 | L9: ='P057'!$B9-'P057'!$K9 -> 0
A10: Junio | K10: ='P057'!$B10-('P057'!$C10+'P057'!$D10+'P057'!$E10+'P057'!$F10+'P057'!$G10+'P057'!$H10+'P057'!$I10+'P057'!$J10) -> 0 | L10: ='P057'!$B10-'P057'!$K10 -> 0
A11: Julio | K11: ='P057'!$B11-('P057'!$C11+'P057'!$D11+'P057'!$E11+'P057'!$F11+'P057'!$G11+'P057'!$H11+'P057'!$I11+'P057'!$J11) -> 0 | L11: ='P057'!$B11-'P057'!$K11 -> 0
A12: Agosto | K12: ='P057'!$B12-('P057'!$C12+'P057'!$D12+'P057'!$E12+'P057'!$F12+'P057'!$G12+'P057'!$H12+'P057'!$I12+'P057'!$J12) -> 0 | L12: ='P057'!$B12-'P057'!$K12 -> 0
A13: Septiembre | K13: ='P057'!$B13-('P057'!$C13+'P057'!$D13+'P057'!$E13+'P057'!$F13+'P057'!$G13+'P057'!$H13+'P057'!$I13+'P057'!$J13) -> 0 | L13: ='P057'!$B13-'P057'!$K13 -> 0
A14: Octubre | K14: ='P057'!$B14-('P057'!$C14+'P057'!$D14+'P057'!$E14+'P057'!$F14+'P057'!$G14+'P057'!$H14+'P057'!$I14+'P057'!$J14) -> 0 | L14: ='P057'!$B14-'P057'!$K14 -> 0
A15: Noviembre | K15: ='P057'!$B15-('P057'!$C15+'P057'!$D15+'P057'!$E15+'P057'!$F15+'P057'!$G15+'P057'!$H15+'P057'!$I15+'P057'!$J15) -> 0 | L15: ='P057'!$B15-'P057'!$K15 -> 0
A16: Diciembre | K16: ='P057'!$B16-('P057'!$C16+'P057'!$D16+'P057'!$E16+'P057'!$F16+'P057'!$G16+'P057'!$H16+'P057'!$I16+'P057'!$J16) -> 0 | L16: ='P057'!$B16-'P057'!$K16 -> 0
A18: NRO DE RECIBOS DE LOS PAGOS
C19: RECIBO 1 | D19: RECIBO 2 | E19: RECIBO 3 | F19: RECIBO 4 | G19: RECIBO 5 | H19: RECIBO 6 | I19: RECIBO 7 | J19: RECIBO 8
A20: Enero
A21: Febrero
A22: Marzo
A23: Abril
A24: Mayo
A25: Junio
A26: Julio
A27: Agosto
A28: Septiembre
A29: Octubre
A30: Noviembre
A31: Diciembre

Sheet P058

Sheet P060
A3: PAGOS DEL ALQUILER
B4: COSTO | C4: PAGO 1 | D4: PAGO 2 | E4: PAGO 3 | F4: PAGO 4 | G4: PAGO 5 | H4: PAGO 6 | I4: PAGO 7 | J4: PAGO 8 | K4: SALDO | L4: RECAUDADO
A5: Enero | K5: ='P060'!$B5-('P060'!$C5+'P060'!$D5+'P060'!$E5+'P060'!$F5+'P060'!$G5+'P060'!$H5+'P060'!$I5+'P060'!$J5) -> 0 | L5: ='P060'!$B5-'P060'!$K5 -> 0
A6: Febrero | K6: ='P060'!$B6-('P060'!$C6+'P060'!$D6+'P060'!$E6+'P060'!$F6+'P060'!$G6+'P060'!$H6+'P060'!$I6+'P060'!$J6) -> 0 | L6: ='P060'!$B6-'P060'!$K6 -> 0
A7: Marzo | K7: ='P060'!$B7-('P060'!$C7+'P060'!$D7+'P060'!$E7+'P060'!$F7+'P060'!$G7+'P060'!$H7+'P060'!$I7+'P060'!$J7) -> 0 | L7: ='P060'!$B7-'P060'!$K7 -> 0
A8: Abril | K8: ='P060'!$B8-('P060'!$C8+'P060'!$D8+'P060'!$E8+'P060'!$F8+'P060'!$G8+'P060'!$H8+'P060'!$I8+'P060'!$J8) -> 0 | L8: ='P060'!$B8-'P060'!$K8 -> 0
A9: Mayo | K9: ='P060'!$B9-('P060'!$C9+'P060'!$D9+'P060'!$E9+'P060'!$F9+'P060'!$G9+'P060'!$H9+'P060'!$I9+'P060'!$J9) -> 0 | L9: ='P060'!$B9-'P060'!$K9 -> 0
A10: Junio | K10: ='P060'!$B10-('P060'!$C10+'P060'!$D10+'P060'!$E10+'P060'!$F10+'P060'!$G10+'P060'!$H10+'P060'!$I10+'P060'!$J10) -> 0 | L10: ='P060'!$B10-'P060'!$K10 -> 0
A11: Julio | K11: ='P060'!$B11-('P060'!$C11+'P060'!$D11+'P060'!$E11+'P060'!$F11+'P060'!$G11+'P060'!$H11+'P060'!$I11+'P060'!$J11) -> 0 | L11: ='P060'!$B11-'P060'!$K11 -> 0
A12: Agosto | K12: ='P060'!$B12-('P060'!$C12+'P060'!$D12+'P060'!$E12+'P060'!$F12+'P060'!$G12+'P060'!$H12+'P060'!$I12+'P060'!$J12) -> 0 | L12: ='P060'!$B12-'P060'!$K12 -> 0
A13: Septiembre | K13: ='P060'!$B13-('P060'!$C13+'P060'!$D13+'P060'!$E13+'P060'!$F13+'P060'!$G13+'P060'!$H13+'P060'!$I13+'P060'!$J13) -> 0 | L13: ='P060'!$B13-'P060'!$K13 -> 0
A14: Octubre | K14: ='P060'!$B14-('P060'!$C14+'P060'!$D14+'P060'!$E14+'P060'!$F14+'P060'!$G14+'P060'!$H14+'P060'!$I14+'P060'!$J14) -> 0 | L14: ='P060'!$B14-'P060'!$K14 -> 0
A15: Noviembre | K15: ='P060'!$B15-('P060'!$C15+'P060'!$D15+'P060'!$E15+'P060'!$F15+'P060'!$G15+'P060'!$H15+'P060'!$I15+'P060'!$J15) -> 0 | L15: ='P060'!$B15-'P060'!$K15 -> 0
A16: Diciembre | K16: ='P060'!$B16-('P060'!$C16+'P060'!$D16+'P060'!$E16+'P060'!$F16+'P060'!$G16+'P060'!$H16+'P060'!$I16+'P060'!$J16) -> 0 | L16: ='P060'!$B16-'P060'!$K16 -> 0
A18: NRO DE RECIBOS DE LOS PAGOS
C19: RECIBO 1 | D19: RECIBO 2 | E19: RECIBO 3 | F19: RECIBO 4 | G19: RECIBO 5 | H19: RECIBO 6 | I19: RECIBO 7 | J19: RECIBO 8
A20: Enero
A21: Febrero
A22: Marzo
A23: Abril
A24: Mayo
A25: Junio
A26: Julio
A27: Agosto
A28: Septiembre
A29: Octubre
A30: Noviembre
A31: Diciembre

Sheet P061
A3: PAGOS DEL ALQUILER
B4: COSTO | C4: PAGO 1 | D4: PAGO 2 | E4: PAGO 3 | F4: PAGO 4 | G4: PAGO 5 | H4: PAGO 6 | I4: PAGO 7 | J4: PAGO 8 | K4: SALDO | L4: RECAUDADO
A5: Enero | K5: ='P061'!$B5-('P061'!$C5+'P061'!$D5+'P061'!$E5+'P061'!$F5+'P061'!$G5+'P061'!$H5+'P061'!$I5+'P061'!$J5) -> 0 | L5: ='P061'!$B5-'P061'!$K5 -> 0
A6: Febrero | K6: ='P061'!$B6-('P061'!$C6+'P061'!$D6+'P061'!$E6+'P061'!$F6+'P061'!$G6+'P061'!$H6+'P061'!$I6+'P061'!$J6) -> 0 | L6: ='P061'!$B6-'P061'!$K6 -> 0
A7: Marzo | K7: ='P061'!$B7-('P061'!$C7+'P061'!$D7+'P061'!$E7+'P061'!$F7+'P061'!$G7+'P061'!$H7+'P061'!$I7+'P061'!$J7) -> 0 | L7: ='P061'!$B7-'P061'!$K7 -> 0
A8: Abril | K8: ='P061'!$B8-('P061'!$C8+'P061'!$D8+'P061'!$E8+'P061'!$F8+'P061'!$G8+'P061'!$H8+'P061'!$I8+'P061'!$J8) -> 0 | L8: ='P061'!$B8-'P061'!$K8 -> 0
A9: Mayo | K9: ='P061'!$B9-('P061'!$C9+'P061'!$D9+'P061'!$E9+'P061'!$F9+'P061'!$G9+'P061'!$H9+'P061'!$I9+'P061'!$J9) -> 0 | L9: ='P061'!$B9-'P061'!$K9 -> 0
A10: Junio | K10: ='P061'!$B10-('P061'!$C10+'P061'!$D10+'P061'!$E10+'P061'!$F10+'P061'!$G10+'P061'!$H10+'P061'!$I10+'P061'!$J10) -> 0 | L10: ='P061'!$B10-'P061'!$K10 -> 0
A11: Julio | K11: ='P061'!$B11-('P061'!$C11+'P061'!$D11+'P061'!$E11+'P061'!$F11+'P061'!$G11+'P061'!$H11+'P061'!$I11+'P061'!$J11) -> 0 | L11: ='P061'!$B11-'P061'!$K11 -> 0
A12: Agosto | K12: ='P061'!$B12-('P061'!$C12+'P061'!$D12+'P061'!$E12+'P061'!$F12+'P061'!$G12+'P061'!$H12+'P061'!$I12+'P061'!$J12) -> 0 | L12: ='P061'!$B12-'P061'!$K12 -> 0
A13: Septiembre | K13: ='P061'!$B13-('P061'!$C13+'P061'!$D13+'P061'!$E13+'P061'!$F13+'P061'!$G13+'P061'!$H13+'P061'!$I13+'P061'!$J13) -> 0 | L13: ='P061'!$B13-'P061'!$K13 -> 0
A14: Octubre | K14: ='P061'!$B14-('P061'!$C14+'P061'!$D14+'P061'!$E14+'P061'!$F14+'P061'!$G14+'P061'!$H14+'P061'!$I14+'P061'!$J14) -> 0 | L14: ='P061'!$B14-'P061'!$K14 -> 0
A15: Noviembre | K15: ='P061'!$B15-('P061'!$C15+'P061'!$D15+'P061'!$E15+'P061'!$F15+'P061'!$G15+'P061'!$H15+'P061'!$I15+'P061'!$J15) -> 0 | L15: ='P061'!$B15-'P061'!$K15 -> 0
A16: Diciembre | K16: ='P061'!$B16-('P061'!$C16+'P061'!$D16+'P061'!$E16+'P061'!$F16+'P061'!$G16+'P061'!$H16+'P061'!$I16+'P061'!$J16) -> 0 | L16: ='P061'!$B16-'P061'!$K16 -> 0
A18: NRO DE RECIBOS DE LOS PAGOS
C19: RECIBO 1 | D19: RECIBO 2 | E19: RECIBO 3 | F19: RECIBO 4 | G19: RECIBO 5 | H19: RECIBO 6 | I19: RECIBO 7 | J19: RECIBO 8
A20: Enero
A21: Febrero
A22: Marzo
A23: Abril
A24: Mayo
A25: Junio
A26: Julio
A27: Agosto
A28: Septiembre
A29: Octubre
A30: Noviembre
A31: Diciembre

Sheet P062
A1: P062 | C1: MARIA C.CABRAL
A3: PAGOS DEL ALQUILER
B4: COSTO | C4: PAGO 1 | D4: PAGO 2 | E4: PAGO 3 | F4: PAGO 4 | G4: PAGO 5 | H4: PAGO 6 | I4: PAGO 7 | J4: PAGO 8 | K4: SALDO | L4: RECAUDADO
A5: Enero | B5: 58000 | C5: 58000 | K5: ='P062'!$B5-('P062'!$C5+'P062'!$D5+'P062'!$E5+'P062'!$F5+'P062'!$G5+'P062'!$H5+'P062'!$I5+'P062'!$J5) -> 0 | L5: ='P062'!$B5-'P062'!$K5 -> 58000
A6: Febrero | B6: 63700 | C6: 58000 | D6: 6840 | K6: ='P062'!$B6-('P062'!$C6+'P062'!$D6+'P062'!$E6+'P062'!$F6+'P062'!$G6+'P062'!$H6+'P062'!$I6+'P062'!$J6) -> -1140 | L6: ='P062'!$B6-'P062'!$K6 -> 64840
A7: Marzo | B7: 84100 | C7: 84100 | K7: ='P062'!$B7-('P062'!$C7+'P062'!$D7+'P062'!$E7+'P062'!$F7+'P062'!$G7+'P062'!$H7+'P062'!$I7+'P062'!$J7) -> 0 | L7: ='P062'!$B7-'P062'!$K7 -> 84100
A8: Abril | B8: 90100 | C8: 5960 | D8: 77000 | E8: 7140 | K8: ='P062'!$B8-('P062'!$C8+'P062'!$D8+'P062'!$E8+'P062'!$F8+'P062'!$G8+'P062'!$H8+'P062'!$I8+'P062'!$J8) -> 0 | L8: ='P062'!$B8-'P062'!$K8 -> 90100
A9: Mayo | B9: 84100 | C9: 84100 | K9: ='P062'!$B9-('P062'!$C9+'P062'!$D9+'P062'!$E9+'P062'!$F9+'P062'!$G9+'P062'!$H9+'P062'!$I9+'P062'!$J9) -> 0 | L9: ='P062'!$B9-'P062'!$K9 -> 84100
A10: Junio | K10: ='P062'!$B10-('P062'!$C10+'P062'!$D10+'P062'!$E10+'P062'!$F10+'P062'!$G10+'P062'!$H10+'P062'!$I10+'P062'!$J10) -> 0 | L10: ='P062'!$B10-'P062'!$K10 -> 0
A11: Julio | K11: ='P062'!$B11-('P062'!$C11+'P062'!$D11+'P062'!$E11+'P062'!$F11+'P062'!$G11+'P062'!$H11+'P062'!$I11+'P062'!$J11) -> 0 | L11: ='P062'!$B11-'P062'!$K11 -> 0
A12: Agosto | K12: ='P062'!$B12-('P062'!$C12+'P062'!$D12+'P062'!$E12+'P062'!$F12+'P062'!$G12+'P062'!$H12+'P062'!$I12+'P062'!$J12) -> 0 | L12: ='P062'!$B12-'P062'!$K12 -> 0
A13: Septiembre | K13: ='P062'!$B13-('P062'!$C13+'P062'!$D13+'P062'!$E13+'P062'!$F13+'P062'!$G13+'P062'!$H13+'P062'!$I13+'P062'!$J13) -> 0 | L13: ='P062'!$B13-'P062'!$K13 -> 0
A14: Octubre | K14: ='P062'!$B14-('P062'!$C14+'P062'!$D14+'P062'!$E14+'P062'!$F14+'P062'!$G14+'P062'!$H14+'P062'!$I14+'P062'!$J14) -> 0 | L14: ='P062'!$B14-'P062'!$K14 -> 0
A15: Noviembre | K15: ='P062'!$B15-('P062'!$C15+'P062'!$D15+'P062'!$E15+'P062'!$F15+'P062'!$G15+'P062'!$H15+'P062'!$I15+'P062'!$J15) -> 0 | L15: ='P062'!$B15-'P062'!$K15 -> 0
A16: Diciembre | K16: ='P062'!$B16-('P062'!$C16+'P062'!$D16+'P062'!$E16+'P062'!$F16+'P062'!$G16+'P062'!$H16+'P062'!$I16+'P062'!$J16) -> 0 | L16: ='P062'!$B16-'P062'!$K16 -> 0
A18: NRO DE RECIBOS DE LOS PAGOS
C19: RECIBO 1 | D19: RECIBO 2 | E19: RECIBO 3 | F19: RECIBO 4 | G19: RECIBO 5 | H19: RECIBO 6 | I19: RECIBO 7 | J19: RECIBO 8
A20: Enero | C20: 7766
A21: Febrero | C21: 7766
A22: Marzo
A23: Abril | C23: 7888
A24: Mayo
A25: Junio | C25: 8043
A26: Julio
A27: Agosto
A28: Septiembre
A29: Octubre
A30: Noviembre
A31: Diciembre
N46: 21500
N47: 21500
N48: 16000
N49: 16000
N50: 16000

Sheet P063
A3: PAGOS DEL ALQUILER
B4: COSTO | C4: PAGO 1 | D4: PAGO 2 | E4: PAGO 3 | F4: PAGO 4 | G4: PAGO 5 | H4: PAGO 6 | I4: PAGO 7 | J4: PAGO 8 | K4: SALDO | L4: RECAUDADO
A5: Enero | K5: ='P063'!$B5-('P063'!$C5+'P063'!$D5+'P063'!$E5+'P063'!$F5+'P063'!$G5+'P063'!$H5+'P063'!$I5+'P063'!$J5) -> 0 | L5: ='P063'!$B5-'P063'!$K5 -> 0
A6: Febrero | K6: ='P063'!$B6-('P063'!$C6+'P063'!$D6+'P063'!$E6+'P063'!$F6+'P063'!$G6+'P063'!$H6+'P063'!$I6+'P063'!$J6) -> 0 | L6: ='P063'!$B6-'P063'!$K6 -> 0
A7: Marzo | K7: ='P063'!$B7-('P063'!$C7+'P063'!$D7+'P063'!$E7+'P063'!$F7+'P063'!$G7+'P063'!$H7+'P063'!$I7+'P063'!$J7) -> 0 | L7: ='P063'!$B7-'P063'!$K7 -> 0
A8: Abril | K8: ='P063'!$B8-('P063'!$C8+'P063'!$D8+'P063'!$E8+'P063'!$F8+'P063'!$G8+'P063'!$H8+'P063'!$I8+'P063'!$J8) -> 0 | L8: ='P063'!$B8-'P063'!$K8 -> 0
A9: Mayo | K9: ='P063'!$B9-('P063'!$C9+'P063'!$D9+'P063'!$E9+'P063'!$F9+'P063'!$G9+'P063'!$H9+'P063'!$I9+'P063'!$J9) -> 0 | L9: ='P063'!$B9-'P063'!$K9 -> 0
A10: Junio | K10: ='P063'!$B10-('P063'!$C10+'P063'!$D10+'P063'!$E10+'P063'!$F10+'P063'!$G10+'P063'!$H10+'P063'!$I10+'P063'!$J10) -> 0 | L10: ='P063'!$B10-'P063'!$K10 -> 0
A11: Julio | K11: ='P063'!$B11-('P063'!$C11+'P063'!$D11+'P063'!$E11+'P063'!$F11+'P063'!$G11+'P063'!$H11+'P063'!$I11+'P063'!$J11) -> 0 | L11: ='P063'!$B11-'P063'!$K11 -> 0
A12: Agosto | K12: ='P063'!$B12-('P063'!$C12+'P063'!$D12+'P063'!$E12+'P063'!$F12+'P063'!$G12+'P063'!$H12+'P063'!$I12+'P063'!$J12) -> 0 | L12: ='P063'!$B12-'P063'!$K12 -> 0
A13: Septiembre | K13: ='P063'!$B13-('P063'!$C13+'P063'!$D13+'P063'!$E13+'P063'!$F13+'P063'!$G13+'P063'!$H13+'P063'!$I13+'P063'!$J13) -> 0 | L13: ='P063'!$B13-'P063'!$K13 -> 0
A14: Octubre | K14: ='P063'!$B14-('P063'!$C14+'P063'!$D14+'P063'!$E14+'P063'!$F14+'P063'!$G14+'P063'!$H14+'P063'!$I14+'P063'!$J14) -> 0 | L14: ='P063'!$B14-'P063'!$K14 -> 0
A15: Noviembre | K15: ='P063'!$B15-('P063'!$C15+'P063'!$D15+'P063'!$E15+'P063'!$F15+'P063'!$G15+'P063'!$H15+'P063'!$I15+'P063'!$J15) -> 0 | L15: ='P063'!$B15-'P063'!$K15 -> 0
A16: Diciembre | K16: ='P063'!$B16-('P063'!$C16+'P063'!$D16+'P063'!$E16+'P063'!$F16+'P063'!$G16+'P063'!$H16+'P063'!$I16+'P063'!$J16) -> 0 | L16: ='P063'!$B16-'P063'!$K16 -> 0
A18: NRO DE RECIBOS DE LOS PAGOS
C19: RECIBO 1 | D19: RECIBO 2 | E19: RECIBO 3 | F19: RECIBO 4 | G19: RECIBO 5 | H19: RECIBO 6 | I19: RECIBO 7 | J19: RECIBO 8
A20: Enero
A21: Febrero
A22: Marzo
A23: Abril
A24: Mayo
A25: Junio
A26: Julio
A27: Agosto
A28: Septiembre
A29: Octubre
A30: Noviembre
A31: Diciembre

Sheet P064
A3: PAGOS DEL ALQUILER
B4: COSTO | C4: PAGO 1 | D4: PAGO 2 | E4: PAGO 3 | F4: PAGO 4 | G4: PAGO 5 | H4: PAGO 6 | I4: PAGO 7 | J4: PAGO 8 | K4: SALDO | L4: RECAUDADO
A5: Enero | K5: ='P064'!$B5-('P064'!$C5+'P064'!$D5+'P064'!$E5+'P064'!$F5+'P064'!$G5+'P064'!$H5+'P064'!$I5+'P064'!$J5) -> 0 | L5: ='P064'!$B5-'P064'!$K5 -> 0
A6: Febrero | K6: ='P064'!$B6-('P064'!$C6+'P064'!$D6+'P064'!$E6+'P064'!$F6+'P064'!$G6+'P064'!$H6+'P064'!$I6+'P064'!$J6) -> 0 | L6: ='P064'!$B6-'P064'!$K6 -> 0
A7: Marzo | K7: ='P064'!$B7-('P064'!$C7+'P064'!$D7+'P064'!$E7+'P064'!$F7+'P064'!$G7+'P064'!$H7+'P064'!$I7+'P064'!$J7) -> 0 | L7: ='P064'!$B7-'P064'!$K7 -> 0
A8: Abril | K8: ='P064'!$B8-('P064'!$C8+'P064'!$D8+'P064'!$E8+'P064'!$F8+'P064'!$G8+'P064'!$H8+'P064'!$I8+'P064'!$J8) -> 0 | L8: ='P064'!$B8-'P064'!$K8 -> 0
A9: Mayo | K9: ='P064'!$B9-('P064'!$C9+'P064'!$D9+'P064'!$E9+'P064'!$F9+'P064'!$G9+'P064'!$H9+'P064'!$I9+'P064'!$J9) -> 0 | L9: ='P064'!$B9-'P064'!$K9 -> 0
A10: Junio | K10: ='P064'!$B10-('P064'!$C10+'P064'!$D10+'P064'!$E10+'P064'!$F10+'P064'!$G10+'P064'!$H10+'P064'!$I10+'P064'!$J10) -> 0 | L10: ='P064'!$B10-'P064'!$K10 -> 0
A11: Julio | K11: ='P064'!$B11-('P064'!$C11+'P064'!$D11+'P064'!$E11+'P064'!$F11+'P064'!$G11+'P064'!$H11+'P064'!$I11+'P064'!$J11) -> 0 | L11: ='P064'!$B11-'P064'!$K11 -> 0
A12: Agosto | K12: ='P064'!$B12-('P064'!$C12+'P064'!$D12+'P064'!$E12+'P064'!$F12+'P064'!$G12+'P064'!$H12+'P064'!$I12+'P064'!$J12) -> 0 | L12: ='P064'!$B12-'P064'!$K12 -> 0
A13: Septiembre | K13: ='P064'!$B13-('P064'!$C13+'P064'!$D13+'P064'!$E13+'P064'!$F13+'P064'!$G13+'P064'!$H13+'P064'!$I13+'P064'!$J13) -> 0 | L13: ='P064'!$B13-'P064'!$K13 -> 0
A14: Octubre | K14: ='P064'!$B14-('P064'!$C14+'P064'!$D14+'P064'!$E14+'P064'!$F14+'P064'!$G14+'P064'!$H14+'P064'!$I14+'P064'!$J14) -> 0 | L14: ='P064'!$B14-'P064'!$K14 -> 0
A15: Noviembre | K15: ='P064'!$B15-('P064'!$C15+'P064'!$D15+'P064'!$E15+'P064'!$F15+'P064'!$G15+'P064'!$H15+'P064'!$I15+'P064'!$J15) -> 0 | L15: ='P064'!$B15-'P064'!$K15 -> 0
A16: Diciembre | K16: ='P064'!$B16-('P064'!$C16+'P064'!$D16+'P064'!$E16+'P064'!$F16+'P064'!$G16+'P064'!$H16+'P064'!$I16+'P064'!$J16) -> 0 | L16: ='P064'!$B16-'P064'!$K16 -> 0
A18: NRO DE RECIBOS DE LOS PAGOS
C19: RECIBO 1 | D19: RECIBO 2 | E19: RECIBO 3 | F19: RECIBO 4 | G19: RECIBO 5 | H19: RECIBO 6 | I19: RECIBO 7 | J19: RECIBO 8
A20: Enero
A21: Febrero
A22: Marzo
A23: Abril
A24: Mayo
A25: Junio
A26: Julio
A27: Agosto
A28: Septiembre
A29: Octubre
A30: Noviembre
A31: Diciembre

Sheet P065
A3: PAGOS DEL ALQUILER
B4: COSTO | C4: PAGO 1 | D4: PAGO 2 | E4: PAGO 3 | F4: PAGO 4 | G4: PAGO 5 | H4: PAGO 6 | I4: PAGO 7 | J4: PAGO 8 | K4: SALDO | L4: RECAUDADO
A5: Enero | K5: ='P065'!$B5-('P065'!$C5+'P065'!$D5+'P065'!$E5+'P065'!$F5+'P065'!$G5+'P065'!$H5+'P065'!$I5+'P065'!$J5) -> 0 | L5: ='P065'!$B5-'P065'!$K5 -> 0
A6: Febrero | K6: ='P065'!$B6-('P065'!$C6+'P065'!$D6+'P065'!$E6+'P065'!$F6+'P065'!$G6+'P065'!$H6+'P065'!$I6+'P065'!$J6) -> 0 | L6: ='P065'!$B6-'P065'!$K6 -> 0
A7: Marzo | K7: ='P065'!$B7-('P065'!$C7+'P065'!$D7+'P065'!$E7+'P065'!$F7+'P065'!$G7+'P065'!$H7+'P065'!$I7+'P065'!$J7) -> 0 | L7: ='P065'!$B7-'P065'!$K7 -> 0
A8: Abril | K8: ='P065'!$B8-('P065'!$C8+'P065'!$D8+'P065'!$E8+'P065'!$F8+'P065'!$G8+'P065'!$H8+'P065'!$I8+'P065'!$J8) -> 0 | L8: ='P065'!$B8-'P065'!$K8 -> 0
A9: Mayo | K9: ='P065'!$B9-('P065'!$C9+'P065'!$D9+'P065'!$E9+'P065'!$F9+'P065'!$G9+'P065'!$H9+'P065'!$I9+'P065'!$J9) -> 0 | L9: ='P065'!$B9-'P065'!$K9 -> 0
A10: Junio | K10: ='P065'!$B10-('P065'!$C10+'P065'!$D10+'P065'!$E10+'P065'!$F10+'P065'!$G10+'P065'!$H10+'P065'!$I10+'P065'!$J10) -> 0 | L10: ='P065'!$B10-'P065'!$K10 -> 0
A11: Julio | K11: ='P065'!$B11-('P065'!$C11+'P065'!$D11+'P065'!$E11+'P065'!$F11+'P065'!$G11+'P065'!$H11+'P065'!$I11+'P065'!$J11) -> 0 | L11: ='P065'!$B11-'P065'!$K11 -> 0
A12: Agosto | K12: ='P065'!$B12-('P065'!$C12+'P065'!$D12+'P065'!$E12+'P065'!$F12+'P065'!$G12+'P065'!$H12+'P065'!$I12+'P065'!$J12) -> 0 | L12: ='P065'!$B12-'P065'!$K12 -> 0
A13: Septiembre | K13: ='P065'!$B13-('P065'!$C13+'P065'!$D13+'P065'!$E13+'P065'!$F13+'P065'!$G13+'P065'!$H13+'P065'!$I13+'P065'!$J13) -> 0 | L13: ='P065'!$B13-'P065'!$K13 -> 0
A14: Octubre | K14: ='P065'!$B14-('P065'!$C14+'P065'!$D14+'P065'!$E14+'P065'!$F14+'P065'!$G14+'P065'!$H14+'P065'!$I14+'P065'!$J14) -> 0 | L14: ='P065'!$B14-'P065'!$K14 -> 0
A15: Noviembre | K15: ='P065'!$B15-('P065'!$C15+'P065'!$D15+'P065'!$E15+'P065'!$F15+'P065'!$G15+'P065'!$H15+'P065'!$I15+'P065'!$J15) -> 0 | L15: ='P065'!$B15-'P065'!$K15 -> 0
A16: Diciembre | K16: ='P065'!$B16-('P065'!$C16+'P065'!$D16+'P065'!$E16+'P065'!$F16+'P065'!$G16+'P065'!$H16+'P065'!$I16+'P065'!$J16) -> 0 | L16: ='P065'!$B16-'P065'!$K16 -> 0
A18: NRO DE RECIBOS DE LOS PAGOS
C19: RECIBO 1 | D19: RECIBO 2 | E19: RECIBO 3 | F19: RECIBO 4 | G19: RECIBO 5 | H19: RECIBO 6 | I19: RECIBO 7 | J19: RECIBO 8
A20: Enero
A21: Febrero
A22: Marzo
A23: Abril
A24: Mayo
A25: Junio
A26: Julio
A27: Agosto
A28: Septiembre
A29: Octubre
A30: Noviembre
A31: Diciembre

Sheet P066
A3: PAGOS DEL ALQUILER
B4: COSTO | C4: PAGO 1 | D4: PAGO 2 | E4: PAGO 3 | F4: PAGO 4 | G4: PAGO 5 | H4: PAGO 6 | I4: PAGO 7 | J4: PAGO 8 | K4: SALDO | L4: RECAUDADO
A5: Enero | K5: ='P066'!$B5-('P066'!$C5+'P066'!$D5+'P066'!$E5+'P066'!$F5+'P066'!$G5+'P066'!$H5+'P066'!$I5+'P066'!$J5) -> 0 | L5: ='P066'!$B5-'P066'!$K5 -> 0
A6: Febrero | K6: ='P066'!$B6-('P066'!$C6+'P066'!$D6+'P066'!$E6+'P066'!$F6+'P066'!$G6+'P066'!$H6+'P066'!$I6+'P066'!$J6) -> 0 | L6: ='P066'!$B6-'P066'!$K6 -> 0
A7: Marzo | K7: ='P066'!$B7-('P066'!$C7+'P066'!$D7+'P066'!$E7+'P066'!$F7+'P066'!$G7+'P066'!$H7+'P066'!$I7+'P066'!$J7) -> 0 | L7: ='P066'!$B7-'P066'!$K7 -> 0
A8: Abril | K8: ='P066'!$B8-('P066'!$C8+'P066'!$D8+'P066'!$E8+'P066'!$F8+'P066'!$G8+'P066'!$H8+'P066'!$I8+'P066'!$J8) -> 0 | L8: ='P066'!$B8-'P066'!$K8 -> 0
A9: Mayo | K9: ='P066'!$B9-('P066'!$C9+'P066'!$D9+'P066'!$E9+'P066'!$F9+'P066'!$G9+'P066'!$H9+'P066'!$I9+'P066'!$J9) -> 0 | L9: ='P066'!$B9-'P066'!$K9 -> 0
A10: Junio | K10: ='P066'!$B10-('P066'!$C10+'P066'!$D10+'P066'!$E10+'P066'!$F10+'P066'!$G10+'P066'!$H10+'P066'!$I10+'P066'!$J10) -> 0 | L10: ='P066'!$B10-'P066'!$K10 -> 0
A11: Julio | K11: ='P066'!$B11-('P066'!$C11+'P066'!$D11+'P066'!$E11+'P066'!$F11+'P066'!$G11+'P066'!$H11+'P066'!$I11+'P066'!$J11) -> 0 | L11: ='P066'!$B11-'P066'!$K11 -> 0
A12: Agosto | K12: ='P066'!$B12-('P066'!$C12+'P066'!$D12+'P066'!$E12+'P066'!$F12+'P066'!$G12+'P066'!$H12+'P066'!$I12+'P066'!$J12) -> 0 | L12: ='P066'!$B12-'P066'!$K12 -> 0
A13: Septiembre | K13: ='P066'!$B13-('P066'!$C13+'P066'!$D13+'P066'!$E13+'P066'!$F13+'P066'!$G13+'P066'!$H13+'P066'!$I13+'P066'!$J13) -> 0 | L13: ='P066'!$B13-'P066'!$K13 -> 0
A14: Octubre | K14: ='P066'!$B14-('P066'!$C14+'P066'!$D14+'P066'!$E14+'P066'!$F14+'P066'!$G14+'P066'!$H14+'P066'!$I14+'P066'!$J14) -> 0 | L14: ='P066'!$B14-'P066'!$K14 -> 0
A15: Noviembre | K15: ='P066'!$B15-('P066'!$C15+'P066'!$D15+'P066'!$E15+'P066'!$F15+'P066'!$G15+'P066'!$H15+'P066'!$I15+'P066'!$J15) -> 0 | L15: ='P066'!$B15-'P066'!$K15 -> 0
A16: Diciembre | K16: ='P066'!$B16-('P066'!$C16+'P066'!$D16+'P066'!$E16+'P066'!$F16+'P066'!$G16+'P066'!$H16+'P066'!$I16+'P066'!$J16) -> 0 | L16: ='P066'!$B16-'P066'!$K16 -> 0
A18: NRO DE RECIBOS DE LOS PAGOS
C19: RECIBO 1 | D19: RECIBO 2 | E19: RECIBO 3 | F19: RECIBO 4 | G19: RECIBO 5 | H19: RECIBO 6 | I19: RECIBO 7 | J19: RECIBO 8
A20: Enero
A21: Febrero
A22: Marzo
A23: Abril
A24: Mayo
A25: Junio
A26: Julio
A27: Agosto
A28: Septiembre
A29: Octubre
A30: Noviembre
A31: Diciembre

Sheet P067
A3: PAGOS DEL ALQUILER
B4: COSTO | C4: PAGO 1 | D4: PAGO 2 | E4: PAGO 3 | F4: PAGO 4 | G4: PAGO 5 | H4: PAGO 6 | I4: PAGO 7 | J4: PAGO 8 | K4: SALDO | L4: RECAUDADO
A5: Enero | K5: ='P067'!$B5-('P067'!$C5+'P067'!$D5+'P067'!$E5+'P067'!$F5+'P067'!$G5+'P067'!$H5+'P067'!$I5+'P067'!$J5) -> 0 | L5: ='P067'!$B5-'P067'!$K5 -> 0
A6: Febrero | K6: ='P067'!$B6-('P067'!$C6+'P067'!$D6+'P067'!$E6+'P067'!$F6+'P067'!$G6+'P067'!$H6+'P067'!$I6+'P067'!$J6) -> 0 | L6: ='P067'!$B6-'P067'!$K6 -> 0
A7: Marzo | K7: ='P067'!$B7-('P067'!$C7+'P067'!$D7+'P067'!$E7+'P067'!$F7+'P067'!$G7+'P067'!$H7+'P067'!$I7+'P067'!$J7) -> 0 | L7: ='P067'!$B7-'P067'!$K7 -> 0
A8: Abril | K8: ='P067'!$B8-('P067'!$C8+'P067'!$D8+'P067'!$E8+'P067'!$F8+'P067'!$G8+'P067'!$H8+'P067'!$I8+'P067'!$J8) -> 0 | L8: ='P067'!$B8-'P067'!$K8 -> 0
A9: Mayo | K9: ='P067'!$B9-('P067'!$C9+'P067'!$D9+'P067'!$E9+'P067'!$F9+'P067'!$G9+'P067'!$H9+'P067'!$I9+'P067'!$J9) -> 0 | L9: ='P067'!$B9-'P067'!$K9 -> 0
A10: Junio | K10: ='P067'!$B10-('P067'!$C10+'P067'!$D10+'P067'!$E10+'P067'!$F10+'P067'!$G10+'P067'!$H10+'P067'!$I10+'P067'!$J10) -> 0 | L10: ='P067'!$B10-'P067'!$K10 -> 0
A11: Julio | K11: ='P067'!$B11-('P067'!$C11+'P067'!$D11+'P067'!$E11+'P067'!$F11+'P067'!$G11+'P067'!$H11+'P067'!$I11+'P067'!$J11) -> 0 | L11: ='P067'!$B11-'P067'!$K11 -> 0
A12: Agosto | K12: ='P067'!$B12-('P067'!$C12+'P067'!$D12+'P067'!$E12+'P067'!$F12+'P067'!$G12+'P067'!$H12+'P067'!$I12+'P067'!$J12) -> 0 | L12: ='P067'!$B12-'P067'!$K12 -> 0
A13: Septiembre | K13: ='P067'!$B13-('P067'!$C13+'P067'!$D13+'P067'!$E13+'P067'!$F13+'P067'!$G13+'P067'!$H13+'P067'!$I13+'P067'!$J13) -> 0 | L13: ='P067'!$B13-'P067'!$K13 -> 0
A14: Octubre | K14: ='P067'!$B14-('P067'!$C14+'P067'!$D14+'P067'!$E14+'P067'!$F14+'P067'!$G14+'P067'!$H14+'P067'!$I14+'P067'!$J14) -> 0 | L14: ='P067'!$B14-'P067'!$K14 -> 0
A15: Noviembre | K15: ='P067'!$B15-('P067'!$C15+'P067'!$D15+'P067'!$E15+'P067'!$F15+'P067'!$G15+'P067'!$H15+'P067'!$I15+'P067'!$J15) -> 0 | L15: ='P067'!$B15-'P067'!$K15 -> 0
A16: Diciembre | K16: ='P067'!$B16-('P067'!$C16+'P067'!$D16+'P067'!$E16+'P067'!$F16+'P067'!$G16+'P067'!$H16+'P067'!$I16+'P067'!$J16) -> 0 | L16: ='P067'!$B16-'P067'!$K16 -> 0
A18: NRO DE RECIBOS DE LOS PAGOS
C19: RECIBO 1 | D19: RECIBO 2 | E19: RECIBO 3 | F19: RECIBO 4 | G19: RECIBO 5 | H19: RECIBO 6 | I19: RECIBO 7 | J19: RECIBO 8
A20: Enero
A21: Febrero
A22: Marzo
A23: Abril
A24: Mayo
A25: Junio
A26: Julio
A27: Agosto
A28: Septiembre
A29: Octubre
A30: Noviembre
A31: Diciembre

Sheet P068
A3: PAGOS DEL ALQUILER
B4: COSTO | C4: PAGO 1 | D4: PAGO 2 | E4: PAGO 3 | F4: PAGO 4 | G4: PAGO 5 | H4: PAGO 6 | I4: PAGO 7 | J4: PAGO 8 | K4: SALDO | L4: RECAUDADO
A5: Enero | K5: ='P068'!$B5-('P068'!$C5+'P068'!$D5+'P068'!$E5+'P068'!$F5+'P068'!$G5+'P068'!$H5+'P068'!$I5+'P068'!$J5) -> 0 | L5: ='P068'!$B5-'P068'!$K5 -> 0
A6: Febrero | K6: ='P068'!$B6-('P068'!$C6+'P068'!$D6+'P068'!$E6+'P068'!$F6+'P068'!$G6+'P068'!$H6+'P068'!$I6+'P068'!$J6) -> 0 | L6: ='P068'!$B6-'P068'!$K6 -> 0
A7: Marzo | K7: ='P068'!$B7-('P068'!$C7+'P068'!$D7+'P068'!$E7+'P068'!$F7+'P068'!$G7+'P068'!$H7+'P068'!$I7+'P068'!$J7) -> 0 | L7: ='P068'!$B7-'P068'!$K7 -> 0
A8: Abril | K8: ='P068'!$B8-('P068'!$C8+'P068'!$D8+'P068'!$E8+'P068'!$F8+'P068'!$G8+'P068'!$H8+'P068'!$I8+'P068'!$J8) -> 0 | L8: ='P068'!$B8-'P068'!$K8 -> 0
A9: Mayo | K9: ='P068'!$B9-('P068'!$C9+'P068'!$D9+'P068'!$E9+'P068'!$F9+'P068'!$G9+'P068'!$H9+'P068'!$I9+'P068'!$J9) -> 0 | L9: ='P068'!$B9-'P068'!$K9 -> 0
A10: Junio | K10: ='P068'!$B10-('P068'!$C10+'P068'!$D10+'P068'!$E10+'P068'!$F10+'P068'!$G10+'P068'!$H10+'P068'!$I10+'P068'!$J10) -> 0 | L10: ='P068'!$B10-'P068'!$K10 -> 0
A11: Julio | K11: ='P068'!$B11-('P068'!$C11+'P068'!$D11+'P068'!$E11+'P068'!$F11+'P068'!$G11+'P068'!$H11+'P068'!$I11+'P068'!$J11) -> 0 | L11: ='P068'!$B11-'P068'!$K11 -> 0
A12: Agosto | K12: ='P068'!$B12-('P068'!$C12+'P068'!$D12+'P068'!$E12+'P068'!$F12+'P068'!$G12+'P068'!$H12+'P068'!$I12+'P068'!$J12) -> 0 | L12: ='P068'!$B12-'P068'!$K12 -> 0
A13: Septiembre | K13: ='P068'!$B13-('P068'!$C13+'P068'!$D13+'P068'!$E13+'P068'!$F13+'P068'!$G13+'P068'!$H13+'P068'!$I13+'P068'!$J13) -> 0 | L13: ='P068'!$B13-'P068'!$K13 -> 0
A14: Octubre | K14: ='P068'!$B14-('P068'!$C14+'P068'!$D14+'P068'!$E14+'P068'!$F14+'P068'!$G14+'P068'!$H14+'P068'!$I14+'P068'!$J14) -> 0 | L14: ='P068'!$B14-'P068'!$K14 -> 0
A15: Noviembre | K15: ='P068'!$B15-('P068'!$C15+'P068'!$D15+'P068'!$E15+'P068'!$F15+'P068'!$G15+'P068'!$H15+'P068'!$I15+'P068'!$J15) -> 0 | L15: ='P068'!$B15-'P068'!$K15 -> 0
A16: Diciembre | K16: ='P068'!$B16-('P068'!$C16+'P068'!$D16+'P068'!$E16+'P068'!$F16+'P068'!$G16+'P068'!$H16+'P068'!$I16+'P068'!$J16) -> 0 | L16: ='P068'!$B16-'P068'!$K16 -> 0
A18: NRO DE RECIBOS DE LOS PAGOS
C19: RECIBO 1 | D19: RECIBO 2 | E19: RECIBO 3 | F19: RECIBO 4 | G19: RECIBO 5 | H19: RECIBO 6 | I19: RECIBO 7 | J19: RECIBO 8
A20: Enero
A21: Febrero
A22: Marzo
A23: Abril
A24: Mayo
A25: Junio
A26: Julio
A27: Agosto
A28: Septiembre
A29: Octubre
A30: Noviembre
A31: Diciembre

Sheet P069
A3: PAGOS DEL ALQUILER
B4: COSTO | C4: PAGO 1 | D4: PAGO 2 | E4: PAGO 3 | F4: PAGO 4 | G4: PAGO 5 | H4: PAGO 6 | I4: PAGO 7 | J4: PAGO 8 | K4: SALDO | L4: RECAUDADO
A5: Enero | K5: ='P069'!$B5-('P069'!$C5+'P069'!$D5+'P069'!$E5+'P069'!$F5+'P069'!$G5+'P069'!$H5+'P069'!$I5+'P069'!$J5) -> 0 | L5: ='P069'!$B5-'P069'!$K5 -> 0
A6: Febrero | K6: ='P069'!$B6-('P069'!$C6+'P069'!$D6+'P069'!$E6+'P069'!$F6+'P069'!$G6+'P069'!$H6+'P069'!$I6+'P069'!$J6) -> 0 | L6: ='P069'!$B6-'P069'!$K6 -> 0
A7: Marzo | K7: ='P069'!$B7-('P069'!$C7+'P069'!$D7+'P069'!$E7+'P069'!$F7+'P069'!$G7+'P069'!$H7+'P069'!$I7+'P069'!$J7) -> 0 | L7: ='P069'!$B7-'P069'!$K7 -> 0
A8: Abril | K8: ='P069'!$B8-('P069'!$C8+'P069'!$D8+'P069'!$E8+'P069'!$F8+'P069'!$G8+'P069'!$H8+'P069'!$I8+'P069'!$J8) -> 0 | L8: ='P069'!$B8-'P069'!$K8 -> 0
A9: Mayo | K9: ='P069'!$B9-('P069'!$C9+'P069'!$D9+'P069'!$E9+'P069'!$F9+'P069'!$G9+'P069'!$H9+'P069'!$I9+'P069'!$J9) -> 0 | L9: ='P069'!$B9-'P069'!$K9 -> 0
A10: Junio | K10: ='P069'!$B10-('P069'!$C10+'P069'!$D10+'P069'!$E10+'P069'!$F10+'P069'!$G10+'P069'!$H10+'P069'!$I10+'P069'!$J10) -> 0 | L10: ='P069'!$B10-'P069'!$K10 -> 0
A11: Julio | K11: ='P069'!$B11-('P069'!$C11+'P069'!$D11+'P069'!$E11+'P069'!$F11+'P069'!$G11+'P069'!$H11+'P069'!$I11+'P069'!$J11) -> 0 | L11: ='P069'!$B11-'P069'!$K11 -> 0
A12: Agosto | K12: ='P069'!$B12-('P069'!$C12+'P069'!$D12+'P069'!$E12+'P069'!$F12+'P069'!$G12+'P069'!$H12+'P069'!$I12+'P069'!$J12) -> 0 | L12: ='P069'!$B12-'P069'!$K12 -> 0
A13: Septiembre | K13: ='P069'!$B13-('P069'!$C13+'P069'!$D13+'P069'!$E13+'P069'!$F13+'P069'!$G13+'P069'!$H13+'P069'!$I13+'P069'!$J13) -> 0 | L13: ='P069'!$B13-'P069'!$K13 -> 0
A14: Octubre | K14: ='P069'!$B14-('P069'!$C14+'P069'!$D14+'P069'!$E14+'P069'!$F14+'P069'!$G14+'P069'!$H14+'P069'!$I14+'P069'!$J14) -> 0 | L14: ='P069'!$B14-'P069'!$K14 -> 0
A15: Noviembre | K15: ='P069'!$B15-('P069'!$C15+'P069'!$D15+'P069'!$E15+'P069'!$F15+'P069'!$G15+'P069'!$H15+'P069'!$I15+'P069'!$J15) -> 0 | L15: ='P069'!$B15-'P069'!$K15 -> 0
A16: Diciembre | K16: ='P069'!$B16-('P069'!$C16+'P069'!$D16+'P069'!$E16+'P069'!$F16+'P069'!$G16+'P069'!$H16+'P069'!$I16+'P069'!$J16) -> 0 | L16: ='P069'!$B16-'P069'!$K16 -> 0
A18: NRO DE RECIBOS DE LOS PAGOS
C19: RECIBO 1 | D19: RECIBO 2 | E19: RECIBO 3 | F19: RECIBO 4 | G19: RECIBO 5 | H19: RECIBO 6 | I19: RECIBO 7 | J19: RECIBO 8
A20: Enero
A21: Febrero
A22: Marzo
A23: Abril
A24: Mayo
A25: Junio
A26: Julio
A27: Agosto
A28: Septiembre
A29: Octubre
A30: Noviembre
A31: Diciembre

Sheet P070
A1: Pto.69/70/isl3/3/7 | C1: PANIAGUA LUCIA
A3: PAGOS DEL ALQUILER
B4: COSTO | C4: PAGO 1 | D4: PAGO 2 | E4: PAGO 3 | F4: PAGO 4 | G4: PAGO 5 | H4: PAGO 6 | I4: PAGO 7 | J4: PAGO 8 | K4: SALDO | L4: RECAUDADO
A5: Enero | B5: 857300 | C5: 857300 | K5: ='P070'!$B5-('P070'!$C5+'P070'!$D5+'P070'!$E5+'P070'!$F5+'P070'!$G5+'P070'!$H5+'P070'!$I5+'P070'!$J5) -> 0 | L5: ='P070'!$B5-'P070'!$K5 -> 857300 | M5: 54000
A6: Febrero | B6: 857300 | C6: 857300 | K6: ='P070'!$B6-('P070'!$C6+'P070'!$D6+'P070'!$E6+'P070'!$F6+'P070'!$G6+'P070'!$H6+'P070'!$I6+'P070'!$J6) -> 0 | L6: ='P070'!$B6-'P070'!$K6 -> 857300 | M6: 54000
A7: Marzo | K7: ='P070'!$B7-('P070'!$C7+'P070'!$D7+'P070'!$E7+'P070'!$F7+'P070'!$G7+'P070'!$H7+'P070'!$I7+'P070'!$J7) -> 0 | L7: ='P070'!$B7-'P070'!$K7 -> 0
A8: Abril | K8: ='P070'!$B8-('P070'!$C8+'P070'!$D8+'P070'!$E8+'P070'!$F8+'P070'!$G8+'P070'!$H8+'P070'!$I8+'P070'!$J8) -> 0 | L8: ='P070'!$B8-'P070'!$K8 -> 0
A9: Mayo | K9: ='P070'!$B9-('P070'!$C9+'P070'!$D9+'P070'!$E9+'P070'!$F9+'P070'!$G9+'P070'!$H9+'P070'!$I9+'P070'!$J9) -> 0 | L9: ='P070'!$B9-'P070'!$K9 -> 0
A10: Junio | K10: ='P070'!$B10-('P070'!$C10+'P070'!$D10+'P070'!$E10+'P070'!$F10+'P070'!$G10+'P070'!$H10+'P070'!$I10+'P070'!$J10) -> 0 | L10: ='P070'!$B10-'P070'!$K10 -> 0
A11: Julio | K11: ='P070'!$B11-('P070'!$C11+'P070'!$D11+'P070'!$E11+'P070'!$F11+'P070'!$G11+'P070'!$H11+'P070'!$I11+'P070'!$J11) -> 0 | L11: ='P070'!$B11-'P070'!$K11 -> 0
A12: Agosto | K12: ='P070'!$B12-('P070'!$C12+'P070'!$D12+'P070'!$E12+'P070'!$F12+'P070'!$G12+'P070'!$H12+'P070'!$I12+'P070'!$J12) -> 0 | L12: ='P070'!$B12-'P070'!$K12 -> 0
A13: Septiembre | K13: ='P070'!$B13-('P070'!$C13+'P070'!$D13+'P070'!$E13+'P070'!$F13+'P070'!$G13+'P070'!$H13+'P070'!$I13+'P070'!$J13) -> 0 | L13: ='P070'!$B13-'P070'!$K13 -> 0
A14: Octubre | K14: ='P070'!$B14-('P070'!$C14+'P070'!$D14+'P070'!$E14+'P070'!$F14+'P070'!$G14+'P070'!$H14+'P070'!$I14+'P070'!$J14) -> 0 | L14: ='P070'!$B14-'P070'!$K14 -> 0
A15: Noviembre | K15: ='P070'!$B15-('P070'!$C15+'P070'!$D15+'P070'!$E15+'P070'!$F15+'P070'!$G15+'P070'!$H15+'P070'!$I15+'P070'!$J15) -> 0 | L15: ='P070'!$B15-'P070'!$K15 -> 0
A16: Diciembre | K16: ='P070'!$B16-('P070'!$C16+'P070'!$D16+'P070'!$E16+'P070'!$F16+'P070'!$G16+'P070'!$H16+'P070'!$I16+'P070'!$J16) -> 0 | L16: ='P070'!$B16-'P070'!$K16 -> 0
A18: NRO DE RECIBOS DE LOS PAGOS
C19: RECIBO 1 | D19: RECIBO 2 | E19: RECIBO 3 | F19: RECIBO 4 | G19: RECIBO 5 | H19: RECIBO 6 | I19: RECIBO 7 | J19: RECIBO 8
A20: Enero | C20: 9631
A21: Febrero | C21: 9670
A22: Marzo
A23: Abril
A24: Mayo
A25: Junio
A26: Julio
A27: Agosto
A28: Septiembre
A29: Octubre
A30: Noviembre
A31: Diciembre

Sheet P071
A3: PAGOS DEL ALQUILER
B4: COSTO | C4: PAGO 1 | D4: PAGO 2 | E4: PAGO 3 | F4: PAGO 4 | G4: PAGO 5 | H4: PAGO 6 | I4: PAGO 7 | J4: PAGO 8 | K4: SALDO | L4: RECAUDADO
A5: Enero | K5: ='P071'!$B5-('P071'!$C5+'P071'!$D5+'P071'!$E5+'P071'!$F5+'P071'!$G5+'P071'!$H5+'P071'!$I5+'P071'!$J5) -> 0 | L5: ='P071'!$B5-'P071'!$K5 -> 0
A6: Febrero | K6: ='P071'!$B6-('P071'!$C6+'P071'!$D6+'P071'!$E6+'P071'!$F6+'P071'!$G6+'P071'!$H6+'P071'!$I6+'P071'!$J6) -> 0 | L6: ='P071'!$B6-'P071'!$K6 -> 0
A7: Marzo | K7: ='P071'!$B7-('P071'!$C7+'P071'!$D7+'P071'!$E7+'P071'!$F7+'P071'!$G7+'P071'!$H7+'P071'!$I7+'P071'!$J7) -> 0 | L7: ='P071'!$B7-'P071'!$K7 -> 0
A8: Abril | K8: ='P071'!$B8-('P071'!$C8+'P071'!$D8+'P071'!$E8+'P071'!$F8+'P071'!$G8+'P071'!$H8+'P071'!$I8+'P071'!$J8) -> 0 | L8: ='P071'!$B8-'P071'!$K8 -> 0
A9: Mayo | K9: ='P071'!$B9-('P071'!$C9+'P071'!$D9+'P071'!$E9+'P071'!$F9+'P071'!$G9+'P071'!$H9+'P071'!$I9+'P071'!$J9) -> 0 | L9: ='P071'!$B9-'P071'!$K9 -> 0
A10: Junio | K10: ='P071'!$B10-('P071'!$C10+'P071'!$D10+'P071'!$E10+'P071'!$F10+'P071'!$G10+'P071'!$H10+'P071'!$I10+'P071'!$J10) -> 0 | L10: ='P071'!$B10-'P071'!$K10 -> 0
A11: Julio | K11: ='P071'!$B11-('P071'!$C11+'P071'!$D11+'P071'!$E11+'P071'!$F11+'P071'!$G11+'P071'!$H11+'P071'!$I11+'P071'!$J11) -> 0 | L11: ='P071'!$B11-'P071'!$K11 -> 0
A12: Agosto | K12: ='P071'!$B12-('P071'!$C12+'P071'!$D12+'P071'!$E12+'P071'!$F12+'P071'!$G12+'P071'!$H12+'P071'!$I12+'P071'!$J12) -> 0 | L12: ='P071'!$B12-'P071'!$K12 -> 0
A13: Septiembre | K13: ='P071'!$B13-('P071'!$C13+'P071'!$D13+'P071'!$E13+'P071'!$F13+'P071'!$G13+'P071'!$H13+'P071'!$I13+'P071'!$J13) -> 0 | L13: ='P071'!$B13-'P071'!$K13 -> 0
A14: Octubre | K14: ='P071'!$B14-('P071'!$C14+'P071'!$D14+'P071'!$E14+'P071'!$F14+'P071'!$G14+'P071'!$H14+'P071'!$I14+'P071'!$J14) -> 0 | L14: ='P071'!$B14-'P071'!$K14 -> 0
A15: Noviembre | K15: ='P071'!$B15-('P071'!$C15+'P071'!$D15+'P071'!$E15+'P071'!$F15+'P071'!$G15+'P071'!$H15+'P071'!$I15+'P071'!$J15) -> 0 | L15: ='P071'!$B15-'P071'!$K15 -> 0
A16: Diciembre | K16: ='P071'!$B16-('P071'!$C16+'P071'!$D16+'P071'!$E16+'P071'!$F16+'P071'!$G16+'P071'!$H16+'P071'!$I16+'P071'!$J16) -> 0 | L16: ='P071'!$B16-'P071'!$K16 -> 0
A18: NRO DE RECIBOS DE LOS PAGOS
C19: RECIBO 1 | D19: RECIBO 2 | E19: RECIBO 3 | F19: RECIBO 4 | G19: RECIBO 5 | H19: RECIBO 6 | I19: RECIBO 7 | J19: RECIBO 8
A20: Enero
A21: Febrero
A22: Marzo
A23: Abril
A24: Mayo
A25: Junio
A26: Julio
A27: Agosto
A28: Septiembre
A29: Octubre
A30: Noviembre
A31: Diciembre

Sheet P072
A3: PAGOS DEL ALQUILER
B4: COSTO | C4: PAGO 1 | D4: PAGO 2 | E4: PAGO 3 | F4: PAGO 4 | G4: PAGO 5 | H4: PAGO 6 | I4: PAGO 7 | J4: PAGO 8 | K4: SALDO | L4: RECAUDADO
A5: Enero | K5: ='P072'!$B5-('P072'!$C5+'P072'!$D5+'P072'!$E5+'P072'!$F5+'P072'!$G5+'P072'!$H5+'P072'!$I5+'P072'!$J5) -> 0 | L5: ='P072'!$B5-'P072'!$K5 -> 0
A6: Febrero | K6: ='P072'!$B6-('P072'!$C6+'P072'!$D6+'P072'!$E6+'P072'!$F6+'P072'!$G6+'P072'!$H6+'P072'!$I6+'P072'!$J6) -> 0 | L6: ='P072'!$B6-'P072'!$K6 -> 0
A7: Marzo | K7: ='P072'!$B7-('P072'!$C7+'P072'!$D7+'P072'!$E7+'P072'!$F7+'P072'!$G7+'P072'!$H7+'P072'!$I7+'P072'!$J7) -> 0 | L7: ='P072'!$B7-'P072'!$K7 -> 0
A8: Abril | K8: ='P072'!$B8-('P072'!$C8+'P072'!$D8+'P072'!$E8+'P072'!$F8+'P072'!$G8+'P072'!$H8+'P072'!$I8+'P072'!$J8) -> 0 | L8: ='P072'!$B8-'P072'!$K8 -> 0
A9: Mayo | K9: ='P072'!$B9-('P072'!$C9+'P072'!$D9+'P072'!$E9+'P072'!$F9+'P072'!$G9+'P072'!$H9+'P072'!$I9+'P072'!$J9) -> 0 | L9: ='P072'!$B9-'P072'!$K9 -> 0
A10: Junio | K10: ='P072'!$B10-('P072'!$C10+'P072'!$D10+'P072'!$E10+'P072'!$F10+'P072'!$G10+'P072'!$H10+'P072'!$I10+'P072'!$J10) -> 0 | L10: ='P072'!$B10-'P072'!$K10 -> 0
A11: Julio | K11: ='P072'!$B11-('P072'!$C11+'P072'!$D11+'P072'!$E11+'P072'!$F11+'P072'!$G11+'P072'!$H11+'P072'!$I11+'P072'!$J11) -> 0 | L11: ='P072'!$B11-'P072'!$K11 -> 0
A12: Agosto | K12: ='P072'!$B12-('P072'!$C12+'P072'!$D12+'P072'!$E12+'P072'!$F12+'P072'!$G12+'P072'!$H12+'P072'!$I12+'P072'!$J12) -> 0 | L12: ='P072'!$B12-'P072'!$K12 -> 0
A13: Septiembre | K13: ='P072'!$B13-('P072'!$C13+'P072'!$D13+'P072'!$E13+'P072'!$F13+'P072'!$G13+'P072'!$H13+'P072'!$I13+'P072'!$J13) -> 0 | L13: ='P072'!$B13-'P072'!$K13 -> 0
A14: Octubre | K14: ='P072'!$B14-('P072'!$C14+'P072'!$D14+'P072'!$E14+'P072'!$F14+'P072'!$G14+'P072'!$H14+'P072'!$I14+'P072'!$J14) -> 0 | L14: ='P072'!$B14-'P072'!$K14 -> 0
A15: Noviembre | K15: ='P072'!$B15-('P072'!$C15+'P072'!$D15+'P072'!$E15+'P072'!$F15+'P072'!$G15+'P072'!$H15+'P072'!$I15+'P072'!$J15) -> 0 | L15: ='P072'!$B15-'P072'!$K15 -> 0
A16: Diciembre | K16: ='P072'!$B16-('P072'!$C16+'P072'!$D16+'P072'!$E16+'P072'!$F16+'P072'!$G16+'P072'!$H16+'P072'!$I16+'P072'!$J16) -> 0 | L16: ='P072'!$B16-'P072'!$K16 -> 0
A18: NRO DE RECIBOS DE LOS PAGOS
C19: RECIBO 1 | D19: RECIBO 2 | E19: RECIBO 3 | F19: RECIBO 4 | G19: RECIBO 5 | H19: RECIBO 6 | I19: RECIBO 7 | J19: RECIBO 8
A20: Enero
A21: Febrero
A22: Marzo
A23: Abril
A24: Mayo
A25: Junio
A26: Julio
A27: Agosto
A28: Septiembre
A29: Octubre
A30: Noviembre
A31: Diciembre

Sheet P073
A3: PAGOS DEL ALQUILER
B4: COSTO | C4: PAGO 1 | D4: PAGO 2 | E4: PAGO 3 | F4: PAGO 4 | G4: PAGO 5 | H4: PAGO 6 | I4: PAGO 7 | J4: PAGO 8 | K4: SALDO | L4: RECAUDADO
A5: Enero | K5: ='P073'!$B5-('P073'!$C5+'P073'!$D5+'P073'!$E5+'P073'!$F5+'P073'!$G5+'P073'!$H5+'P073'!$I5+'P073'!$J5) -> 0 | L5: ='P073'!$B5-'P073'!$K5 -> 0
A6: Febrero | K6: ='P073'!$B6-('P073'!$C6+'P073'!$D6+'P073'!$E6+'P073'!$F6+'P073'!$G6+'P073'!$H6+'P073'!$I6+'P073'!$J6) -> 0 | L6: ='P073'!$B6-'P073'!$K6 -> 0
A7: Marzo | K7: ='P073'!$B7-('P073'!$C7+'P073'!$D7+'P073'!$E7+'P073'!$F7+'P073'!$G7+'P073'!$H7+'P073'!$I7+'P073'!$J7) -> 0 | L7: ='P073'!$B7-'P073'!$K7 -> 0
A8: Abril | K8: ='P073'!$B8-('P073'!$C8+'P073'!$D8+'P073'!$E8+'P073'!$F8+'P073'!$G8+'P073'!$H8+'P073'!$I8+'P073'!$J8) -> 0 | L8: ='P073'!$B8-'P073'!$K8 -> 0
A9: Mayo | K9: ='P073'!$B9-('P073'!$C9+'P073'!$D9+'P073'!$E9+'P073'!$F9+'P073'!$G9+'P073'!$H9+'P073'!$I9+'P073'!$J9) -> 0 | L9: ='P073'!$B9-'P073'!$K9 -> 0
A10: Junio | K10: ='P073'!$B10-('P073'!$C10+'P073'!$D10+'P073'!$E10+'P073'!$F10+'P073'!$G10+'P073'!$H10+'P073'!$I10+'P073'!$J10) -> 0 | L10: ='P073'!$B10-'P073'!$K10 -> 0
A11: Julio | K11: ='P073'!$B11-('P073'!$C11+'P073'!$D11+'P073'!$E11+'P073'!$F11+'P073'!$G11+'P073'!$H11+'P073'!$I11+'P073'!$J11) -> 0 | L11: ='P073'!$B11-'P073'!$K11 -> 0
A12: Agosto | K12: ='P073'!$B12-('P073'!$C12+'P073'!$D12+'P073'!$E12+'P073'!$F12+'P073'!$G12+'P073'!$H12+'P073'!$I12+'P073'!$J12) -> 0 | L12: ='P073'!$B12-'P073'!$K12 -> 0
A13: Septiembre | K13: ='P073'!$B13-('P073'!$C13+'P073'!$D13+'P073'!$E13+'P073'!$F13+'P073'!$G13+'P073'!$H13+'P073'!$I13+'P073'!$J13) -> 0 | L13: ='P073'!$B13-'P073'!$K13 -> 0
A14: Octubre | K14: ='P073'!$B14-('P073'!$C14+'P073'!$D14+'P073'!$E14+'P073'!$F14+'P073'!$G14+'P073'!$H14+'P073'!$I14+'P073'!$J14) -> 0 | L14: ='P073'!$B14-'P073'!$K14 -> 0
A15: Noviembre | K15: ='P073'!$B15-('P073'!$C15+'P073'!$D15+'P073'!$E15+'P073'!$F15+'P073'!$G15+'P073'!$H15+'P073'!$I15+'P073'!$J15) -> 0 | L15: ='P073'!$B15-'P073'!$K15 -> 0
A16: Diciembre | K16: ='P073'!$B16-('P073'!$C16+'P073'!$D16+'P073'!$E16+'P073'!$F16+'P073'!$G16+'P073'!$H16+'P073'!$I16+'P073'!$J16) -> 0 | L16: ='P073'!$B16-'P073'!$K16 -> 0
A18: NRO DE RECIBOS DE LOS PAGOS
C19: RECIBO 1 | D19: RECIBO 2 | E19: RECIBO 3 | F19: RECIBO 4 | G19: RECIBO 5 | H19: RECIBO 6 | I19: RECIBO 7 | J19: RECIBO 8
A20: Enero
A21: Febrero
A22: Marzo
A23: Abril
A24: Mayo
A25: Junio
A26: Julio
A27: Agosto
A28: Septiembre
A29: Octubre
A30: Noviembre
A31: Diciembre

Sheet PO73
A1: Pto-73 | C1: CASAPAVA YOLANDA
A3: PAGOS DEL ALQUILER
B4: COSTO | C4: PAGO 1 | D4: PAGO 2 | E4: PAGO 3 | F4: PAGO 4 | G4: PAGO 5 | H4: PAGO 6 | I4: PAGO 7 | J4: PAGO 8 | K4: SALDO | L4: RECAUDADO
A5: Enero | B5: 266400 | C5: 266400 | K5: ='PO73'!$B5-('PO73'!$C5+'PO73'!$D5+'PO73'!$E5+'PO73'!$F5+'PO73'!$G5+'PO73'!$H5+'PO73'!$I5+'PO73'!$J5) -> 0 | L5: ='PO73'!$B5-'PO73'!$K5 -> 266400 | M5: 13500
A6: Febrero | B6: 266400 | C6: 1500 | D6: 264900 | K6: ='PO73'!$B6-('PO73'!$C6+'PO73'!$D6+'PO73'!$E6+'PO73'!$F6+'PO73'!$G6+'PO73'!$H6+'PO73'!$I6+'PO73'!$J6) -> 0 | L6: ='PO73'!$B6-'PO73'!$K6 -> 266400 | M6: 13500
A7: Marzo | K7: ='PO73'!$B7-('PO73'!$C7+'PO73'!$D7+'PO73'!$E7+'PO73'!$F7+'PO73'!$G7+'PO73'!$H7+'PO73'!$I7+'PO73'!$J7) -> 0 | L7: ='PO73'!$B7-'PO73'!$K7 -> 0
A8: Abril | K8: ='PO73'!$B8-('PO73'!$C8+'PO73'!$D8+'PO73'!$E8+'PO73'!$F8+'PO73'!$G8+'PO73'!$H8+'PO73'!$I8+'PO73'!$J8) -> 0 | L8: ='PO73'!$B8-'PO73'!$K8 -> 0
A9: Mayo | K9: ='PO73'!$B9-('PO73'!$C9+'PO73'!$D9+'PO73'!$E9+'PO73'!$F9+'PO73'!$G9+'PO73'!$H9+'PO73'!$I9+'PO73'!$J9) -> 0 | L9: ='PO73'!$B9-'PO73'!$K9 -> 0
A10: Junio | K10: ='PO73'!$B10-('PO73'!$C10+'PO73'!$D10+'PO73'!$E10+'PO73'!$F10+'PO73'!$G10+'PO73'!$H10+'PO73'!$I10+'PO73'!$J10) -> 0 | L10: ='PO73'!$B10-'PO73'!$K10 -> 0
A11: Julio | K11: ='PO73'!$B11-('PO73'!$C11+'PO73'!$D11+'PO73'!$E11+'PO73'!$F11+'PO73'!$G11+'PO73'!$H11+'PO73'!$I11+'PO73'!$J11) -> 0 | L11: ='PO73'!$B11-'PO73'!$K11 -> 0
A12: Agosto | K12: ='PO73'!$B12-('PO73'!$C12+'PO73'!$D12+'PO73'!$E12+'PO73'!$F12+'PO73'!$G12+'PO73'!$H12+'PO73'!$I12+'PO73'!$J12) -> 0 | L12: ='PO73'!$B12-'PO73'!$K12 -> 0
A13: Septiembre | K13: ='PO73'!$B13-('PO73'!$C13+'PO73'!$D13+'PO73'!$E13+'PO73'!$F13+'PO73'!$G13+'PO73'!$H13+'PO73'!$I13+'PO73'!$J13) -> 0 | L13: ='PO73'!$B13-'PO73'!$K13 -> 0
A14: Octubre | K14: ='PO73'!$B14-('PO73'!$C14+'PO73'!$D14+'PO73'!$E14+'PO73'!$F14+'PO73'!$G14+'PO73'!$H14+'PO73'!$I14+'PO73'!$J14) -> 0 | L14: ='PO73'!$B14-'PO73'!$K14 -> 0
A15: Noviembre | K15: ='PO73'!$B15-('PO73'!$C15+'PO73'!$D15+'PO73'!$E15+'PO73'!$F15+'PO73'!$G15+'PO73'!$H15+'PO73'!$I15+'PO73'!$J15) -> 0 | L15: ='PO73'!$B15-'PO73'!$K15 -> 0
A16: Diciembre | K16: ='PO73'!$B16-('PO73'!$C16+'PO73'!$D16+'PO73'!$E16+'PO73'!$F16+'PO73'!$G16+'PO73'!$H16+'PO73'!$I16+'PO73'!$J16) -> 0 | L16: ='PO73'!$B16-'PO73'!$K16 -> 0
A18: NRO DE RECIBOS DE LOS PAGOS
C19: RECIBO 1 | D19: RECIBO 2 | E19: RECIBO 3 | F19: RECIBO 4 | G19: RECIBO 5 | H19: RECIBO 6 | I19: RECIBO 7 | J19: RECIBO 8
A20: Enero | C20: 9609
A21: Febrero | C21: 9680
A22: Marzo
A23: Abril
A24: Mayo
A25: Junio
A26: Julio
A27: Agosto
A28: Septiembre
A29: Octubre
A30: Noviembre
A31: Diciembre

Sheet P075
C1: GARCIA LUCIO
A3: PAGOS DEL ALQUILER
B4: COSTO | C4: PAGO 1 | D4: PAGO 2 | E4: PAGO 3 | F4: PAGO 4 | G4: PAGO 5 | H4: PAGO 6 | I4: PAGO 7 | J4: PAGO 8 | K4: SALDO | L4: RECAUDADO
A5: Enero | B5: 222300 | K5: ='P075'!$B5-('P075'!$C5+'P075'!$D5+'P075'!$E5+'P075'!$F5+'P075'!$G5+'P075'!$H5+'P075'!$I5+'P075'!$J5) -> 222300 | L5: ='P075'!$B5-'P075'!$K5 -> 0
A6: Febrero | B6: 222300 | K6: ='P075'!$B6-('P075'!$C6+'P075'!$D6+'P075'!$E6+'P075'!$F6+'P075'!$G6+'P075'!$H6+'P075'!$I6+'P075'!$J6) -> 222300 | L6: ='P075'!$B6-'P075'!$K6 -> 0
A7: Marzo | B7: 222300 | K7: ='P075'!$B7-('P075'!$C7+'P075'!$D7+'P075'!$E7+'P075'!$F7+'P075'!$G7+'P075'!$H7+'P075'!$I7+'P075'!$J7) -> 222300 | L7: ='P075'!$B7-'P075'!$K7 -> 0
A8: Abril | K8: ='P075'!$B8-('P075'!$C8+'P075'!$D8+'P075'!$E8+'P075'!$F8+'P075'!$G8+'P075'!$H8+'P075'!$I8+'P075'!$J8) -> 0 | L8: ='P075'!$B8-'P075'!$K8 -> 0
A9: Mayo | K9: ='P075'!$B9-('P075'!$C9+'P075'!$D9+'P075'!$E9+'P075'!$F9+'P075'!$G9+'P075'!$H9+'P075'!$I9+'P075'!$J9) -> 0 | L9: ='P075'!$B9-'P075'!$K9 -> 0
A10: Junio | K10: ='P075'!$B10-('P075'!$C10+'P075'!$D10+'P075'!$E10+'P075'!$F10+'P075'!$G10+'P075'!$H10+'P075'!$I10+'P075'!$J10) -> 0 | L10: ='P075'!$B10-'P075'!$K10 -> 0
A11: Julio | K11: ='P075'!$B11-('P075'!$C11+'P075'!$D11+'P075'!$E11+'P075'!$F11+'P075'!$G11+'P075'!$H11+'P075'!$I11+'P075'!$J11) -> 0 | L11: ='P075'!$B11-'P075'!$K11 -> 0
A12: Agosto | K12: ='P075'!$B12-('P075'!$C12+'P075'!$D12+'P075'!$E12+'P075'!$F12+'P075'!$G12+'P075'!$H12+'P075'!$I12+'P075'!$J12) -> 0 | L12: ='P075'!$B12-'P075'!$K12 -> 0
A13: Septiembre | K13: ='P075'!$B13-('P075'!$C13+'P075'!$D13+'P075'!$E13+'P075'!$F13+'P075'!$G13+'P075'!$H13+'P075'!$I13+'P075'!$J13) -> 0 | L13: ='P075'!$B13-'P075'!$K13 -> 0
A14: Octubre | K14: ='P075'!$B14-('P075'!$C14+'P075'!$D14+'P075'!$E14+'P075'!$F14+'P075'!$G14+'P075'!$H14+'P075'!$I14+'P075'!$J14) -> 0 | L14: ='P075'!$B14-'P075'!$K14 -> 0
A15: Noviembre | K15: ='P075'!$B15-('P075'!$C15+'P075'!$D15+'P075'!$E15+'P075'!$F15+'P075'!$G15+'P075'!$H15+'P075'!$I15+'P075'!$J15) -> 0 | L15: ='P075'!$B15-'P075'!$K15 -> 0
A16: Diciembre | K16: ='P075'!$B16-('P075'!$C16+'P075'!$D16+'P075'!$E16+'P075'!$F16+'P075'!$G16+'P075'!$H16+'P075'!$I16+'P075'!$J16) -> 0 | L16: ='P075'!$B16-'P075'!$K16 -> 0
A18: NRO DE RECIBOS DE LOS PAGOS
C19: RECIBO 1 | D19: RECIBO 2 | E19: RECIBO 3 | F19: RECIBO 4 | G19: RECIBO 5 | H19: RECIBO 6 | I19: RECIBO 7 | J19: RECIBO 8
A20: Enero
A21: Febrero
A22: Marzo
A23: Abril
A24: Mayo
A25: Junio
A26: Julio
A27: Agosto
A28: Septiembre
A29: Octubre
A30: Noviembre
A31: Diciembre

Sheet P080
A1: 63/64/79/80 | C1: BENITEZ EVELIN
A3: PAGOS DEL ALQUILER
B4: COSTO | C4: PAGO 1 | D4: PAGO 2 | E4: PAGO 3 | F4: PAGO 4 | G4: PAGO 5 | H4: PAGO 6 | I4: PAGO 7 | J4: PAGO 8 | K4: SALDO | L4: RECAUDADO
A5: Enero | B5: 907500 | C5: 907500 | K5: ='P080'!$B5-('P080'!$C5+'P080'!$D5+'P080'!$E5+'P080'!$F5+'P080'!$G5+'P080'!$H5+'P080'!$I5+'P080'!$J5) -> 0 | L5: ='P080'!$B5-'P080'!$K5 -> 907500 | M5: 40500
A6: Febrero | B6: 615750 | C6: 615750 | K6: ='P080'!$B6-('P080'!$C6+'P080'!$D6+'P080'!$E6+'P080'!$F6+'P080'!$G6+'P080'!$H6+'P080'!$I6+'P080'!$J6) -> 0 | L6: ='P080'!$B6-'P080'!$K6 -> 615750 | M6: 20250
A7: Marzo | K7: ='P080'!$B7-('P080'!$C7+'P080'!$D7+'P080'!$E7+'P080'!$F7+'P080'!$G7+'P080'!$H7+'P080'!$I7+'P080'!$J7) -> 0 | L7: ='P080'!$B7-'P080'!$K7 -> 0
A8: Abril | K8: ='P080'!$B8-('P080'!$C8+'P080'!$D8+'P080'!$E8+'P080'!$F8+'P080'!$G8+'P080'!$H8+'P080'!$I8+'P080'!$J8) -> 0 | L8: ='P080'!$B8-'P080'!$K8 -> 0
A9: Mayo | L9: ='P080'!$B9-'P080'!$K9 -> 0
A10: Junio | K10: ='P080'!$B10-('P080'!$C10+'P080'!$D10+'P080'!$E10+'P080'!$F10+'P080'!$G10+'P080'!$H10+'P080'!$I10+'P080'!$J10) -> 0 | L10: ='P080'!$B10-'P080'!$K10 -> 0
A11: Julio | K11: ='P080'!$B11-('P080'!$C11+'P080'!$D11+'P080'!$E11+'P080'!$F11+'P080'!$G11+'P080'!$H11+'P080'!$I11+'P080'!$J11) -> 0 | L11: ='P080'!$B11-'P080'!$K11 -> 0
A12: Agosto | K12: ='P080'!$B12-('P080'!$C12+'P080'!$D12+'P080'!$E12+'P080'!$F12+'P080'!$G12+'P080'!$H12+'P080'!$I12+'P080'!$J12) -> 0 | L12: ='P080'!$B12-'P080'!$K12 -> 0
A13: Septiembre | K13: ='P080'!$B13-('P080'!$C13+'P080'!$D13+'P080'!$E13+'P080'!$F13+'P080'!$G13+'P080'!$H13+'P080'!$I13+'P080'!$J13) -> 0 | L13: ='P080'!$B13-'P080'!$K13 -> 0
A14: Octubre | K14: ='P080'!$B14-('P080'!$C14+'P080'!$D14+'P080'!$E14+'P080'!$F14+'P080'!$G14+'P080'!$H14+'P080'!$I14+'P080'!$J14) -> 0 | L14: ='P080'!$B14-'P080'!$K14 -> 0
A15: Noviembre | K15: ='P080'!$B15-('P080'!$C15+'P080'!$D15+'P080'!$E15+'P080'!$F15+'P080'!$G15+'P080'!$H15+'P080'!$I15+'P080'!$J15) -> 0 | L15: ='P080'!$B15-'P080'!$K15 -> 0
A16: Diciembre
A18: NRO DE RECIBOS DE LOS PAGOS
C19: RECIBO 1 | D19: RECIBO 2 | E19: RECIBO 3 | F19: RECIBO 4 | G19: RECIBO 5 | H19: RECIBO 6 | I19: RECIBO 7 | J19: RECIBO 8
A20: Enero | C20: 9626
A21: Febrero | C21: 9691
A22: Marzo
A23: Abril
A24: Mayo
A25: Junio
A26: Julio
A27: Agosto
A28: Septiembre
A29: Octubre
A30: Noviembre
A31: Diciembre

Sheet P076
A3: PAGOS DEL ALQUILER
B4: COSTO | C4: PAGO 1 | D4: PAGO 2 | E4: PAGO 3 | F4: PAGO 4 | G4: PAGO 5 | H4: PAGO 6 | I4: PAGO 7 | J4: PAGO 8 | K4: SALDO | L4: RECAUDADO
A5: Enero | K5: ='P076'!$B5-('P076'!$C5+'P076'!$D5+'P076'!$E5+'P076'!$F5+'P076'!$G5+'P076'!$H5+'P076'!$I5+'P076'!$J5) -> 0 | L5: ='P076'!$B5-'P076'!$K5 -> 0
A6: Febrero | K6: ='P076'!$B6-('P076'!$C6+'P076'!$D6+'P076'!$E6+'P076'!$F6+'P076'!$G6+'P076'!$H6+'P076'!$I6+'P076'!$J6) -> 0 | L6: ='P076'!$B6-'P076'!$K6 -> 0
A7: Marzo | K7: ='P076'!$B7-('P076'!$C7+'P076'!$D7+'P076'!$E7+'P076'!$F7+'P076'!$G7+'P076'!$H7+'P076'!$I7+'P076'!$J7) -> 0 | L7: ='P076'!$B7-'P076'!$K7 -> 0
A8: Abril | K8: ='P076'!$B8-('P076'!$C8+'P076'!$D8+'P076'!$E8+'P076'!$F8+'P076'!$G8+'P076'!$H8+'P076'!$I8+'P076'!$J8) -> 0 | L8: ='P076'!$B8-'P076'!$K8 -> 0
A9: Mayo | K9: ='P076'!$B9-('P076'!$C9+'P076'!$D9+'P076'!$E9+'P076'!$F9+'P076'!$G9+'P076'!$H9+'P076'!$I9+'P076'!$J9) -> 0 | L9: ='P076'!$B9-'P076'!$K9 -> 0
A10: Junio | K10: ='P076'!$B10-('P076'!$C10+'P076'!$D10+'P076'!$E10+'P076'!$F10+'P076'!$G10+'P076'!$H10+'P076'!$I10+'P076'!$J10) -> 0 | L10: ='P076'!$B10-'P076'!$K10 -> 0
A11: Julio | K11: ='P076'!$B11-('P076'!$C11+'P076'!$D11+'P076'!$E11+'P076'!$F11+'P076'!$G11+'P076'!$H11+'P076'!$I11+'P076'!$J11) -> 0 | L11: ='P076'!$B11-'P076'!$K11 -> 0
A12: Agosto | K12: ='P076'!$B12-('P076'!$C12+'P076'!$D12+'P076'!$E12+'P076'!$F12+'P076'!$G12+'P076'!$H12+'P076'!$I12+'P076'!$J12) -> 0 | L12: ='P076'!$B12-'P076'!$K12 -> 0
A13: Septiembre | K13: ='P076'!$B13-('P076'!$C13+'P076'!$D13+'P076'!$E13+'P076'!$F13+'P076'!$G13+'P076'!$H13+'P076'!$I13+'P076'!$J13) -> 0 | L13: ='P076'!$B13-'P076'!$K13 -> 0
A14: Octubre | K14: ='P076'!$B14-('P076'!$C14+'P076'!$D14+'P076'!$E14+'P076'!$F14+'P076'!$G14+'P076'!$H14+'P076'!$I14+'P076'!$J14) -> 0 | L14: ='P076'!$B14-'P076'!$K14 -> 0
A15: Noviembre | K15: ='P076'!$B15-('P076'!$C15+'P076'!$D15+'P076'!$E15+'P076'!$F15+'P076'!$G15+'P076'!$H15+'P076'!$I15+'P076'!$J15) -> 0 | L15: ='P076'!$B15-'P076'!$K15 -> 0
A16: Diciembre | K16: ='P076'!$B16-('P076'!$C16+'P076'!$D16+'P076'!$E16+'P076'!$F16+'P076'!$G16+'P076'!$H16+'P076'!$I16+'P076'!$J16) -> 0 | L16: ='P076'!$B16-'P076'!$K16 -> 0
A18: NRO DE RECIBOS DE LOS PAGOS
C19: RECIBO 1 | D19: RECIBO 2 | E19: RECIBO 3 | F19: RECIBO 4 | G19: RECIBO 5 | H19: RECIBO 6 | I19: RECIBO 7 | J19: RECIBO 8
A20: Enero
A21: Febrero
A22: Marzo
A23: Abril
A24: Mayo
A25: Junio
A26: Julio
A27: Agosto
A28: Septiembre
A29: Octubre
A30: Noviembre
A31: Diciembre

Sheet P077
A3: PAGOS DEL ALQUILER
B4: COSTO | C4: PAGO 1 | D4: PAGO 2 | E4: PAGO 3 | F4: PAGO 4 | G4: PAGO 5 | H4: PAGO 6 | I4: PAGO 7 | J4: PAGO 8 | K4: SALDO | L4: RECAUDADO
A5: Enero | K5: ='P077'!$B5-('P077'!$C5+'P077'!$D5+'P077'!$E5+'P077'!$F5+'P077'!$G5+'P077'!$H5+'P077'!$I5+'P077'!$J5) -> 0 | L5: ='P077'!$B5-'P077'!$K5 -> 0
A6: Febrero | K6: ='P077'!$B6-('P077'!$C6+'P077'!$D6+'P077'!$E6+'P077'!$F6+'P077'!$G6+'P077'!$H6+'P077'!$I6+'P077'!$J6) -> 0 | L6: ='P077'!$B6-'P077'!$K6 -> 0
A7: Marzo | K7: ='P077'!$B7-('P077'!$C7+'P077'!$D7+'P077'!$E7+'P077'!$F7+'P077'!$G7+'P077'!$H7+'P077'!$I7+'P077'!$J7) -> 0 | L7: ='P077'!$B7-'P077'!$K7 -> 0
A8: Abril | K8: ='P077'!$B8-('P077'!$C8+'P077'!$D8+'P077'!$E8+'P077'!$F8+'P077'!$G8+'P077'!$H8+'P077'!$I8+'P077'!$J8) -> 0 | L8: ='P077'!$B8-'P077'!$K8 -> 0
A9: Mayo | K9: ='P077'!$B9-('P077'!$C9+'P077'!$D9+'P077'!$E9+'P077'!$F9+'P077'!$G9+'P077'!$H9+'P077'!$I9+'P077'!$J9) -> 0 | L9: ='P077'!$B9-'P077'!$K9 -> 0
A10: Junio | K10: ='P077'!$B10-('P077'!$C10+'P077'!$D10+'P077'!$E10+'P077'!$F10+'P077'!$G10+'P077'!$H10+'P077'!$I10+'P077'!$J10) -> 0 | L10: ='P077'!$B10-'P077'!$K10 -> 0
A11: Julio | K11: ='P077'!$B11-('P077'!$C11+'P077'!$D11+'P077'!$E11+'P077'!$F11+'P077'!$G11+'P077'!$H11+'P077'!$I11+'P077'!$J11) -> 0 | L11: ='P077'!$B11-'P077'!$K11 -> 0
A12: Agosto | K12: ='P077'!$B12-('P077'!$C12+'P077'!$D12+'P077'!$E12+'P077'!$F12+'P077'!$G12+'P077'!$H12+'P077'!$I12+'P077'!$J12) -> 0 | L12: ='P077'!$B12-'P077'!$K12 -> 0
A13: Septiembre | K13: ='P077'!$B13-('P077'!$C13+'P077'!$D13+'P077'!$E13+'P077'!$F13+'P077'!$G13+'P077'!$H13+'P077'!$I13+'P077'!$J13) -> 0 | L13: ='P077'!$B13-'P077'!$K13 -> 0
A14: Octubre | K14: ='P077'!$B14-('P077'!$C14+'P077'!$D14+'P077'!$E14+'P077'!$F14+'P077'!$G14+'P077'!$H14+'P077'!$I14+'P077'!$J14) -> 0 | L14: ='P077'!$B14-'P077'!$K14 -> 0
A15: Noviembre | K15: ='P077'!$B15-('P077'!$C15+'P077'!$D15+'P077'!$E15+'P077'!$F15+'P077'!$G15+'P077'!$H15+'P077'!$I15+'P077'!$J15) -> 0 | L15: ='P077'!$B15-'P077'!$K15 -> 0
A16: Diciembre | K16: ='P077'!$B16-('P077'!$C16+'P077'!$D16+'P077'!$E16+'P077'!$F16+'P077'!$G16+'P077'!$H16+'P077'!$I16+'P077'!$J16) -> 0 | L16: ='P077'!$B16-'P077'!$K16 -> 0
A18: NRO DE RECIBOS DE LOS PAGOS
C19: RECIBO 1 | D19: RECIBO 2 | E19: RECIBO 3 | F19: RECIBO 4 | G19: RECIBO 5 | H19: RECIBO 6 | I19: RECIBO 7 | J19: RECIBO 8
A20: Enero
A21: Febrero
A22: Marzo
A23: Abril
A24: Mayo
A25: Junio
A26: Julio
A27: Agosto
A28: Septiembre
A29: Octubre
A30: Noviembre
A31: Diciembre

Sheet P078
A3: PAGOS DEL ALQUILER
B4: COSTO | C4: PAGO 1 | D4: PAGO 2 | E4: PAGO 3 | F4: PAGO 4 | G4: PAGO 5 | H4: PAGO 6 | I4: PAGO 7 | J4: PAGO 8 | K4: SALDO | L4: RECAUDADO
A5: Enero | K5: ='P078'!$B5-('P078'!$C5+'P078'!$D5+'P078'!$E5+'P078'!$F5+'P078'!$G5+'P078'!$H5+'P078'!$I5+'P078'!$J5) -> 0 | L5: ='P078'!$B5-'P078'!$K5 -> 0
A6: Febrero | K6: ='P078'!$B6-('P078'!$C6+'P078'!$D6+'P078'!$E6+'P078'!$F6+'P078'!$G6+'P078'!$H6+'P078'!$I6+'P078'!$J6) -> 0 | L6: ='P078'!$B6-'P078'!$K6 -> 0
A7: Marzo | K7: ='P078'!$B7-('P078'!$C7+'P078'!$D7+'P078'!$E7+'P078'!$F7+'P078'!$G7+'P078'!$H7+'P078'!$I7+'P078'!$J7) -> 0 | L7: ='P078'!$B7-'P078'!$K7 -> 0
A8: Abril | K8: ='P078'!$B8-('P078'!$C8+'P078'!$D8+'P078'!$E8+'P078'!$F8+'P078'!$G8+'P078'!$H8+'P078'!$I8+'P078'!$J8) -> 0 | L8: ='P078'!$B8-'P078'!$K8 -> 0
A9: Mayo | K9: ='P078'!$B9-('P078'!$C9+'P078'!$D9+'P078'!$E9+'P078'!$F9+'P078'!$G9+'P078'!$H9+'P078'!$I9+'P078'!$J9) -> 0 | L9: ='P078'!$B9-'P078'!$K9 -> 0
A10: Junio | K10: ='P078'!$B10-('P078'!$C10+'P078'!$D10+'P078'!$E10+'P078'!$F10+'P078'!$G10+'P078'!$H10+'P078'!$I10+'P078'!$J10) -> 0 | L10: ='P078'!$B10-'P078'!$K10 -> 0
A11: Julio | K11: ='P078'!$B11-('P078'!$C11+'P078'!$D11+'P078'!$E11+'P078'!$F11+'P078'!$G11+'P078'!$H11+'P078'!$I11+'P078'!$J11) -> 0 | L11: ='P078'!$B11-'P078'!$K11 -> 0
A12: Agosto | K12: ='P078'!$B12-('P078'!$C12+'P078'!$D12+'P078'!$E12+'P078'!$F12+'P078'!$G12+'P078'!$H12+'P078'!$I12+'P078'!$J12) -> 0 | L12: ='P078'!$B12-'P078'!$K12 -> 0
A13: Septiembre | K13: ='P078'!$B13-('P078'!$C13+'P078'!$D13+'P078'!$E13+'P078'!$F13+'P078'!$G13+'P078'!$H13+'P078'!$I13+'P078'!$J13) -> 0 | L13: ='P078'!$B13-'P078'!$K13 -> 0
A14: Octubre | K14: ='P078'!$B14-('P078'!$C14+'P078'!$D14+'P078'!$E14+'P078'!$F14+'P078'!$G14+'P078'!$H14+'P078'!$I14+'P078'!$J14) -> 0 | L14: ='P078'!$B14-'P078'!$K14 -> 0
A15: Noviembre | K15: ='P078'!$B15-('P078'!$C15+'P078'!$D15+'P078'!$E15+'P078'!$F15+'P078'!$G15+'P078'!$H15+'P078'!$I15+'P078'!$J15) -> 0 | L15: ='P078'!$B15-'P078'!$K15 -> 0
A16: Diciembre | K16: ='P078'!$B16-('P078'!$C16+'P078'!$D16+'P078'!$E16+'P078'!$F16+'P078'!$G16+'P078'!$H16+'P078'!$I16+'P078'!$J16) -> 0 | L16: ='P078'!$B16-'P078'!$K16 -> 0
A18: NRO DE RECIBOS DE LOS PAGOS
C19: RECIBO 1 | D19: RECIBO 2 | E19: RECIBO 3 | F19: RECIBO 4 | G19: RECIBO 5 | H19: RECIBO 6 | I19: RECIBO 7 | J19: RECIBO 8
A20: Enero
A21: Febrero
A22: Marzo
A23: Abril
A24: Mayo
A25: Junio
A26: Julio
A27: Agosto
A28: Septiembre
A29: Octubre
A30: Noviembre
A31: Diciembre

Sheet P079
A3: PAGOS DEL ALQUILER
B4: COSTO | C4: PAGO 1 | D4: PAGO 2 | E4: PAGO 3 | F4: PAGO 4 | G4: PAGO 5 | H4: PAGO 6 | I4: PAGO 7 | J4: PAGO 8 | K4: SALDO | L4: RECAUDADO
A5: Enero | K5: ='P079'!$B5-('P079'!$C5+'P079'!$D5+'P079'!$E5+'P079'!$F5+'P079'!$G5+'P079'!$H5+'P079'!$I5+'P079'!$J5) -> 0 | L5: ='P079'!$B5-'P079'!$K5 -> 0
A6: Febrero | K6: ='P079'!$B6-('P079'!$C6+'P079'!$D6+'P079'!$E6+'P079'!$F6+'P079'!$G6+'P079'!$H6+'P079'!$I6+'P079'!$J6) -> 0 | L6: ='P079'!$B6-'P079'!$K6 -> 0
A7: Marzo | K7: ='P079'!$B7-('P079'!$C7+'P079'!$D7+'P079'!$E7+'P079'!$F7+'P079'!$G7+'P079'!$H7+'P079'!$I7+'P079'!$J7) -> 0 | L7: ='P079'!$B7-'P079'!$K7 -> 0
A8: Abril | K8: ='P079'!$B8-('P079'!$C8+'P079'!$D8+'P079'!$E8+'P079'!$F8+'P079'!$G8+'P079'!$H8+'P079'!$I8+'P079'!$J8) -> 0 | L8: ='P079'!$B8-'P079'!$K8 -> 0
A9: Mayo | K9: ='P079'!$B9-('P079'!$C9+'P079'!$D9+'P079'!$E9+'P079'!$F9+'P079'!$G9+'P079'!$H9+'P079'!$I9+'P079'!$J9) -> 0 | L9: ='P079'!$B9-'P079'!$K9 -> 0
A10: Junio | K10: ='P079'!$B10-('P079'!$C10+'P079'!$D10+'P079'!$E10+'P079'!$F10+'P079'!$G10+'P079'!$H10+'P079'!$I10+'P079'!$J10) -> 0 | L10: ='P079'!$B10-'P079'!$K10 -> 0
